Workbook

Sheet GACS Securitizations
A1: Event_ID | B1: Bank | C1: Ticker | D1: SPV_Name | E1: Servicer | F1: GACS_Issuing_Date | G1: Date | H1: GBV_EUR_bn | I1: Pct_Secured | J1: Senior_PctGBV | K1: Mezz_PctGBV | L1: Junior_PctGBV | M1: Senior_Yield | N1: Mezz_Yield | O1: Buyer | P1: GACS | Q1: Deal_Type | R1: Capital_Raise_Simultaneous | S1: Bank_NPL_Ratio | T1: Bank_CET1 | U1: Crisis_Period | V1: PwC_Source | W1: Notes
A2: GACS-001 | B2: UniCredit | C2: UCG | D2: FINO 1 Securitisation S.r.l. | E2: doValue | F2: Nov-17 | G2: 43081 | H2: 5.4 | I2: 52.0% | J2: 12.1% | K2: 1.3% | L2: 0.9% | M2: 5.1% | N2: 8.7% | O2: Fortress/PIMCO | P2: Yes | Q2: Bad Loans | U2: Yes | V2: PwC Dec 2023 pp.20-21
A3: GACS-002 | B3: MPS | C3: BMPS | D3: Siena NPL 2018 S.r.l. | E3: Cerved/Prelios/doValue/CF | F3: Jan-18 | G3: 43230 | H3: 24.1 | I3: 41.6% | J3: 12.1% | K3: 3.5% | L3: 2.3% | M3: 5.1% | N3: 11.6% | O3: Quaestio/Atlante II | P3: Yes | Q3: Bad Loans | U3: No | V3: PwC Dec 2023 pp.20-21
A4: GACS-003 | B4: BPER | C4: BPE | D4: 4Mori Sardegna S.r.l. | E4: Prelios | F4: Jun-18 | G4: 43273 | H4: 1 | I4: 53.0% | J4: 22.2% | K4: 1.2% | L4: 0.8% | M4: 1.4% | N4: 11.9% | O4: n.a. | P4: Yes | Q4: Bad Loans | U4: No | V4: PwC Dec 2023 pp.20-21
A5: GACS-004 | B5: Banco BPM | C5: BAMI | D5: Red Sea SPV S.r.l. | E5: Prelios | F5: Jul-18 | G5: 43251 | H5: 5.1 | I5: 76.6% | J5: 32.5% | K5: 3.0% | L5: 1.0% | M5: 4.5% | N5: 9.9% | O5: n.a. | P5: Yes | Q5: Bad Loans | U5: No | V5: PwC Dec 2023 pp.20-21
A6: GACS-005 | B6: BPER | C6: BPE | D6: Aqui SPV S.r.l. | E6: Prelios | F6: Nov-18 | G6: 43412 | H6: 2.1 | I6: 59.5% | J6: 26.2% | K6: 3.0% | L6: 0.5% | M6: 2.0% | N6: 10.9% | O6: n.a. | P6: Yes | Q6: Bad Loans | U6: No | V6: PwC Dec 2023 pp.20-21
A7: GACS-006 | B7: Banco BPM | C7: BAMI | D7: Leviticus SPV S.r.l. | E7: Credito Fondiario | F7: Feb-19 | G7: 43444 | H7: 7.4 | I7: 66.9% | J7: 19.5% | K7: 3.0% | L7: 3.4% | M7: 2.1% | N7: 11.9% | O7: n.a. | P7: Yes | Q7: Bad Loans | U7: No | V7: PwC Dec 2023 pp.20-21
A8: GACS-007 | B8: UniCredit | C8: UCG | D8: Prisma SPV S.r.l. | E8: doValue | F8: Oct-19 | G8: 43756 | H8: 6.1 | I8: 64.0% | J8: 20.0% | K8: 1.3% | L8: 0.5% | M8: 5.4% | N8: 12.9% | O8: n.a. | P8: Yes | Q8: Bad Loans | U8: No | V8: PwC Dec 2023 pp.20-21
A9: GACS-008 | B9: BPER | C9: BPE | D9: Spring SPV S.r.l. | E9: Prelios | F9: Jun-20 | G9: 44000 | H9: 1.4 | I9: 52.5% | J9: 23.2% | K9: 1.5% | L9: 0.2% | M9: 4.4% | N9: 13.4% | O9: n.a. | P9: Yes | Q9: Bad Loans | U9: No | V9: PwC Dec 2023 pp.20-21
A10: GACS-009 | B10: Banca Popolare di Sondrio | C10: BPSO | D10: Diana SPV S.r.l. | E10: Prelios | F10: Jun-20 | G10: 43999 | H10: 1 | I10: 64.7% | J10: 23.5% | K10: 3.5% | L10: 0.4% | M10: 4.4% | N10: 12.9% | O10: n.a. | P10: Yes | Q10: Bad Loans | U10: No | V10: PwC Dec 2023 pp.20-21
A11: GACS-010 | B11: UniCredit | C11: UCG | D11: Relais SPV S.r.l. | E11: doValue | F11: Dec-20 | G11: 44179 | H11: 1.6 | I11: 86.5% | J11: 29.4% | K11: 5.7% | L11: 0.6% | M11: 5.4% | N11: 13.4% | O11: n.a. | P11: Yes | Q11: Bad Loans | U11: No | V11: PwC Dec 2023 pp.20-21
A12: GACS-011 | B12: Intesa Sanpaolo | C12: ISP | D12: Yoda SPV S.r.l. | E12: Intrum | F12: Dec-20 | G12: 44183 | H12: 6 | I12: 41.2% | J12: 16.7% | K12: 3.5% | L12: 0.3% | M12: 4.1% | N12: 13.1% | O12: n.a. | P12: Yes | Q12: Bad Loans | U12: No | V12: PwC Dec 2023 pp.20-21
A13: GACS-012 | B13: BPER | C13: BPE | D13: Summer SPV S.r.l. | E13: Fire | F13: Dec-20 | G13: 44195 | H13: 0.3 | I13: 44.4% | J13: 26.5% | K13: 3.1% | L13: 0.3% | M13: 4.4% | N13: 15.9% | O13: Institutional inv. | P13: Yes | Q13: Bad Loans | U13: No | V13: PwC Dec 2023 pp.20-21
... A19: GACS-018 | B19: UniCredit | C19: UCG | D19: Itaca SPV S.r.l. | E19: doValue | F19: Jun-22 | G19: 44727 | H19: 1.1 | I19: 29.0% | J19: 11.1% | K19: 2.1% | L19: 0.5% | M19: 4.9% | N19: 13.4% | O19: CRC | P19: Yes | Q19: Bad Loans | U19: No | V19: PwC Dec 2023 pp.20-21
B23: Company | C23: Ticker | D23: Count
B24: {=_xlfn.UNIQUE(B2:B19)} -> UniCredit | C24: =VLOOKUP(B24,$B$2:$C$19,2, FALSE) -> UCG | D24: =COUNTIF($C$2:$C$19,C24) -> 5
B25: MPS | C25: =VLOOKUP(B25,$B$2:$C$19,2, FALSE) -> BMPS | D25: =COUNTIF($C$2:$C$19,C25) -> 1
B26: BPER | C26: =VLOOKUP(B26,$B$2:$C$19,2, FALSE) -> BPE | D26: =COUNTIF($C$2:$C$19,C26) -> 4
B27: Banco BPM | C27: =VLOOKUP(B27,$B$2:$C$19,2, FALSE) -> BAMI | D27: =COUNTIF($C$2:$C$19,C27) -> 3
B28: Banca Popolare di Sondrio | C28: =VLOOKUP(B28,$B$2:$C$19,2, FALSE) -> BPSO | D28: =COUNTIF($C$2:$C$19,C28) -> 2
B29: Intesa Sanpaolo | C29: =VLOOKUP(B29,$B$2:$C$19,2, FALSE) -> ISP | D29: =COUNTIF($C$2:$C$19,C29) -> 2
B30: Intesa Sanpaolo/BPER | C30: =VLOOKUP(B30,$B$2:$C$19,2, FALSE) -> ISP/BPE | D30: =COUNTIF($C$2:$C$19,C30) -> 1
B32: UCG | D32: Price on event day | E32: Pfm 1 day | F32: Pfm next three days | G32: Pfm 1 week | H32: Pfm 1 month
C33: {=_xlfn._xlws.FILTER($G$2:$G$19,$C$2:$C$19=B32)} -> 43081 | D33: =SUM(_xldudf_WISEPRICE($B$32 & ".MI", "Close",, TEXT($C33, "yyyy-mm-dd"), TEXT($C33, "yyyy-mm-dd"))) -> 17.41 | E33: =(SUM(_xldudf_WISEPRICE($B$32 & ".MI", "Close",, TEXT(WORKDAY($C33, 1), "yyyy-mm-dd"), TEXT(WORKDAY($C33, 1), "yyyy-mm-dd"))) / $D33) - 1 -> -0.046524986 | F33: =(SUM(_xldudf_WISEPRICE($B$32 & ".MI", "Close",, TEXT(WORKDAY($C33, 3), "yyyy-mm-dd"), TEXT(WORKDAY($C33, 3), "yyyy-mm-dd"))) / $D33) - 1 -> -0.0723722 | G33: =(SUM(_xldudf_WISEPRICE($B$32 & ".MI", "Close",, TEXT(WORKDAY($C33, 5), "yyyy-mm-dd"), TEXT(WORKDAY($C33, 5), "yyyy-mm-dd"))) / $D33) - 1 -> -0.050545663 | H33: =(SUM(_xldudf_WISEPRICE($B$32 & ".MI", "Close",, TEXT(WORKDAY(EDATE($C33, 1)-1, 1), "yyyy-mm-dd"), TEXT(WORKDAY(EDATE($C33, 1)-1, 1), "yyyy-mm-dd"))) / $D33) - 1 -> 0.0034462952
C34: 43756 | D34: =SUM(_xldudf_WISEPRICE("UCG.MI","Close",,C34,C34)) -> 11.5 | E34: =(SUM(_xldudf_WISEPRICE($B$32 & ".MI", "Close",, TEXT(WORKDAY($C34, 1), "yyyy-mm-dd"), TEXT(WORKDAY($C34, 1), "yyyy-mm-dd"))) / $D34) - 1 -> 0.020869565 | F34: =(SUM(_xldudf_WISEPRICE($B$32 & ".MI", "Close",, TEXT(WORKDAY($C34, 3), "yyyy-mm-dd"), TEXT(WORKDAY($C34, 3), "yyyy-mm-dd"))) / $D34) - 1 -> 0.013913043 | G34: =(SUM(_xldudf_WISEPRICE($B$32 & ".MI", "Close",, TEXT(WORKDAY($C34, 5), "yyyy-mm-dd"), TEXT(WORKDAY($C34, 5), "yyyy-mm-dd"))) / $D34) - 1 -> 0.0026086957 | H34: =(SUM(_xldudf_WISEPRICE($B$32 & ".MI", "Close",, TEXT(WORKDAY(EDATE($C34, 1)-1, 1), "yyyy-mm-dd"), TEXT(WORKDAY(EDATE($C34, 1)-1, 1), "yyyy-mm-dd"))) / $D34) - 1 -> 0.073043478
C35: 44179 | D35: =SUM(_xldudf_WISEPRICE("UCG.MI","Close",,C35,C35)) -> 7.69 | E35: =(SUM(_xldudf_WISEPRICE($B$32 & ".MI", "Close",, TEXT(WORKDAY($C35, 1), "yyyy-mm-dd"), TEXT(WORKDAY($C35, 1), "yyyy-mm-dd"))) / $D35) - 1 -> 0.026007802 | F35: =(SUM(_xldudf_WISEPRICE($B$32 & ".MI", "Close",, TEXT(WORKDAY($C35, 3), "yyyy-mm-dd"), TEXT(WORKDAY($C35, 3), "yyyy-mm-dd"))) / $D35) - 1 -> 0.013003901 | G35: =(SUM(_xldudf_WISEPRICE($B$32 & ".MI", "Close",, TEXT(WORKDAY($C35, 5), "yyyy-mm-dd"), TEXT(WORKDAY($C35, 5), "yyyy-mm-dd"))) / $D35) - 1 -> -0.035110533 | H35: =(SUM(_xldudf_WISEPRICE($B$32 & ".MI", "Close",, TEXT(WORKDAY(EDATE($C35, 1)-1, 1), "yyyy-mm-dd"), TEXT(WORKDAY(EDATE($C35, 1)-1, 1), "yyyy-mm-dd"))) / $D35) - 1 -> 0.019505852
C36: 44525 | D36: =SUM(_xldudf_WISEPRICE("UCG.MI","Close",,C36,C36)) -> 11.27 | E36: =(SUM(_xldudf_WISEPRICE($B$32 & ".MI", "Close",, TEXT(WORKDAY($C36, 1), "yyyy-mm-dd"), TEXT(WORKDAY($C36, 1), "yyyy-mm-dd"))) / $D36) - 1 -> -0.069210293 | F36: =(SUM(_xldudf_WISEPRICE($B$32 & ".MI", "Close",, TEXT(WORKDAY($C36, 3), "yyyy-mm-dd"), TEXT(WORKDAY($C36, 3), "yyyy-mm-dd"))) / $D36) - 1 -> -0.051464064 | G36: =(SUM(_xldudf_WISEPRICE($B$32 & ".MI", "Close",, TEXT(WORKDAY($C36, 5), "yyyy-mm-dd"), TEXT(WORKDAY($C36, 5), "yyyy-mm-dd"))) / $D36) - 1 -> -0.023070098 | H36: =(SUM(_xldudf_WISEPRICE($B$32 & ".MI", "Close",, TEXT(WORKDAY(EDATE($C36, 1)-1, 1), "yyyy-mm-dd"), TEXT(WORKDAY(EDATE($C36, 1)-1, 1), "yyyy-mm-dd"))) / $D36) - 1 -> 0.20053239
C37: 44727 | D37: =SUM(_xldudf_WISEPRICE("UCG.MI","Close",,C37,C37)) -> 10.08 | E37: =(SUM(_xldudf_WISEPRICE($B$32 & ".MI", "Close",, TEXT(WORKDAY($C37, 1), "yyyy-mm-dd"), TEXT(WORKDAY($C37, 1), "yyyy-mm-dd"))) / $D37) - 1 -> -0.032738095 | F37: =(SUM(_xldudf_WISEPRICE($B$32 & ".MI", "Close",, TEXT(WORKDAY($C37, 3), "yyyy-mm-dd"), TEXT(WORKDAY($C37, 3), "yyyy-mm-dd"))) / $D37) - 1 -> 0.015873016 | G37: =(SUM(_xldudf_WISEPRICE($B$32 & ".MI", "Close",, TEXT(WORKDAY($C37, 5), "yyyy-mm-dd"), TEXT(WORKDAY($C37, 5), "yyyy-mm-dd"))) / $D37) - 1 -> 0.013888889 | H37: =(SUM(_xldudf_WISEPRICE($B$32 & ".MI", "Close",, TEXT(WORKDAY(EDATE($C37, 1)-1, 1), "yyyy-mm-dd"), TEXT(WORKDAY(EDATE($C37, 1)-1, 1), "yyyy-mm-dd"))) / $D37) - 1 -> -0.14980159
C38: Average Performance | D38: =_xlfn.AGGREGATE(1,6,D33:D37) -> 11.59 | E38: =_xlfn.AGGREGATE(1,6,E33:E37) -> -0.020319201 | F38: =_xlfn.AGGREGATE(1,6,F33:F37) -> -0.016209261 | G38: =_xlfn.AGGREGATE(1,6,G33:G37) -> -0.018445742 | H38: =_xlfn.AGGREGATE(1,6,H33:H37) -> 0.029345285
B39: BMPS | D39: Price on event day | E39: Pfm 1 day | F39: Pfm next three days | G39: Pfm 1 week | H39: Pfm 1 month
C40: {=_xlfn._xlws.FILTER($G$2:$G$19,$C$2:$C$19=B39)} -> 43230 | D40: =SUM(_xldudf_WISEPRICE($B$39 & ".MI", "Close",, TEXT($C40, "yyyy-mm-dd"), TEXT($C40, "yyyy-mm-dd"))) -> 272 | E40: =(SUM(_xldudf_WISEPRICE($B$39 & ".MI", "Close",, TEXT(WORKDAY($C40, 1), "yyyy-mm-dd"), TEXT(WORKDAY($C40, 1), "yyyy-mm-dd"))) / $D40) - 1 -> 0.17647059 | F40: =(SUM(_xldudf_WISEPRICE($B$39 & ".MI", "Close",, TEXT(WORKDAY($C40, 3), "yyyy-mm-dd"), TEXT(WORKDAY($C40, 3), "yyyy-mm-dd"))) / $D40) - 1 -> 0.1875 | G40: =(SUM(_xldudf_WISEPRICE($B$39 & ".MI", "Close",, TEXT(WORKDAY($C40, 5), "yyyy-mm-dd"), TEXT(WORKDAY($C40, 5), "yyyy-mm-dd"))) / $D40) - 1 -> 0.074632309 | H40: =(SUM(_xldudf_WISEPRICE($B$39 & ".MI", "Close",, TEXT(WORKDAY(EDATE($C40, 1)-1, 1), "yyyy-mm-dd"), TEXT(WORKDAY(EDATE($C40, 1)-1, 1), "yyyy-mm-dd"))) / $D40) - 1 -> 0.022058824
C41: Average Performance | D41: =_xlfn.AGGREGATE(1,6,D40:D40) -> 272 | E41: =_xlfn.AGGREGATE(1,6,E40:E40) -> 0.17647059 | F41: =_xlfn.AGGREGATE(1,6,F40:F40) -> 0.1875 | G41: =_xlfn.AGGREGATE(1,6,G40:G40) -> 0.074632309 | H41: =_xlfn.AGGREGATE(1,6,H40:H40) -> 0.022058824
B42: BPE | D42: Price on event day | E42: Pfm 1 day | F42: Pfm next three days | G42: Pfm 1 week | H42: Pfm 1 month
C43: {=_xlfn._xlws.FILTER($G$2:$G$19,$C$2:$C$19=B42)} -> 43273 | D43: =SUM(_xldudf_WISEPRICE($B$42 & ".MI", "Close",, TEXT($C43, "yyyy-mm-dd"), TEXT($C43, "yyyy-mm-dd"))) -> 3.24 | E43: =(SUM(_xldudf_WISEPRICE($B$42 & ".MI", "Close",, TEXT(WORKDAY($C43, 1), "yyyy-mm-dd"), TEXT(WORKDAY($C43, 1), "yyyy-mm-dd"))) / $D43) - 1 -> -0.021604938 | F43: =(SUM(_xldudf_WISEPRICE($B$42 & ".MI", "Close",, TEXT(WORKDAY($C43, 3), "yyyy-mm-dd"), TEXT(WORKDAY($C43, 3), "yyyy-mm-dd"))) / $D43) - 1 -> -0.030864198 | G43: =(SUM(_xldudf_WISEPRICE($B$42 & ".MI", "Close",, TEXT(WORKDAY($C43, 5), "yyyy-mm-dd"), TEXT(WORKDAY($C43, 5), "yyyy-mm-dd"))) / $D43) - 1 -> -0.015432099 | H43: =(SUM(_xldudf_WISEPRICE($B$42 & ".MI", "Close",, TEXT(WORKDAY(EDATE($C43, 1)-1, 1), "yyyy-mm-dd"), TEXT(WORKDAY(EDATE($C43, 1)-1, 1), "yyyy-mm-dd"))) / $D43) - 1 -> -0.052469136
C44: 43412 | D44: =SUM(_xldudf_WISEPRICE($B$42 & ".MI", "Close",, TEXT($C44, "yyyy-mm-dd"), TEXT($C44, "yyyy-mm-dd"))) -> 2.34 | E44: =(SUM(_xldudf_WISEPRICE($B$42 & ".MI", "Close",, TEXT(WORKDAY($C44, 1), "yyyy-mm-dd"), TEXT(WORKDAY($C44, 1), "yyyy-mm-dd"))) / $D44) - 1 -> 0.0085470085 | F44: =(SUM(_xldudf_WISEPRICE($B$42 & ".MI", "Close",, TEXT(WORKDAY($C44, 3), "yyyy-mm-dd"), TEXT(WORKDAY($C44, 3), "yyyy-mm-dd"))) / $D44) - 1 -> 0.012820513 | G44: =(SUM(_xldudf_WISEPRICE($B$42 & ".MI", "Close",, TEXT(WORKDAY($C44, 5), "yyyy-mm-dd"), TEXT(WORKDAY($C44, 5), "yyyy-mm-dd"))) / $D44) - 1 -> -0.012820513 | H44: =(SUM(_xldudf_WISEPRICE($B$42 & ".MI", "Close",, TEXT(WORKDAY(EDATE($C44, 1)-1, 1), "yyyy-mm-dd"), TEXT(WORKDAY(EDATE($C44, 1)-1, 1), "yyyy-mm-dd"))) / $D44) - 1 -> 0.021367521
C45: 44000 | D45: =SUM(_xldudf_WISEPRICE($B$42 & ".MI", "Close",, TEXT($C45, "yyyy-mm-dd"), TEXT($C45, "yyyy-mm-dd"))) -> 1.58 | E45: =(SUM(_xldudf_WISEPRICE($B$42 & ".MI", "Close",, TEXT(WORKDAY($C45, 1), "yyyy-mm-dd"), TEXT(WORKDAY($C45, 1), "yyyy-mm-dd"))) / $D45) - 1 -> 0.012658228 | F45: =(SUM(_xldudf_WISEPRICE($B$42 & ".MI", "Close",, TEXT(WORKDAY($C45, 3), "yyyy-mm-dd"), TEXT(WORKDAY($C45, 3), "yyyy-mm-dd"))) / $D45) - 1 -> -0.0063291139 | G45: =(SUM(_xldudf_WISEPRICE($B$42 & ".MI", "Close",, TEXT(WORKDAY($C45, 5), "yyyy-mm-dd"), TEXT(WORKDAY($C45, 5), "yyyy-mm-dd"))) / $D45) - 1 -> -0.044303797 | H45: =(SUM(_xldudf_WISEPRICE($B$42 & ".MI", "Close",, TEXT(WORKDAY(EDATE($C45, 1)-1, 1), "yyyy-mm-dd"), TEXT(WORKDAY(EDATE($C45, 1)-1, 1), "yyyy-mm-dd"))) / $D45) - 1 -> 0.063291139
C46: 44195 | D46: =SUM(_xldudf_WISEPRICE($B$42 & ".MI", "Close",, TEXT($C46, "yyyy-mm-dd"), TEXT($C46, "yyyy-mm-dd"))) -> 1.49 | E46: / | F46: =(SUM(_xldudf_WISEPRICE($B$42 & ".MI", "Close",, TEXT(WORKDAY($C46, 3), "yyyy-mm-dd"), TEXT(WORKDAY($C46, 3), "yyyy-mm-dd"))) / $D46) - 1 -> -0.020134228 | G46: =(SUM(_xldudf_WISEPRICE($B$42 & ".MI", "Close",, TEXT(WORKDAY($C46, 5), "yyyy-mm-dd"), TEXT(WORKDAY($C46, 5), "yyyy-mm-dd"))) / $D46) - 1 -> 0.040268456 | H46: =(SUM(_xldudf_WISEPRICE($B$42 & ".MI", "Close",, TEXT(WORKDAY(EDATE($C46, 1)-1, 1), "yyyy-mm-dd"), TEXT(WORKDAY(EDATE($C46, 1)-1, 1), "yyyy-mm-dd"))) / $D46) - 1 -> 0.026845638
C47: Average Performance | D47: =_xlfn.AGGREGATE(1,6,D43:D46) -> 2.1625 | E47: =_xlfn.AGGREGATE(1,6,E43:E46) -> -0.00013323396 | F47: =_xlfn.AGGREGATE(1,6,F43:F46) -> -0.011126757 | G47: =_xlfn.AGGREGATE(1,6,G43:G46) -> -0.0080719882 | H47: =_xlfn.AGGREGATE(1,6,H43:H46) -> 0.014758791
B48: BAMI
D49: Price on event day | E49: Pfm 1 day | F49: Pfm next three days | G49: Pfm 1 week | H49: Pfm 1 month
C50: {=_xlfn._xlws.FILTER($G$2:$G$19,$C$2:$C$19=B48)} -> 43251 | D50: =SUM(_xldudf_WISEPRICE($B$48 & ".MI", "Close",, TEXT($C50, "yyyy-mm-dd"), TEXT($C50, "yyyy-mm-dd"))) -> 2.22 | E50: =(SUM(_xldudf_WISEPRICE($B$48 & ".MI", "Close",, TEXT(WORKDAY($C50, 1), "yyyy-mm-dd"), TEXT(WORKDAY($C50, 1), "yyyy-mm-dd"))) / $D50) - 1 -> 0.085585586 | F50: =(SUM(_xldudf_WISEPRICE($B$48 & ".MI", "Close",, TEXT(WORKDAY($C50, 3), "yyyy-mm-dd"), TEXT(WORKDAY($C50, 3), "yyyy-mm-dd"))) / $D50) - 1 -> 0.027027027 | G50: =(SUM(_xldudf_WISEPRICE($B$48 & ".MI", "Close",, TEXT(WORKDAY($C50, 5), "yyyy-mm-dd"), TEXT(WORKDAY($C50, 5), "yyyy-mm-dd"))) / $D50) - 1 -> 0.081081081 | H50: =(SUM(_xldudf_WISEPRICE($B$48 & ".MI", "Close",, TEXT(WORKDAY(EDATE($C50, 1)-1, 1), "yyyy-mm-dd"), TEXT(WORKDAY(EDATE($C50, 1)-1, 1), "yyyy-mm-dd"))) / $D50) - 1 -> 0.13963964
C51: 43444 | D51: =SUM(_xldudf_WISEPRICE($B$48 & ".MI", "Close",, TEXT($C51, "yyyy-mm-dd"), TEXT($C51, "yyyy-mm-dd"))) -> 2.07 | E51: =(SUM(_xldudf_WISEPRICE($B$48 & ".MI", "Close",, TEXT(WORKDAY($C51, 1), "yyyy-mm-dd"), TEXT(WORKDAY($C51, 1), "yyyy-mm-dd"))) / $D51) - 1 -> 0.024154589 | F51: =(SUM(_xldudf_WISEPRICE($B$48 & ".MI", "Close",, TEXT(WORKDAY($C51, 3), "yyyy-mm-dd"), TEXT(WORKDAY($C51, 3), "yyyy-mm-dd"))) / $D51) - 1 -> 0.014492754 | G51: =(SUM(_xldudf_WISEPRICE($B$48 & ".MI", "Close",, TEXT(WORKDAY($C51, 5), "yyyy-mm-dd"), TEXT(WORKDAY($C51, 5), "yyyy-mm-dd"))) / $D51) - 1 -> -0.028985507 | H51: =(SUM(_xldudf_WISEPRICE($B$48 & ".MI", "Close",, TEXT(WORKDAY(EDATE($C51, 1)-1, 1), "yyyy-mm-dd"), TEXT(WORKDAY(EDATE($C51, 1)-1, 1), "yyyy-mm-dd"))) / $D51) - 1 -> -0.019323671
C52: 44369 | D52: =SUM(_xldudf_WISEPRICE($B$48 & ".MI", "Close",, TEXT($C52, "yyyy-mm-dd"), TEXT($C52, "yyyy-mm-dd"))) -> 2.85 | E52: =(SUM(_xldudf_WISEPRICE($B$48 & ".MI", "Close",, TEXT(WORKDAY($C52, 1), "yyyy-mm-dd"), TEXT(WORKDAY($C52, 1), "yyyy-mm-dd"))) / $D52) - 1 -> -0.0035087719 | F52: =(SUM(_xldudf_WISEPRICE($B$48 & ".MI", "Close",, TEXT(WORKDAY($C52, 3), "yyyy-mm-dd"), TEXT(WORKDAY($C52, 3), "yyyy-mm-dd"))) / $D52) - 1 -> -0.0035087719 | G52: =(SUM(_xldudf_WISEPRICE($B$48 & ".MI", "Close",, TEXT(WORKDAY($C52, 5), "yyyy-mm-dd"), TEXT(WORKDAY($C52, 5), "yyyy-mm-dd"))) / $D52) - 1 -> -0.038596491 | H52: =(SUM(_xldudf_WISEPRICE($B$48 & ".MI", "Close",, TEXT(WORKDAY(EDATE($C52, 1)-1, 1), "yyyy-mm-dd"), TEXT(WORKDAY(EDATE($C52, 1)-1, 1), "yyyy-mm-dd"))) / $D52) - 1 -> -0.09122807
C53: Average Performance | D53: =_xlfn.AGGREGATE(1,6,D50:D52) -> 2.38 | E53: =_xlfn.AGGREGATE(1,6,E50:E52) -> 0.035410468 | F53: =_xlfn.AGGREGATE(1,6,F50:F52) -> 0.012670336 | G53: =_xlfn.AGGREGATE(1,6,G50:G52) -> 0.0044996942 | H53: =_xlfn.AGGREGATE(1,6,H50:H52) -> 0.009695966
B54: BPSO
D55: Price on event day | E55: Pfm 1 day | F55: Pfm next three days | G55: Pfm 1 week | H55: Pfm 1 month
C56: {=_xlfn._xlws.FILTER($G$2:$G$19,$C$2:$C$19=B54)} -> 43999 | D56: =SUM(_xldudf_WISEPRICE($B$54 & ".MI", "Close",, TEXT($C56, "yyyy-mm-dd"), TEXT($C56, "yyyy-mm-dd"))) -> 1.57 | E56: =(SUM(_xldudf_WISEPRICE($B$54 & ".MI", "Close",, TEXT(WORKDAY($C56, 1), "yyyy-mm-dd"), TEXT(WORKDAY($C56, 1), "yyyy-mm-dd"))) / $D56) - 1 -> 0.038216561 | F56: =(SUM(_xldudf_WISEPRICE($B$54 & ".MI", "Close",, TEXT(WORKDAY($C56, 3), "yyyy-mm-dd"), TEXT(WORKDAY($C56, 3), "yyyy-mm-dd"))) / $D56) - 1 -> -0.01910828 | G56: =(SUM(_xldudf_WISEPRICE($B$54 & ".MI", "Close",, TEXT(WORKDAY($C56, 5), "yyyy-mm-dd"), TEXT(WORKDAY($C56, 5), "yyyy-mm-dd"))) / $D56) - 1 -> -0.012738854 | H56: =(SUM(_xldudf_WISEPRICE($B$54 & ".MI", "Close",, TEXT(WORKDAY(EDATE($C56, 1)-1, 1), "yyyy-mm-dd"), TEXT(WORKDAY(EDATE($C56, 1)-1, 1), "yyyy-mm-dd"))) / $D56) - 1 -> 0.22292994
C57: 44553 | D57: =SUM(_xldudf_WISEPRICE($B$54 & ".MI", "Close",, TEXT($C57, "yyyy-mm-dd"), TEXT($C57, "yyyy-mm-dd"))) -> 3.71 | E57: / | F57: =(SUM(_xldudf_WISEPRICE($B$54 & ".MI", "Close",, TEXT(WORKDAY($C57, 3), "yyyy-mm-dd"), TEXT(WORKDAY($C57, 3), "yyyy-mm-dd"))) / $D57) - 1 -> 0.0026954178 | G57: =(SUM(_xldudf_WISEPRICE($B$54 & ".MI", "Close",, TEXT(WORKDAY($C57, 5), "yyyy-mm-dd"), TEXT(WORKDAY($C57, 5), "yyyy-mm-dd"))) / $D57) - 1 -> -0.0026954178 | H57: =(SUM(_xldudf_WISEPRICE($B$54 & ".MI", "Close",, TEXT(WORKDAY(EDATE($C57, 1)-1, 1), "yyyy-mm-dd"), TEXT(WORKDAY(EDATE($C57, 1)-1, 1), "yyyy-mm-dd"))) / $D57) - 1 -> -0.037735849
C58: Average Performance | D58: =_xlfn.AGGREGATE(1,6,D56:D57) -> 2.64 | E58: =_xlfn.AGGREGATE(1,6,E56:E57) -> 0.038216561 | F58: =_xlfn.AGGREGATE(1,6,F56:F57) -> -0.0082064312 | G58: =_xlfn.AGGREGATE(1,6,G56:G57) -> -0.0077171356 | H58: =_xlfn.AGGREGATE(1,6,H56:H57) -> 0.092597044
B59: ISP
D60: Price on event day | E60: Pfm 1 day | F60: Pfm next three days | G60: Pfm 1 week | H60: Pfm 1 month
C61: {=_xlfn._xlws.FILTER($G$2:$G$19,$C$2:$C$19=B59)} -> 44183 | D61: =SUM(_xldudf_WISEPRICE($B$59 & ".MI", "Close",, TEXT($C61, "yyyy-mm-dd"), TEXT($C61, "yyyy-mm-dd"))) -> 1.94 | E61: =(SUM(_xldudf_WISEPRICE($B$59 & ".MI", "Close",, TEXT(WORKDAY($C61, 1), "yyyy-mm-dd"), TEXT(WORKDAY($C61, 1), "yyyy-mm-dd"))) / $D61) - 1 -> -0.036082474 | F61: =(SUM(_xldudf_WISEPRICE($B$59 & ".MI", "Close",, TEXT(WORKDAY($C61, 3), "yyyy-mm-dd"), TEXT(WORKDAY($C61, 3), "yyyy-mm-dd"))) / $D61) - 1 -> -0.015463918 | G61: =(SUM(_xldudf_WISEPRICE($B$59 & ".MI", "Close", , "2020-12-28", "2020-12-28")) / $D61) - 1 -> -0.010309278 | H61: =(SUM(_xldudf_WISEPRICE($B$59 & ".MI", "Close",, TEXT(WORKDAY(EDATE($C61, 1)-1, 1), "yyyy-mm-dd"), TEXT(WORKDAY(EDATE($C61, 1)-1, 1), "yyyy-mm-dd"))) / $D61) - 1 -> -0.010309278
C62: 44672 | D62: =SUM(_xldudf_WISEPRICE($B$59 & ".MI", "Close",, TEXT($C62, "yyyy-mm-dd"), TEXT($C62, "yyyy-mm-dd"))) -> 2.03 | E62: =(SUM(_xldudf_WISEPRICE($B$59 & ".MI", "Close",, TEXT(WORKDAY($C62, 1), "yyyy-mm-dd"), TEXT(WORKDAY($C62, 1), "yyyy-mm-dd"))) / $D62) - 1 -> -0.024630542 | F62: =(SUM(_xldudf_WISEPRICE($B$59 & ".MI", "Close",, TEXT(WORKDAY($C62, 3), "yyyy-mm-dd"), TEXT(WORKDAY($C62, 3), "yyyy-mm-dd"))) / $D62) - 1 -> -0.054187192 | G62: =(SUM(_xldudf_WISEPRICE($B$59 & ".MI", "Close",, TEXT(WORKDAY($C62, 5), "yyyy-mm-dd"), TEXT(WORKDAY($C62, 5), "yyyy-mm-dd"))) / $D62) - 1 -> -0.049261084 | H62: =(SUM(_xldudf_WISEPRICE($B$59 & ".MI", "Close",, TEXT(WORKDAY(EDATE($C62, 1)-1, 1), "yyyy-mm-dd"), TEXT(WORKDAY(EDATE($C62, 1)-1, 1), "yyyy-mm-dd"))) / $D62) - 1 -> -0.024630542
C63: Average Performance | D63: =_xlfn.AGGREGATE(1,6,D61:D62) -> 1.985 | E63: =_xlfn.AGGREGATE(1,6,E61:E62) -> -0.030356508 | F63: =_xlfn.AGGREGATE(1,6,F61:F62) -> -0.034825555 | G63: =_xlfn.AGGREGATE(1,6,G61:G62) -> -0.029785181 | H63: =_xlfn.AGGREGATE(1,6,H61:H62) -> -0.01746991

Sheet Non-GACS Deals
A1: Event_ID | B1: Bank | C1: Ticker | D1: Date_Quarter | E1: Date | F1: GBV_EUR_m | G1: NPE_Category | H1: Asset_Class | I1: Buyer | J1: Project_Name | K1: GACS | L1: Capital_Raise_Simultaneous | M1: Bank_NPL_Ratio | N1: Bank_CET1 | O1: Crisis_Period | P1: PwC_Source | Q1: Notes
A2: NG-001 | B2: UniCredit | C2: UCG | D2: 2015 Q1 | E2: 42046 | F2: 2400 | G2: Bad Loans | H2: Mixed Sec/Unsec | I2: Fortress & Prelios | J2: Platform sale + UCCMB | K2: No | O2: Yes | P2: PwC Jun 2016 p.23
A3: NG-002 | B3: UniCredit | C3: UCG | D3: 2015 Q2 | E3: 42185 | F3: 625 | G3: Bad Loans | H3: Unsecured | I3: PRA | K3: No | O3: Yes | P3: PwC Jun 2016 p.23
A4: NG-003 | B4: UniCredit | C4: UCG | D4: 2015 Q2 | E4: 42186 | F4: 205 | G4: Bad Loans | H4: Leasing | I4: Cerberus | K4: No | O4: Yes | P4: PwC Jun 2016 p.23
A5: NG-004 | B5: UniCredit | C5: UCG | D5: 2015 Q3 | E5: 42275 | F5: 1200 | G5: Bad Loans | H5: Mainly Unsecured | I5: Anacap | K5: No | O5: Yes | P5: PwC Jun 2016 p.23
A6: NG-005 | B6: UniCredit | C6: UCG | D6: 2015 Q4 | E6: 42355 | F6: 250 | G6: Bad Loans | H6: Mixed Sec/Unsec | I6: Cerberus | K6: No | O6: Yes | P6: PwC Jun 2016 p.23
A7: NG-006 | B7: MPS | C7: BMPS | D7: 2015 Q2 | E7: 42178 | F7: 1300 | G7: Bad Loans | H7: Consumer | I7: Banca IFIS/Cerberus | J7: Consum.it portfolio | K7: No | O7: Yes | P7: PwC Jun 2016 p.23
A8: NG-007 | B8: MPS | C8: BMPS | D8: 2015 Q4 | E8: 42366 | F8: 1700 | G8: Bad Loans | H8: Unsecured | I8: Deutsche Bank | K8: No | O8: Yes | P8: PwC Jun 2016 p.23
A9: NG-008 | B9: UniCredit | C9: UCG | D9: 2017 Q1 | E9: 42717 | F9: 17700 | G9: Bad Loans | H9: Mixed Sec/Unsec | I9: Fortress/PIMCO | J9: Project Fino (total incl. GACS) | K9: No | O9: Yes | P9: PwC Jul 2017 p.21
A10: NG-009 | B10: Intesa Sanpaolo | C10: ISP | D10: 2017 Q2 | E10: 42859 | F10: 2500 | G10: Bad Loans | H10: Mixed | I10: Christofferson Robb/Bayview | J10: Project Beyond the Clouds | K10: No | O10: Yes | P10: PwC Jul 2017 p.21
A11: NG-010 | B11: Banco BPM | C11: BAMI | D11: 2017 Q2 | E11: 42908 | F11: 750 | G11: Bad Loans | H11: n.a. | I11: Algebris Investments | J11: Project Rainbow | K11: No | O11: Yes | P11: PwC Jul 2017 p.21
A12: NG-011 | B12: Intesa Sanpaolo | C12: ISP | D12: 2018 Q2 | E12: 43206 | F12: 10800 | G12: Bad Loans | H12: Mainly Secured | I12: Intrum | J12: ISP-Intrum deal | K12: No | O12: No | P12: PwC Dec 2019 p.52
A13: NG-012 | B13: Banco BPM | C13: BAMI | D13: 2018 Q2 | E13: 43270 | F13: 5100 | G13: Bad Loans | H13: Mainly Secured | I13: CRC | K13: No | O13: No | P13: PwC Dec 2019 p.52
A14: NG-013 | B14: MPS | C14: BMPS | D14: 2018 Q3 | E14: 43497 | F14: 300 | G14: UtP | H14: Secured | I14: Confidential | K14: No | O14: No | P14: PwC Dec 2019 p.52
A15: NG-014 | B15: MPS | C15: BMPS | D15: 2018 Q3 | E15: 43313 | F15: 135 | G15: NPE | H15: Secured | I15: SC Lowy | K15: No | O15: No | P15: PwC Dec 2019 p.52
A16: NG-015 | B16: MPS | C16: BMPS | D16: 2018 Q4 | E16: 43497 | F16: 2200 | G16: Bad Loans | H16: Unsecured | I16: IFIS NPL/CF/Balbec | K16: No | O16: No | P16: PwC Dec 2019 p.51
A17: NG-016 | B17: MPS | C17: BMPS | D17: 2018 Q4 | E17: 43454 | F17: 900 | G17: Bad Loans | H17: Mixed Sec/Unsec | I17: Bain Capital Credit | J17: Project Morgana (leasing) | K17: No | O17: No | P17: PwC Dec 2019 p.51
A18: NG-017 | B18: MPS | C18: BMPS | D18: 2018 Q1 | E18: 43190 | F18: 100 | G18: UtP | H18: Secured | I18: Confidential | K18: No | O18: No | P18: PwC Dec 2019 p.52
A19: NG-018 | B19: MPS | C19: BMPS | D19: 2018 Q2 | E19: 43281 | F19: 500 | G19: UtP | H19: Secured | I19: Confidential | J19: Aggregate single names | K19: No | O19: No | P19: PwC Dec 2019 p.52
A20: NG-019 | B20: BPER | C20: BPE | D20: 2018 Q4 | E20: 43454 | F20: 200 | G20: Bad Loans | H20: Mixed Sec/Unsec | I20: MBCredit Solutions | K20: No | O20: No | P20: PwC Dec 2019 p.51 | X20: Event ID | Y20: Verified Date | Z20: Verified GBV (€m) | AA20: Notes
A21: NG-020 | B21: UniCredit | C21: UCG | D21: 2018 Q4 | E21: 43445 | F21: 642 | G21: Bad Loans | H21: Secured | I21: Fortress | K21: No | O21: No | P21: PwC Dec 2019 p.51 | X21: NG-020 | Y21: 43445 | Z21: 642 | AA21: Correct. Portfolio sold to Fortress.
A22: NG-021 | B22: UniCredit | C22: UCG | D22: 2018 Q4 | E22: 43454 | F22: 449 | G22: Bad Loans | H22: Unsecured | I22: J-Invest & illimity | K22: No | O22: No | P22: PwC Dec 2019 p.51 | X22: NG-021 | Y22: 43454 | Z22: 450 | AA22: Correct (rounded from 449). Sold to J-Invest and illimity.
A23: NG-022 | B23: UniCredit | C23: UCG | D23: 2018 Q4 | E23: 43462 | F23: 170 | G23: Bad Loans | H23: Unsecured | I23: Guber | K23: No | O23: No | P23: PwC Dec 2019 p.51 | X23: NG-022 | Y23: 43462 | Z23: 170 | AA23: Correct. Sold to Guber Banca.
A24: NG-023 | B24: UniCredit | C24: UCG | D24: 2018 Q3 | E24: 43371 | F24: 1090 | G24: NPE | H24: Unsecured | I24: IFIS NPL | K24: No | O24: No | P24: PwC Dec 2019 p.51 | X24: NG-023 | Y24: 43371 | Z24: 1090 | AA24: Correct. Consumer and credit card loans to IFIS.
A25: NG-024 | B25: UniCredit | C25: UCG | D25: 2018 Q3 | E25: 43315 | F25: 537 | G25: NPE | H25: Mixed Sec/Unsec | I25: Banca IFIS | K25: No | O25: No | P25: PwC Dec 2019 p.51 | X25: NG-024 | Y25: 43315 | Z25: 537 | AA25: Adjustment. Official announcement was Aug 3, not Aug 31.
A26: NG-025 | B26: UniCredit | C26: UCG | D26: 2018 Q2 | E26: 43280 | F26: 124 | G26: NPE | H26: Unsecured | I26: MBCredit Solutions | K26: No | O26: No | P26: PwC Dec 2019 p.52 | X26: NG-025 | Y26: 43280 | Z26: 124 | AA26: Correct. Small unsecured portfolio to MBCredit.
A27: NG-026 | B27: UniCredit | C27: UCG | D27: 2019 Q4 | E27: 43818 | F27: 1039 | G27: Bad Loans | H27: Unsecured | I27: Confidential | K27: No | O27: No | P27: PwC Dec 2019 p.50 | X27: NG-026 | Y27: 43818 | Z27: 1039 | AA27: Correct. Major unsecured bad loan disposal.
A28: NG-027 | B28: UniCredit | C28: UCG | D28: 2019 Q3 | E28: 43734 | F28: 1100 | G28: Bad Loans | H28: Unsecured | I28: SPF Investment Mgmt | K28: No | O28: No | P28: PwC Dec 2019 p.50 | X28: NG-027 | Y28: 43734 | Z28: 1100 | AA28: Correct. Sold to SPF Investment Management.
A29: NG-028 | B29: UniCredit | C29: UCG | D29: 2019 Q3 | E29: 43735 | F29: 664 | G29: Bad Loans | H29: Secured | I29: illimity | K29: No | O29: No | P29: PwC Dec 2019 p.50 | X29: NG-028 | Y29: 43735 | Z29: 664 | AA29: Correct. Real estate secured portfolio to illimity.
A30: NG-029 | B30: UniCredit | C30: UCG | D30: 2019 Q3 | E30: 43738 | F30: 375 | G30: Bad Loans | H30: Mainly Unsecured | I30: n.a. | K30: No | O30: No | P30: PwC Dec 2019 p.50 | X30: NG-029 | Y30: 43738 | Z30: 375 | AA30: Correct. Part of the "Sandokan" series of disposals.
A31: NG-030 | B31: UniCredit | C31: UCG | D31: 2019 Q3 | E31: 43812 | F31: 240 | G31: Bad Loans | H31: Unsecured | I31: illimity | K31: No | O31: No | P31: PwC Dec 2019 p.50 | X31: NG-030 | Y31: 43812 | Z31: 240 | AA31: Adjustment. This specific deal with illimity was announced Dec 13.
A32: NG-031 | B32: UniCredit | C32: UCG | D32: 2019 Q3 | E32: 43804 | F32: 210 | G32: Bad Loans | H32: Unsecured | I32: Guber & Barclays | K32: No | O32: No | P32: PwC Dec 2019 p.50 | X32: NG-031 | Y32: 43804 | Z32: 210 | AA32: Correct. Announced during the 2019-2023 Strategic Plan rollout.
A33: NG-032 | B33: Intesa Sanpaolo | C33: ISP | D33: 2019 Q3 | E33: 43733 | F33: 3000 | G33: UtP | H33: Mixed Sec/Unsec | I33: DK / Prelios | J33: Project M | K33: No | O33: No | P33: PwC Dec 2019 p.50
A34: NG-033 | B34: Intesa Sanpaolo | C34: ISP | D34: 2019 Q1 | E34: 43552 | F34: 187 | G34: NPE | H34: Secured | I34: WRM | K34: No | O34: No | P34: PwC Dec 2019 p.50
A35: NG-034 | B35: MPS | C35: BMPS | D35: 2019 Q3 | E35: 43738 | F35: 455 | G35: UtP | H35: Secured | I35: Cerberus | K35: No | O35: No | P35: PwC Dec 2019 p.50
A36: NG-035 | B36: MPS | C36: BMPS | D36: 2019 Q3 | E36: 43677 | F36: 450 | G36: UtP | H36: Mainly Unsecured | I36: illimity | K36: No | O36: No | P36: PwC Dec 2019 p.50
A37: NG-036 | B37: MPS | C37: BMPS | D37: 2019 Q3 | E37: 43677 | F37: 240 | G37: Bad Loans | H37: Mixed Sec/Unsec | I37: illimity | K37: No | O37: No | P37: PwC Dec 2019 p.50
A38: NG-037 | B38: MPS | C38: BMPS | D38: 2019 Q3 | E38: 43690 | F38: 202 | G38: UtP | H38: Mainly Secured | I38: Unknown | K38: No | O38: No | P38: PwC Dec 2019 p.50
A39: NG-038 | B39: MPS | C39: BMPS | D39: 2019 Q3 | E39: 43690 | F39: 137 | G39: Bad Loans | H39: Mixed Sec/Unsec | I39: Unknown | K39: No | O39: No | P39: PwC Dec 2019 p.50
A40: NG-039 | B40: MPS | C40: BMPS | D40: 2019 Q3 | E40: 43614 | F40: 130 | G40: UtP | H40: Secured | I40: BofA Merrill Lynch | K40: No | O40: No | P40: PwC Dec 2019 p.50
A41: NG-040 | B41: Banco BPM | C41: BAMI | D41: 2019 Q2 | E41: 43572 | F41: 650 | G41: Bad Loans | H41: Secured | I41: illimity | K41: No | O41: No | P41: PwC Dec 2019 p.50
A42: NG-041 | B42: BPER | C42: BPE | D42: 2019 Q1 | E42: 43504 | F42: 1300 | G42: Bad Loans | H42: Mainly Unsecured | I42: UnipolReC | K42: No | O42: No | P42: PwC Dec 2019 p.50
A43: NG-042 | B43: UniCredit | C43: UCG | D43: 2020 Q1 | E43: 43867 | F43: 115 | G43: Bad Loans | H43: Secured | I43: illimity | K43: No | O43: No | P43: PwC Dec 2021 p.15
A44: NG-043 | B44: UniCredit | C44: UCG | D44: 2020 Q3 | E44: 44034 | F44: 840 | G44: Bad Loans | H44: Unsecured | I44: IFIS NPL/Guber/Barclays | K44: No | O44: No | P44: PwC Dec 2021 p.15
A45: NG-044 | B45: UniCredit | C45: UCG | D45: 2020 Q3 | E45: 44033 | F45: 702 | G45: Bad Loans | H45: Unsecured | I45: illimity/Guber/Barclays | K45: No | O45: No | P45: PwC Dec 2021 p.15
... A69: NG-068 | B69: BPER | C69: BPE | D69: 2022 Q3 | E69: 44777 | F69: 1500 | G69: Bad Loans | H69: Mixed Sec/Unsec | I69: Gardant | K69: No | O69: No | P69: PwC Dec 2023 p.17
B72: {=_xlfn.UNIQUE(C2:C69)} -> UCG | C72: =COUNTIF($C$1:$C$69,B72) -> 27
B73: BMPS | C73: =COUNTIF($C$1:$C$69,B73) -> 19
B74: ISP | C74: =COUNTIF($C$1:$C$69,B74) -> 11
B75: BAMI | C75: =COUNTIF($C$1:$C$69,B75) -> 5
B76: BPE | C76: =COUNTIF($C$1:$C$69,B76) -> 6

Sheet Non-GACS Analysis
B1: Company | C1: Ticker | D1: Count
B2: UniCredit | C2: UCG | D2: 27
B3: MPS | C3: BMPS | D3: 19
B4: Intesa Sanpaolo | C4: ISP | D4: 11
B5: Banco BPM | C5: BAMI | D5: 5
B6: BPER | C6: BPE | D6: 6
B8: UCG | D8: Price on event day | E8: Pfm 1 day | F8: Pfm next three days | G8: Pfm 1 week | H8: Pfm 1 month
C9: 42046 | D9: =IF(SUM(_xldudf_WISEPRICE($B$8 & ".MI", "Close",, TEXT(WORKDAY($C9+1,-1), "yyyy-mm-dd"), TEXT(WORKDAY($C9+1,-1), "yyyy-mm-dd")))=0, "/", SUM(_xldudf_WISEPRICE($B$8 & ".MI", "Close",, TEXT(WORKDAY($C9+1,-1), "yyyy-mm-dd"), TEXT(WORKDAY($C9+1,-1), "yyyy-mm-dd")))) -> 26.55 | E9: =IFERROR(IF(SUM(_xldudf_WISEPRICE($B$8 & ".MI", "Close",, TEXT(WORKDAY(WORKDAY($C9+1,-1), 1), "yyyy-mm-dd"), TEXT(WORKDAY(WORKDAY($C9+1,-1), 1), "yyyy-mm-dd")))=0, "/", (SUM(_xldudf_WISEPRICE($B$8 & ".MI", "Close",, TEXT(WORKDAY(WORKDAY($C9+1,-1), 1), "yyyy-mm-dd"), TEXT(WORKDAY(WORKDAY($C9+1,-1), 1), "yyyy-mm-dd"))) / $D9) - 1), "/") -> 0.0056497175 | F9: =IFERROR(IF(SUM(_xldudf_WISEPRICE($B$8 & ".MI", "Close",, TEXT(WORKDAY(WORKDAY($C9+1,-1), 3), "yyyy-mm-dd"), TEXT(WORKDAY(WORKDAY($C9+1,-1), 3), "yyyy-mm-dd")))=0, "/", (SUM(_xldudf_WISEPRICE($B$8 & ".MI", "Close",, TEXT(WORKDAY(WORKDAY($C9+1,-1), 3), "yyyy-mm-dd"), TEXT(WORKDAY(WORKDAY($C9+1,-1), 3), "yyyy-mm-dd"))) / $D9) - 1), "/") -> 0.047457627 | G9: =IFERROR(IF(SUM(_xldudf_WISEPRICE($B$8 & ".MI", "Close",, TEXT(WORKDAY(WORKDAY($C9+1,-1), 5), "yyyy-mm-dd"), TEXT(WORKDAY(WORKDAY($C9+1,-1), 5), "yyyy-mm-dd")))=0, "/", (SUM(_xldudf_WISEPRICE($B$8 & ".MI", "Close",, TEXT(WORKDAY(WORKDAY($C9+1,-1), 5), "yyyy-mm-dd"), TEXT(WORKDAY(WORKDAY($C9+1,-1), 5), "yyyy-mm-dd"))) / $D9) - 1), "/") -> 0.083239171 | H9: =IFERROR(IF(SUM(_xldudf_WISEPRICE($B$8 & ".MI", "Close",, TEXT(WORKDAY(EDATE(WORKDAY($C9+1,-1), 1)-1, 1), "yyyy-mm-dd"), TEXT(WORKDAY(EDATE(WORKDAY($C9+1,-1), 1)-1, 1), "yyyy-mm-dd")))=0, "/", (SUM(_xldudf_WISEPRICE($B$8 & ".MI", "Close",, TEXT(WORKDAY(EDATE(WORKDAY($C9+1,-1), 1)-1, 1), "yyyy-mm-dd"), TEXT(WORKDAY(EDATE(WORKDAY($C9+1,-1), 1)-1, 1), "yyyy-mm-dd"))) / $D9) - 1), "/") -> 0.1559322
C10: 42185 | D10: =IF(SUM(_xldudf_WISEPRICE($B$8 & ".MI", "Close",, TEXT(WORKDAY($C10+1,-1), "yyyy-mm-dd"), TEXT(WORKDAY($C10+1,-1), "yyyy-mm-dd")))=0, "/", SUM(_xldudf_WISEPRICE($B$8 & ".MI", "Close",, TEXT(WORKDAY($C10+1,-1), "yyyy-mm-dd"), TEXT(WORKDAY($C10+1,-1), "yyyy-mm-dd")))) -> 30.19 | E10: =IFERROR(IF(SUM(_xldudf_WISEPRICE($B$8 & ".MI", "Close",, TEXT(WORKDAY(WORKDAY($C10+1,-1), 1), "yyyy-mm-dd"), TEXT(WORKDAY(WORKDAY($C10+1,-1), 1), "yyyy-mm-dd")))=0, "/", (SUM(_xldudf_WISEPRICE($B$8 & ".MI", "Close",, TEXT(WORKDAY(WORKDAY($C10+1,-1), 1), "yyyy-mm-dd"), TEXT(WORKDAY(WORKDAY($C10+1,-1), 1), "yyyy-mm-dd"))) / $D10) - 1), "/") -> 0.033786022 | F10: =IFERROR(IF(SUM(_xldudf_WISEPRICE($B$8 & ".MI", "Close",, TEXT(WORKDAY(WORKDAY($C10+1,-1), 3), "yyyy-mm-dd"), TEXT(WORKDAY(WORKDAY($C10+1,-1), 3), "yyyy-mm-dd")))=0, "/", (SUM(_xldudf_WISEPRICE($B$8 & ".MI", "Close",, TEXT(WORKDAY(WORKDAY($C10+1,-1), 3), "yyyy-mm-dd"), TEXT(WORKDAY(WORKDAY($C10+1,-1), 3), "yyyy-mm-dd"))) / $D10) - 1), "/") -> 0.0039748261 | G10: =IFERROR(IF(SUM(_xldudf_WISEPRICE($B$8 & ".MI", "Close",, TEXT(WORKDAY(WORKDAY($C10+1,-1), 5), "yyyy-mm-dd"), TEXT(WORKDAY(WORKDAY($C10+1,-1), 5), "yyyy-mm-dd")))=0, "/", (SUM(_xldudf_WISEPRICE($B$8 & ".MI", "Close",, TEXT(WORKDAY(WORKDAY($C10+1,-1), 5), "yyyy-mm-dd"), TEXT(WORKDAY(WORKDAY($C10+1,-1), 5), "yyyy-mm-dd"))) / $D10) - 1), "/") -> -0.093739649 | H10: =IFERROR(IF(SUM(_xldudf_WISEPRICE($B$8 & ".MI", "Close",, TEXT(WORKDAY(EDATE(WORKDAY($C10+1,-1), 1)-1, 1), "yyyy-mm-dd"), TEXT(WORKDAY(EDATE(WORKDAY($C10+1,-1), 1)-1, 1), "yyyy-mm-dd")))=0, "/", (SUM(_xldudf_WISEPRICE($B$8 & ".MI", "Close",, TEXT(WORKDAY(EDATE(WORKDAY($C10+1,-1), 1)-1, 1), "yyyy-mm-dd"), TEXT(WORKDAY(EDATE(WORKDAY($C10+1,-1), 1)-1, 1), "yyyy-mm-dd"))) / $D10) - 1), "/") -> -0.0092745942
C11: 42186 | D11: =IF(SUM(_xldudf_WISEPRICE($B$8 & ".MI", "Close",, TEXT(WORKDAY($C11+1,-1), "yyyy-mm-dd"), TEXT(WORKDAY($C11+1,-1), "yyyy-mm-dd")))=0, "/", SUM(_xldudf_WISEPRICE($B$8 & ".MI", "Close",, TEXT(WORKDAY($C11+1,-1), "yyyy-mm-dd"), TEXT(WORKDAY($C11+1,-1), "yyyy-mm-dd")))) -> 31.21 | E11: =IFERROR(IF(SUM(_xldudf_WISEPRICE($B$8 & ".MI", "Close",, TEXT(WORKDAY(WORKDAY($C11+1,-1), 1), "yyyy-mm-dd"), TEXT(WORKDAY(WORKDAY($C11+1,-1), 1), "yyyy-mm-dd")))=0, "/", (SUM(_xldudf_WISEPRICE($B$8 & ".MI", "Close",, TEXT(WORKDAY(WORKDAY($C11+1,-1), 1), "yyyy-mm-dd"), TEXT(WORKDAY(WORKDAY($C11+1,-1), 1), "yyyy-mm-dd"))) / $D11) - 1), "/") -> -0.019224607 | F11: =IFERROR(IF(SUM(_xldudf_WISEPRICE($B$8 & ".MI", "Close",, TEXT(WORKDAY(WORKDAY($C11+1,-1), 3), "yyyy-mm-dd"), TEXT(WORKDAY(WORKDAY($C11+1,-1), 3), "yyyy-mm-dd")))=0, "/", (SUM(_xldudf_WISEPRICE($B$8 & ".MI", "Close",, TEXT(WORKDAY(WORKDAY($C11+1,-1), 3), "yyyy-mm-dd"), TEXT(WORKDAY(WORKDAY($C11+1,-1), 3), "yyyy-mm-dd"))) / $D11) - 1), "/") -> -0.088112784 | G11: =IFERROR(IF(SUM(_xldudf_WISEPRICE($B$8 & ".MI", "Close",, TEXT(WORKDAY(WORKDAY($C11+1,-1), 5), "yyyy-mm-dd"), TEXT(WORKDAY(WORKDAY($C11+1,-1), 5), "yyyy-mm-dd")))=0, "/", (SUM(_xldudf_WISEPRICE($B$8 & ".MI", "Close",, TEXT(WORKDAY(WORKDAY($C11+1,-1), 5), "yyyy-mm-dd"), TEXT(WORKDAY(WORKDAY($C11+1,-1), 5), "yyyy-mm-dd"))) / $D11) - 1), "/") -> -0.093880167 | H11: =IFERROR(IF(SUM(_xldudf_WISEPRICE($B$8 & ".MI", "Close",, TEXT(WORKDAY(EDATE(WORKDAY($C11+1,-1), 1)-1, 1), "yyyy-mm-dd"), TEXT(WORKDAY(EDATE(WORKDAY($C11+1,-1), 1)-1, 1), "yyyy-mm-dd")))=0, "/", (SUM(_xldudf_WISEPRICE($B$8 & ".MI", "Close",, TEXT(WORKDAY(EDATE(WORKDAY($C11+1,-1), 1)-1, 1), "yyyy-mm-dd"), TEXT(WORKDAY(EDATE(WORKDAY($C11+1,-1), 1)-1, 1), "yyyy-mm-dd"))) / $D11) - 1), "/") -> -0.030438962
C12: 42275 | D12: =IF(SUM(_xldudf_WISEPRICE($B$8 & ".MI", "Close",, TEXT(WORKDAY($C12+1,-1), "yyyy-mm-dd"), TEXT(WORKDAY($C12+1,-1), "yyyy-mm-dd")))=0, "/", SUM(_xldudf_WISEPRICE($B$8 & ".MI", "Close",, TEXT(WORKDAY($C12+1,-1), "yyyy-mm-dd"), TEXT(WORKDAY($C12+1,-1), "yyyy-mm-dd")))) -> 26.98 | E12: =IFERROR(IF(SUM(_xldudf_WISEPRICE($B$8 & ".MI", "Close",, TEXT(WORKDAY(WORKDAY($C12+1,-1), 1), "yyyy-mm-dd"), TEXT(WORKDAY(WORKDAY($C12+1,-1), 1), "yyyy-mm-dd")))=0, "/", (SUM(_xldudf_WISEPRICE($B$8 & ".MI", "Close",, TEXT(WORKDAY(WORKDAY($C12+1,-1), 1), "yyyy-mm-dd"), TEXT(WORKDAY(WORKDAY($C12+1,-1), 1), "yyyy-mm-dd"))) / $D12) - 1), "/") -> 0.00074128984 | F12: =IFERROR(IF(SUM(_xldudf_WISEPRICE($B$8 & ".MI", "Close",, TEXT(WORKDAY(WORKDAY($C12+1,-1), 3), "yyyy-mm-dd"), TEXT(WORKDAY(WORKDAY($C12+1,-1), 3), "yyyy-mm-dd")))=0, "/", (SUM(_xldudf_WISEPRICE($B$8 & ".MI", "Close",, TEXT(WORKDAY(WORKDAY($C12+1,-1), 3), "yyyy-mm-dd"), TEXT(WORKDAY(WORKDAY($C12+1,-1), 3), "yyyy-mm-dd"))) / $D12) - 1), "/") -> 0.038176427 | G12: =IFERROR(IF(SUM(_xldudf_WISEPRICE($B$8 & ".MI", "Close",, TEXT(WORKDAY(WORKDAY($C12+1,-1), 5), "yyyy-mm-dd"), TEXT(WORKDAY(WORKDAY($C12+1,-1), 5), "yyyy-mm-dd")))=0, "/", (SUM(_xldudf_WISEPRICE($B$8 & ".MI", "Close",, TEXT(WORKDAY(WORKDAY($C12+1,-1), 5), "yyyy-mm-dd"), TEXT(WORKDAY(WORKDAY($C12+1,-1), 5), "yyyy-mm-dd"))) / $D12) - 1), "/") -> 0.078947368 | H12: =IFERROR(IF(SUM(_xldudf_WISEPRICE($B$8 & ".MI", "Close",, TEXT(WORKDAY(EDATE(WORKDAY($C12+1,-1), 1)-1, 1), "yyyy-mm-dd"), TEXT(WORKDAY(EDATE(WORKDAY($C12+1,-1), 1)-1, 1), "yyyy-mm-dd")))=0, "/", (SUM(_xldudf_WISEPRICE($B$8 & ".MI", "Close",, TEXT(WORKDAY(EDATE(WORKDAY($C12+1,-1), 1)-1, 1), "yyyy-mm-dd"), TEXT(WORKDAY(EDATE(WORKDAY($C12+1,-1), 1)-1, 1), "yyyy-mm-dd"))) / $D12) - 1), "/") -> 0.11971831
C13: 42355 | D13: =IF(SUM(_xldudf_WISEPRICE($B$8 & ".MI", "Close",, TEXT(WORKDAY($C13+1,-1), "yyyy-mm-dd"), TEXT(WORKDAY($C13+1,-1), "yyyy-mm-dd")))=0, "/", SUM(_xldudf_WISEPRICE($B$8 & ".MI", "Close",, TEXT(WORKDAY($C13+1,-1), "yyyy-mm-dd"), TEXT(WORKDAY($C13+1,-1), "yyyy-mm-dd")))) -> 26.08 | E13: =IFERROR(IF(SUM(_xldudf_WISEPRICE($B$8 & ".MI", "Close",, TEXT(WORKDAY(WORKDAY($C13+1,-1), 1), "yyyy-mm-dd"), TEXT(WORKDAY(WORKDAY($C13+1,-1), 1), "yyyy-mm-dd")))=0, "/", (SUM(_xldudf_WISEPRICE($B$8 & ".MI", "Close",, TEXT(WORKDAY(WORKDAY($C13+1,-1), 1), "yyyy-mm-dd"), TEXT(WORKDAY(WORKDAY($C13+1,-1), 1), "yyyy-mm-dd"))) / $D13) - 1), "/") -> -0.018404908 | F13: =IFERROR(IF(SUM(_xldudf_WISEPRICE($B$8 & ".MI", "Close",, TEXT(WORKDAY(WORKDAY($C13+1,-1), 3), "yyyy-mm-dd"), TEXT(WORKDAY(WORKDAY($C13+1,-1), 3), "yyyy-mm-dd")))=0, "/", (SUM(_xldudf_WISEPRICE($B$8 & ".MI", "Close",, TEXT(WORKDAY(WORKDAY($C13+1,-1), 3), "yyyy-mm-dd"), TEXT(WORKDAY(WORKDAY($C13+1,-1), 3), "yyyy-mm-dd"))) / $D13) - 1), "/") -> -0.014570552 | G13: =IFERROR(IF(SUM(_xldudf_WISEPRICE($B$8 & ".MI", "Close",, TEXT(WORKDAY(WORKDAY($C13+1,-1), 5), "yyyy-mm-dd"), TEXT(WORKDAY(WORKDAY($C13+1,-1), 5), "yyyy-mm-dd")))=0, "/", (SUM(_xldudf_WISEPRICE($B$8 & ".MI", "Close",, TEXT(WORKDAY(WORKDAY($C13+1,-1), 5), "yyyy-mm-dd"), TEXT(WORKDAY(WORKDAY($C13+1,-1), 5), "yyyy-mm-dd"))) / $D13) - 1), "/") -> / | H13: =IFERROR(IF(SUM(_xldudf_WISEPRICE($B$8 & ".MI", "Close",, TEXT(WORKDAY(EDATE(WORKDAY($C13+1,-1), 1)-1, 1), "yyyy-mm-dd"), TEXT(WORKDAY(EDATE(WORKDAY($C13+1,-1), 1)-1, 1), "yyyy-mm-dd")))=0, "/", (SUM(_xldudf_WISEPRICE($B$8 & ".MI", "Close",, TEXT(WORKDAY(EDATE(WORKDAY($C13+1,-1), 1)-1, 1), "yyyy-mm-dd"), TEXT(WORKDAY(EDATE(WORKDAY($C13+1,-1), 1)-1, 1), "yyyy-mm-dd"))) / $D13) - 1), "/") -> -0.20053681
C14: 42717 | D14: =IF(SUM(_xldudf_WISEPRICE($B$8 & ".MI", "Close",, TEXT(WORKDAY($C14+1,-1), "yyyy-mm-dd"), TEXT(WORKDAY($C14+1,-1), "yyyy-mm-dd")))=0, "/", SUM(_xldudf_WISEPRICE($B$8 & ".MI", "Close",, TEXT(WORKDAY($C14+1,-1), "yyyy-mm-dd"), TEXT(WORKDAY($C14+1,-1), "yyyy-mm-dd")))) -> 14.08 | E14: =IFERROR(IF(SUM(_xldudf_WISEPRICE($B$8 & ".MI", "Close",, TEXT(WORKDAY(WORKDAY($C14+1,-1), 1), "yyyy-mm-dd"), TEXT(WORKDAY(WORKDAY($C14+1,-1), 1), "yyyy-mm-dd")))=0, "/", (SUM(_xldudf_WISEPRICE($B$8 & ".MI", "Close",, TEXT(WORKDAY(WORKDAY($C14+1,-1), 1), "yyyy-mm-dd"), TEXT(WORKDAY(WORKDAY($C14+1,-1), 1), "yyyy-mm-dd"))) / $D14) - 1), "/") -> -0.063920455 | F14: =IFERROR(IF(SUM(_xldudf_WISEPRICE($B$8 & ".MI", "Close",, TEXT(WORKDAY(WORKDAY($C14+1,-1), 3), "yyyy-mm-dd"), TEXT(WORKDAY(WORKDAY($C14+1,-1), 3), "yyyy-mm-dd")))=0, "/", (SUM(_xldudf_WISEPRICE($B$8 & ".MI", "Close",, TEXT(WORKDAY(WORKDAY($C14+1,-1), 3), "yyyy-mm-dd"), TEXT(WORKDAY(WORKDAY($C14+1,-1), 3), "yyyy-mm-dd"))) / $D14) - 1), "/") -> 0.022017045 | G14: =IFERROR(IF(SUM(_xldudf_WISEPRICE($B$8 & ".MI", "Close",, TEXT(WORKDAY(WORKDAY($C14+1,-1), 5), "yyyy-mm-dd"), TEXT(WORKDAY(WORKDAY($C14+1,-1), 5), "yyyy-mm-dd")))=0, "/", (SUM(_xldudf_WISEPRICE($B$8 & ".MI", "Close",, TEXT(WORKDAY(WORKDAY($C14+1,-1), 5), "yyyy-mm-dd"), TEXT(WORKDAY(WORKDAY($C14+1,-1), 5), "yyyy-mm-dd"))) / $D14) - 1), "/") -> -0.0042613636 | H14: =IFERROR(IF(SUM(_xldudf_WISEPRICE($B$8 & ".MI", "Close",, TEXT(WORKDAY(EDATE(WORKDAY($C14+1,-1), 1)-1, 1), "yyyy-mm-dd"), TEXT(WORKDAY(EDATE(WORKDAY($C14+1,-1), 1)-1, 1), "yyyy-mm-dd")))=0, "/", (SUM(_xldudf_WISEPRICE($B$8 & ".MI", "Close",, TEXT(WORKDAY(EDATE(WORKDAY($C14+1,-1), 1)-1, 1), "yyyy-mm-dd"), TEXT(WORKDAY(EDATE(WORKDAY($C14+1,-1), 1)-1, 1), "yyyy-mm-dd"))) / $D14) - 1), "/") -> -0.049715909
C15: 43280 | D15: =IF(SUM(_xldudf_WISEPRICE($B$8 & ".MI", "Close",, TEXT(WORKDAY($C15+1,-1), "yyyy-mm-dd"), TEXT(WORKDAY($C15+1,-1), "yyyy-mm-dd")))=0, "/", SUM(_xldudf_WISEPRICE($B$8 & ".MI", "Close",, TEXT(WORKDAY($C15+1,-1), "yyyy-mm-dd"), TEXT(WORKDAY($C15+1,-1), "yyyy-mm-dd")))) -> 14.3 | E15: =IFERROR(IF(SUM(_xldudf_WISEPRICE($B$8 & ".MI", "Close",, TEXT(WORKDAY(WORKDAY($C15+1,-1), 1), "yyyy-mm-dd"), TEXT(WORKDAY(WORKDAY($C15+1,-1), 1), "yyyy-mm-dd")))=0, "/", (SUM(_xldudf_WISEPRICE($B$8 & ".MI", "Close",, TEXT(WORKDAY(WORKDAY($C15+1,-1), 1), "yyyy-mm-dd"), TEXT(WORKDAY(WORKDAY($C15+1,-1), 1), "yyyy-mm-dd"))) / $D15) - 1), "/") -> -0.0041958042 | F15: =IFERROR(IF(SUM(_xldudf_WISEPRICE($B$8 & ".MI", "Close",, TEXT(WORKDAY(WORKDAY($C15+1,-1), 3), "yyyy-mm-dd"), TEXT(WORKDAY(WORKDAY($C15+1,-1), 3), "yyyy-mm-dd")))=0, "/", (SUM(_xldudf_WISEPRICE($B$8 & ".MI", "Close",, TEXT(WORKDAY(WORKDAY($C15+1,-1), 3), "yyyy-mm-dd"), TEXT(WORKDAY(WORKDAY($C15+1,-1), 3), "yyyy-mm-dd"))) / $D15) - 1), "/") -> 0.023776224 | G15: =IFERROR(IF(SUM(_xldudf_WISEPRICE($B$8 & ".MI", "Close",, TEXT(WORKDAY(WORKDAY($C15+1,-1), 5), "yyyy-mm-dd"), TEXT(WORKDAY(WORKDAY($C15+1,-1), 5), "yyyy-mm-dd")))=0, "/", (SUM(_xldudf_WISEPRICE($B$8 & ".MI", "Close",, TEXT(WORKDAY(WORKDAY($C15+1,-1), 5), "yyyy-mm-dd"), TEXT(WORKDAY(WORKDAY($C15+1,-1), 5), "yyyy-mm-dd"))) / $D15) - 1), "/") -> 0.027272727 | H15: =IFERROR(IF(SUM(_xldudf_WISEPRICE($B$8 & ".MI", "Close",, TEXT(WORKDAY(EDATE(WORKDAY($C15+1,-1), 1)-1, 1), "yyyy-mm-dd"), TEXT(WORKDAY(EDATE(WORKDAY($C15+1,-1), 1)-1, 1), "yyyy-mm-dd")))=0, "/", (SUM(_xldudf_WISEPRICE($B$8 & ".MI", "Close",, TEXT(WORKDAY(EDATE(WORKDAY($C15+1,-1), 1)-1, 1), "yyyy-mm-dd"), TEXT(WORKDAY(EDATE(WORKDAY($C15+1,-1), 1)-1, 1), "yyyy-mm-dd"))) / $D15) - 1), "/") -> 0.048951049
C16: 43315 | D16: =IF(SUM(_xldudf_WISEPRICE($B$8 & ".MI", "Close",, TEXT(WORKDAY($C16+1,-1), "yyyy-mm-dd"), TEXT(WORKDAY($C16+1,-1), "yyyy-mm-dd")))=0, "/", SUM(_xldudf_WISEPRICE($B$8 & ".MI", "Close",, TEXT(WORKDAY($C16+1,-1), "yyyy-mm-dd"), TEXT(WORKDAY($C16+1,-1), "yyyy-mm-dd")))) -> 14.39 | E16: =IFERROR(IF(SUM(_xldudf_WISEPRICE($B$8 & ".MI", "Close",, TEXT(WORKDAY(WORKDAY($C16+1,-1), 1), "yyyy-mm-dd"), TEXT(WORKDAY(WORKDAY($C16+1,-1), 1), "yyyy-mm-dd")))=0, "/", (SUM(_xldudf_WISEPRICE($B$8 & ".MI", "Close",, TEXT(WORKDAY(WORKDAY($C16+1,-1), 1), "yyyy-mm-dd"), TEXT(WORKDAY(WORKDAY($C16+1,-1), 1), "yyyy-mm-dd"))) / $D16) - 1), "/") -> -0.00069492703 | F16: =IFERROR(IF(SUM(_xldudf_WISEPRICE($B$8 & ".MI", "Close",, TEXT(WORKDAY(WORKDAY($C16+1,-1), 3), "yyyy-mm-dd"), TEXT(WORKDAY(WORKDAY($C16+1,-1), 3), "yyyy-mm-dd")))=0, "/", (SUM(_xldudf_WISEPRICE($B$8 & ".MI", "Close",, TEXT(WORKDAY(WORKDAY($C16+1,-1), 3), "yyyy-mm-dd"), TEXT(WORKDAY(WORKDAY($C16+1,-1), 3), "yyyy-mm-dd"))) / $D16) - 1), "/") -> 0.024322446 | G16: =IFERROR(IF(SUM(_xldudf_WISEPRICE($B$8 & ".MI", "Close",, TEXT(WORKDAY(WORKDAY($C16+1,-1), 5), "yyyy-mm-dd"), TEXT(WORKDAY(WORKDAY($C16+1,-1), 5), "yyyy-mm-dd")))=0, "/", (SUM(_xldudf_WISEPRICE($B$8 & ".MI", "Close",, TEXT(WORKDAY(WORKDAY($C16+1,-1), 5), "yyyy-mm-dd"), TEXT(WORKDAY(WORKDAY($C16+1,-1), 5), "yyyy-mm-dd"))) / $D16) - 1), "/") -> -0.042390549 | H16: =IFERROR(IF(SUM(_xldudf_WISEPRICE($B$8 & ".MI", "Close",, TEXT(WORKDAY(EDATE(WORKDAY($C16+1,-1), 1)-1, 1), "yyyy-mm-dd"), TEXT(WORKDAY(EDATE(WORKDAY($C16+1,-1), 1)-1, 1), "yyyy-mm-dd")))=0, "/", (SUM(_xldudf_WISEPRICE($B$8 & ".MI", "Close",, TEXT(WORKDAY(EDATE(WORKDAY($C16+1,-1), 1)-1, 1), "yyyy-mm-dd"), TEXT(WORKDAY(EDATE(WORKDAY($C16+1,-1), 1)-1, 1), "yyyy-mm-dd"))) / $D16) - 1), "/") -> -0.13203614
C17: 43371 | D17: =IF(SUM(_xldudf_WISEPRICE($B$8 & ".MI", "Close",, TEXT(WORKDAY($C17+1,-1), "yyyy-mm-dd"), TEXT(WORKDAY($C17+1,-1), "yyyy-mm-dd")))=0, "/", SUM(_xldudf_WISEPRICE($B$8 & ".MI", "Close",, TEXT(WORKDAY($C17+1,-1), "yyyy-mm-dd"), TEXT(WORKDAY($C17+1,-1), "yyyy-mm-dd")))) -> 12.96 | E17: =IFERROR(IF(SUM(_xldudf_WISEPRICE($B$8 & ".MI", "Close",, TEXT(WORKDAY(WORKDAY($C17+1,-1), 1), "yyyy-mm-dd"), TEXT(WORKDAY(WORKDAY($C17+1,-1), 1), "yyyy-mm-dd")))=0, "/", (SUM(_xldudf_WISEPRICE($B$8 & ".MI", "Close",, TEXT(WORKDAY(WORKDAY($C17+1,-1), 1), "yyyy-mm-dd"), TEXT(WORKDAY(WORKDAY($C17+1,-1), 1), "yyyy-mm-dd"))) / $D17) - 1), "/") -> -0.023148148 | F17: =IFERROR(IF(SUM(_xldudf_WISEPRICE($B$8 & ".MI", "Close",, TEXT(WORKDAY(WORKDAY($C17+1,-1), 3), "yyyy-mm-dd"), TEXT(WORKDAY(WORKDAY($C17+1,-1), 3), "yyyy-mm-dd")))=0, "/", (SUM(_xldudf_WISEPRICE($B$8 & ".MI", "Close",, TEXT(WORKDAY(WORKDAY($C17+1,-1), 3), "yyyy-mm-dd"), TEXT(WORKDAY(WORKDAY($C17+1,-1), 3), "yyyy-mm-dd"))) / $D17) - 1), "/") -> -0.033950617 | G17: =IFERROR(IF(SUM(_xldudf_WISEPRICE($B$8 & ".MI", "Close",, TEXT(WORKDAY(WORKDAY($C17+1,-1), 5), "yyyy-mm-dd"), TEXT(WORKDAY(WORKDAY($C17+1,-1), 5), "yyyy-mm-dd")))=0, "/", (SUM(_xldudf_WISEPRICE($B$8 & ".MI", "Close",, TEXT(WORKDAY(WORKDAY($C17+1,-1), 5), "yyyy-mm-dd"), TEXT(WORKDAY(WORKDAY($C17+1,-1), 5), "yyyy-mm-dd"))) / $D17) - 1), "/") -> -0.042438272 | H17: =IFERROR(IF(SUM(_xldudf_WISEPRICE($B$8 & ".MI", "Close",, TEXT(WORKDAY(EDATE(WORKDAY($C17+1,-1), 1)-1, 1), "yyyy-mm-dd"), TEXT(WORKDAY(EDATE(WORKDAY($C17+1,-1), 1)-1, 1), "yyyy-mm-dd")))=0, "/", (SUM(_xldudf_WISEPRICE($B$8 & ".MI", "Close",, TEXT(WORKDAY(EDATE(WORKDAY($C17+1,-1), 1)-1, 1), "yyyy-mm-dd"), TEXT(WORKDAY(EDATE(WORKDAY($C17+1,-1), 1)-1, 1), "yyyy-mm-dd"))) / $D17) - 1), "/") -> -0.11651235
C18: 43445 | D18: =IF(SUM(_xldudf_WISEPRICE($B$8 & ".MI", "Close",, TEXT(WORKDAY($C18+1,-1), "yyyy-mm-dd"), TEXT(WORKDAY($C18+1,-1), "yyyy-mm-dd")))=0, "/", SUM(_xldudf_WISEPRICE($B$8 & ".MI", "Close",, TEXT(WORKDAY($C18+1,-1), "yyyy-mm-dd"), TEXT(WORKDAY($C18+1,-1), "yyyy-mm-dd")))) -> 10.54 | E18: =IFERROR(IF(SUM(_xldudf_WISEPRICE($B$8 & ".MI", "Close",, TEXT(WORKDAY(WORKDAY($C18+1,-1), 1), "yyyy-mm-dd"), TEXT(WORKDAY(WORKDAY($C18+1,-1), 1), "yyyy-mm-dd")))=0, "/", (SUM(_xldudf_WISEPRICE($B$8 & ".MI", "Close",, TEXT(WORKDAY(WORKDAY($C18+1,-1), 1), "yyyy-mm-dd"), TEXT(WORKDAY(WORKDAY($C18+1,-1), 1), "yyyy-mm-dd"))) / $D18) - 1), "/") -> 0.024667932 | F18: =IFERROR(IF(SUM(_xldudf_WISEPRICE($B$8 & ".MI", "Close",, TEXT(WORKDAY(WORKDAY($C18+1,-1), 3), "yyyy-mm-dd"), TEXT(WORKDAY(WORKDAY($C18+1,-1), 3), "yyyy-mm-dd")))=0, "/", (SUM(_xldudf_WISEPRICE($B$8 & ".MI", "Close",, TEXT(WORKDAY(WORKDAY($C18+1,-1), 3), "yyyy-mm-dd"), TEXT(WORKDAY(WORKDAY($C18+1,-1), 3), "yyyy-mm-dd"))) / $D18) - 1), "/") -> 0.025616698 | G18: =IFERROR(IF(SUM(_xldudf_WISEPRICE($B$8 & ".MI", "Close",, TEXT(WORKDAY(WORKDAY($C18+1,-1), 5), "yyyy-mm-dd"), TEXT(WORKDAY(WORKDAY($C18+1,-1), 5), "yyyy-mm-dd")))=0, "/", (SUM(_xldudf_WISEPRICE($B$8 & ".MI", "Close",, TEXT(WORKDAY(WORKDAY($C18+1,-1), 5), "yyyy-mm-dd"), TEXT(WORKDAY(WORKDAY($C18+1,-1), 5), "yyyy-mm-dd"))) / $D18) - 1), "/") -> -0.0066413662 | H18: =IFERROR(IF(SUM(_xldudf_WISEPRICE($B$8 & ".MI", "Close",, TEXT(WORKDAY(EDATE(WORKDAY($C18+1,-1), 1)-1, 1), "yyyy-mm-dd"), TEXT(WORKDAY(EDATE(WORKDAY($C18+1,-1), 1)-1, 1), "yyyy-mm-dd")))=0, "/", (SUM(_xldudf_WISEPRICE($B$8 & ".MI", "Close",, TEXT(WORKDAY(EDATE(WORKDAY($C18+1,-1), 1)-1, 1), "yyyy-mm-dd"), TEXT(WORKDAY(EDATE(WORKDAY($C18+1,-1), 1)-1, 1), "yyyy-mm-dd"))) / $D18) - 1), "/") -> 0.004743833
C19: 43454 | D19: =IF(SUM(_xldudf_WISEPRICE($B$8 & ".MI", "Close",, TEXT(WORKDAY($C19+1,-1), "yyyy-mm-dd"), TEXT(WORKDAY($C19+1,-1), "yyyy-mm-dd")))=0, "/", SUM(_xldudf_WISEPRICE($B$8 & ".MI", "Close",, TEXT(WORKDAY($C19+1,-1), "yyyy-mm-dd"), TEXT(WORKDAY($C19+1,-1), "yyyy-mm-dd")))) -> 10.21 | E19: =IFERROR(IF(SUM(_xldudf_WISEPRICE($B$8 & ".MI", "Close",, TEXT(WORKDAY(WORKDAY($C19+1,-1), 1), "yyyy-mm-dd"), TEXT(WORKDAY(WORKDAY($C19+1,-1), 1), "yyyy-mm-dd")))=0, "/", (SUM(_xldudf_WISEPRICE($B$8 & ".MI", "Close",, TEXT(WORKDAY(WORKDAY($C19+1,-1), 1), "yyyy-mm-dd"), TEXT(WORKDAY(WORKDAY($C19+1,-1), 1), "yyyy-mm-dd"))) / $D19) - 1), "/") -> -0.038197845 | F19: =IFERROR(IF(SUM(_xldudf_WISEPRICE($B$8 & ".MI", "Close",, TEXT(WORKDAY(WORKDAY($C19+1,-1), 3), "yyyy-mm-dd"), TEXT(WORKDAY(WORKDAY($C19+1,-1), 3), "yyyy-mm-dd")))=0, "/", (SUM(_xldudf_WISEPRICE($B$8 & ".MI", "Close",, TEXT(WORKDAY(WORKDAY($C19+1,-1), 3), "yyyy-mm-dd"), TEXT(WORKDAY(WORKDAY($C19+1,-1), 3), "yyyy-mm-dd"))) / $D19) - 1), "/") -> / | G19: =IFERROR(IF(SUM(_xldudf_WISEPRICE($B$8 & ".MI", "Close",, TEXT(WORKDAY(WORKDAY($C19+1,-1), 5), "yyyy-mm-dd"), TEXT(WORKDAY(WORKDAY($C19+1,-1), 5), "yyyy-mm-dd")))=0, "/", (SUM(_xldudf_WISEPRICE($B$8 & ".MI", "Close",, TEXT(WORKDAY(WORKDAY($C19+1,-1), 5), "yyyy-mm-dd"), TEXT(WORKDAY(WORKDAY($C19+1,-1), 5), "yyyy-mm-dd"))) / $D19) - 1), "/") -> -0.059745348 | H19: =IFERROR(IF(SUM(_xldudf_WISEPRICE($B$8 & ".MI", "Close",, TEXT(WORKDAY(EDATE(WORKDAY($C19+1,-1), 1)-1, 1), "yyyy-mm-dd"), TEXT(WORKDAY(EDATE(WORKDAY($C19+1,-1), 1)-1, 1), "yyyy-mm-dd")))=0, "/", (SUM(_xldudf_WISEPRICE($B$8 & ".MI", "Close",, TEXT(WORKDAY(EDATE(WORKDAY($C19+1,-1), 1)-1, 1), "yyyy-mm-dd"), TEXT(WORKDAY(EDATE(WORKDAY($C19+1,-1), 1)-1, 1), "yyyy-mm-dd"))) / $D19) - 1), "/") -> 0.041136141
C20: 43462 | D20: =IF(SUM(_xldudf_WISEPRICE($B$8 & ".MI", "Close",, TEXT(WORKDAY($C20+1,-1), "yyyy-mm-dd"), TEXT(WORKDAY($C20+1,-1), "yyyy-mm-dd")))=0, "/", SUM(_xldudf_WISEPRICE($B$8 & ".MI", "Close",, TEXT(WORKDAY($C20+1,-1), "yyyy-mm-dd"), TEXT(WORKDAY($C20+1,-1), "yyyy-mm-dd")))) -> 9.89 | E20: =IFERROR(IF(SUM(_xldudf_WISEPRICE($B$8 & ".MI", "Close",, TEXT(WORKDAY(WORKDAY($C20+1,-1), 1), "yyyy-mm-dd"), TEXT(WORKDAY(WORKDAY($C20+1,-1), 1), "yyyy-mm-dd")))=0, "/", (SUM(_xldudf_WISEPRICE($B$8 & ".MI", "Close",, TEXT(WORKDAY(WORKDAY($C20+1,-1), 1), "yyyy-mm-dd"), TEXT(WORKDAY(WORKDAY($C20+1,-1), 1), "yyyy-mm-dd"))) / $D20) - 1), "/") -> / | F20: =IFERROR(IF(SUM(_xldudf_WISEPRICE($B$8 & ".MI", "Close",, TEXT(WORKDAY(WORKDAY($C20+1,-1), 3), "yyyy-mm-dd"), TEXT(WORKDAY(WORKDAY($C20+1,-1), 3), "yyyy-mm-dd")))=0, "/", (SUM(_xldudf_WISEPRICE($B$8 & ".MI", "Close",, TEXT(WORKDAY(WORKDAY($C20+1,-1), 3), "yyyy-mm-dd"), TEXT(WORKDAY(WORKDAY($C20+1,-1), 3), "yyyy-mm-dd"))) / $D20) - 1), "/") -> -0.012133468 | G20: =IFERROR(IF(SUM(_xldudf_WISEPRICE($B$8 & ".MI", "Close",, TEXT(WORKDAY(WORKDAY($C20+1,-1), 5), "yyyy-mm-dd"), TEXT(WORKDAY(WORKDAY($C20+1,-1), 5), "yyyy-mm-dd")))=0, "/", (SUM(_xldudf_WISEPRICE($B$8 & ".MI", "Close",, TEXT(WORKDAY(WORKDAY($C20+1,-1), 5), "yyyy-mm-dd"), TEXT(WORKDAY(WORKDAY($C20+1,-1), 5), "yyyy-mm-dd"))) / $D20) - 1), "/") -> 0.032355915 | H20: =IFERROR(IF(SUM(_xldudf_WISEPRICE($B$8 & ".MI", "Close",, TEXT(WORKDAY(EDATE(WORKDAY($C20+1,-1), 1)-1, 1), "yyyy-mm-dd"), TEXT(WORKDAY(EDATE(WORKDAY($C20+1,-1), 1)-1, 1), "yyyy-mm-dd")))=0, "/", (SUM(_xldudf_WISEPRICE($B$8 & ".MI", "Close",, TEXT(WORKDAY(EDATE(WORKDAY($C20+1,-1), 1)-1, 1), "yyyy-mm-dd"), TEXT(WORKDAY(EDATE(WORKDAY($C20+1,-1), 1)-1, 1), "yyyy-mm-dd"))) / $D20) - 1), "/") -> 0.083923155
... C35: 44747 | D35: =IF(SUM(_xldudf_WISEPRICE($B$8 & ".MI", "Close",, TEXT(WORKDAY($C35+1,-1), "yyyy-mm-dd"), TEXT(WORKDAY($C35+1,-1), "yyyy-mm-dd")))=0, "/", SUM(_xldudf_WISEPRICE($B$8 & ".MI", "Close",, TEXT(WORKDAY($C35+1,-1), "yyyy-mm-dd"), TEXT(WORKDAY($C35+1,-1), "yyyy-mm-dd")))) -> 8.83 | E35: =IFERROR(IF(SUM(_xldudf_WISEPRICE($B$8 & ".MI", "Close",, TEXT(WORKDAY(WORKDAY($C35+1,-1), 1), "yyyy-mm-dd"), TEXT(WORKDAY(WORKDAY($C35+1,-1), 1), "yyyy-mm-dd")))=0, "/", (SUM(_xldudf_WISEPRICE($B$8 & ".MI", "Close",, TEXT(WORKDAY(WORKDAY($C35+1,-1), 1), "yyyy-mm-dd"), TEXT(WORKDAY(WORKDAY($C35+1,-1), 1), "yyyy-mm-dd"))) / $D35) - 1), "/") -> 0 | F35: =IFERROR(IF(SUM(_xldudf_WISEPRICE($B$8 & ".MI", "Close",, TEXT(WORKDAY(WORKDAY($C35+1,-1), 3), "yyyy-mm-dd"), TEXT(WORKDAY(WORKDAY($C35+1,-1), 3), "yyyy-mm-dd")))=0, "/", (SUM(_xldudf_WISEPRICE($B$8 & ".MI", "Close",, TEXT(WORKDAY(WORKDAY($C35+1,-1), 3), "yyyy-mm-dd"), TEXT(WORKDAY(WORKDAY($C35+1,-1), 3), "yyyy-mm-dd"))) / $D35) - 1), "/") -> 0.074745187 | G35: =IFERROR(IF(SUM(_xldudf_WISEPRICE($B$8 & ".MI", "Close",, TEXT(WORKDAY(WORKDAY($C35+1,-1), 5), "yyyy-mm-dd"), TEXT(WORKDAY(WORKDAY($C35+1,-1), 5), "yyyy-mm-dd")))=0, "/", (SUM(_xldudf_WISEPRICE($B$8 & ".MI", "Close",, TEXT(WORKDAY(WORKDAY($C35+1,-1), 5), "yyyy-mm-dd"), TEXT(WORKDAY(WORKDAY($C35+1,-1), 5), "yyyy-mm-dd"))) / $D35) - 1), "/") -> 0.030577576 | H35: =IFERROR(IF(SUM(_xldudf_WISEPRICE($B$8 & ".MI", "Close",, TEXT(WORKDAY(EDATE(WORKDAY($C35+1,-1), 1)-1, 1), "yyyy-mm-dd"), TEXT(WORKDAY(EDATE(WORKDAY($C35+1,-1), 1)-1, 1), "yyyy-mm-dd")))=0, "/", (SUM(_xldudf_WISEPRICE($B$8 & ".MI", "Close",, TEXT(WORKDAY(EDATE(WORKDAY($C35+1,-1), 1)-1, 1), "yyyy-mm-dd"), TEXT(WORKDAY(EDATE(WORKDAY($C35+1,-1), 1)-1, 1), "yyyy-mm-dd"))) / $D35) - 1), "/") -> 0.1200453
C36: Average Performance | D36: =_xlfn.AGGREGATE(1,6,D9:D35) -> 14.388148 | E36: =_xlfn.AGGREGATE(1,6,E9:E35) -> -0.0039368676 | F36: =_xlfn.AGGREGATE(1,6,F9:F35) -> 0.0014041793 | G36: =_xlfn.AGGREGATE(1,6,G9:G35) -> -0.015526021 | H36: =_xlfn.AGGREGATE(1,6,H9:H35) -> 0.0060694986
B38: BMPS | D38: Price on event day | E38: Pfm 1 day | F38: Pfm next three days | G38: Pfm 1 week | H38: Pfm 1 month
C39: 42178 | D39: =IF(SUM(_xldudf_WISEPRICE($B$38 & ".MI", "Close",, TEXT(WORKDAY($C39+1,-1), "yyyy-mm-dd"), TEXT(WORKDAY($C39+1,-1), "yyyy-mm-dd")))=0, "/", SUM(_xldudf_WISEPRICE($B$38 & ".MI", "Close",, TEXT(WORKDAY($C39+1,-1), "yyyy-mm-dd"), TEXT(WORKDAY($C39+1,-1), "yyyy-mm-dd")))) -> 19560 | E39: =IFERROR(IF(SUM(_xldudf_WISEPRICE($B$38 & ".MI", "Close",, TEXT(WORKDAY(WORKDAY($C39+1,-1), 1), "yyyy-mm-dd"), TEXT(WORKDAY(WORKDAY($C39+1,-1), 1), "yyyy-mm-dd")))=0, "/", (SUM(_xldudf_WISEPRICE($B$38 & ".MI", "Close",, TEXT(WORKDAY(WORKDAY($C39+1,-1), 1), "yyyy-mm-dd"), TEXT(WORKDAY(WORKDAY($C39+1,-1), 1), "yyyy-mm-dd"))) / $D39) - 1), "/") -> -0.020449898 | F39: =IFERROR(IF(SUM(_xldudf_WISEPRICE($B$38 & ".MI", "Close",, TEXT(WORKDAY(WORKDAY($C39+1,-1), 3), "yyyy-mm-dd"), TEXT(WORKDAY(WORKDAY($C39+1,-1), 3), "yyyy-mm-dd")))=0, "/", (SUM(_xldudf_WISEPRICE($B$38 & ".MI", "Close",, TEXT(WORKDAY(WORKDAY($C39+1,-1), 3), "yyyy-mm-dd"), TEXT(WORKDAY(WORKDAY($C39+1,-1), 3), "yyyy-mm-dd"))) / $D39) - 1), "/") -> 0.0081799591 | G39: =IFERROR(IF(SUM(_xldudf_WISEPRICE($B$38 & ".MI", "Close",, TEXT(WORKDAY(WORKDAY($C39+1,-1), 5), "yyyy-mm-dd"), TEXT(WORKDAY(WORKDAY($C39+1,-1), 5), "yyyy-mm-dd")))=0, "/", (SUM(_xldudf_WISEPRICE($B$38 & ".MI", "Close",, TEXT(WORKDAY(WORKDAY($C39+1,-1), 5), "yyyy-mm-dd"), TEXT(WORKDAY(WORKDAY($C39+1,-1), 5), "yyyy-mm-dd"))) / $D39) - 1), "/") -> -0.10736196 | H39: =IFERROR(IF(SUM(_xldudf_WISEPRICE($B$38 & ".MI", "Close",, TEXT(WORKDAY(EDATE(WORKDAY($C39+1,-1), 1)-1, 1), "yyyy-mm-dd"), TEXT(WORKDAY(EDATE(WORKDAY($C39+1,-1), 1)-1, 1), "yyyy-mm-dd")))=0, "/", (SUM(_xldudf_WISEPRICE($B$38 & ".MI", "Close",, TEXT(WORKDAY(EDATE(WORKDAY($C39+1,-1), 1)-1, 1), "yyyy-mm-dd"), TEXT(WORKDAY(EDATE(WORKDAY($C39+1,-1), 1)-1, 1), "yyyy-mm-dd"))) / $D39) - 1), "/") -> -0.038343558
C40: 42366 | D40: =IF(SUM(_xldudf_WISEPRICE($B$38 & ".MI", "Close",, TEXT(WORKDAY($C40+1,-1), "yyyy-mm-dd"), TEXT(WORKDAY($C40+1,-1), "yyyy-mm-dd")))=0, "/", SUM(_xldudf_WISEPRICE($B$38 & ".MI", "Close",, TEXT(WORKDAY($C40+1,-1), "yyyy-mm-dd"), TEXT(WORKDAY($C40+1,-1), "yyyy-mm-dd")))) -> 12520 | E40: =IFERROR(IF(SUM(_xldudf_WISEPRICE($B$38 & ".MI", "Close",, TEXT(WORKDAY(WORKDAY($C40+1,-1), 1), "yyyy-mm-dd"), TEXT(WORKDAY(WORKDAY($C40+1,-1), 1), "yyyy-mm-dd")))=0, "/", (SUM(_xldudf_WISEPRICE($B$38 & ".MI", "Close",, TEXT(WORKDAY(WORKDAY($C40+1,-1), 1), "yyyy-mm-dd"), TEXT(WORKDAY(WORKDAY($C40+1,-1), 1), "yyyy-mm-dd"))) / $D40) - 1), "/") -> -0.0031948882 | F40: =IFERROR(IF(SUM(_xldudf_WISEPRICE($B$38 & ".MI", "Close",, TEXT(WORKDAY(WORKDAY($C40+1,-1), 3), "yyyy-mm-dd"), TEXT(WORKDAY(WORKDAY($C40+1,-1), 3), "yyyy-mm-dd")))=0, "/", (SUM(_xldudf_WISEPRICE($B$38 & ".MI", "Close",, TEXT(WORKDAY(WORKDAY($C40+1,-1), 3), "yyyy-mm-dd"), TEXT(WORKDAY(WORKDAY($C40+1,-1), 3), "yyyy-mm-dd"))) / $D40) - 1), "/") -> -0.015974441 | G40: =IFERROR(IF(SUM(_xldudf_WISEPRICE($B$38 & ".MI", "Close",, TEXT(WORKDAY(WORKDAY($C40+1,-1), 5), "yyyy-mm-dd"), TEXT(WORKDAY(WORKDAY($C40+1,-1), 5), "yyyy-mm-dd")))=0, "/", (SUM(_xldudf_WISEPRICE($B$38 & ".MI", "Close",, TEXT(WORKDAY(WORKDAY($C40+1,-1), 5), "yyyy-mm-dd"), TEXT(WORKDAY(WORKDAY($C40+1,-1), 5), "yyyy-mm-dd"))) / $D40) - 1), "/") -> -0.06629393 | H40: =IFERROR(IF(SUM(_xldudf_WISEPRICE($B$38 & ".MI", "Close",, TEXT(WORKDAY(EDATE(WORKDAY($C40+1,-1), 1)-1, 1), "yyyy-mm-dd"), TEXT(WORKDAY(EDATE(WORKDAY($C40+1,-1), 1)-1, 1), "yyyy-mm-dd")))=0, "/", (SUM(_xldudf_WISEPRICE($B$38 & ".MI", "Close",, TEXT(WORKDAY(EDATE(WORKDAY($C40+1,-1), 1)-1, 1), "yyyy-mm-dd"), TEXT(WORKDAY(EDATE(WORKDAY($C40+1,-1), 1)-1, 1), "yyyy-mm-dd"))) / $D40) - 1), "/") -> -0.47683706
C41: 43190 | D41: =IF(SUM(_xldudf_WISEPRICE($B$38 & ".MI", "Close",, TEXT(WORKDAY($C41+1,-1), "yyyy-mm-dd"), TEXT(WORKDAY($C41+1,-1), "yyyy-mm-dd")))=0, "/", SUM(_xldudf_WISEPRICE($B$38 & ".MI", "Close",, TEXT(WORKDAY($C41+1,-1), "yyyy-mm-dd"), TEXT(WORKDAY($C41+1,-1), "yyyy-mm-dd")))) -> / | E41: =IFERROR(IF(SUM(_xldudf_WISEPRICE($B$38 & ".MI", "Close",, TEXT(WORKDAY(WORKDAY($C41+1,-1), 1), "yyyy-mm-dd"), TEXT(WORKDAY(WORKDAY($C41+1,-1), 1), "yyyy-mm-dd")))=0, "/", (SUM(_xldudf_WISEPRICE($B$38 & ".MI", "Close",, TEXT(WORKDAY(WORKDAY($C41+1,-1), 1), "yyyy-mm-dd"), TEXT(WORKDAY(WORKDAY($C41+1,-1), 1), "yyyy-mm-dd"))) / $D41) - 1), "/") -> / | F41: =IFERROR(IF(SUM(_xldudf_WISEPRICE($B$38 & ".MI", "Close",, TEXT(WORKDAY(WORKDAY($C41+1,-1), 3), "yyyy-mm-dd"), TEXT(WORKDAY(WORKDAY($C41+1,-1), 3), "yyyy-mm-dd")))=0, "/", (SUM(_xldudf_WISEPRICE($B$38 & ".MI", "Close",, TEXT(WORKDAY(WORKDAY($C41+1,-1), 3), "yyyy-mm-dd"), TEXT(WORKDAY(WORKDAY($C41+1,-1), 3), "yyyy-mm-dd"))) / $D41) - 1), "/") -> / | G41: =IFERROR(IF(SUM(_xldudf_WISEPRICE($B$38 & ".MI", "Close",, TEXT(WORKDAY(WORKDAY($C41+1,-1), 5), "yyyy-mm-dd"), TEXT(WORKDAY(WORKDAY($C41+1,-1), 5), "yyyy-mm-dd")))=0, "/", (SUM(_xldudf_WISEPRICE($B$38 & ".MI", "Close",, TEXT(WORKDAY(WORKDAY($C41+1,-1), 5), "yyyy-mm-dd"), TEXT(WORKDAY(WORKDAY($C41+1,-1), 5), "yyyy-mm-dd"))) / $D41) - 1), "/") -> / | H41: =IFERROR(IF(SUM(_xldudf_WISEPRICE($B$38 & ".MI", "Close",, TEXT(WORKDAY(EDATE(WORKDAY($C41+1,-1), 1)-1, 1), "yyyy-mm-dd"), TEXT(WORKDAY(EDATE(WORKDAY($C41+1,-1), 1)-1, 1), "yyyy-mm-dd")))=0, "/", (SUM(_xldudf_WISEPRICE($B$38 & ".MI", "Close",, TEXT(WORKDAY(EDATE(WORKDAY($C41+1,-1), 1)-1, 1), "yyyy-mm-dd"), TEXT(WORKDAY(EDATE(WORKDAY($C41+1,-1), 1)-1, 1), "yyyy-mm-dd"))) / $D41) - 1), "/") -> /
C42: 43281 | D42: =IF(SUM(_xldudf_WISEPRICE($B$38 & ".MI", "Close",, TEXT(WORKDAY($C42+1,-1), "yyyy-mm-dd"), TEXT(WORKDAY($C42+1,-1), "yyyy-mm-dd")))=0, "/", SUM(_xldudf_WISEPRICE($B$38 & ".MI", "Close",, TEXT(WORKDAY($C42+1,-1), "yyyy-mm-dd"), TEXT(WORKDAY($C42+1,-1), "yyyy-mm-dd")))) -> 246.5 | E42: =IFERROR(IF(SUM(_xldudf_WISEPRICE($B$38 & ".MI", "Close",, TEXT(WORKDAY(WORKDAY($C42+1,-1), 1), "yyyy-mm-dd"), TEXT(WORKDAY(WORKDAY($C42+1,-1), 1), "yyyy-mm-dd")))=0, "/", (SUM(_xldudf_WISEPRICE($B$38 & ".MI", "Close",, TEXT(WORKDAY(WORKDAY($C42+1,-1), 1), "yyyy-mm-dd"), TEXT(WORKDAY(WORKDAY($C42+1,-1), 1), "yyyy-mm-dd"))) / $D42) - 1), "/") -> 0.0012170507 | F42: =IFERROR(IF(SUM(_xldudf_WISEPRICE($B$38 & ".MI", "Close",, TEXT(WORKDAY(WORKDAY($C42+1,-1), 3), "yyyy-mm-dd"), TEXT(WORKDAY(WORKDAY($C42+1,-1), 3), "yyyy-mm-dd")))=0, "/", (SUM(_xldudf_WISEPRICE($B$38 & ".MI", "Close",, TEXT(WORKDAY(WORKDAY($C42+1,-1), 3), "yyyy-mm-dd"), TEXT(WORKDAY(WORKDAY($C42+1,-1), 3), "yyyy-mm-dd"))) / $D42) - 1), "/") -> -0.0036510913 | G42: =IFERROR(IF(SUM(_xldudf_WISEPRICE($B$38 & ".MI", "Close",, TEXT(WORKDAY(WORKDAY($C42+1,-1), 5), "yyyy-mm-dd"), TEXT(WORKDAY(WORKDAY($C42+1,-1), 5), "yyyy-mm-dd")))=0, "/", (SUM(_xldudf_WISEPRICE($B$38 & ".MI", "Close",, TEXT(WORKDAY(WORKDAY($C42+1,-1), 5), "yyyy-mm-dd"), TEXT(WORKDAY(WORKDAY($C42+1,-1), 5), "yyyy-mm-dd"))) / $D42) - 1), "/") -> -0.0056794888 | H42: =IFERROR(IF(SUM(_xldudf_WISEPRICE($B$38 & ".MI", "Close",, TEXT(WORKDAY(EDATE(WORKDAY($C42+1,-1), 1)-1, 1), "yyyy-mm-dd"), TEXT(WORKDAY(EDATE(WORKDAY($C42+1,-1), 1)-1, 1), "yyyy-mm-dd")))=0, "/", (SUM(_xldudf_WISEPRICE($B$38 & ".MI", "Close",, TEXT(WORKDAY(EDATE(WORKDAY($C42+1,-1), 1)-1, 1), "yyyy-mm-dd"), TEXT(WORKDAY(EDATE(WORKDAY($C42+1,-1), 1)-1, 1), "yyyy-mm-dd"))) / $D42) - 1), "/") -> 0.064908722
C43: 43313 | D43: =IF(SUM(_xldudf_WISEPRICE($B$38 & ".MI", "Close",, TEXT(WORKDAY($C43+1,-1), "yyyy-mm-dd"), TEXT(WORKDAY($C43+1,-1), "yyyy-mm-dd")))=0, "/", SUM(_xldudf_WISEPRICE($B$38 & ".MI", "Close",, TEXT(WORKDAY($C43+1,-1), "yyyy-mm-dd"), TEXT(WORKDAY($C43+1,-1), "yyyy-mm-dd")))) -> 260 | E43: =IFERROR(IF(SUM(_xldudf_WISEPRICE($B$38 & ".MI", "Close",, TEXT(WORKDAY(WORKDAY($C43+1,-1), 1), "yyyy-mm-dd"), TEXT(WORKDAY(WORKDAY($C43+1,-1), 1), "yyyy-mm-dd")))=0, "/", (SUM(_xldudf_WISEPRICE($B$38 & ".MI", "Close",, TEXT(WORKDAY(WORKDAY($C43+1,-1), 1), "yyyy-mm-dd"), TEXT(WORKDAY(WORKDAY($C43+1,-1), 1), "yyyy-mm-dd"))) / $D43) - 1), "/") -> -0.048846142 | F43: =IFERROR(IF(SUM(_xldudf_WISEPRICE($B$38 & ".MI", "Close",, TEXT(WORKDAY(WORKDAY($C43+1,-1), 3), "yyyy-mm-dd"), TEXT(WORKDAY(WORKDAY($C43+1,-1), 3), "yyyy-mm-dd")))=0, "/", (SUM(_xldudf_WISEPRICE($B$38 & ".MI", "Close",, TEXT(WORKDAY(WORKDAY($C43+1,-1), 3), "yyyy-mm-dd"), TEXT(WORKDAY(WORKDAY($C43+1,-1), 3), "yyyy-mm-dd"))) / $D43) - 1), "/") -> -0.088846177 | G43: =IFERROR(IF(SUM(_xldudf_WISEPRICE($B$38 & ".MI", "Close",, TEXT(WORKDAY(WORKDAY($C43+1,-1), 5), "yyyy-mm-dd"), TEXT(WORKDAY(WORKDAY($C43+1,-1), 5), "yyyy-mm-dd")))=0, "/", (SUM(_xldudf_WISEPRICE($B$38 & ".MI", "Close",, TEXT(WORKDAY(WORKDAY($C43+1,-1), 5), "yyyy-mm-dd"), TEXT(WORKDAY(WORKDAY($C43+1,-1), 5), "yyyy-mm-dd"))) / $D43) - 1), "/") -> -0.069999988 | H43: =IFERROR(IF(SUM(_xldudf_WISEPRICE($B$38 & ".MI", "Close",, TEXT(WORKDAY(EDATE(WORKDAY($C43+1,-1), 1)-1, 1), "yyyy-mm-dd"), TEXT(WORKDAY(EDATE(WORKDAY($C43+1,-1), 1)-1, 1), "yyyy-mm-dd")))=0, "/", (SUM(_xldudf_WISEPRICE($B$38 & ".MI", "Close",, TEXT(WORKDAY(EDATE(WORKDAY($C43+1,-1), 1)-1, 1), "yyyy-mm-dd"), TEXT(WORKDAY(EDATE(WORKDAY($C43+1,-1), 1)-1, 1), "yyyy-mm-dd"))) / $D43) - 1), "/") -> -0.17846152
C44: 43454 | D44: =IF(SUM(_xldudf_WISEPRICE($B$38 & ".MI", "Close",, TEXT(WORKDAY($C44+1,-1), "yyyy-mm-dd"), TEXT(WORKDAY($C44+1,-1), "yyyy-mm-dd")))=0, "/", SUM(_xldudf_WISEPRICE($B$38 & ".MI", "Close",, TEXT(WORKDAY($C44+1,-1), "yyyy-mm-dd"), TEXT(WORKDAY($C44+1,-1), "yyyy-mm-dd")))) -> 149.95 | E44: =IFERROR(IF(SUM(_xldudf_WISEPRICE($B$38 & ".MI", "Close",, TEXT(WORKDAY(WORKDAY($C44+1,-1), 1), "yyyy-mm-dd"), TEXT(WORKDAY(WORKDAY($C44+1,-1), 1), "yyyy-mm-dd")))=0, "/", (SUM(_xldudf_WISEPRICE($B$38 & ".MI", "Close",, TEXT(WORKDAY(WORKDAY($C44+1,-1), 1), "yyyy-mm-dd"), TEXT(WORKDAY(WORKDAY($C44+1,-1), 1), "yyyy-mm-dd"))) / $D44) - 1), "/") -> 0.026342095 | F44: =IFERROR(IF(SUM(_xldudf_WISEPRICE($B$38 & ".MI", "Close",, TEXT(WORKDAY(WORKDAY($C44+1,-1), 3), "yyyy-mm-dd"), TEXT(WORKDAY(WORKDAY($C44+1,-1), 3), "yyyy-mm-dd")))=0, "/", (SUM(_xldudf_WISEPRICE($B$38 & ".MI", "Close",, TEXT(WORKDAY(WORKDAY($C44+1,-1), 3), "yyyy-mm-dd"), TEXT(WORKDAY(WORKDAY($C44+1,-1), 3), "yyyy-mm-dd"))) / $D44) - 1), "/") -> / | G44: =IFERROR(IF(SUM(_xldudf_WISEPRICE($B$38 & ".MI", "Close",, TEXT(WORKDAY(WORKDAY($C44+1,-1), 5), "yyyy-mm-dd"), TEXT(WORKDAY(WORKDAY($C44+1,-1), 5), "yyyy-mm-dd")))=0, "/", (SUM(_xldudf_WISEPRICE($B$38 & ".MI", "Close",, TEXT(WORKDAY(WORKDAY($C44+1,-1), 5), "yyyy-mm-dd"), TEXT(WORKDAY(WORKDAY($C44+1,-1), 5), "yyyy-mm-dd"))) / $D44) - 1), "/") -> -0.010003335 | H44: =IFERROR(IF(SUM(_xldudf_WISEPRICE($B$38 & ".MI", "Close",, TEXT(WORKDAY(EDATE(WORKDAY($C44+1,-1), 1)-1, 1), "yyyy-mm-dd"), TEXT(WORKDAY(EDATE(WORKDAY($C44+1,-1), 1)-1, 1), "yyyy-mm-dd")))=0, "/", (SUM(_xldudf_WISEPRICE($B$38 & ".MI", "Close",, TEXT(WORKDAY(EDATE(WORKDAY($C44+1,-1), 1)-1, 1), "yyyy-mm-dd"), TEXT(WORKDAY(EDATE(WORKDAY($C44+1,-1), 1)-1, 1), "yyyy-mm-dd"))) / $D44) - 1), "/") -> -0.18672891
C45: 43497 | D45: =IF(SUM(_xldudf_WISEPRICE($B$38 & ".MI", "Close",, TEXT(WORKDAY($C45+1,-1), "yyyy-mm-dd"), TEXT(WORKDAY($C45+1,-1), "yyyy-mm-dd")))=0, "/", SUM(_xldudf_WISEPRICE($B$38 & ".MI", "Close",, TEXT(WORKDAY($C45+1,-1), "yyyy-mm-dd"), TEXT(WORKDAY($C45+1,-1), "yyyy-mm-dd")))) -> 120.85 | E45: =IFERROR(IF(SUM(_xldudf_WISEPRICE($B$38 & ".MI", "Close",, TEXT(WORKDAY(WORKDAY($C45+1,-1), 1), "yyyy-mm-dd"), TEXT(WORKDAY(WORKDAY($C45+1,-1), 1), "yyyy-mm-dd")))=0, "/", (SUM(_xldudf_WISEPRICE($B$38 & ".MI", "Close",, TEXT(WORKDAY(WORKDAY($C45+1,-1), 1), "yyyy-mm-dd"), TEXT(WORKDAY(WORKDAY($C45+1,-1), 1), "yyyy-mm-dd"))) / $D45) - 1), "/") -> -0.0091021764 | F45: =IFERROR(IF(SUM(_xldudf_WISEPRICE($B$38 & ".MI", "Close",, TEXT(WORKDAY(WORKDAY($C45+1,-1), 3), "yyyy-mm-dd"), TEXT(WORKDAY(WORKDAY($C45+1,-1), 3), "yyyy-mm-dd")))=0, "/", (SUM(_xldudf_WISEPRICE($B$38 & ".MI", "Close",, TEXT(WORKDAY(WORKDAY($C45+1,-1), 3), "yyyy-mm-dd"), TEXT(WORKDAY(WORKDAY($C45+1,-1), 3), "yyyy-mm-dd"))) / $D45) - 1), "/") -> 0.024410468 | G45: =IFERROR(IF(SUM(_xldudf_WISEPRICE($B$38 & ".MI", "Close",, TEXT(WORKDAY(WORKDAY($C45+1,-1), 5), "yyyy-mm-dd"), TEXT(WORKDAY(WORKDAY($C45+1,-1), 5), "yyyy-mm-dd")))=0, "/", (SUM(_xldudf_WISEPRICE($B$38 & ".MI", "Close",, TEXT(WORKDAY(WORKDAY($C45+1,-1), 5), "yyyy-mm-dd"), TEXT(WORKDAY(WORKDAY($C45+1,-1), 5), "yyyy-mm-dd"))) / $D45) - 1), "/") -> 0.018204427 | H45: =IFERROR(IF(SUM(_xldudf_WISEPRICE($B$38 & ".MI", "Close",, TEXT(WORKDAY(EDATE(WORKDAY($C45+1,-1), 1)-1, 1), "yyyy-mm-dd"), TEXT(WORKDAY(EDATE(WORKDAY($C45+1,-1), 1)-1, 1), "yyyy-mm-dd")))=0, "/", (SUM(_xldudf_WISEPRICE($B$38 & ".MI", "Close",, TEXT(WORKDAY(EDATE(WORKDAY($C45+1,-1), 1)-1, 1), "yyyy-mm-dd"), TEXT(WORKDAY(EDATE(WORKDAY($C45+1,-1), 1)-1, 1), "yyyy-mm-dd"))) / $D45) - 1), "/") -> 0.11129504
C46: 43614 | D46: =IF(SUM(_xldudf_WISEPRICE($B$38 & ".MI", "Close",, TEXT(WORKDAY($C46+1,-1), "yyyy-mm-dd"), TEXT(WORKDAY($C46+1,-1), "yyyy-mm-dd")))=0, "/", SUM(_xldudf_WISEPRICE($B$38 & ".MI", "Close",, TEXT(WORKDAY($C46+1,-1), "yyyy-mm-dd"), TEXT(WORKDAY($C46+1,-1), "yyyy-mm-dd")))) -> 106.4 | E46: =IFERROR(IF(SUM(_xldudf_WISEPRICE($B$38 & ".MI", "Close",, TEXT(WORKDAY(WORKDAY($C46+1,-1), 1), "yyyy-mm-dd"), TEXT(WORKDAY(WORKDAY($C46+1,-1), 1), "yyyy-mm-dd")))=0, "/", (SUM(_xldudf_WISEPRICE($B$38 & ".MI", "Close",, TEXT(WORKDAY(WORKDAY($C46+1,-1), 1), "yyyy-mm-dd"), TEXT(WORKDAY(WORKDAY($C46+1,-1), 1), "yyyy-mm-dd"))) / $D46) - 1), "/") -> -0.014097744 | F46: =IFERROR(IF(SUM(_xldudf_WISEPRICE($B$38 & ".MI", "Close",, TEXT(WORKDAY(WORKDAY($C46+1,-1), 3), "yyyy-mm-dd"), TEXT(WORKDAY(WORKDAY($C46+1,-1), 3), "yyyy-mm-dd")))=0, "/", (SUM(_xldudf_WISEPRICE($B$38 & ".MI", "Close",, TEXT(WORKDAY(WORKDAY($C46+1,-1), 3), "yyyy-mm-dd"), TEXT(WORKDAY(WORKDAY($C46+1,-1), 3), "yyyy-mm-dd"))) / $D46) - 1), "/") -> -0.031015075 | G46: =IFERROR(IF(SUM(_xldudf_WISEPRICE($B$38 & ".MI", "Close",, TEXT(WORKDAY(WORKDAY($C46+1,-1), 5), "yyyy-mm-dd"), TEXT(WORKDAY(WORKDAY($C46+1,-1), 5), "yyyy-mm-dd")))=0, "/", (SUM(_xldudf_WISEPRICE($B$38 & ".MI", "Close",, TEXT(WORKDAY(WORKDAY($C46+1,-1), 5), "yyyy-mm-dd"), TEXT(WORKDAY(WORKDAY($C46+1,-1), 5), "yyyy-mm-dd"))) / $D46) - 1), "/") -> -0.045112819 | H46: =IFERROR(IF(SUM(_xldudf_WISEPRICE($B$38 & ".MI", "Close",, TEXT(WORKDAY(EDATE(WORKDAY($C46+1,-1), 1)-1, 1), "yyyy-mm-dd"), TEXT(WORKDAY(EDATE(WORKDAY($C46+1,-1), 1)-1, 1), "yyyy-mm-dd")))=0, "/", (SUM(_xldudf_WISEPRICE($B$38 & ".MI", "Close",, TEXT(WORKDAY(EDATE(WORKDAY($C46+1,-1), 1)-1, 1), "yyyy-mm-dd"), TEXT(WORKDAY(EDATE(WORKDAY($C46+1,-1), 1)-1, 1), "yyyy-mm-dd"))) / $D46) - 1), "/") -> 0.058270638
C47: 43677 | D47: =IF(SUM(_xldudf_WISEPRICE($B$38 & ".MI", "Close",, TEXT(WORKDAY($C47+1,-1), "yyyy-mm-dd"), TEXT(WORKDAY($C47+1,-1), "yyyy-mm-dd")))=0, "/", SUM(_xldudf_WISEPRICE($B$38 & ".MI", "Close",, TEXT(WORKDAY($C47+1,-1), "yyyy-mm-dd"), TEXT(WORKDAY($C47+1,-1), "yyyy-mm-dd")))) -> 131.2 | E47: =IFERROR(IF(SUM(_xldudf_WISEPRICE($B$38 & ".MI", "Close",, TEXT(WORKDAY(WORKDAY($C47+1,-1), 1), "yyyy-mm-dd"), TEXT(WORKDAY(WORKDAY($C47+1,-1), 1), "yyyy-mm-dd")))=0, "/", (SUM(_xldudf_WISEPRICE($B$38 & ".MI", "Close",, TEXT(WORKDAY(WORKDAY($C47+1,-1), 1), "yyyy-mm-dd"), TEXT(WORKDAY(WORKDAY($C47+1,-1), 1), "yyyy-mm-dd"))) / $D47) - 1), "/") -> 0.013719535 | F47: =IFERROR(IF(SUM(_xldudf_WISEPRICE($B$38 & ".MI", "Close",, TEXT(WORKDAY(WORKDAY($C47+1,-1), 3), "yyyy-mm-dd"), TEXT(WORKDAY(WORKDAY($C47+1,-1), 3), "yyyy-mm-dd")))=0, "/", (SUM(_xldudf_WISEPRICE($B$38 & ".MI", "Close",, TEXT(WORKDAY(WORKDAY($C47+1,-1), 3), "yyyy-mm-dd"), TEXT(WORKDAY(WORKDAY($C47+1,-1), 3), "yyyy-mm-dd"))) / $D47) - 1), "/") -> -0.0015243674 | G47: =IFERROR(IF(SUM(_xldudf_WISEPRICE($B$38 & ".MI", "Close",, TEXT(WORKDAY(WORKDAY($C47+1,-1), 5), "yyyy-mm-dd"), TEXT(WORKDAY(WORKDAY($C47+1,-1), 5), "yyyy-mm-dd")))=0, "/", (SUM(_xldudf_WISEPRICE($B$38 & ".MI", "Close",, TEXT(WORKDAY(WORKDAY($C47+1,-1), 5), "yyyy-mm-dd"), TEXT(WORKDAY(WORKDAY($C47+1,-1), 5), "yyyy-mm-dd"))) / $D47) - 1), "/") -> -0.032012173 | H47: =IFERROR(IF(SUM(_xldudf_WISEPRICE($B$38 & ".MI", "Close",, TEXT(WORKDAY(EDATE(WORKDAY($C47+1,-1), 1)-1, 1), "yyyy-mm-dd"), TEXT(WORKDAY(EDATE(WORKDAY($C47+1,-1), 1)-1, 1), "yyyy-mm-dd")))=0, "/", (SUM(_xldudf_WISEPRICE($B$38 & ".MI", "Close",, TEXT(WORKDAY(EDATE(WORKDAY($C47+1,-1), 1)-1, 1), "yyyy-mm-dd"), TEXT(WORKDAY(EDATE(WORKDAY($C47+1,-1), 1)-1, 1), "yyyy-mm-dd"))) / $D47) - 1), "/") -> 0.17759149
C48: 43690 | D48: =IF(SUM(_xldudf_WISEPRICE($B$38 & ".MI", "Close",, TEXT(WORKDAY($C48+1,-1), "yyyy-mm-dd"), TEXT(WORKDAY($C48+1,-1), "yyyy-mm-dd")))=0, "/", SUM(_xldudf_WISEPRICE($B$38 & ".MI", "Close",, TEXT(WORKDAY($C48+1,-1), "yyyy-mm-dd"), TEXT(WORKDAY($C48+1,-1), "yyyy-mm-dd")))) -> 129.10001 | E48: =IFERROR(IF(SUM(_xldudf_WISEPRICE($B$38 & ".MI", "Close",, TEXT(WORKDAY(WORKDAY($C48+1,-1), 1), "yyyy-mm-dd"), TEXT(WORKDAY(WORKDAY($C48+1,-1), 1), "yyyy-mm-dd")))=0, "/", (SUM(_xldudf_WISEPRICE($B$38 & ".MI", "Close",, TEXT(WORKDAY(WORKDAY($C48+1,-1), 1), "yyyy-mm-dd"), TEXT(WORKDAY(WORKDAY($C48+1,-1), 1), "yyyy-mm-dd"))) / $D48) - 1), "/") -> 0.0092950964 | F48: =IFERROR(IF(SUM(_xldudf_WISEPRICE($B$38 & ".MI", "Close",, TEXT(WORKDAY(WORKDAY($C48+1,-1), 3), "yyyy-mm-dd"), TEXT(WORKDAY(WORKDAY($C48+1,-1), 3), "yyyy-mm-dd")))=0, "/", (SUM(_xldudf_WISEPRICE($B$38 & ".MI", "Close",, TEXT(WORKDAY(WORKDAY($C48+1,-1), 3), "yyyy-mm-dd"), TEXT(WORKDAY(WORKDAY($C48+1,-1), 3), "yyyy-mm-dd"))) / $D48) - 1), "/") -> 0.053446891 | G48: =IFERROR(IF(SUM(_xldudf_WISEPRICE($B$38 & ".MI", "Close",, TEXT(WORKDAY(WORKDAY($C48+1,-1), 5), "yyyy-mm-dd"), TEXT(WORKDAY(WORKDAY($C48+1,-1), 5), "yyyy-mm-dd")))=0, "/", (SUM(_xldudf_WISEPRICE($B$38 & ".MI", "Close",, TEXT(WORKDAY(WORKDAY($C48+1,-1), 5), "yyyy-mm-dd"), TEXT(WORKDAY(WORKDAY($C48+1,-1), 5), "yyyy-mm-dd"))) / $D48) - 1), "/") -> 0.030209092 | H48: =IFERROR(IF(SUM(_xldudf_WISEPRICE($B$38 & ".MI", "Close",, TEXT(WORKDAY(EDATE(WORKDAY($C48+1,-1), 1)-1, 1), "yyyy-mm-dd"), TEXT(WORKDAY(EDATE(WORKDAY($C48+1,-1), 1)-1, 1), "yyyy-mm-dd")))=0, "/", (SUM(_xldudf_WISEPRICE($B$38 & ".MI", "Close",, TEXT(WORKDAY(EDATE(WORKDAY($C48+1,-1), 1)-1, 1), "yyyy-mm-dd"), TEXT(WORKDAY(EDATE(WORKDAY($C48+1,-1), 1)-1, 1), "yyyy-mm-dd"))) / $D48) - 1), "/") -> 0.26491089
C49: 43738 | D49: =IF(SUM(_xldudf_WISEPRICE($B$38 & ".MI", "Close",, TEXT(WORKDAY($C49+1,-1), "yyyy-mm-dd"), TEXT(WORKDAY($C49+1,-1), "yyyy-mm-dd")))=0, "/", SUM(_xldudf_WISEPRICE($B$38 & ".MI", "Close",, TEXT(WORKDAY($C49+1,-1), "yyyy-mm-dd"), TEXT(WORKDAY($C49+1,-1), "yyyy-mm-dd")))) -> 152.8 | E49: =IFERROR(IF(SUM(_xldudf_WISEPRICE($B$38 & ".MI", "Close",, TEXT(WORKDAY(WORKDAY($C49+1,-1), 1), "yyyy-mm-dd"), TEXT(WORKDAY(WORKDAY($C49+1,-1), 1), "yyyy-mm-dd")))=0, "/", (SUM(_xldudf_WISEPRICE($B$38 & ".MI", "Close",, TEXT(WORKDAY(WORKDAY($C49+1,-1), 1), "yyyy-mm-dd"), TEXT(WORKDAY(WORKDAY($C49+1,-1), 1), "yyyy-mm-dd"))) / $D49) - 1), "/") -> -0.019633507 | F49: =IFERROR(IF(SUM(_xldudf_WISEPRICE($B$38 & ".MI", "Close",, TEXT(WORKDAY(WORKDAY($C49+1,-1), 3), "yyyy-mm-dd"), TEXT(WORKDAY(WORKDAY($C49+1,-1), 3), "yyyy-mm-dd")))=0, "/", (SUM(_xldudf_WISEPRICE($B$38 & ".MI", "Close",, TEXT(WORKDAY(WORKDAY($C49+1,-1), 3), "yyyy-mm-dd"), TEXT(WORKDAY(WORKDAY($C49+1,-1), 3), "yyyy-mm-dd"))) / $D49) - 1), "/") -> -0.041230385 | G49: =IFERROR(IF(SUM(_xldudf_WISEPRICE($B$38 & ".MI", "Close",, TEXT(WORKDAY(WORKDAY($C49+1,-1), 5), "yyyy-mm-dd"), TEXT(WORKDAY(WORKDAY($C49+1,-1), 5), "yyyy-mm-dd")))=0, "/", (SUM(_xldudf_WISEPRICE($B$38 & ".MI", "Close",, TEXT(WORKDAY(WORKDAY($C49+1,-1), 5), "yyyy-mm-dd"), TEXT(WORKDAY(WORKDAY($C49+1,-1), 5), "yyyy-mm-dd"))) / $D49) - 1), "/") -> -0.02617801 | H49: =IFERROR(IF(SUM(_xldudf_WISEPRICE($B$38 & ".MI", "Close",, TEXT(WORKDAY(EDATE(WORKDAY($C49+1,-1), 1)-1, 1), "yyyy-mm-dd"), TEXT(WORKDAY(EDATE(WORKDAY($C49+1,-1), 1)-1, 1), "yyyy-mm-dd")))=0, "/", (SUM(_xldudf_WISEPRICE($B$38 & ".MI", "Close",, TEXT(WORKDAY(EDATE(WORKDAY($C49+1,-1), 1)-1, 1), "yyyy-mm-dd"), TEXT(WORKDAY(EDATE(WORKDAY($C49+1,-1), 1)-1, 1), "yyyy-mm-dd"))) / $D49) - 1), "/") -> -0.053010509
C50: 44011 | D50: =IF(SUM(_xldudf_WISEPRICE($B$38 & ".MI", "Close",, TEXT(WORKDAY($C50+1,-1), "yyyy-mm-dd"), TEXT(WORKDAY($C50+1,-1), "yyyy-mm-dd")))=0, "/", SUM(_xldudf_WISEPRICE($B$38 & ".MI", "Close",, TEXT(WORKDAY($C50+1,-1), "yyyy-mm-dd"), TEXT(WORKDAY($C50+1,-1), "yyyy-mm-dd")))) -> 161.60001 | E50: =IFERROR(IF(SUM(_xldudf_WISEPRICE($B$38 & ".MI", "Close",, TEXT(WORKDAY(WORKDAY($C50+1,-1), 1), "yyyy-mm-dd"), TEXT(WORKDAY(WORKDAY($C50+1,-1), 1), "yyyy-mm-dd")))=0, "/", (SUM(_xldudf_WISEPRICE($B$38 & ".MI", "Close",, TEXT(WORKDAY(WORKDAY($C50+1,-1), 1), "yyyy-mm-dd"), TEXT(WORKDAY(WORKDAY($C50+1,-1), 1), "yyyy-mm-dd"))) / $D50) - 1), "/") -> -0.024133718 | F50: =IFERROR(IF(SUM(_xldudf_WISEPRICE($B$38 & ".MI", "Close",, TEXT(WORKDAY(WORKDAY($C50+1,-1), 3), "yyyy-mm-dd"), TEXT(WORKDAY(WORKDAY($C50+1,-1), 3), "yyyy-mm-dd")))=0, "/", (SUM(_xldudf_WISEPRICE($B$38 & ".MI", "Close",, TEXT(WORKDAY(WORKDAY($C50+1,-1), 3), "yyyy-mm-dd"), TEXT(WORKDAY(WORKDAY($C50+1,-1), 3), "yyyy-mm-dd"))) / $D50) - 1), "/") -> -0.03527235 | G50: =IFERROR(IF(SUM(_xldudf_WISEPRICE($B$38 & ".MI", "Close",, TEXT(WORKDAY(WORKDAY($C50+1,-1), 5), "yyyy-mm-dd"), TEXT(WORKDAY(WORKDAY($C50+1,-1), 5), "yyyy-mm-dd")))=0, "/", (SUM(_xldudf_WISEPRICE($B$38 & ".MI", "Close",, TEXT(WORKDAY(WORKDAY($C50+1,-1), 5), "yyyy-mm-dd"), TEXT(WORKDAY(WORKDAY($C50+1,-1), 5), "yyyy-mm-dd"))) / $D50) - 1), "/") -> -0.023514869 | H50: =IFERROR(IF(SUM(_xldudf_WISEPRICE($B$38 & ".MI", "Close",, TEXT(WORKDAY(EDATE(WORKDAY($C50+1,-1), 1)-1, 1), "yyyy-mm-dd"), TEXT(WORKDAY(EDATE(WORKDAY($C50+1,-1), 1)-1, 1), "yyyy-mm-dd")))=0, "/", (SUM(_xldudf_WISEPRICE($B$38 & ".MI", "Close",, TEXT(WORKDAY(EDATE(WORKDAY($C50+1,-1), 1)-1, 1), "yyyy-mm-dd"), TEXT(WORKDAY(EDATE(WORKDAY($C50+1,-1), 1)-1, 1), "yyyy-mm-dd"))) / $D50) - 1), "/") -> -0.0080445727
C51: 44778 | D51: =IF(SUM(_xldudf_WISEPRICE($B$38 & ".MI", "Close",, TEXT(WORKDAY($C51+1,-1), "yyyy-mm-dd"), TEXT(WORKDAY($C51+1,-1), "yyyy-mm-dd")))=0, "/", SUM(_xldudf_WISEPRICE($B$38 & ".MI", "Close",, TEXT(WORKDAY($C51+1,-1), "yyyy-mm-dd"), TEXT(WORKDAY($C51+1,-1), "yyyy-mm-dd")))) -> 41.5 | E51: =IFERROR(IF(SUM(_xldudf_WISEPRICE($B$38 & ".MI", "Close",, TEXT(WORKDAY(WORKDAY($C51+1,-1), 1), "yyyy-mm-dd"), TEXT(WORKDAY(WORKDAY($C51+1,-1), 1), "yyyy-mm-dd")))=0, "/", (SUM(_xldudf_WISEPRICE($B$38 & ".MI", "Close",, TEXT(WORKDAY(WORKDAY($C51+1,-1), 1), "yyyy-mm-dd"), TEXT(WORKDAY(WORKDAY($C51+1,-1), 1), "yyyy-mm-dd"))) / $D51) - 1), "/") -> 0.010120434 | F51: =IFERROR(IF(SUM(_xldudf_WISEPRICE($B$38 & ".MI", "Close",, TEXT(WORKDAY(WORKDAY($C51+1,-1), 3), "yyyy-mm-dd"), TEXT(WORKDAY(WORKDAY($C51+1,-1), 3), "yyyy-mm-dd")))=0, "/", (SUM(_xldudf_WISEPRICE($B$38 & ".MI", "Close",, TEXT(WORKDAY(WORKDAY($C51+1,-1), 3), "yyyy-mm-dd"), TEXT(WORKDAY(WORKDAY($C51+1,-1), 3), "yyyy-mm-dd"))) / $D51) - 1), "/") -> -0.0014458072 | G51: =IFERROR(IF(SUM(_xldudf_WISEPRICE($B$38 & ".MI", "Close",, TEXT(WORKDAY(WORKDAY($C51+1,-1), 5), "yyyy-mm-dd"), TEXT(WORKDAY(WORKDAY($C51+1,-1), 5), "yyyy-mm-dd")))=0, "/", (SUM(_xldudf_WISEPRICE($B$38 & ".MI", "Close",, TEXT(WORKDAY(WORKDAY($C51+1,-1), 5), "yyyy-mm-dd"), TEXT(WORKDAY(WORKDAY($C51+1,-1), 5), "yyyy-mm-dd"))) / $D51) - 1), "/") -> 0.035180699 | H51: =IFERROR(IF(SUM(_xldudf_WISEPRICE($B$38 & ".MI", "Close",, TEXT(WORKDAY(EDATE(WORKDAY($C51+1,-1), 1)-1, 1), "yyyy-mm-dd"), TEXT(WORKDAY(EDATE(WORKDAY($C51+1,-1), 1)-1, 1), "yyyy-mm-dd")))=0, "/", (SUM(_xldudf_WISEPRICE($B$38 & ".MI", "Close",, TEXT(WORKDAY(EDATE(WORKDAY($C51+1,-1), 1)-1, 1), "yyyy-mm-dd"), TEXT(WORKDAY(EDATE(WORKDAY($C51+1,-1), 1)-1, 1), "yyyy-mm-dd"))) / $D51) - 1), "/") -> -0.26891566
C52: Average Performance | D52: =_xlfn.AGGREGATE(1,6,D39:D51) -> 2798.325 | E52: =_xlfn.AGGREGATE(1,6,E39:E51) -> -0.0065636553 | F52: =_xlfn.AGGREGATE(1,6,F39:F51) -> -0.012083852 | G52: =_xlfn.AGGREGATE(1,6,G39:G51) -> -0.02521353 | H52: =_xlfn.AGGREGATE(1,6,H39:H51) -> -0.044447085
B54: ISP | D54: Price on event day | E54: Pfm 1 day | F54: Pfm next three days | G54: Pfm 1 week | H54: Pfm 1 month
C55: 42859 | D55: =IF(SUM(_xldudf_WISEPRICE($B$54 & ".MI", "Close",, TEXT(WORKDAY($C55+1,-1), "yyyy-mm-dd"), TEXT(WORKDAY($C55+1,-1), "yyyy-mm-dd")))=0, "/", SUM(_xldudf_WISEPRICE($B$54 & ".MI", "Close",, TEXT(WORKDAY($C55+1,-1), "yyyy-mm-dd"), TEXT(WORKDAY($C55+1,-1), "yyyy-mm-dd")))) -> 2.76 | E55: =IFERROR(IF(SUM(_xldudf_WISEPRICE($B$54 & ".MI", "Close",, TEXT(WORKDAY(WORKDAY($C55+1,-1), 1), "yyyy-mm-dd"), TEXT(WORKDAY(WORKDAY($C55+1,-1), 1), "yyyy-mm-dd")))=0, "/", (SUM(_xldudf_WISEPRICE($B$54 & ".MI", "Close",, TEXT(WORKDAY(WORKDAY($C55+1,-1), 1), "yyyy-mm-dd"), TEXT(WORKDAY(WORKDAY($C55+1,-1), 1), "yyyy-mm-dd"))) / $D55) - 1), "/") -> 0.028985507 | F55: =IFERROR(IF(SUM(_xldudf_WISEPRICE($B$54 & ".MI", "Close",, TEXT(WORKDAY(WORKDAY($C55+1,-1), 3), "yyyy-mm-dd"), TEXT(WORKDAY(WORKDAY($C55+1,-1), 3), "yyyy-mm-dd")))=0, "/", (SUM(_xldudf_WISEPRICE($B$54 & ".MI", "Close",, TEXT(WORKDAY(WORKDAY($C55+1,-1), 3), "yyyy-mm-dd"), TEXT(WORKDAY(WORKDAY($C55+1,-1), 3), "yyyy-mm-dd"))) / $D55) - 1), "/") -> 0.032608696 | G55: =IFERROR(IF(SUM(_xldudf_WISEPRICE($B$54 & ".MI", "Close",, TEXT(WORKDAY(WORKDAY($C55+1,-1), 5), "yyyy-mm-dd"), TEXT(WORKDAY(WORKDAY($C55+1,-1), 5), "yyyy-mm-dd")))=0, "/", (SUM(_xldudf_WISEPRICE($B$54 & ".MI", "Close",, TEXT(WORKDAY(WORKDAY($C55+1,-1), 5), "yyyy-mm-dd"), TEXT(WORKDAY(WORKDAY($C55+1,-1), 5), "yyyy-mm-dd"))) / $D55) - 1), "/") -> 0.025362319 | H55: =IFERROR(IF(SUM(_xldudf_WISEPRICE($B$54 & ".MI", "Close",, TEXT(WORKDAY(EDATE(WORKDAY($C55+1,-1), 1)-1, 1), "yyyy-mm-dd"), TEXT(WORKDAY(EDATE(WORKDAY($C55+1,-1), 1)-1, 1), "yyyy-mm-dd")))=0, "/", (SUM(_xldudf_WISEPRICE($B$54 & ".MI", "Close",, TEXT(WORKDAY(EDATE(WORKDAY($C55+1,-1), 1)-1, 1), "yyyy-mm-dd"), TEXT(WORKDAY(EDATE(WORKDAY($C55+1,-1), 1)-1, 1), "yyyy-mm-dd"))) / $D55) - 1), "/") -> -0.072463768
C56: 43206 | D56: =IF(SUM(_xldudf_WISEPRICE($B$54 & ".MI", "Close",, TEXT(WORKDAY($C56+1,-1), "yyyy-mm-dd"), TEXT(WORKDAY($C56+1,-1), "yyyy-mm-dd")))=0, "/", SUM(_xldudf_WISEPRICE($B$54 & ".MI", "Close",, TEXT(WORKDAY($C56+1,-1), "yyyy-mm-dd"), TEXT(WORKDAY($C56+1,-1), "yyyy-mm-dd")))) -> 3.08 | E56: =IFERROR(IF(SUM(_xldudf_WISEPRICE($B$54 & ".MI", "Close",, TEXT(WORKDAY(WORKDAY($C56+1,-1), 1), "yyyy-mm-dd"), TEXT(WORKDAY(WORKDAY($C56+1,-1), 1), "yyyy-mm-dd")))=0, "/", (SUM(_xldudf_WISEPRICE($B$54 & ".MI", "Close",, TEXT(WORKDAY(WORKDAY($C56+1,-1), 1), "yyyy-mm-dd"), TEXT(WORKDAY(WORKDAY($C56+1,-1), 1), "yyyy-mm-dd"))) / $D56) - 1), "/") -> 0.0097402597 | F56: =IFERROR(IF(SUM(_xldudf_WISEPRICE($B$54 & ".MI", "Close",, TEXT(WORKDAY(WORKDAY($C56+1,-1), 3), "yyyy-mm-dd"), TEXT(WORKDAY(WORKDAY($C56+1,-1), 3), "yyyy-mm-dd")))=0, "/", (SUM(_xldudf_WISEPRICE($B$54 & ".MI", "Close",, TEXT(WORKDAY(WORKDAY($C56+1,-1), 3), "yyyy-mm-dd"), TEXT(WORKDAY(WORKDAY($C56+1,-1), 3), "yyyy-mm-dd"))) / $D56) - 1), "/") -> 0.0097402597 | G56: =IFERROR(IF(SUM(_xldudf_WISEPRICE($B$54 & ".MI", "Close",, TEXT(WORKDAY(WORKDAY($C56+1,-1), 5), "yyyy-mm-dd"), TEXT(WORKDAY(WORKDAY($C56+1,-1), 5), "yyyy-mm-dd")))=0, "/", (SUM(_xldudf_WISEPRICE($B$54 & ".MI", "Close",, TEXT(WORKDAY(WORKDAY($C56+1,-1), 5), "yyyy-mm-dd"), TEXT(WORKDAY(WORKDAY($C56+1,-1), 5), "yyyy-mm-dd"))) / $D56) - 1), "/") -> 0.029220779 | H56: =IFERROR(IF(SUM(_xldudf_WISEPRICE($B$54 & ".MI", "Close",, TEXT(WORKDAY(EDATE(WORKDAY($C56+1,-1), 1)-1, 1), "yyyy-mm-dd"), TEXT(WORKDAY(EDATE(WORKDAY($C56+1,-1), 1)-1, 1), "yyyy-mm-dd")))=0, "/", (SUM(_xldudf_WISEPRICE($B$54 & ".MI", "Close",, TEXT(WORKDAY(EDATE(WORKDAY($C56+1,-1), 1)-1, 1), "yyyy-mm-dd"), TEXT(WORKDAY(EDATE(WORKDAY($C56+1,-1), 1)-1, 1), "yyyy-mm-dd"))) / $D56) - 1), "/") -> 0.0064935065
C57: 43552 | D57: =IF(SUM(_xldudf_WISEPRICE($B$54 & ".MI", "Close",, TEXT(WORKDAY($C57+1,-1), "yyyy-mm-dd"), TEXT(WORKDAY($C57+1,-1), "yyyy-mm-dd")))=0, "/", SUM(_xldudf_WISEPRICE($B$54 & ".MI", "Close",, TEXT(WORKDAY($C57+1,-1), "yyyy-mm-dd"), TEXT(WORKDAY($C57+1,-1), "yyyy-mm-dd")))) -> 2.16 | E57: =IFERROR(IF(SUM(_xldudf_WISEPRICE($B$54 & ".MI", "Close",, TEXT(WORKDAY(WORKDAY($C57+1,-1), 1), "yyyy-mm-dd"), TEXT(WORKDAY(WORKDAY($C57+1,-1), 1), "yyyy-mm-dd")))=0, "/", (SUM(_xldudf_WISEPRICE($B$54 & ".MI", "Close",, TEXT(WORKDAY(WORKDAY($C57+1,-1), 1), "yyyy-mm-dd"), TEXT(WORKDAY(WORKDAY($C57+1,-1), 1), "yyyy-mm-dd"))) / $D57) - 1), "/") -> 0.0046296296 | F57: =IFERROR(IF(SUM(_xldudf_WISEPRICE($B$54 & ".MI", "Close",, TEXT(WORKDAY(WORKDAY($C57+1,-1), 3), "yyyy-mm-dd"), TEXT(WORKDAY(WORKDAY($C57+1,-1), 3), "yyyy-mm-dd")))=0, "/", (SUM(_xldudf_WISEPRICE($B$54 & ".MI", "Close",, TEXT(WORKDAY(WORKDAY($C57+1,-1), 3), "yyyy-mm-dd"), TEXT(WORKDAY(WORKDAY($C57+1,-1), 3), "yyyy-mm-dd"))) / $D57) - 1), "/") -> 0.018518519 | G57: =IFERROR(IF(SUM(_xldudf_WISEPRICE($B$54 & ".MI", "Close",, TEXT(WORKDAY(WORKDAY($C57+1,-1), 5), "yyyy-mm-dd"), TEXT(WORKDAY(WORKDAY($C57+1,-1), 5), "yyyy-mm-dd")))=0, "/", (SUM(_xldudf_WISEPRICE($B$54 & ".MI", "Close",, TEXT(WORKDAY(WORKDAY($C57+1,-1), 5), "yyyy-mm-dd"), TEXT(WORKDAY(WORKDAY($C57+1,-1), 5), "yyyy-mm-dd"))) / $D57) - 1), "/") -> 0.032407407 | H57: =IFERROR(IF(SUM(_xldudf_WISEPRICE($B$54 & ".MI", "Close",, TEXT(WORKDAY(EDATE(WORKDAY($C57+1,-1), 1)-1, 1), "yyyy-mm-dd"), TEXT(WORKDAY(EDATE(WORKDAY($C57+1,-1), 1)-1, 1), "yyyy-mm-dd")))=0, "/", (SUM(_xldudf_WISEPRICE($B$54 & ".MI", "Close",, TEXT(WORKDAY(EDATE(WORKDAY($C57+1,-1), 1)-1, 1), "yyyy-mm-dd"), TEXT(WORKDAY(EDATE(WORKDAY($C57+1,-1), 1)-1, 1), "yyyy-mm-dd"))) / $D57) - 1), "/") -> 0.078703704
C58: 43733 | D58: =IF(SUM(_xldudf_WISEPRICE($B$54 & ".MI", "Close",, TEXT(WORKDAY($C58+1,-1), "yyyy-mm-dd"), TEXT(WORKDAY($C58+1,-1), "yyyy-mm-dd")))=0, "/", SUM(_xldudf_WISEPRICE($B$54 & ".MI", "Close",, TEXT(WORKDAY($C58+1,-1), "yyyy-mm-dd"), TEXT(WORKDAY($C58+1,-1), "yyyy-mm-dd")))) -> 2.13 | E58: =IFERROR(IF(SUM(_xldudf_WISEPRICE($B$54 & ".MI", "Close",, TEXT(WORKDAY(WORKDAY($C58+1,-1), 1), "yyyy-mm-dd"), TEXT(WORKDAY(WORKDAY($C58+1,-1), 1), "yyyy-mm-dd")))=0, "/", (SUM(_xldudf_WISEPRICE($B$54 & ".MI", "Close",, TEXT(WORKDAY(WORKDAY($C58+1,-1), 1), "yyyy-mm-dd"), TEXT(WORKDAY(WORKDAY($C58+1,-1), 1), "yyyy-mm-dd"))) / $D58) - 1), "/") -> 0.0046948357 | F58: =IFERROR(IF(SUM(_xldudf_WISEPRICE($B$54 & ".MI", "Close",, TEXT(WORKDAY(WORKDAY($C58+1,-1), 3), "yyyy-mm-dd"), TEXT(WORKDAY(WORKDAY($C58+1,-1), 3), "yyyy-mm-dd")))=0, "/", (SUM(_xldudf_WISEPRICE($B$54 & ".MI", "Close",, TEXT(WORKDAY(WORKDAY($C58+1,-1), 3), "yyyy-mm-dd"), TEXT(WORKDAY(WORKDAY($C58+1,-1), 3), "yyyy-mm-dd"))) / $D58) - 1), "/") -> 0.023474178 | G58: =IFERROR(IF(SUM(_xldudf_WISEPRICE($B$54 & ".MI", "Close",, TEXT(WORKDAY(WORKDAY($C58+1,-1), 5), "yyyy-mm-dd"), TEXT(WORKDAY(WORKDAY($C58+1,-1), 5), "yyyy-mm-dd")))=0, "/", (SUM(_xldudf_WISEPRICE($B$54 & ".MI", "Close",, TEXT(WORKDAY(WORKDAY($C58+1,-1), 5), "yyyy-mm-dd"), TEXT(WORKDAY(WORKDAY($C58+1,-1), 5), "yyyy-mm-dd"))) / $D58) - 1), "/") -> -0.018779343 | H58: =IFERROR(IF(SUM(_xldudf_WISEPRICE($B$54 & ".MI", "Close",, TEXT(WORKDAY(EDATE(WORKDAY($C58+1,-1), 1)-1, 1), "yyyy-mm-dd"), TEXT(WORKDAY(EDATE(WORKDAY($C58+1,-1), 1)-1, 1), "yyyy-mm-dd")))=0, "/", (SUM(_xldudf_WISEPRICE($B$54 & ".MI", "Close",, TEXT(WORKDAY(EDATE(WORKDAY($C58+1,-1), 1)-1, 1), "yyyy-mm-dd"), TEXT(WORKDAY(EDATE(WORKDAY($C58+1,-1), 1)-1, 1), "yyyy-mm-dd"))) / $D58) - 1), "/") -> 0.0657277
C59: 44146 | D59: =IF(SUM(_xldudf_WISEPRICE($B$54 & ".MI", "Close",, TEXT(WORKDAY($C59+1,-1), "yyyy-mm-dd"), TEXT(WORKDAY($C59+1,-1), "yyyy-mm-dd")))=0, "/", SUM(_xldudf_WISEPRICE($B$54 & ".MI", "Close",, TEXT(WORKDAY($C59+1,-1), "yyyy-mm-dd"), TEXT(WORKDAY($C59+1,-1), "yyyy-mm-dd")))) -> 1.82 | E59: =IFERROR(IF(SUM(_xldudf_WISEPRICE($B$54 & ".MI", "Close",, TEXT(WORKDAY(WORKDAY($C59+1,-1), 1), "yyyy-mm-dd"), TEXT(WORKDAY(WORKDAY($C59+1,-1), 1), "yyyy-mm-dd")))=0, "/", (SUM(_xldudf_WISEPRICE($B$54 & ".MI", "Close",, TEXT(WORKDAY(WORKDAY($C59+1,-1), 1), "yyyy-mm-dd"), TEXT(WORKDAY(WORKDAY($C59+1,-1), 1), "yyyy-mm-dd"))) / $D59) - 1), "/") -> -0.010989011 | F59: =IFERROR(IF(SUM(_xldudf_WISEPRICE($B$54 & ".MI", "Close",, TEXT(WORKDAY(WORKDAY($C59+1,-1), 3), "yyyy-mm-dd"), TEXT(WORKDAY(WORKDAY($C59+1,-1), 3), "yyyy-mm-dd")))=0, "/", (SUM(_xldudf_WISEPRICE($B$54 & ".MI", "Close",, TEXT(WORKDAY(WORKDAY($C59+1,-1), 3), "yyyy-mm-dd"), TEXT(WORKDAY(WORKDAY($C59+1,-1), 3), "yyyy-mm-dd"))) / $D59) - 1), "/") -> 0.010989011 | G59: =IFERROR(IF(SUM(_xldudf_WISEPRICE($B$54 & ".MI", "Close",, TEXT(WORKDAY(WORKDAY($C59+1,-1), 5), "yyyy-mm-dd"), TEXT(WORKDAY(WORKDAY($C59+1,-1), 5), "yyyy-mm-dd")))=0, "/", (SUM(_xldudf_WISEPRICE($B$54 & ".MI", "Close",, TEXT(WORKDAY(WORKDAY($C59+1,-1), 5), "yyyy-mm-dd"), TEXT(WORKDAY(WORKDAY($C59+1,-1), 5), "yyyy-mm-dd"))) / $D59) - 1), "/") -> 0.027472527 | H59: =IFERROR(IF(SUM(_xldudf_WISEPRICE($B$54 & ".MI", "Close",, TEXT(WORKDAY(EDATE(WORKDAY($C59+1,-1), 1)-1, 1), "yyyy-mm-dd"), TEXT(WORKDAY(EDATE(WORKDAY($C59+1,-1), 1)-1, 1), "yyyy-mm-dd")))=0, "/", (SUM(_xldudf_WISEPRICE($B$54 & ".MI", "Close",, TEXT(WORKDAY(EDATE(WORKDAY($C59+1,-1), 1)-1, 1), "yyyy-mm-dd"), TEXT(WORKDAY(EDATE(WORKDAY($C59+1,-1), 1)-1, 1), "yyyy-mm-dd"))) / $D59) - 1), "/") -> 0.065934066
C60: 44411 | D60: =IF(SUM(_xldudf_WISEPRICE($B$54 & ".MI", "Close",, TEXT(WORKDAY($C60+1,-1), "yyyy-mm-dd"), TEXT(WORKDAY($C60+1,-1), "yyyy-mm-dd")))=0, "/", SUM(_xldudf_WISEPRICE($B$54 & ".MI", "Close",, TEXT(WORKDAY($C60+1,-1), "yyyy-mm-dd"), TEXT(WORKDAY($C60+1,-1), "yyyy-mm-dd")))) -> 2.33 | E60: =IFERROR(IF(SUM(_xldudf_WISEPRICE($B$54 & ".MI", "Close",, TEXT(WORKDAY(WORKDAY($C60+1,-1), 1), "yyyy-mm-dd"), TEXT(WORKDAY(WORKDAY($C60+1,-1), 1), "yyyy-mm-dd")))=0, "/", (SUM(_xldudf_WISEPRICE($B$54 & ".MI", "Close",, TEXT(WORKDAY(WORKDAY($C60+1,-1), 1), "yyyy-mm-dd"), TEXT(WORKDAY(WORKDAY($C60+1,-1), 1), "yyyy-mm-dd"))) / $D60) - 1), "/") -> 0.0042918455 | F60: =IFERROR(IF(SUM(_xldudf_WISEPRICE($B$54 & ".MI", "Close",, TEXT(WORKDAY(WORKDAY($C60+1,-1), 3), "yyyy-mm-dd"), TEXT(WORKDAY(WORKDAY($C60+1,-1), 3), "yyyy-mm-dd")))=0, "/", (SUM(_xldudf_WISEPRICE($B$54 & ".MI", "Close",, TEXT(WORKDAY(WORKDAY($C60+1,-1), 3), "yyyy-mm-dd"), TEXT(WORKDAY(WORKDAY($C60+1,-1), 3), "yyyy-mm-dd"))) / $D60) - 1), "/") -> 0.030042918 | G60: =IFERROR(IF(SUM(_xldudf_WISEPRICE($B$54 & ".MI", "Close",, TEXT(WORKDAY(WORKDAY($C60+1,-1), 5), "yyyy-mm-dd"), TEXT(WORKDAY(WORKDAY($C60+1,-1), 5), "yyyy-mm-dd")))=0, "/", (SUM(_xldudf_WISEPRICE($B$54 & ".MI", "Close",, TEXT(WORKDAY(WORKDAY($C60+1,-1), 5), "yyyy-mm-dd"), TEXT(WORKDAY(WORKDAY($C60+1,-1), 5), "yyyy-mm-dd"))) / $D60) - 1), "/") -> 0.034334764 | H60: =IFERROR(IF(SUM(_xldudf_WISEPRICE($B$54 & ".MI", "Close",, TEXT(WORKDAY(EDATE(WORKDAY($C60+1,-1), 1)-1, 1), "yyyy-mm-dd"), TEXT(WORKDAY(EDATE(WORKDAY($C60+1,-1), 1)-1, 1), "yyyy-mm-dd")))=0, "/", (SUM(_xldudf_WISEPRICE($B$54 & ".MI", "Close",, TEXT(WORKDAY(EDATE(WORKDAY($C60+1,-1), 1)-1, 1), "yyyy-mm-dd"), TEXT(WORKDAY(EDATE(WORKDAY($C60+1,-1), 1)-1, 1), "yyyy-mm-dd"))) / $D60) - 1), "/") -> 0.025751073
C61: 44468 | D61: =IF(SUM(_xldudf_WISEPRICE($B$54 & ".MI", "Close",, TEXT(WORKDAY($C61+1,-1), "yyyy-mm-dd"), TEXT(WORKDAY($C61+1,-1), "yyyy-mm-dd")))=0, "/", SUM(_xldudf_WISEPRICE($B$54 & ".MI", "Close",, TEXT(WORKDAY($C61+1,-1), "yyyy-mm-dd"), TEXT(WORKDAY($C61+1,-1), "yyyy-mm-dd")))) -> 2.46 | E61: =IFERROR(IF(SUM(_xldudf_WISEPRICE($B$54 & ".MI", "Close",, TEXT(WORKDAY(WORKDAY($C61+1,-1), 1), "yyyy-mm-dd"), TEXT(WORKDAY(WORKDAY($C61+1,-1), 1), "yyyy-mm-dd")))=0, "/", (SUM(_xldudf_WISEPRICE($B$54 & ".MI", "Close",, TEXT(WORKDAY(WORKDAY($C61+1,-1), 1), "yyyy-mm-dd"), TEXT(WORKDAY(WORKDAY($C61+1,-1), 1), "yyyy-mm-dd"))) / $D61) - 1), "/") -> -0.0040650407 | F61: =IFERROR(IF(SUM(_xldudf_WISEPRICE($B$54 & ".MI", "Close",, TEXT(WORKDAY(WORKDAY($C61+1,-1), 3), "yyyy-mm-dd"), TEXT(WORKDAY(WORKDAY($C61+1,-1), 3), "yyyy-mm-dd")))=0, "/", (SUM(_xldudf_WISEPRICE($B$54 & ".MI", "Close",, TEXT(WORKDAY(WORKDAY($C61+1,-1), 3), "yyyy-mm-dd"), TEXT(WORKDAY(WORKDAY($C61+1,-1), 3), "yyyy-mm-dd"))) / $D61) - 1), "/") -> -0.016260163 | G61: =IFERROR(IF(SUM(_xldudf_WISEPRICE($B$54 & ".MI", "Close",, TEXT(WORKDAY(WORKDAY($C61+1,-1), 5), "yyyy-mm-dd"), TEXT(WORKDAY(WORKDAY($C61+1,-1), 5), "yyyy-mm-dd")))=0, "/", (SUM(_xldudf_WISEPRICE($B$54 & ".MI", "Close",, TEXT(WORKDAY(WORKDAY($C61+1,-1), 5), "yyyy-mm-dd"), TEXT(WORKDAY(WORKDAY($C61+1,-1), 5), "yyyy-mm-dd"))) / $D61) - 1), "/") -> 0.0081300813 | H61: =IFERROR(IF(SUM(_xldudf_WISEPRICE($B$54 & ".MI", "Close",, TEXT(WORKDAY(EDATE(WORKDAY($C61+1,-1), 1)-1, 1), "yyyy-mm-dd"), TEXT(WORKDAY(EDATE(WORKDAY($C61+1,-1), 1)-1, 1), "yyyy-mm-dd")))=0, "/", (SUM(_xldudf_WISEPRICE($B$54 & ".MI", "Close",, TEXT(WORKDAY(EDATE(WORKDAY($C61+1,-1), 1)-1, 1), "yyyy-mm-dd"), TEXT(WORKDAY(EDATE(WORKDAY($C61+1,-1), 1)-1, 1), "yyyy-mm-dd"))) / $D61) - 1), "/") -> 0
C62: 44743 | D62: =IF(SUM(_xldudf_WISEPRICE($B$54 & ".MI", "Close",, TEXT(WORKDAY($C62+1,-1), "yyyy-mm-dd"), TEXT(WORKDAY($C62+1,-1), "yyyy-mm-dd")))=0, "/", SUM(_xldudf_WISEPRICE($B$54 & ".MI", "Close",, TEXT(WORKDAY($C62+1,-1), "yyyy-mm-dd"), TEXT(WORKDAY($C62+1,-1), "yyyy-mm-dd")))) -> 1.77 | E62: =IFERROR(IF(SUM(_xldudf_WISEPRICE($B$54 & ".MI", "Close",, TEXT(WORKDAY(WORKDAY($C62+1,-1), 1), "yyyy-mm-dd"), TEXT(WORKDAY(WORKDAY($C62+1,-1), 1), "yyyy-mm-dd")))=0, "/", (SUM(_xldudf_WISEPRICE($B$54 & ".MI", "Close",, TEXT(WORKDAY(WORKDAY($C62+1,-1), 1), "yyyy-mm-dd"), TEXT(WORKDAY(WORKDAY($C62+1,-1), 1), "yyyy-mm-dd"))) / $D62) - 1), "/") -> -0.02259887 | F62: =IFERROR(IF(SUM(_xldudf_WISEPRICE($B$54 & ".MI", "Close",, TEXT(WORKDAY(WORKDAY($C62+1,-1), 3), "yyyy-mm-dd"), TEXT(WORKDAY(WORKDAY($C62+1,-1), 3), "yyyy-mm-dd")))=0, "/", (SUM(_xldudf_WISEPRICE($B$54 & ".MI", "Close",, TEXT(WORKDAY(WORKDAY($C62+1,-1), 3), "yyyy-mm-dd"), TEXT(WORKDAY(WORKDAY($C62+1,-1), 3), "yyyy-mm-dd"))) / $D62) - 1), "/") -> -0.050847458 | G62: =IFERROR(IF(SUM(_xldudf_WISEPRICE($B$54 & ".MI", "Close",, TEXT(WORKDAY(WORKDAY($C62+1,-1), 5), "yyyy-mm-dd"), TEXT(WORKDAY(WORKDAY($C62+1,-1), 5), "yyyy-mm-dd")))=0, "/", (SUM(_xldudf_WISEPRICE($B$54 & ".MI", "Close",, TEXT(WORKDAY(WORKDAY($C62+1,-1), 5), "yyyy-mm-dd"), TEXT(WORKDAY(WORKDAY($C62+1,-1), 5), "yyyy-mm-dd"))) / $D62) - 1), "/") -> -0.0056497175 | H62: =IFERROR(IF(SUM(_xldudf_WISEPRICE($B$54 & ".MI", "Close",, TEXT(WORKDAY(EDATE(WORKDAY($C62+1,-1), 1)-1, 1), "yyyy-mm-dd"), TEXT(WORKDAY(EDATE(WORKDAY($C62+1,-1), 1)-1, 1), "yyyy-mm-dd")))=0, "/", (SUM(_xldudf_WISEPRICE($B$54 & ".MI", "Close",, TEXT(WORKDAY(EDATE(WORKDAY($C62+1,-1), 1)-1, 1), "yyyy-mm-dd"), TEXT(WORKDAY(EDATE(WORKDAY($C62+1,-1), 1)-1, 1), "yyyy-mm-dd"))) / $D62) - 1), "/") -> -0.011299435
C63: Average Performance | D63: =_xlfn.AGGREGATE(1,6,D55:D62) -> 2.31375 | E63: =_xlfn.AGGREGATE(1,6,E55:E62) -> 0.0018361445 | F63: =_xlfn.AGGREGATE(1,6,F55:F62) -> 0.0072832452 | G63: =_xlfn.AGGREGATE(1,6,G55:G62) -> 0.016562352 | H63: =_xlfn.AGGREGATE(1,6,H55:H62) -> 0.019855856
B65: BAMI | D65: Price on event day | E65: Pfm 1 day | F65: Pfm next three days | G65: Pfm 1 week | H65: Pfm 1 month
C66: 42908 | D66: =IF(SUM(_xldudf_WISEPRICE($B$65 & ".MI", "Close",, TEXT(WORKDAY($C66+1,-1), "yyyy-mm-dd"), TEXT(WORKDAY($C66+1,-1), "yyyy-mm-dd")))=0, "/", SUM(_xldudf_WISEPRICE($B$65 & ".MI", "Close",, TEXT(WORKDAY($C66+1,-1), "yyyy-mm-dd"), TEXT(WORKDAY($C66+1,-1), "yyyy-mm-dd")))) -> 2.73 | E66: =IFERROR(IF(SUM(_xldudf_WISEPRICE($B$65 & ".MI", "Close",, TEXT(WORKDAY(WORKDAY($C66+1,-1), 1), "yyyy-mm-dd"), TEXT(WORKDAY(WORKDAY($C66+1,-1), 1), "yyyy-mm-dd")))=0, "/", (SUM(_xldudf_WISEPRICE($B$65 & ".MI", "Close",, TEXT(WORKDAY(WORKDAY($C66+1,-1), 1), "yyyy-mm-dd"), TEXT(WORKDAY(WORKDAY($C66+1,-1), 1), "yyyy-mm-dd"))) / $D66) - 1), "/") -> -0.014652015 | F66: =IFERROR(IF(SUM(_xldudf_WISEPRICE($B$65 & ".MI", "Close",, TEXT(WORKDAY(WORKDAY($C66+1,-1), 3), "yyyy-mm-dd"), TEXT(WORKDAY(WORKDAY($C66+1,-1), 3), "yyyy-mm-dd")))=0, "/", (SUM(_xldudf_WISEPRICE($B$65 & ".MI", "Close",, TEXT(WORKDAY(WORKDAY($C66+1,-1), 3), "yyyy-mm-dd"), TEXT(WORKDAY(WORKDAY($C66+1,-1), 3), "yyyy-mm-dd"))) / $D66) - 1), "/") -> 0.018315018 | G66: =IFERROR(IF(SUM(_xldudf_WISEPRICE($B$65 & ".MI", "Close",, TEXT(WORKDAY(WORKDAY($C66+1,-1), 5), "yyyy-mm-dd"), TEXT(WORKDAY(WORKDAY($C66+1,-1), 5), "yyyy-mm-dd")))=0, "/", (SUM(_xldudf_WISEPRICE($B$65 & ".MI", "Close",, TEXT(WORKDAY(WORKDAY($C66+1,-1), 5), "yyyy-mm-dd"), TEXT(WORKDAY(WORKDAY($C66+1,-1), 5), "yyyy-mm-dd"))) / $D66) - 1), "/") -> 0.076923077 | H66: =IFERROR(IF(SUM(_xldudf_WISEPRICE($B$65 & ".MI", "Close",, TEXT(WORKDAY(EDATE(WORKDAY($C66+1,-1), 1)-1, 1), "yyyy-mm-dd"), TEXT(WORKDAY(EDATE(WORKDAY($C66+1,-1), 1)-1, 1), "yyyy-mm-dd")))=0, "/", (SUM(_xldudf_WISEPRICE($B$65 & ".MI", "Close",, TEXT(WORKDAY(EDATE(WORKDAY($C66+1,-1), 1)-1, 1), "yyyy-mm-dd"), TEXT(WORKDAY(EDATE(WORKDAY($C66+1,-1), 1)-1, 1), "yyyy-mm-dd"))) / $D66) - 1), "/") -> 0.15384615
C67: 43270 | D67: =IF(SUM(_xldudf_WISEPRICE($B$65 & ".MI", "Close",, TEXT(WORKDAY($C67+1,-1), "yyyy-mm-dd"), TEXT(WORKDAY($C67+1,-1), "yyyy-mm-dd")))=0, "/", SUM(_xldudf_WISEPRICE($B$65 & ".MI", "Close",, TEXT(WORKDAY($C67+1,-1), "yyyy-mm-dd"), TEXT(WORKDAY($C67+1,-1), "yyyy-mm-dd")))) -> 2.53 | E67: =IFERROR(IF(SUM(_xldudf_WISEPRICE($B$65 & ".MI", "Close",, TEXT(WORKDAY(WORKDAY($C67+1,-1), 1), "yyyy-mm-dd"), TEXT(WORKDAY(WORKDAY($C67+1,-1), 1), "yyyy-mm-dd")))=0, "/", (SUM(_xldudf_WISEPRICE($B$65 & ".MI", "Close",, TEXT(WORKDAY(WORKDAY($C67+1,-1), 1), "yyyy-mm-dd"), TEXT(WORKDAY(WORKDAY($C67+1,-1), 1), "yyyy-mm-dd"))) / $D67) - 1), "/") -> 0.027667984 | F67: =IFERROR(IF(SUM(_xldudf_WISEPRICE($B$65 & ".MI", "Close",, TEXT(WORKDAY(WORKDAY($C67+1,-1), 3), "yyyy-mm-dd"), TEXT(WORKDAY(WORKDAY($C67+1,-1), 3), "yyyy-mm-dd")))=0, "/", (SUM(_xldudf_WISEPRICE($B$65 & ".MI", "Close",, TEXT(WORKDAY(WORKDAY($C67+1,-1), 3), "yyyy-mm-dd"), TEXT(WORKDAY(WORKDAY($C67+1,-1), 3), "yyyy-mm-dd"))) / $D67) - 1), "/") -> 0.043478261 | G67: =IFERROR(IF(SUM(_xldudf_WISEPRICE($B$65 & ".MI", "Close",, TEXT(WORKDAY(WORKDAY($C67+1,-1), 5), "yyyy-mm-dd"), TEXT(WORKDAY(WORKDAY($C67+1,-1), 5), "yyyy-mm-dd")))=0, "/", (SUM(_xldudf_WISEPRICE($B$65 & ".MI", "Close",, TEXT(WORKDAY(WORKDAY($C67+1,-1), 5), "yyyy-mm-dd"), TEXT(WORKDAY(WORKDAY($C67+1,-1), 5), "yyyy-mm-dd"))) / $D67) - 1), "/") -> -0.019762846 | H67: =IFERROR(IF(SUM(_xldudf_WISEPRICE($B$65 & ".MI", "Close",, TEXT(WORKDAY(EDATE(WORKDAY($C67+1,-1), 1)-1, 1), "yyyy-mm-dd"), TEXT(WORKDAY(EDATE(WORKDAY($C67+1,-1), 1)-1, 1), "yyyy-mm-dd")))=0, "/", (SUM(_xldudf_WISEPRICE($B$65 & ".MI", "Close",, TEXT(WORKDAY(EDATE(WORKDAY($C67+1,-1), 1)-1, 1), "yyyy-mm-dd"), TEXT(WORKDAY(EDATE(WORKDAY($C67+1,-1), 1)-1, 1), "yyyy-mm-dd"))) / $D67) - 1), "/") -> 0.035573123
C68: 43572 | D68: =IF(SUM(_xldudf_WISEPRICE($B$65 & ".MI", "Close",, TEXT(WORKDAY($C68+1,-1), "yyyy-mm-dd"), TEXT(WORKDAY($C68+1,-1), "yyyy-mm-dd")))=0, "/", SUM(_xldudf_WISEPRICE($B$65 & ".MI", "Close",, TEXT(WORKDAY($C68+1,-1), "yyyy-mm-dd"), TEXT(WORKDAY($C68+1,-1), "yyyy-mm-dd")))) -> 2.13 | E68: =IFERROR(IF(SUM(_xldudf_WISEPRICE($B$65 & ".MI", "Close",, TEXT(WORKDAY(WORKDAY($C68+1,-1), 1), "yyyy-mm-dd"), TEXT(WORKDAY(WORKDAY($C68+1,-1), 1), "yyyy-mm-dd")))=0, "/", (SUM(_xldudf_WISEPRICE($B$65 & ".MI", "Close",, TEXT(WORKDAY(WORKDAY($C68+1,-1), 1), "yyyy-mm-dd"), TEXT(WORKDAY(WORKDAY($C68+1,-1), 1), "yyyy-mm-dd"))) / $D68) - 1), "/") -> 0 | F68: =IFERROR(IF(SUM(_xldudf_WISEPRICE($B$65 & ".MI", "Close",, TEXT(WORKDAY(WORKDAY($C68+1,-1), 3), "yyyy-mm-dd"), TEXT(WORKDAY(WORKDAY($C68+1,-1), 3), "yyyy-mm-dd")))=0, "/", (SUM(_xldudf_WISEPRICE($B$65 & ".MI", "Close",, TEXT(WORKDAY(WORKDAY($C68+1,-1), 3), "yyyy-mm-dd"), TEXT(WORKDAY(WORKDAY($C68+1,-1), 3), "yyyy-mm-dd"))) / $D68) - 1), "/") -> / | G68: =IFERROR(IF(SUM(_xldudf_WISEPRICE($B$65 & ".MI", "Close",, TEXT(WORKDAY(WORKDAY($C68+1,-1), 5), "yyyy-mm-dd"), TEXT(WORKDAY(WORKDAY($C68+1,-1), 5), "yyyy-mm-dd")))=0, "/", (SUM(_xldudf_WISEPRICE($B$65 & ".MI", "Close",, TEXT(WORKDAY(WORKDAY($C68+1,-1), 5), "yyyy-mm-dd"), TEXT(WORKDAY(WORKDAY($C68+1,-1), 5), "yyyy-mm-dd"))) / $D68) - 1), "/") -> -0.037558685 | H68: =IFERROR(IF(SUM(_xldudf_WISEPRICE($B$65 & ".MI", "Close",, TEXT(WORKDAY(EDATE(WORKDAY($C68+1,-1), 1)-1, 1), "yyyy-mm-dd"), TEXT(WORKDAY(EDATE(WORKDAY($C68+1,-1), 1)-1, 1), "yyyy-mm-dd")))=0, "/", (SUM(_xldudf_WISEPRICE($B$65 & ".MI", "Close",, TEXT(WORKDAY(EDATE(WORKDAY($C68+1,-1), 1)-1, 1), "yyyy-mm-dd"), TEXT(WORKDAY(EDATE(WORKDAY($C68+1,-1), 1)-1, 1), "yyyy-mm-dd"))) / $D68) - 1), "/") -> -0.18779343
C69: 44140 | D69: =IF(SUM(_xldudf_WISEPRICE($B$65 & ".MI", "Close",, TEXT(WORKDAY($C69+1,-1), "yyyy-mm-dd"), TEXT(WORKDAY($C69+1,-1), "yyyy-mm-dd")))=0, "/", SUM(_xldudf_WISEPRICE($B$65 & ".MI", "Close",, TEXT(WORKDAY($C69+1,-1), "yyyy-mm-dd"), TEXT(WORKDAY($C69+1,-1), "yyyy-mm-dd")))) -> 1.65 | E69: =IFERROR(IF(SUM(_xldudf_WISEPRICE($B$65 & ".MI", "Close",, TEXT(WORKDAY(WORKDAY($C69+1,-1), 1), "yyyy-mm-dd"), TEXT(WORKDAY(WORKDAY($C69+1,-1), 1), "yyyy-mm-dd")))=0, "/", (SUM(_xldudf_WISEPRICE($B$65 & ".MI", "Close",, TEXT(WORKDAY(WORKDAY($C69+1,-1), 1), "yyyy-mm-dd"), TEXT(WORKDAY(WORKDAY($C69+1,-1), 1), "yyyy-mm-dd"))) / $D69) - 1), "/") -> 0 | F69: =IFERROR(IF(SUM(_xldudf_WISEPRICE($B$65 & ".MI", "Close",, TEXT(WORKDAY(WORKDAY($C69+1,-1), 3), "yyyy-mm-dd"), TEXT(WORKDAY(WORKDAY($C69+1,-1), 3), "yyyy-mm-dd")))=0, "/", (SUM(_xldudf_WISEPRICE($B$65 & ".MI", "Close",, TEXT(WORKDAY(WORKDAY($C69+1,-1), 3), "yyyy-mm-dd"), TEXT(WORKDAY(WORKDAY($C69+1,-1), 3), "yyyy-mm-dd"))) / $D69) - 1), "/") -> 0.090909091 | G69: =IFERROR(IF(SUM(_xldudf_WISEPRICE($B$65 & ".MI", "Close",, TEXT(WORKDAY(WORKDAY($C69+1,-1), 5), "yyyy-mm-dd"), TEXT(WORKDAY(WORKDAY($C69+1,-1), 5), "yyyy-mm-dd")))=0, "/", (SUM(_xldudf_WISEPRICE($B$65 & ".MI", "Close",, TEXT(WORKDAY(WORKDAY($C69+1,-1), 5), "yyyy-mm-dd"), TEXT(WORKDAY(WORKDAY($C69+1,-1), 5), "yyyy-mm-dd"))) / $D69) - 1), "/") -> 0.084848485 | H69: =IFERROR(IF(SUM(_xldudf_WISEPRICE($B$65 & ".MI", "Close",, TEXT(WORKDAY(EDATE(WORKDAY($C69+1,-1), 1)-1, 1), "yyyy-mm-dd"), TEXT(WORKDAY(EDATE(WORKDAY($C69+1,-1), 1)-1, 1), "yyyy-mm-dd")))=0, "/", (SUM(_xldudf_WISEPRICE($B$65 & ".MI", "Close",, TEXT(WORKDAY(EDATE(WORKDAY($C69+1,-1), 1)-1, 1), "yyyy-mm-dd"), TEXT(WORKDAY(EDATE(WORKDAY($C69+1,-1), 1)-1, 1), "yyyy-mm-dd"))) / $D69) - 1), "/") -> 0.10909091
C70: 44686 | D70: =IF(SUM(_xldudf_WISEPRICE($B$65 & ".MI", "Close",, TEXT(WORKDAY($C70+1,-1), "yyyy-mm-dd"), TEXT(WORKDAY($C70+1,-1), "yyyy-mm-dd")))=0, "/", SUM(_xldudf_WISEPRICE($B$65 & ".MI", "Close",, TEXT(WORKDAY($C70+1,-1), "yyyy-mm-dd"), TEXT(WORKDAY($C70+1,-1), "yyyy-mm-dd")))) -> 2.92 | E70: =IFERROR(IF(SUM(_xldudf_WISEPRICE($B$65 & ".MI", "Close",, TEXT(WORKDAY(WORKDAY($C70+1,-1), 1), "yyyy-mm-dd"), TEXT(WORKDAY(WORKDAY($C70+1,-1), 1), "yyyy-mm-dd")))=0, "/", (SUM(_xldudf_WISEPRICE($B$65 & ".MI", "Close",, TEXT(WORKDAY(WORKDAY($C70+1,-1), 1), "yyyy-mm-dd"), TEXT(WORKDAY(WORKDAY($C70+1,-1), 1), "yyyy-mm-dd"))) / $D70) - 1), "/") -> -0.010273973 | F70: =IFERROR(IF(SUM(_xldudf_WISEPRICE($B$65 & ".MI", "Close",, TEXT(WORKDAY(WORKDAY($C70+1,-1), 3), "yyyy-mm-dd"), TEXT(WORKDAY(WORKDAY($C70+1,-1), 3), "yyyy-mm-dd")))=0, "/", (SUM(_xldudf_WISEPRICE($B$65 & ".MI", "Close",, TEXT(WORKDAY(WORKDAY($C70+1,-1), 3), "yyyy-mm-dd"), TEXT(WORKDAY(WORKDAY($C70+1,-1), 3), "yyyy-mm-dd"))) / $D70) - 1), "/") -> -0.034246575 | G70: =IFERROR(IF(SUM(_xldudf_WISEPRICE($B$65 & ".MI", "Close",, TEXT(WORKDAY(WORKDAY($C70+1,-1), 5), "yyyy-mm-dd"), TEXT(WORKDAY(WORKDAY($C70+1,-1), 5), "yyyy-mm-dd")))=0, "/", (SUM(_xldudf_WISEPRICE($B$65 & ".MI", "Close",, TEXT(WORKDAY(WORKDAY($C70+1,-1), 5), "yyyy-mm-dd"), TEXT(WORKDAY(WORKDAY($C70+1,-1), 5), "yyyy-mm-dd"))) / $D70) - 1), "/") -> 0.0068493151 | H70: =IFERROR(IF(SUM(_xldudf_WISEPRICE($B$65 & ".MI", "Close",, TEXT(WORKDAY(EDATE(WORKDAY($C70+1,-1), 1)-1, 1), "yyyy-mm-dd"), TEXT(WORKDAY(EDATE(WORKDAY($C70+1,-1), 1)-1, 1), "yyyy-mm-dd")))=0, "/", (SUM(_xldudf_WISEPRICE($B$65 & ".MI", "Close",, TEXT(WORKDAY(EDATE(WORKDAY($C70+1,-1), 1)-1, 1), "yyyy-mm-dd"), TEXT(WORKDAY(EDATE(WORKDAY($C70+1,-1), 1)-1, 1), "yyyy-mm-dd"))) / $D70) - 1), "/") -> 0.095890411
C71: Average Performance | D71: =_xlfn.AGGREGATE(1,6,D66:D70) -> 2.392 | E71: =_xlfn.AGGREGATE(1,6,E66:E70) -> 0.00054839939 | F71: =_xlfn.AGGREGATE(1,6,F66:F70) -> 0.029613949 | G71: =_xlfn.AGGREGATE(1,6,G66:G70) -> 0.022259869 | H71: =_xlfn.AGGREGATE(1,6,H66:H70) -> 0.041321434
B73: BPE | D73: Price on event day | E73: Pfm 1 day | F73: Pfm next three days | G73: Pfm 1 week | H73: Pfm 1 month
C74: 43454 | D74: =IF(SUM(_xldudf_WISEPRICE($B$73 & ".MI", "Close",, TEXT(WORKDAY($C74+1,-1), "yyyy-mm-dd"), TEXT(WORKDAY($C74+1,-1), "yyyy-mm-dd")))=0, "/", SUM(_xldudf_WISEPRICE($B$73 & ".MI", "Close",, TEXT(WORKDAY($C74+1,-1), "yyyy-mm-dd"), TEXT(WORKDAY($C74+1,-1), "yyyy-mm-dd")))) -> 2.27 | E74: =IFERROR(IF(SUM(_xldudf_WISEPRICE($B$73 & ".MI", "Close",, TEXT(WORKDAY(WORKDAY($C74+1,-1), 1), "yyyy-mm-dd"), TEXT(WORKDAY(WORKDAY($C74+1,-1), 1), "yyyy-mm-dd")))=0, "/", (SUM(_xldudf_WISEPRICE($B$73 & ".MI", "Close",, TEXT(WORKDAY(WORKDAY($C74+1,-1), 1), "yyyy-mm-dd"), TEXT(WORKDAY(WORKDAY($C74+1,-1), 1), "yyyy-mm-dd"))) / $D74) - 1), "/") -> -0.0088105727 | F74: =IFERROR(IF(SUM(_xldudf_WISEPRICE($B$73 & ".MI", "Close",, TEXT(WORKDAY(WORKDAY($C74+1,-1), 3), "yyyy-mm-dd"), TEXT(WORKDAY(WORKDAY($C74+1,-1), 3), "yyyy-mm-dd")))=0, "/", (SUM(_xldudf_WISEPRICE($B$73 & ".MI", "Close",, TEXT(WORKDAY(WORKDAY($C74+1,-1), 3), "yyyy-mm-dd"), TEXT(WORKDAY(WORKDAY($C74+1,-1), 3), "yyyy-mm-dd"))) / $D74) - 1), "/") -> / | G74: =IFERROR(IF(SUM(_xldudf_WISEPRICE($B$73 & ".MI", "Close",, TEXT(WORKDAY(WORKDAY($C74+1,-1), 5), "yyyy-mm-dd"), TEXT(WORKDAY(WORKDAY($C74+1,-1), 5), "yyyy-mm-dd")))=0, "/", (SUM(_xldudf_WISEPRICE($B$73 & ".MI", "Close",, TEXT(WORKDAY(WORKDAY($C74+1,-1), 5), "yyyy-mm-dd"), TEXT(WORKDAY(WORKDAY($C74+1,-1), 5), "yyyy-mm-dd"))) / $D74) - 1), "/") -> -0.022026432 | H74: =IFERROR(IF(SUM(_xldudf_WISEPRICE($B$73 & ".MI", "Close",, TEXT(WORKDAY(EDATE(WORKDAY($C74+1,-1), 1)-1, 1), "yyyy-mm-dd"), TEXT(WORKDAY(EDATE(WORKDAY($C74+1,-1), 1)-1, 1), "yyyy-mm-dd")))=0, "/", (SUM(_xldudf_WISEPRICE($B$73 & ".MI", "Close",, TEXT(WORKDAY(EDATE(WORKDAY($C74+1,-1), 1)-1, 1), "yyyy-mm-dd"), TEXT(WORKDAY(EDATE(WORKDAY($C74+1,-1), 1)-1, 1), "yyyy-mm-dd"))) / $D74) - 1), "/") -> -0.083700441
C75: 43504 | D75: =IF(SUM(_xldudf_WISEPRICE($B$73 & ".MI", "Close",, TEXT(WORKDAY($C75+1,-1), "yyyy-mm-dd"), TEXT(WORKDAY($C75+1,-1), "yyyy-mm-dd")))=0, "/", SUM(_xldudf_WISEPRICE($B$73 & ".MI", "Close",, TEXT(WORKDAY($C75+1,-1), "yyyy-mm-dd"), TEXT(WORKDAY($C75+1,-1), "yyyy-mm-dd")))) -> 2.22 | E75: =IFERROR(IF(SUM(_xldudf_WISEPRICE($B$73 & ".MI", "Close",, TEXT(WORKDAY(WORKDAY($C75+1,-1), 1), "yyyy-mm-dd"), TEXT(WORKDAY(WORKDAY($C75+1,-1), 1), "yyyy-mm-dd")))=0, "/", (SUM(_xldudf_WISEPRICE($B$73 & ".MI", "Close",, TEXT(WORKDAY(WORKDAY($C75+1,-1), 1), "yyyy-mm-dd"), TEXT(WORKDAY(WORKDAY($C75+1,-1), 1), "yyyy-mm-dd"))) / $D75) - 1), "/") -> 0.040540541 | F75: =IFERROR(IF(SUM(_xldudf_WISEPRICE($B$73 & ".MI", "Close",, TEXT(WORKDAY(WORKDAY($C75+1,-1), 3), "yyyy-mm-dd"), TEXT(WORKDAY(WORKDAY($C75+1,-1), 3), "yyyy-mm-dd")))=0, "/", (SUM(_xldudf_WISEPRICE($B$73 & ".MI", "Close",, TEXT(WORKDAY(WORKDAY($C75+1,-1), 3), "yyyy-mm-dd"), TEXT(WORKDAY(WORKDAY($C75+1,-1), 3), "yyyy-mm-dd"))) / $D75) - 1), "/") -> 0.031531532 | G75: =IFERROR(IF(SUM(_xldudf_WISEPRICE($B$73 & ".MI", "Close",, TEXT(WORKDAY(WORKDAY($C75+1,-1), 5), "yyyy-mm-dd"), TEXT(WORKDAY(WORKDAY($C75+1,-1), 5), "yyyy-mm-dd")))=0, "/", (SUM(_xldudf_WISEPRICE($B$73 & ".MI", "Close",, TEXT(WORKDAY(WORKDAY($C75+1,-1), 5), "yyyy-mm-dd"), TEXT(WORKDAY(WORKDAY($C75+1,-1), 5), "yyyy-mm-dd"))) / $D75) - 1), "/") -> 0.076576577 | H75: =IFERROR(IF(SUM(_xldudf_WISEPRICE($B$73 & ".MI", "Close",, TEXT(WORKDAY(EDATE(WORKDAY($C75+1,-1), 1)-1, 1), "yyyy-mm-dd"), TEXT(WORKDAY(EDATE(WORKDAY($C75+1,-1), 1)-1, 1), "yyyy-mm-dd")))=0, "/", (SUM(_xldudf_WISEPRICE($B$73 & ".MI", "Close",, TEXT(WORKDAY(EDATE(WORKDAY($C75+1,-1), 1)-1, 1), "yyyy-mm-dd"), TEXT(WORKDAY(EDATE(WORKDAY($C75+1,-1), 1)-1, 1), "yyyy-mm-dd"))) / $D75) - 1), "/") -> 0.072072072
C76: 44305 | D76: =IF(SUM(_xldudf_WISEPRICE($B$73 & ".MI", "Close",, TEXT(WORKDAY($C76+1,-1), "yyyy-mm-dd"), TEXT(WORKDAY($C76+1,-1), "yyyy-mm-dd")))=0, "/", SUM(_xldudf_WISEPRICE($B$73 & ".MI", "Close",, TEXT(WORKDAY($C76+1,-1), "yyyy-mm-dd"), TEXT(WORKDAY($C76+1,-1), "yyyy-mm-dd")))) -> 1.95 | E76: =IFERROR(IF(SUM(_xldudf_WISEPRICE($B$73 & ".MI", "Close",, TEXT(WORKDAY(WORKDAY($C76+1,-1), 1), "yyyy-mm-dd"), TEXT(WORKDAY(WORKDAY($C76+1,-1), 1), "yyyy-mm-dd")))=0, "/", (SUM(_xldudf_WISEPRICE($B$73 & ".MI", "Close",, TEXT(WORKDAY(WORKDAY($C76+1,-1), 1), "yyyy-mm-dd"), TEXT(WORKDAY(WORKDAY($C76+1,-1), 1), "yyyy-mm-dd"))) / $D76) - 1), "/") -> -0.051282051 | F76: =IFERROR(IF(SUM(_xldudf_WISEPRICE($B$73 & ".MI", "Close",, TEXT(WORKDAY(WORKDAY($C76+1,-1), 3), "yyyy-mm-dd"), TEXT(WORKDAY(WORKDAY($C76+1,-1), 3), "yyyy-mm-dd")))=0, "/", (SUM(_xldudf_WISEPRICE($B$73 & ".MI", "Close",, TEXT(WORKDAY(WORKDAY($C76+1,-1), 3), "yyyy-mm-dd"), TEXT(WORKDAY(WORKDAY($C76+1,-1), 3), "yyyy-mm-dd"))) / $D76) - 1), "/") -> -0.071794872 | G76: =IFERROR(IF(SUM(_xldudf_WISEPRICE($B$73 & ".MI", "Close",, TEXT(WORKDAY(WORKDAY($C76+1,-1), 5), "yyyy-mm-dd"), TEXT(WORKDAY(WORKDAY($C76+1,-1), 5), "yyyy-mm-dd")))=0, "/", (SUM(_xldudf_WISEPRICE($B$73 & ".MI", "Close",, TEXT(WORKDAY(WORKDAY($C76+1,-1), 5), "yyyy-mm-dd"), TEXT(WORKDAY(WORKDAY($C76+1,-1), 5), "yyyy-mm-dd"))) / $D76) - 1), "/") -> -0.041025641 | H76: =IFERROR(IF(SUM(_xldudf_WISEPRICE($B$73 & ".MI", "Close",, TEXT(WORKDAY(EDATE(WORKDAY($C76+1,-1), 1)-1, 1), "yyyy-mm-dd"), TEXT(WORKDAY(EDATE(WORKDAY($C76+1,-1), 1)-1, 1), "yyyy-mm-dd")))=0, "/", (SUM(_xldudf_WISEPRICE($B$73 & ".MI", "Close",, TEXT(WORKDAY(EDATE(WORKDAY($C76+1,-1), 1)-1, 1), "yyyy-mm-dd"), TEXT(WORKDAY(EDATE(WORKDAY($C76+1,-1), 1)-1, 1), "yyyy-mm-dd"))) / $D76) - 1), "/") -> 0.015384615
C77: 44552 | D77: =IF(SUM(_xldudf_WISEPRICE($B$73 & ".MI", "Close",, TEXT(WORKDAY($C77+1,-1), "yyyy-mm-dd"), TEXT(WORKDAY($C77+1,-1), "yyyy-mm-dd")))=0, "/", SUM(_xldudf_WISEPRICE($B$73 & ".MI", "Close",, TEXT(WORKDAY($C77+1,-1), "yyyy-mm-dd"), TEXT(WORKDAY($C77+1,-1), "yyyy-mm-dd")))) -> 1.78 | E77: =IFERROR(IF(SUM(_xldudf_WISEPRICE($B$73 & ".MI", "Close",, TEXT(WORKDAY(WORKDAY($C77+1,-1), 1), "yyyy-mm-dd"), TEXT(WORKDAY(WORKDAY($C77+1,-1), 1), "yyyy-mm-dd")))=0, "/", (SUM(_xldudf_WISEPRICE($B$73 & ".MI", "Close",, TEXT(WORKDAY(WORKDAY($C77+1,-1), 1), "yyyy-mm-dd"), TEXT(WORKDAY(WORKDAY($C77+1,-1), 1), "yyyy-mm-dd"))) / $D77) - 1), "/") -> -0.011235955 | F77: =IFERROR(IF(SUM(_xldudf_WISEPRICE($B$73 & ".MI", "Close",, TEXT(WORKDAY(WORKDAY($C77+1,-1), 3), "yyyy-mm-dd"), TEXT(WORKDAY(WORKDAY($C77+1,-1), 3), "yyyy-mm-dd")))=0, "/", (SUM(_xldudf_WISEPRICE($B$73 & ".MI", "Close",, TEXT(WORKDAY(WORKDAY($C77+1,-1), 3), "yyyy-mm-dd"), TEXT(WORKDAY(WORKDAY($C77+1,-1), 3), "yyyy-mm-dd"))) / $D77) - 1), "/") -> 0.0056179775 | G77: =IFERROR(IF(SUM(_xldudf_WISEPRICE($B$73 & ".MI", "Close",, TEXT(WORKDAY(WORKDAY($C77+1,-1), 5), "yyyy-mm-dd"), TEXT(WORKDAY(WORKDAY($C77+1,-1), 5), "yyyy-mm-dd")))=0, "/", (SUM(_xldudf_WISEPRICE($B$73 & ".MI", "Close",, TEXT(WORKDAY(WORKDAY($C77+1,-1), 5), "yyyy-mm-dd"), TEXT(WORKDAY(WORKDAY($C77+1,-1), 5), "yyyy-mm-dd"))) / $D77) - 1), "/") -> 0.028089888 | H77: =IFERROR(IF(SUM(_xldudf_WISEPRICE($B$73 & ".MI", "Close",, TEXT(WORKDAY(EDATE(WORKDAY($C77+1,-1), 1)-1, 1), "yyyy-mm-dd"), TEXT(WORKDAY(EDATE(WORKDAY($C77+1,-1), 1)-1, 1), "yyyy-mm-dd")))=0, "/", (SUM(_xldudf_WISEPRICE($B$73 & ".MI", "Close",, TEXT(WORKDAY(EDATE(WORKDAY($C77+1,-1), 1)-1, 1), "yyyy-mm-dd"), TEXT(WORKDAY(EDATE(WORKDAY($C77+1,-1), 1)-1, 1), "yyyy-mm-dd"))) / $D77) - 1), "/") -> 0.0056179775
C78: 44777 | D78: =IF(SUM(_xldudf_WISEPRICE($B$73 & ".MI", "Close",, TEXT(WORKDAY($C78+1,-1), "yyyy-mm-dd"), TEXT(WORKDAY($C78+1,-1), "yyyy-mm-dd")))=0, "/", SUM(_xldudf_WISEPRICE($B$73 & ".MI", "Close",, TEXT(WORKDAY($C78+1,-1), "yyyy-mm-dd"), TEXT(WORKDAY($C78+1,-1), "yyyy-mm-dd")))) -> 1.43 | E78: =IFERROR(IF(SUM(_xldudf_WISEPRICE($B$73 & ".MI", "Close",, TEXT(WORKDAY(WORKDAY($C78+1,-1), 1), "yyyy-mm-dd"), TEXT(WORKDAY(WORKDAY($C78+1,-1), 1), "yyyy-mm-dd")))=0, "/", (SUM(_xldudf_WISEPRICE($B$73 & ".MI", "Close",, TEXT(WORKDAY(WORKDAY($C78+1,-1), 1), "yyyy-mm-dd"), TEXT(WORKDAY(WORKDAY($C78+1,-1), 1), "yyyy-mm-dd"))) / $D78) - 1), "/") -> 0.097902098 | F78: =IFERROR(IF(SUM(_xldudf_WISEPRICE($B$73 & ".MI", "Close",, TEXT(WORKDAY(WORKDAY($C78+1,-1), 3), "yyyy-mm-dd"), TEXT(WORKDAY(WORKDAY($C78+1,-1), 3), "yyyy-mm-dd")))=0, "/", (SUM(_xldudf_WISEPRICE($B$73 & ".MI", "Close",, TEXT(WORKDAY(WORKDAY($C78+1,-1), 3), "yyyy-mm-dd"), TEXT(WORKDAY(WORKDAY($C78+1,-1), 3), "yyyy-mm-dd"))) / $D78) - 1), "/") -> 0.13286713 | G78: =IFERROR(IF(SUM(_xldudf_WISEPRICE($B$73 & ".MI", "Close",, TEXT(WORKDAY(WORKDAY($C78+1,-1), 5), "yyyy-mm-dd"), TEXT(WORKDAY(WORKDAY($C78+1,-1), 5), "yyyy-mm-dd")))=0, "/", (SUM(_xldudf_WISEPRICE($B$73 & ".MI", "Close",, TEXT(WORKDAY(WORKDAY($C78+1,-1), 5), "yyyy-mm-dd"), TEXT(WORKDAY(WORKDAY($C78+1,-1), 5), "yyyy-mm-dd"))) / $D78) - 1), "/") -> 0.14685315 | H78: =IFERROR(IF(SUM(_xldudf_WISEPRICE($B$73 & ".MI", "Close",, TEXT(WORKDAY(EDATE(WORKDAY($C78+1,-1), 1)-1, 1), "yyyy-mm-dd"), TEXT(WORKDAY(EDATE(WORKDAY($C78+1,-1), 1)-1, 1), "yyyy-mm-dd")))=0, "/", (SUM(_xldudf_WISEPRICE($B$73 & ".MI", "Close",, TEXT(WORKDAY(EDATE(WORKDAY($C78+1,-1), 1)-1, 1), "yyyy-mm-dd"), TEXT(WORKDAY(EDATE(WORKDAY($C78+1,-1), 1)-1, 1), "yyyy-mm-dd"))) / $D78) - 1), "/") -> 0.027972028
C79: Average Performance | D79: =_xlfn.AGGREGATE(1,6,D74:D78) -> 1.93 | E79: =_xlfn.AGGREGATE(1,6,E74:E78) -> 0.013422812 | F79: =_xlfn.AGGREGATE(1,6,F74:F78) -> 0.024555443 | G79: =_xlfn.AGGREGATE(1,6,G74:G78) -> 0.037693508 | H79: =_xlfn.AGGREGATE(1,6,H74:H78) -> 0.0074692505

Sheet Event Master List
A1: Event_ID | B1: Bank | C1: Ticker | D1: Announcement_Date | E1: GBV_EUR_m | F1: GACS | G1: Deal_Type | H1: Source_Sheet
A2: NG-001 | B2: UniCredit | C2: UCG | D2: 42046 | E2: 2400 | F2: No | G2: Bad Loans | H2: Non-GACS
A3: NG-006 | B3: MPS | C3: BMPS | D3: 42178 | E3: 1300 | F3: No | G3: Bad Loans | H3: Non-GACS
A4: NG-002 | B4: UniCredit | C4: UCG | D4: 42185 | E4: 625 | F4: No | G4: Bad Loans | H4: Non-GACS
A5: NG-003 | B5: UniCredit | C5: UCG | D5: 42186 | E5: 205 | F5: No | G5: Bad Loans | H5: Non-GACS
A6: NG-004 | B6: UniCredit | C6: UCG | D6: 42275 | E6: 1200 | F6: No | G6: Bad Loans | H6: Non-GACS
A7: NG-005 | B7: UniCredit | C7: UCG | D7: 42355 | E7: 250 | F7: No | G7: Bad Loans | H7: Non-GACS
A8: NG-008 | B8: UniCredit | C8: UCG | D8: 42717 | E8: 17700 | F8: No | G8: Bad Loans | H8: Non-GACS
A9: NG-009 | B9: Intesa Sanpaolo | C9: ISP | D9: 42859 | E9: 2500 | F9: No | G9: Bad Loans | H9: Non-GACS
A10: NG-010 | B10: Banco BPM | C10: BAMI | D10: 42908 | E10: 750 | F10: No | G10: Bad Loans | H10: Non-GACS
A11: GACS-001 | B11: UniCredit | C11: UCG | D11: 43081 | E11: 5400 | F11: Yes | G11: Bad Loans | H11: GACS
A12: NG-011 | B12: Intesa Sanpaolo | C12: ISP | D12: 43206 | E12: 10800 | F12: No | G12: Bad Loans | H12: Non-GACS
A13: GACS-002 | B13: MPS | C13: BMPS | D13: 43230 | E13: 24100 | F13: Yes | G13: Bad Loans | H13: GACS
... A75: NG-068 | B75: BPER | C75: BPE | D75: 44777 | E75: 1500 | F75: No | G75: Bad Loans | H75: Non-GACS

Sheet Daily Returns
A1: Date | B1: FTSEMIB.MI_Close | C1: FTSEMIB.MI_Return | D1: UCG.MI_Close | E1: UCG.MI_Return | F1: BMPS.MI_Close | G1: BMPS.MI_Return | H1: ISP.MI_Close | I1: ISP.MI_Return | J1: BPE.MI_Close | K1: BPE.MI_Return | L1: BAMI.MI_Close | M1: BAMI.MI_Return | N1: BPSO.MI_Close | O1: BPSO.MI_Return
A2: 41821 | B2: =IFERROR(INDEX('Price Data'!B:B,MATCH(TEXT(A2,"YYYY-MM-DD"),'Price Data'!A:A,0)),"") -> 21563 | D2: =IFERROR(INDEX('Price Data'!E:E,MATCH(TEXT(A2,"YYYY-MM-DD"),'Price Data'!D:D,0)),"") -> 31.39 | F2: =IFERROR(INDEX('Price Data'!H:H,MATCH(TEXT(A2,"YYYY-MM-DD"),'Price Data'!G:G,0)),"") -> 62503.816 | H2: =IFERROR(INDEX('Price Data'!K:K,MATCH(TEXT(A2,"YYYY-MM-DD"),'Price Data'!J:J,0)),"") -> 2.32 | J2: =IFERROR(INDEX('Price Data'!N:N,MATCH(TEXT(A2,"YYYY-MM-DD"),'Price Data'!M:M,0)),"") -> 4.64 | L2: =IFERROR(INDEX('Price Data'!Q:Q,MATCH(TEXT(A2,"YYYY-MM-DD"),'Price Data'!P:P,0)),"") -> 9.24 | N2: =IFERROR(INDEX('Price Data'!T:T,MATCH(TEXT(A2,"YYYY-MM-DD"),'Price Data'!S:S,0)),"") -> 3.6
A3: 41822 | B3: =IFERROR(INDEX('Price Data'!B:B,MATCH(TEXT(A3,"YYYY-MM-DD"),'Price Data'!A:A,0)),"") -> 21678 | C3: {=IFERROR(IF(ISNUMBER(B3),(B3-INDEX('Price Data'!B:B,MATCH(TEXT(A3,"YYYY-MM-DD"),'Price Data'!A:A,0)+1))/INDEX('Price Data'!B:B,MATCH(TEXT(A3,"YYYY-MM-DD"),'Price Data'!A:A,0)+1),""),"")} -> 0.0053332097 | D3: =IFERROR(INDEX('Price Data'!E:E,MATCH(TEXT(A3,"YYYY-MM-DD"),'Price Data'!D:D,0)),"") -> 31.49 | E3: {=IFERROR(IF(ISNUMBER(D3),(D3-INDEX('Price Data'!E:E,MATCH(TEXT(A3,"YYYY-MM-DD"),'Price Data'!D:D,0)+1))/INDEX('Price Data'!E:E,MATCH(TEXT(A3,"YYYY-MM-DD"),'Price Data'!D:D,0)+1),""),"")} -> 0.0031857279 | F3: =IFERROR(INDEX('Price Data'!H:H,MATCH(TEXT(A3,"YYYY-MM-DD"),'Price Data'!G:G,0)),"") -> 61812.039 | G3: {=IFERROR(IF(ISNUMBER(F3),(F3-INDEX('Price Data'!H:H,MATCH(TEXT(A3,"YYYY-MM-DD"),'Price Data'!G:G,0)+1))/INDEX('Price Data'!H:H,MATCH(TEXT(A3,"YYYY-MM-DD"),'Price Data'!G:G,0)+1),""),"")} -> -0.011067762 | H3: =IFERROR(INDEX('Price Data'!K:K,MATCH(TEXT(A3,"YYYY-MM-DD"),'Price Data'!J:J,0)),"") -> 2.33 | I3: {=IFERROR(IF(ISNUMBER(H3),(H3-INDEX('Price Data'!K:K,MATCH(TEXT(A3,"YYYY-MM-DD"),'Price Data'!J:J,0)+1))/INDEX('Price Data'!K:K,MATCH(TEXT(A3,"YYYY-MM-DD"),'Price Data'!J:J,0)+1),""),"")} -> 0.0043103448 | J3: =IFERROR(INDEX('Price Data'!N:N,MATCH(TEXT(A3,"YYYY-MM-DD"),'Price Data'!M:M,0)),"") -> 4.7 | K3: {=IFERROR(IF(ISNUMBER(J3),(J3-INDEX('Price Data'!N:N,MATCH(TEXT(A3,"YYYY-MM-DD"),'Price Data'!M:M,0)+1))/INDEX('Price Data'!N:N,MATCH(TEXT(A3,"YYYY-MM-DD"),'Price Data'!M:M,0)+1),""),"")} -> 0.012931034 | L3: =IFERROR(INDEX('Price Data'!Q:Q,MATCH(TEXT(A3,"YYYY-MM-DD"),'Price Data'!P:P,0)),"") -> 9.32 | M3: {=IFERROR(IF(ISNUMBER(L3),(L3-INDEX('Price Data'!Q:Q,MATCH(TEXT(A3,"YYYY-MM-DD"),'Price Data'!P:P,0)+1))/INDEX('Price Data'!Q:Q,MATCH(TEXT(A3,"YYYY-MM-DD"),'Price Data'!P:P,0)+1),""),"")} -> 0.0086580087 | N3: =IFERROR(INDEX('Price Data'!T:T,MATCH(TEXT(A3,"YYYY-MM-DD"),'Price Data'!S:S,0)),"") -> 3.75 | O3: {=IFERROR(IF(ISNUMBER(N3),(N3-INDEX('Price Data'!T:T,MATCH(TEXT(A3,"YYYY-MM-DD"),'Price Data'!S:S,0)+1))/INDEX('Price Data'!T:T,MATCH(TEXT(A3,"YYYY-MM-DD"),'Price Data'!S:S,0)+1),""),"")} -> 0.041666667
A4: 41823 | B4: =IFERROR(INDEX('Price Data'!B:B,MATCH(TEXT(A4,"YYYY-MM-DD"),'Price Data'!A:A,0)),"") -> 21884 | C4: {=IFERROR(IF(ISNUMBER(B4),(B4-INDEX('Price Data'!B:B,MATCH(TEXT(A4,"YYYY-MM-DD"),'Price Data'!A:A,0)+1))/INDEX('Price Data'!B:B,MATCH(TEXT(A4,"YYYY-MM-DD"),'Price Data'!A:A,0)+1),""),"")} -> 0.0095027217 | D4: =IFERROR(INDEX('Price Data'!E:E,MATCH(TEXT(A4,"YYYY-MM-DD"),'Price Data'!D:D,0)),"") -> 32.01 | E4: {=IFERROR(IF(ISNUMBER(D4),(D4-INDEX('Price Data'!E:E,MATCH(TEXT(A4,"YYYY-MM-DD"),'Price Data'!D:D,0)+1))/INDEX('Price Data'!E:E,MATCH(TEXT(A4,"YYYY-MM-DD"),'Price Data'!D:D,0)+1),""),"")} -> 0.016513179 | F4: =IFERROR(INDEX('Price Data'!H:H,MATCH(TEXT(A4,"YYYY-MM-DD"),'Price Data'!G:G,0)),"") -> 62625.895 | G4: {=IFERROR(IF(ISNUMBER(F4),(F4-INDEX('Price Data'!H:H,MATCH(TEXT(A4,"YYYY-MM-DD"),'Price Data'!G:G,0)+1))/INDEX('Price Data'!H:H,MATCH(TEXT(A4,"YYYY-MM-DD"),'Price Data'!G:G,0)+1),""),"")} -> 0.013166617 | H4: =IFERROR(INDEX('Price Data'!K:K,MATCH(TEXT(A4,"YYYY-MM-DD"),'Price Data'!J:J,0)),"") -> 2.35 | I4: {=IFERROR(IF(ISNUMBER(H4),(H4-INDEX('Price Data'!K:K,MATCH(TEXT(A4,"YYYY-MM-DD"),'Price Data'!J:J,0)+1))/INDEX('Price Data'!K:K,MATCH(TEXT(A4,"YYYY-MM-DD"),'Price Data'!J:J,0)+1),""),"")} -> 0.008583691 | J4: =IFERROR(INDEX('Price Data'!N:N,MATCH(TEXT(A4,"YYYY-MM-DD"),'Price Data'!M:M,0)),"") -> 4.69 | K4: {=IFERROR(IF(ISNUMBER(J4),(J4-INDEX('Price Data'!N:N,MATCH(TEXT(A4,"YYYY-MM-DD"),'Price Data'!M:M,0)+1))/INDEX('Price Data'!N:N,MATCH(TEXT(A4,"YYYY-MM-DD"),'Price Data'!M:M,0)+1),""),"")} -> -0.0021276596 | L4: =IFERROR(INDEX('Price Data'!Q:Q,MATCH(TEXT(A4,"YYYY-MM-DD"),'Price Data'!P:P,0)),"") -> 9.06 | M4: {=IFERROR(IF(ISNUMBER(L4),(L4-INDEX('Price Data'!Q:Q,MATCH(TEXT(A4,"YYYY-MM-DD"),'Price Data'!P:P,0)+1))/INDEX('Price Data'!Q:Q,MATCH(TEXT(A4,"YYYY-MM-DD"),'Price Data'!P:P,0)+1),""),"")} -> -0.027896996 | N4: =IFERROR(INDEX('Price Data'!T:T,MATCH(TEXT(A4,"YYYY-MM-DD"),'Price Data'!S:S,0)),"") -> 3.77 | O4: {=IFERROR(IF(ISNUMBER(N4),(N4-INDEX('Price Data'!T:T,MATCH(TEXT(A4,"YYYY-MM-DD"),'Price Data'!S:S,0)+1))/INDEX('Price Data'!T:T,MATCH(TEXT(A4,"YYYY-MM-DD"),'Price Data'!S:S,0)+1),""),"")} -> 0.0053333333
A5: 41824 | B5: =IFERROR(INDEX('Price Data'!B:B,MATCH(TEXT(A5,"YYYY-MM-DD"),'Price Data'!A:A,0)),"") -> 21559 | C5: {=IFERROR(IF(ISNUMBER(B5),(B5-INDEX('Price Data'!B:B,MATCH(TEXT(A5,"YYYY-MM-DD"),'Price Data'!A:A,0)+1))/INDEX('Price Data'!B:B,MATCH(TEXT(A5,"YYYY-MM-DD"),'Price Data'!A:A,0)+1),""),"")} -> -0.014851033 | D5: =IFERROR(INDEX('Price Data'!E:E,MATCH(TEXT(A5,"YYYY-MM-DD"),'Price Data'!D:D,0)),"") -> 30.99 | E5: {=IFERROR(IF(ISNUMBER(D5),(D5-INDEX('Price Data'!E:E,MATCH(TEXT(A5,"YYYY-MM-DD"),'Price Data'!D:D,0)+1))/INDEX('Price Data'!E:E,MATCH(TEXT(A5,"YYYY-MM-DD"),'Price Data'!D:D,0)+1),""),"")} -> -0.031865042 | F5: =IFERROR(INDEX('Price Data'!H:H,MATCH(TEXT(A5,"YYYY-MM-DD"),'Price Data'!G:G,0)),"") -> 61038.883 | G5: {=IFERROR(IF(ISNUMBER(F5),(F5-INDEX('Price Data'!H:H,MATCH(TEXT(A5,"YYYY-MM-DD"),'Price Data'!G:G,0)+1))/INDEX('Price Data'!H:H,MATCH(TEXT(A5,"YYYY-MM-DD"),'Price Data'!G:G,0)+1),""),"")} -> -0.025341143 | H5: =IFERROR(INDEX('Price Data'!K:K,MATCH(TEXT(A5,"YYYY-MM-DD"),'Price Data'!J:J,0)),"") -> 2.27 | I5: {=IFERROR(IF(ISNUMBER(H5),(H5-INDEX('Price Data'!K:K,MATCH(TEXT(A5,"YYYY-MM-DD"),'Price Data'!J:J,0)+1))/INDEX('Price Data'!K:K,MATCH(TEXT(A5,"YYYY-MM-DD"),'Price Data'!J:J,0)+1),""),"")} -> -0.034042553 | J5: =IFERROR(INDEX('Price Data'!N:N,MATCH(TEXT(A5,"YYYY-MM-DD"),'Price Data'!M:M,0)),"") -> 4.55 | K5: {=IFERROR(IF(ISNUMBER(J5),(J5-INDEX('Price Data'!N:N,MATCH(TEXT(A5,"YYYY-MM-DD"),'Price Data'!M:M,0)+1))/INDEX('Price Data'!N:N,MATCH(TEXT(A5,"YYYY-MM-DD"),'Price Data'!M:M,0)+1),""),"")} -> -0.029850746 | L5: =IFERROR(INDEX('Price Data'!Q:Q,MATCH(TEXT(A5,"YYYY-MM-DD"),'Price Data'!P:P,0)),"") -> 8.87 | M5: {=IFERROR(IF(ISNUMBER(L5),(L5-INDEX('Price Data'!Q:Q,MATCH(TEXT(A5,"YYYY-MM-DD"),'Price Data'!P:P,0)+1))/INDEX('Price Data'!Q:Q,MATCH(TEXT(A5,"YYYY-MM-DD"),'Price Data'!P:P,0)+1),""),"")} -> -0.020971302 | N5: =IFERROR(INDEX('Price Data'!T:T,MATCH(TEXT(A5,"YYYY-MM-DD"),'Price Data'!S:S,0)),"") -> 3.65 | O5: {=IFERROR(IF(ISNUMBER(N5),(N5-INDEX('Price Data'!T:T,MATCH(TEXT(A5,"YYYY-MM-DD"),'Price Data'!S:S,0)+1))/INDEX('Price Data'!T:T,MATCH(TEXT(A5,"YYYY-MM-DD"),'Price Data'!S:S,0)+1),""),"")} -> -0.031830239
A6: 41825 | B6: =IFERROR(INDEX('Price Data'!B:B,MATCH(TEXT(A6,"YYYY-MM-DD"),'Price Data'!A:A,0)),"") | C6: {=IFERROR(IF(ISNUMBER(B6),(B6-INDEX('Price Data'!B:B,MATCH(TEXT(A6,"YYYY-MM-DD"),'Price Data'!A:A,0)+1))/INDEX('Price Data'!B:B,MATCH(TEXT(A6,"YYYY-MM-DD"),'Price Data'!A:A,0)+1),""),"")} | D6: =IFERROR(INDEX('Price Data'!E:E,MATCH(TEXT(A6,"YYYY-MM-DD"),'Price Data'!D:D,0)),"") | E6: {=IFERROR(IF(ISNUMBER(D6),(D6-INDEX('Price Data'!E:E,MATCH(TEXT(A6,"YYYY-MM-DD"),'Price Data'!D:D,0)+1))/INDEX('Price Data'!E:E,MATCH(TEXT(A6,"YYYY-MM-DD"),'Price Data'!D:D,0)+1),""),"")} | F6: =IFERROR(INDEX('Price Data'!H:H,MATCH(TEXT(A6,"YYYY-MM-DD"),'Price Data'!G:G,0)),"") | G6: {=IFERROR(IF(ISNUMBER(F6),(F6-INDEX('Price Data'!H:H,MATCH(TEXT(A6,"YYYY-MM-DD"),'Price Data'!G:G,0)+1))/INDEX('Price Data'!H:H,MATCH(TEXT(A6,"YYYY-MM-DD"),'Price Data'!G:G,0)+1),""),"")} | H6: =IFERROR(INDEX('Price Data'!K:K,MATCH(TEXT(A6,"YYYY-MM-DD"),'Price Data'!J:J,0)),"") | I6: {=IFERROR(IF(ISNUMBER(H6),(H6-INDEX('Price Data'!K:K,MATCH(TEXT(A6,"YYYY-MM-DD"),'Price Data'!J:J,0)+1))/INDEX('Price Data'!K:K,MATCH(TEXT(A6,"YYYY-MM-DD"),'Price Data'!J:J,0)+1),""),"")} | J6: =IFERROR(INDEX('Price Data'!N:N,MATCH(TEXT(A6,"YYYY-MM-DD"),'Price Data'!M:M,0)),"") | K6: {=IFERROR(IF(ISNUMBER(J6),(J6-INDEX('Price Data'!N:N,MATCH(TEXT(A6,"YYYY-MM-DD"),'Price Data'!M:M,0)+1))/INDEX('Price Data'!N:N,MATCH(TEXT(A6,"YYYY-MM-DD"),'Price Data'!M:M,0)+1),""),"")} | L6: =IFERROR(INDEX('Price Data'!Q:Q,MATCH(TEXT(A6,"YYYY-MM-DD"),'Price Data'!P:P,0)),"") | M6: {=IFERROR(IF(ISNUMBER(L6),(L6-INDEX('Price Data'!Q:Q,MATCH(TEXT(A6,"YYYY-MM-DD"),'Price Data'!P:P,0)+1))/INDEX('Price Data'!Q:Q,MATCH(TEXT(A6,"YYYY-MM-DD"),'Price Data'!P:P,0)+1),""),"")} | N6: =IFERROR(INDEX('Price Data'!T:T,MATCH(TEXT(A6,"YYYY-MM-DD"),'Price Data'!S:S,0)),"") | O6: {=IFERROR(IF(ISNUMBER(N6),(N6-INDEX('Price Data'!T:T,MATCH(TEXT(A6,"YYYY-MM-DD"),'Price Data'!S:S,0)+1))/INDEX('Price Data'!T:T,MATCH(TEXT(A6,"YYYY-MM-DD"),'Price Data'!S:S,0)+1),""),"")}
A7: 41826 | B7: =IFERROR(INDEX('Price Data'!B:B,MATCH(TEXT(A7,"YYYY-MM-DD"),'Price Data'!A:A,0)),"") | C7: {=IFERROR(IF(ISNUMBER(B7),(B7-INDEX('Price Data'!B:B,MATCH(TEXT(A7,"YYYY-MM-DD"),'Price Data'!A:A,0)+1))/INDEX('Price Data'!B:B,MATCH(TEXT(A7,"YYYY-MM-DD"),'Price Data'!A:A,0)+1),""),"")} | D7: =IFERROR(INDEX('Price Data'!E:E,MATCH(TEXT(A7,"YYYY-MM-DD"),'Price Data'!D:D,0)),"") | E7: {=IFERROR(IF(ISNUMBER(D7),(D7-INDEX('Price Data'!E:E,MATCH(TEXT(A7,"YYYY-MM-DD"),'Price Data'!D:D,0)+1))/INDEX('Price Data'!E:E,MATCH(TEXT(A7,"YYYY-MM-DD"),'Price Data'!D:D,0)+1),""),"")} | F7: =IFERROR(INDEX('Price Data'!H:H,MATCH(TEXT(A7,"YYYY-MM-DD"),'Price Data'!G:G,0)),"") | G7: {=IFERROR(IF(ISNUMBER(F7),(F7-INDEX('Price Data'!H:H,MATCH(TEXT(A7,"YYYY-MM-DD"),'Price Data'!G:G,0)+1))/INDEX('Price Data'!H:H,MATCH(TEXT(A7,"YYYY-MM-DD"),'Price Data'!G:G,0)+1),""),"")} | H7: =IFERROR(INDEX('Price Data'!K:K,MATCH(TEXT(A7,"YYYY-MM-DD"),'Price Data'!J:J,0)),"") | I7: {=IFERROR(IF(ISNUMBER(H7),(H7-INDEX('Price Data'!K:K,MATCH(TEXT(A7,"YYYY-MM-DD"),'Price Data'!J:J,0)+1))/INDEX('Price Data'!K:K,MATCH(TEXT(A7,"YYYY-MM-DD"),'Price Data'!J:J,0)+1),""),"")} | J7: =IFERROR(INDEX('Price Data'!N:N,MATCH(TEXT(A7,"YYYY-MM-DD"),'Price Data'!M:M,0)),"") | K7: {=IFERROR(IF(ISNUMBER(J7),(J7-INDEX('Price Data'!N:N,MATCH(TEXT(A7,"YYYY-MM-DD"),'Price Data'!M:M,0)+1))/INDEX('Price Data'!N:N,MATCH(TEXT(A7,"YYYY-MM-DD"),'Price Data'!M:M,0)+1),""),"")} | L7: =IFERROR(INDEX('Price Data'!Q:Q,MATCH(TEXT(A7,"YYYY-MM-DD"),'Price Data'!P:P,0)),"") | M7: {=IFERROR(IF(ISNUMBER(L7),(L7-INDEX('Price Data'!Q:Q,MATCH(TEXT(A7,"YYYY-MM-DD"),'Price Data'!P:P,0)+1))/INDEX('Price Data'!Q:Q,MATCH(TEXT(A7,"YYYY-MM-DD"),'Price Data'!P:P,0)+1),""),"")} | N7: =IFERROR(INDEX('Price Data'!T:T,MATCH(TEXT(A7,"YYYY-MM-DD"),'Price Data'!S:S,0)),"") | O7: {=IFERROR(IF(ISNUMBER(N7),(N7-INDEX('Price Data'!T:T,MATCH(TEXT(A7,"YYYY-MM-DD"),'Price Data'!S:S,0)+1))/INDEX('Price Data'!T:T,MATCH(TEXT(A7,"YYYY-MM-DD"),'Price Data'!S:S,0)+1),""),"")}
A8: 41827 | B8: =IFERROR(INDEX('Price Data'!B:B,MATCH(TEXT(A8,"YYYY-MM-DD"),'Price Data'!A:A,0)),"") -> 21273 | C8: {=IFERROR(IF(ISNUMBER(B8),(B8-INDEX('Price Data'!B:B,MATCH(TEXT(A8,"YYYY-MM-DD"),'Price Data'!A:A,0)+1))/INDEX('Price Data'!B:B,MATCH(TEXT(A8,"YYYY-MM-DD"),'Price Data'!A:A,0)+1),""),"")} -> -0.013265921 | D8: =IFERROR(INDEX('Price Data'!E:E,MATCH(TEXT(A8,"YYYY-MM-DD"),'Price Data'!D:D,0)),"") -> 30.51 | E8: {=IFERROR(IF(ISNUMBER(D8),(D8-INDEX('Price Data'!E:E,MATCH(TEXT(A8,"YYYY-MM-DD"),'Price Data'!D:D,0)+1))/INDEX('Price Data'!E:E,MATCH(TEXT(A8,"YYYY-MM-DD"),'Price Data'!D:D,0)+1),""),"")} -> -0.015488867 | F8: =IFERROR(INDEX('Price Data'!H:H,MATCH(TEXT(A8,"YYYY-MM-DD"),'Price Data'!G:G,0)),"") -> 59126.332 | G8: {=IFERROR(IF(ISNUMBER(F8),(F8-INDEX('Price Data'!H:H,MATCH(TEXT(A8,"YYYY-MM-DD"),'Price Data'!G:G,0)+1))/INDEX('Price Data'!H:H,MATCH(TEXT(A8,"YYYY-MM-DD"),'Price Data'!G:G,0)+1),""),"")} -> -0.031333319 | H8: =IFERROR(INDEX('Price Data'!K:K,MATCH(TEXT(A8,"YYYY-MM-DD"),'Price Data'!J:J,0)),"") -> 2.23 | I8: {=IFERROR(IF(ISNUMBER(H8),(H8-INDEX('Price Data'!K:K,MATCH(TEXT(A8,"YYYY-MM-DD"),'Price Data'!J:J,0)+1))/INDEX('Price Data'!K:K,MATCH(TEXT(A8,"YYYY-MM-DD"),'Price Data'!J:J,0)+1),""),"")} -> -0.017621145 | J8: =IFERROR(INDEX('Price Data'!N:N,MATCH(TEXT(A8,"YYYY-MM-DD"),'Price Data'!M:M,0)),"") -> 4.41 | K8: {=IFERROR(IF(ISNUMBER(J8),(J8-INDEX('Price Data'!N:N,MATCH(TEXT(A8,"YYYY-MM-DD"),'Price Data'!M:M,0)+1))/INDEX('Price Data'!N:N,MATCH(TEXT(A8,"YYYY-MM-DD"),'Price Data'!M:M,0)+1),""),"")} -> -0.030769231 | L8: =IFERROR(INDEX('Price Data'!Q:Q,MATCH(TEXT(A8,"YYYY-MM-DD"),'Price Data'!P:P,0)),"") -> 8.68 | M8: {=IFERROR(IF(ISNUMBER(L8),(L8-INDEX('Price Data'!Q:Q,MATCH(TEXT(A8,"YYYY-MM-DD"),'Price Data'!P:P,0)+1))/INDEX('Price Data'!Q:Q,MATCH(TEXT(A8,"YYYY-MM-DD"),'Price Data'!P:P,0)+1),""),"")} -> -0.021420519 | N8: =IFERROR(INDEX('Price Data'!T:T,MATCH(TEXT(A8,"YYYY-MM-DD"),'Price Data'!S:S,0)),"") -> 3.59 | O8: {=IFERROR(IF(ISNUMBER(N8),(N8-INDEX('Price Data'!T:T,MATCH(TEXT(A8,"YYYY-MM-DD"),'Price Data'!S:S,0)+1))/INDEX('Price Data'!T:T,MATCH(TEXT(A8,"YYYY-MM-DD"),'Price Data'!S:S,0)+1),""),"")} -> -0.016438356
A9: 41828 | B9: =IFERROR(INDEX('Price Data'!B:B,MATCH(TEXT(A9,"YYYY-MM-DD"),'Price Data'!A:A,0)),"") -> 20700 | C9: {=IFERROR(IF(ISNUMBER(B9),(B9-INDEX('Price Data'!B:B,MATCH(TEXT(A9,"YYYY-MM-DD"),'Price Data'!A:A,0)+1))/INDEX('Price Data'!B:B,MATCH(TEXT(A9,"YYYY-MM-DD"),'Price Data'!A:A,0)+1),""),"")} -> -0.026935552 | D9: =IFERROR(INDEX('Price Data'!E:E,MATCH(TEXT(A9,"YYYY-MM-DD"),'Price Data'!D:D,0)),"") -> 29.51 | E9: {=IFERROR(IF(ISNUMBER(D9),(D9-INDEX('Price Data'!E:E,MATCH(TEXT(A9,"YYYY-MM-DD"),'Price Data'!D:D,0)+1))/INDEX('Price Data'!E:E,MATCH(TEXT(A9,"YYYY-MM-DD"),'Price Data'!D:D,0)+1),""),"")} -> -0.032776139 | F9: =IFERROR(INDEX('Price Data'!H:H,MATCH(TEXT(A9,"YYYY-MM-DD"),'Price Data'!G:G,0)),"") -> 55260.535 | G9: {=IFERROR(IF(ISNUMBER(F9),(F9-INDEX('Price Data'!H:H,MATCH(TEXT(A9,"YYYY-MM-DD"),'Price Data'!G:G,0)+1))/INDEX('Price Data'!H:H,MATCH(TEXT(A9,"YYYY-MM-DD"),'Price Data'!G:G,0)+1),""),"")} -> -0.065381984 | H9: =IFERROR(INDEX('Price Data'!K:K,MATCH(TEXT(A9,"YYYY-MM-DD"),'Price Data'!J:J,0)),"") -> 2.14 | I9: {=IFERROR(IF(ISNUMBER(H9),(H9-INDEX('Price Data'!K:K,MATCH(TEXT(A9,"YYYY-MM-DD"),'Price Data'!J:J,0)+1))/INDEX('Price Data'!K:K,MATCH(TEXT(A9,"YYYY-MM-DD"),'Price Data'!J:J,0)+1),""),"")} -> -0.040358744 | J9: =IFERROR(INDEX('Price Data'!N:N,MATCH(TEXT(A9,"YYYY-MM-DD"),'Price Data'!M:M,0)),"") -> 4.22 | K9: {=IFERROR(IF(ISNUMBER(J9),(J9-INDEX('Price Data'!N:N,MATCH(TEXT(A9,"YYYY-MM-DD"),'Price Data'!M:M,0)+1))/INDEX('Price Data'!N:N,MATCH(TEXT(A9,"YYYY-MM-DD"),'Price Data'!M:M,0)+1),""),"")} -> -0.0430839 | L9: =IFERROR(INDEX('Price Data'!Q:Q,MATCH(TEXT(A9,"YYYY-MM-DD"),'Price Data'!P:P,0)),"") -> 8.26 | M9: {=IFERROR(IF(ISNUMBER(L9),(L9-INDEX('Price Data'!Q:Q,MATCH(TEXT(A9,"YYYY-MM-DD"),'Price Data'!P:P,0)+1))/INDEX('Price Data'!Q:Q,MATCH(TEXT(A9,"YYYY-MM-DD"),'Price Data'!P:P,0)+1),""),"")} -> -0.048387097 | N9: =IFERROR(INDEX('Price Data'!T:T,MATCH(TEXT(A9,"YYYY-MM-DD"),'Price Data'!S:S,0)),"") -> 3.56 | O9: {=IFERROR(IF(ISNUMBER(N9),(N9-INDEX('Price Data'!T:T,MATCH(TEXT(A9,"YYYY-MM-DD"),'Price Data'!S:S,0)+1))/INDEX('Price Data'!T:T,MATCH(TEXT(A9,"YYYY-MM-DD"),'Price Data'!S:S,0)+1),""),"")} -> -0.008356546
A10: 41829 | B10: =IFERROR(INDEX('Price Data'!B:B,MATCH(TEXT(A10,"YYYY-MM-DD"),'Price Data'!A:A,0)),"") -> 20885 | C10: {=IFERROR(IF(ISNUMBER(B10),(B10-INDEX('Price Data'!B:B,MATCH(TEXT(A10,"YYYY-MM-DD"),'Price Data'!A:A,0)+1))/INDEX('Price Data'!B:B,MATCH(TEXT(A10,"YYYY-MM-DD"),'Price Data'!A:A,0)+1),""),"")} -> 0.0089371981 | D10: =IFERROR(INDEX('Price Data'!E:E,MATCH(TEXT(A10,"YYYY-MM-DD"),'Price Data'!D:D,0)),"") -> 29.81 | E10: {=IFERROR(IF(ISNUMBER(D10),(D10-INDEX('Price Data'!E:E,MATCH(TEXT(A10,"YYYY-MM-DD"),'Price Data'!D:D,0)+1))/INDEX('Price Data'!E:E,MATCH(TEXT(A10,"YYYY-MM-DD"),'Price Data'!D:D,0)+1),""),"")} -> 0.010166045 | F10: =IFERROR(INDEX('Price Data'!H:H,MATCH(TEXT(A10,"YYYY-MM-DD"),'Price Data'!G:G,0)),"") -> 56888.238 | G10: {=IFERROR(IF(ISNUMBER(F10),(F10-INDEX('Price Data'!H:H,MATCH(TEXT(A10,"YYYY-MM-DD"),'Price Data'!G:G,0)+1))/INDEX('Price Data'!H:H,MATCH(TEXT(A10,"YYYY-MM-DD"),'Price Data'!G:G,0)+1),""),"")} -> 0.029455074 | H10: =IFERROR(INDEX('Price Data'!K:K,MATCH(TEXT(A10,"YYYY-MM-DD"),'Price Data'!J:J,0)),"") -> 2.2 | I10: {=IFERROR(IF(ISNUMBER(H10),(H10-INDEX('Price Data'!K:K,MATCH(TEXT(A10,"YYYY-MM-DD"),'Price Data'!J:J,0)+1))/INDEX('Price Data'!K:K,MATCH(TEXT(A10,"YYYY-MM-DD"),'Price Data'!J:J,0)+1),""),"")} -> 0.028037383 | J10: =IFERROR(INDEX('Price Data'!N:N,MATCH(TEXT(A10,"YYYY-MM-DD"),'Price Data'!M:M,0)),"") -> 4.29 | K10: {=IFERROR(IF(ISNUMBER(J10),(J10-INDEX('Price Data'!N:N,MATCH(TEXT(A10,"YYYY-MM-DD"),'Price Data'!M:M,0)+1))/INDEX('Price Data'!N:N,MATCH(TEXT(A10,"YYYY-MM-DD"),'Price Data'!M:M,0)+1),""),"")} -> 0.016587678 | L10: =IFERROR(INDEX('Price Data'!Q:Q,MATCH(TEXT(A10,"YYYY-MM-DD"),'Price Data'!P:P,0)),"") -> 8.53 | M10: {=IFERROR(IF(ISNUMBER(L10),(L10-INDEX('Price Data'!Q:Q,MATCH(TEXT(A10,"YYYY-MM-DD"),'Price Data'!P:P,0)+1))/INDEX('Price Data'!Q:Q,MATCH(TEXT(A10,"YYYY-MM-DD"),'Price Data'!P:P,0)+1),""),"")} -> 0.032687651 | N10: =IFERROR(INDEX('Price Data'!T:T,MATCH(TEXT(A10,"YYYY-MM-DD"),'Price Data'!S:S,0)),"") -> 3.48 | O10: {=IFERROR(IF(ISNUMBER(N10),(N10-INDEX('Price Data'!T:T,MATCH(TEXT(A10,"YYYY-MM-DD"),'Price Data'!S:S,0)+1))/INDEX('Price Data'!T:T,MATCH(TEXT(A10,"YYYY-MM-DD"),'Price Data'!S:S,0)+1),""),"")} -> -0.02247191
A11: 41830 | B11: =IFERROR(INDEX('Price Data'!B:B,MATCH(TEXT(A11,"YYYY-MM-DD"),'Price Data'!A:A,0)),"") -> 20488 | C11: {=IFERROR(IF(ISNUMBER(B11),(B11-INDEX('Price Data'!B:B,MATCH(TEXT(A11,"YYYY-MM-DD"),'Price Data'!A:A,0)+1))/INDEX('Price Data'!B:B,MATCH(TEXT(A11,"YYYY-MM-DD"),'Price Data'!A:A,0)+1),""),"")} -> -0.019008858 | D11: =IFERROR(INDEX('Price Data'!E:E,MATCH(TEXT(A11,"YYYY-MM-DD"),'Price Data'!D:D,0)),"") -> 29.06 | E11: {=IFERROR(IF(ISNUMBER(D11),(D11-INDEX('Price Data'!E:E,MATCH(TEXT(A11,"YYYY-MM-DD"),'Price Data'!D:D,0)+1))/INDEX('Price Data'!E:E,MATCH(TEXT(A11,"YYYY-MM-DD"),'Price Data'!D:D,0)+1),""),"")} -> -0.025159343 | F11: =IFERROR(INDEX('Price Data'!H:H,MATCH(TEXT(A11,"YYYY-MM-DD"),'Price Data'!G:G,0)),"") -> 54446.684 | G11: {=IFERROR(IF(ISNUMBER(F11),(F11-INDEX('Price Data'!H:H,MATCH(TEXT(A11,"YYYY-MM-DD"),'Price Data'!G:G,0)+1))/INDEX('Price Data'!H:H,MATCH(TEXT(A11,"YYYY-MM-DD"),'Price Data'!G:G,0)+1),""),"")} -> -0.042918444 | H11: =IFERROR(INDEX('Price Data'!K:K,MATCH(TEXT(A11,"YYYY-MM-DD"),'Price Data'!J:J,0)),"") -> 2.18 | I11: {=IFERROR(IF(ISNUMBER(H11),(H11-INDEX('Price Data'!K:K,MATCH(TEXT(A11,"YYYY-MM-DD"),'Price Data'!J:J,0)+1))/INDEX('Price Data'!K:K,MATCH(TEXT(A11,"YYYY-MM-DD"),'Price Data'!J:J,0)+1),""),"")} -> -0.0090909091 | J11: =IFERROR(INDEX('Price Data'!N:N,MATCH(TEXT(A11,"YYYY-MM-DD"),'Price Data'!M:M,0)),"") -> 4.19 | K11: {=IFERROR(IF(ISNUMBER(J11),(J11-INDEX('Price Data'!N:N,MATCH(TEXT(A11,"YYYY-MM-DD"),'Price Data'!M:M,0)+1))/INDEX('Price Data'!N:N,MATCH(TEXT(A11,"YYYY-MM-DD"),'Price Data'!M:M,0)+1),""),"")} -> -0.023310023 | L11: =IFERROR(INDEX('Price Data'!Q:Q,MATCH(TEXT(A11,"YYYY-MM-DD"),'Price Data'!P:P,0)),"") -> 8.29 | M11: {=IFERROR(IF(ISNUMBER(L11),(L11-INDEX('Price Data'!Q:Q,MATCH(TEXT(A11,"YYYY-MM-DD"),'Price Data'!P:P,0)+1))/INDEX('Price Data'!Q:Q,MATCH(TEXT(A11,"YYYY-MM-DD"),'Price Data'!P:P,0)+1),""),"")} -> -0.028135991 | N11: =IFERROR(INDEX('Price Data'!T:T,MATCH(TEXT(A11,"YYYY-MM-DD"),'Price Data'!S:S,0)),"") -> 3.43 | O11: {=IFERROR(IF(ISNUMBER(N11),(N11-INDEX('Price Data'!T:T,MATCH(TEXT(A11,"YYYY-MM-DD"),'Price Data'!S:S,0)+1))/INDEX('Price Data'!T:T,MATCH(TEXT(A11,"YYYY-MM-DD"),'Price Data'!S:S,0)+1),""),"")} -> -0.014367816
A12: 41831 | B12: =IFERROR(INDEX('Price Data'!B:B,MATCH(TEXT(A12,"YYYY-MM-DD"),'Price Data'!A:A,0)),"") -> 20614 | C12: {=IFERROR(IF(ISNUMBER(B12),(B12-INDEX('Price Data'!B:B,MATCH(TEXT(A12,"YYYY-MM-DD"),'Price Data'!A:A,0)+1))/INDEX('Price Data'!B:B,MATCH(TEXT(A12,"YYYY-MM-DD"),'Price Data'!A:A,0)+1),""),"")} -> 0.0061499414 | D12: =IFERROR(INDEX('Price Data'!E:E,MATCH(TEXT(A12,"YYYY-MM-DD"),'Price Data'!D:D,0)),"") -> 29.03 | E12: {=IFERROR(IF(ISNUMBER(D12),(D12-INDEX('Price Data'!E:E,MATCH(TEXT(A12,"YYYY-MM-DD"),'Price Data'!D:D,0)+1))/INDEX('Price Data'!E:E,MATCH(TEXT(A12,"YYYY-MM-DD"),'Price Data'!D:D,0)+1),""),"")} -> -0.0010323469 | F12: =IFERROR(INDEX('Price Data'!H:H,MATCH(TEXT(A12,"YYYY-MM-DD"),'Price Data'!G:G,0)),"") -> 54568.762 | G12: {=IFERROR(IF(ISNUMBER(F12),(F12-INDEX('Price Data'!H:H,MATCH(TEXT(A12,"YYYY-MM-DD"),'Price Data'!G:G,0)+1))/INDEX('Price Data'!H:H,MATCH(TEXT(A12,"YYYY-MM-DD"),'Price Data'!G:G,0)+1),""),"")} -> 0.0022421591 | H12: =IFERROR(INDEX('Price Data'!K:K,MATCH(TEXT(A12,"YYYY-MM-DD"),'Price Data'!J:J,0)),"") -> 2.2 | I12: {=IFERROR(IF(ISNUMBER(H12),(H12-INDEX('Price Data'!K:K,MATCH(TEXT(A12,"YYYY-MM-DD"),'Price Data'!J:J,0)+1))/INDEX('Price Data'!K:K,MATCH(TEXT(A12,"YYYY-MM-DD"),'Price Data'!J:J,0)+1),""),"")} -> 0.0091743119 | J12: =IFERROR(INDEX('Price Data'!N:N,MATCH(TEXT(A12,"YYYY-MM-DD"),'Price Data'!M:M,0)),"") -> 4.27 | K12: {=IFERROR(IF(ISNUMBER(J12),(J12-INDEX('Price Data'!N:N,MATCH(TEXT(A12,"YYYY-MM-DD"),'Price Data'!M:M,0)+1))/INDEX('Price Data'!N:N,MATCH(TEXT(A12,"YYYY-MM-DD"),'Price Data'!M:M,0)+1),""),"")} -> 0.019093079 | L12: =IFERROR(INDEX('Price Data'!Q:Q,MATCH(TEXT(A12,"YYYY-MM-DD"),'Price Data'!P:P,0)),"") -> 8.27 | M12: {=IFERROR(IF(ISNUMBER(L12),(L12-INDEX('Price Data'!Q:Q,MATCH(TEXT(A12,"YYYY-MM-DD"),'Price Data'!P:P,0)+1))/INDEX('Price Data'!Q:Q,MATCH(TEXT(A12,"YYYY-MM-DD"),'Price Data'!P:P,0)+1),""),"")} -> -0.0024125452 | N12: =IFERROR(INDEX('Price Data'!T:T,MATCH(TEXT(A12,"YYYY-MM-DD"),'Price Data'!S:S,0)),"") -> 3.38 | O12: {=IFERROR(IF(ISNUMBER(N12),(N12-INDEX('Price Data'!T:T,MATCH(TEXT(A12,"YYYY-MM-DD"),'Price Data'!S:S,0)+1))/INDEX('Price Data'!T:T,MATCH(TEXT(A12,"YYYY-MM-DD"),'Price Data'!S:S,0)+1),""),"")} -> -0.014577259
A13: 41832 | B13: =IFERROR(INDEX('Price Data'!B:B,MATCH(TEXT(A13,"YYYY-MM-DD"),'Price Data'!A:A,0)),"") | C13: {=IFERROR(IF(ISNUMBER(B13),(B13-INDEX('Price Data'!B:B,MATCH(TEXT(A13,"YYYY-MM-DD"),'Price Data'!A:A,0)+1))/INDEX('Price Data'!B:B,MATCH(TEXT(A13,"YYYY-MM-DD"),'Price Data'!A:A,0)+1),""),"")} | D13: =IFERROR(INDEX('Price Data'!E:E,MATCH(TEXT(A13,"YYYY-MM-DD"),'Price Data'!D:D,0)),"") | E13: {=IFERROR(IF(ISNUMBER(D13),(D13-INDEX('Price Data'!E:E,MATCH(TEXT(A13,"YYYY-MM-DD"),'Price Data'!D:D,0)+1))/INDEX('Price Data'!E:E,MATCH(TEXT(A13,"YYYY-MM-DD"),'Price Data'!D:D,0)+1),""),"")} | F13: =IFERROR(INDEX('Price Data'!H:H,MATCH(TEXT(A13,"YYYY-MM-DD"),'Price Data'!G:G,0)),"") | G13: {=IFERROR(IF(ISNUMBER(F13),(F13-INDEX('Price Data'!H:H,MATCH(TEXT(A13,"YYYY-MM-DD"),'Price Data'!G:G,0)+1))/INDEX('Price Data'!H:H,MATCH(TEXT(A13,"YYYY-MM-DD"),'Price Data'!G:G,0)+1),""),"")} | H13: =IFERROR(INDEX('Price Data'!K:K,MATCH(TEXT(A13,"YYYY-MM-DD"),'Price Data'!J:J,0)),"") | I13: {=IFERROR(IF(ISNUMBER(H13),(H13-INDEX('Price Data'!K:K,MATCH(TEXT(A13,"YYYY-MM-DD"),'Price Data'!J:J,0)+1))/INDEX('Price Data'!K:K,MATCH(TEXT(A13,"YYYY-MM-DD"),'Price Data'!J:J,0)+1),""),"")} | J13: =IFERROR(INDEX('Price Data'!N:N,MATCH(TEXT(A13,"YYYY-MM-DD"),'Price Data'!M:M,0)),"") | K13: {=IFERROR(IF(ISNUMBER(J13),(J13-INDEX('Price Data'!N:N,MATCH(TEXT(A13,"YYYY-MM-DD"),'Price Data'!M:M,0)+1))/INDEX('Price Data'!N:N,MATCH(TEXT(A13,"YYYY-MM-DD"),'Price Data'!M:M,0)+1),""),"")} | L13: =IFERROR(INDEX('Price Data'!Q:Q,MATCH(TEXT(A13,"YYYY-MM-DD"),'Price Data'!P:P,0)),"") | M13: {=IFERROR(IF(ISNUMBER(L13),(L13-INDEX('Price Data'!Q:Q,MATCH(TEXT(A13,"YYYY-MM-DD"),'Price Data'!P:P,0)+1))/INDEX('Price Data'!Q:Q,MATCH(TEXT(A13,"YYYY-MM-DD"),'Price Data'!P:P,0)+1),""),"")} | N13: =IFERROR(INDEX('Price Data'!T:T,MATCH(TEXT(A13,"YYYY-MM-DD"),'Price Data'!S:S,0)),"") | O13: {=IFERROR(IF(ISNUMBER(N13),(N13-INDEX('Price Data'!T:T,MATCH(TEXT(A13,"YYYY-MM-DD"),'Price Data'!S:S,0)+1))/INDEX('Price Data'!T:T,MATCH(TEXT(A13,"YYYY-MM-DD"),'Price Data'!S:S,0)+1),""),"")}
A14: 41833 | B14: =IFERROR(INDEX('Price Data'!B:B,MATCH(TEXT(A14,"YYYY-MM-DD"),'Price Data'!A:A,0)),"") | C14: {=IFERROR(IF(ISNUMBER(B14),(B14-INDEX('Price Data'!B:B,MATCH(TEXT(A14,"YYYY-MM-DD"),'Price Data'!A:A,0)+1))/INDEX('Price Data'!B:B,MATCH(TEXT(A14,"YYYY-MM-DD"),'Price Data'!A:A,0)+1),""),"")} | D14: =IFERROR(INDEX('Price Data'!E:E,MATCH(TEXT(A14,"YYYY-MM-DD"),'Price Data'!D:D,0)),"") | E14: {=IFERROR(IF(ISNUMBER(D14),(D14-INDEX('Price Data'!E:E,MATCH(TEXT(A14,"YYYY-MM-DD"),'Price Data'!D:D,0)+1))/INDEX('Price Data'!E:E,MATCH(TEXT(A14,"YYYY-MM-DD"),'Price Data'!D:D,0)+1),""),"")} | F14: =IFERROR(INDEX('Price Data'!H:H,MATCH(TEXT(A14,"YYYY-MM-DD"),'Price Data'!G:G,0)),"") | G14: {=IFERROR(IF(ISNUMBER(F14),(F14-INDEX('Price Data'!H:H,MATCH(TEXT(A14,"YYYY-MM-DD"),'Price Data'!G:G,0)+1))/INDEX('Price Data'!H:H,MATCH(TEXT(A14,"YYYY-MM-DD"),'Price Data'!G:G,0)+1),""),"")} | H14: =IFERROR(INDEX('Price Data'!K:K,MATCH(TEXT(A14,"YYYY-MM-DD"),'Price Data'!J:J,0)),"") | I14: {=IFERROR(IF(ISNUMBER(H14),(H14-INDEX('Price Data'!K:K,MATCH(TEXT(A14,"YYYY-MM-DD"),'Price Data'!J:J,0)+1))/INDEX('Price Data'!K:K,MATCH(TEXT(A14,"YYYY-MM-DD"),'Price Data'!J:J,0)+1),""),"")} | J14: =IFERROR(INDEX('Price Data'!N:N,MATCH(TEXT(A14,"YYYY-MM-DD"),'Price Data'!M:M,0)),"") | K14: {=IFERROR(IF(ISNUMBER(J14),(J14-INDEX('Price Data'!N:N,MATCH(TEXT(A14,"YYYY-MM-DD"),'Price Data'!M:M,0)+1))/INDEX('Price Data'!N:N,MATCH(TEXT(A14,"YYYY-MM-DD"),'Price Data'!M:M,0)+1),""),"")} | L14: =IFERROR(INDEX('Price Data'!Q:Q,MATCH(TEXT(A14,"YYYY-MM-DD"),'Price Data'!P:P,0)),"") | M14: {=IFERROR(IF(ISNUMBER(L14),(L14-INDEX('Price Data'!Q:Q,MATCH(TEXT(A14,"YYYY-MM-DD"),'Price Data'!P:P,0)+1))/INDEX('Price Data'!Q:Q,MATCH(TEXT(A14,"YYYY-MM-DD"),'Price Data'!P:P,0)+1),""),"")} | N14: =IFERROR(INDEX('Price Data'!T:T,MATCH(TEXT(A14,"YYYY-MM-DD"),'Price Data'!S:S,0)),"") | O14: {=IFERROR(IF(ISNUMBER(N14),(N14-INDEX('Price Data'!T:T,MATCH(TEXT(A14,"YYYY-MM-DD"),'Price Data'!S:S,0)+1))/INDEX('Price Data'!T:T,MATCH(TEXT(A14,"YYYY-MM-DD"),'Price Data'!S:S,0)+1),""),"")}
... A3107: 44926 | B3107: =IFERROR(INDEX('Price Data'!B:B,MATCH(TEXT(A3107,"YYYY-MM-DD"),'Price Data'!A:A,0)),"") | C3107: {=IFERROR(IF(ISNUMBER(B3107),(B3107-INDEX('Price Data'!B:B,MATCH(TEXT(A3107,"YYYY-MM-DD"),'Price Data'!A:A,0)+1))/INDEX('Price Data'!B:B,MATCH(TEXT(A3107,"YYYY-MM-DD"),'Price Data'!A:A,0)+1),""),"")} | D3107: =IFERROR(INDEX('Price Data'!E:E,MATCH(TEXT(A3107,"YYYY-MM-DD"),'Price Data'!D:D,0)),"") | E3107: {=IFERROR(IF(ISNUMBER(D3107),(D3107-INDEX('Price Data'!E:E,MATCH(TEXT(A3107,"YYYY-MM-DD"),'Price Data'!D:D,0)+1))/INDEX('Price Data'!E:E,MATCH(TEXT(A3107,"YYYY-MM-DD"),'Price Data'!D:D,0)+1),""),"")} | F3107: =IFERROR(INDEX('Price Data'!H:H,MATCH(TEXT(A3107,"YYYY-MM-DD"),'Price Data'!G:G,0)),"") | G3107: {=IFERROR(IF(ISNUMBER(F3107),(F3107-INDEX('Price Data'!H:H,MATCH(TEXT(A3107,"YYYY-MM-DD"),'Price Data'!G:G,0)+1))/INDEX('Price Data'!H:H,MATCH(TEXT(A3107,"YYYY-MM-DD"),'Price Data'!G:G,0)+1),""),"")} | H3107: =IFERROR(INDEX('Price Data'!K:K,MATCH(TEXT(A3107,"YYYY-MM-DD"),'Price Data'!J:J,0)),"") | I3107: {=IFERROR(IF(ISNUMBER(H3107),(H3107-INDEX('Price Data'!K:K,MATCH(TEXT(A3107,"YYYY-MM-DD"),'Price Data'!J:J,0)+1))/INDEX('Price Data'!K:K,MATCH(TEXT(A3107,"YYYY-MM-DD"),'Price Data'!J:J,0)+1),""),"")} | J3107: =IFERROR(INDEX('Price Data'!N:N,MATCH(TEXT(A3107,"YYYY-MM-DD"),'Price Data'!M:M,0)),"") | K3107: {=IFERROR(IF(ISNUMBER(J3107),(J3107-INDEX('Price Data'!N:N,MATCH(TEXT(A3107,"YYYY-MM-DD"),'Price Data'!M:M,0)+1))/INDEX('Price Data'!N:N,MATCH(TEXT(A3107,"YYYY-MM-DD"),'Price Data'!M:M,0)+1),""),"")} | L3107: =IFERROR(INDEX('Price Data'!Q:Q,MATCH(TEXT(A3107,"YYYY-MM-DD"),'Price Data'!P:P,0)),"") | M3107: {=IFERROR(IF(ISNUMBER(L3107),(L3107-INDEX('Price Data'!Q:Q,MATCH(TEXT(A3107,"YYYY-MM-DD"),'Price Data'!P:P,0)+1))/INDEX('Price Data'!Q:Q,MATCH(TEXT(A3107,"YYYY-MM-DD"),'Price Data'!P:P,0)+1),""),"")} | N3107: =IFERROR(INDEX('Price Data'!T:T,MATCH(TEXT(A3107,"YYYY-MM-DD"),'Price Data'!S:S,0)),"") | O3107: {=IFERROR(IF(ISNUMBER(N3107),(N3107-INDEX('Price Data'!T:T,MATCH(TEXT(A3107,"YYYY-MM-DD"),'Price Data'!S:S,0)+1))/INDEX('Price Data'!T:T,MATCH(TEXT(A3107,"YYYY-MM-DD"),'Price Data'!S:S,0)+1),""),"")}

Sheet Estimation Parameters
A1: Event_ID | B1: Ticker | C1: Announcement_Date | D1: Ticker_Return_Col | E1: Market_Return_Col | F1: Est_Window_Start | G1: Est_Window_End | H1: Est_Start_Row | I1: Est_End_Row | J1: Beta | K1: Alpha | L1: R_squared
A2: ='Event Master List'!A2 -> NG-001 | B2: ='Event Master List'!C2 -> UCG | C2: ='Event Master List'!D2 -> 42046 | D2: =IF(B2="UCG","E",IF(B2="BMPS","G",IF(B2="ISP","I",IF(B2="BPE","K",IF(B2="BAMI","M",IF(B2="BPSO","O","?")))))) -> E | E2: C | F2: =WORKDAY(C2,-130) -> 41864 | G2: =WORKDAY(C2,-11) -> 42031 | H2: =MATCH(F2,'Daily Returns'!A:A,1) -> 45 | I2: =MATCH(G2,'Daily Returns'!A:A,1) -> 212 | J2: =IFERROR(IF(B2="UCG",SLOPE(INDEX('Daily Returns'!E:E,H2):INDEX('Daily Returns'!E:E,I2),INDEX('Daily Returns'!C:C,H2):INDEX('Daily Returns'!C:C,I2)),IF(B2="BMPS",SLOPE(INDEX('Daily Returns'!G:G,H2):INDEX('Daily Returns'!G:G,I2),INDEX('Daily Returns'!C:C,H2):INDEX('Daily Returns'!C:C,I2)),IF(B2="ISP",SLOPE(INDEX('Daily Returns'!I:I,H2):INDEX('Daily Returns'!I:I,I2),INDEX('Daily Returns'!C:C,H2):INDEX('Daily Returns'!C:C,I2)),IF(B2="BPE",SLOPE(INDEX('Daily Returns'!K:K,H2):INDEX('Daily Returns'!K:K,I2),INDEX('Daily Returns'!C:C,H2):INDEX('Daily Returns'!C:C,I2)),IF(B2="BAMI",SLOPE(INDEX('Daily Returns'!M:M,H2):INDEX('Daily Returns'!M:M,I2),INDEX('Daily Returns'!C:C,H2):INDEX('Daily Returns'!C:C,I2)),SLOPE(INDEX('Daily Returns'!O:O,H2):INDEX('Daily Returns'!O:O,I2),INDEX('Daily Returns'!C:C,H2):INDEX('Daily Returns'!C:C,I2))))))),"") -> 1.3560016 | K2: =IFERROR(IF(B2="UCG",INTERCEPT(INDEX('Daily Returns'!E:E,H2):INDEX('Daily Returns'!E:E,I2),INDEX('Daily Returns'!C:C,H2):INDEX('Daily Returns'!C:C,I2)),IF(B2="BMPS",INTERCEPT(INDEX('Daily Returns'!G:G,H2):INDEX('Daily Returns'!G:G,I2),INDEX('Daily Returns'!C:C,H2):INDEX('Daily Returns'!C:C,I2)),IF(B2="ISP",INTERCEPT(INDEX('Daily Returns'!I:I,H2):INDEX('Daily Returns'!I:I,I2),INDEX('Daily Returns'!C:C,H2):INDEX('Daily Returns'!C:C,I2)),IF(B2="BPE",INTERCEPT(INDEX('Daily Returns'!K:K,H2):INDEX('Daily Returns'!K:K,I2),INDEX('Daily Returns'!C:C,H2):INDEX('Daily Returns'!C:C,I2)),IF(B2="BAMI",INTERCEPT(INDEX('Daily Returns'!M:M,H2):INDEX('Daily Returns'!M:M,I2),INDEX('Daily Returns'!C:C,H2):INDEX('Daily Returns'!C:C,I2)),INTERCEPT(INDEX('Daily Returns'!O:O,H2):INDEX('Daily Returns'!O:O,I2),INDEX('Daily Returns'!C:C,H2):INDEX('Daily Returns'!C:C,I2))))))),"") -> -0.00070115916 | L2: =IFERROR(IF(B2="UCG",RSQ(INDEX('Daily Returns'!E:E,H2):INDEX('Daily Returns'!E:E,I2),INDEX('Daily Returns'!C:C,H2):INDEX('Daily Returns'!C:C,I2)),IF(B2="BMPS",RSQ(INDEX('Daily Returns'!G:G,H2):INDEX('Daily Returns'!G:G,I2),INDEX('Daily Returns'!C:C,H2):INDEX('Daily Returns'!C:C,I2)),IF(B2="ISP",RSQ(INDEX('Daily Returns'!I:I,H2):INDEX('Daily Returns'!I:I,I2),INDEX('Daily Returns'!C:C,H2):INDEX('Daily Returns'!C:C,I2)),IF(B2="BPE",RSQ(INDEX('Daily Returns'!K:K,H2):INDEX('Daily Returns'!K:K,I2),INDEX('Daily Returns'!C:C,H2):INDEX('Daily Returns'!C:C,I2)),IF(B2="BAMI",RSQ(INDEX('Daily Returns'!M:M,H2):INDEX('Daily Returns'!M:M,I2),INDEX('Daily Returns'!C:C,H2):INDEX('Daily Returns'!C:C,I2)),RSQ(INDEX('Daily Returns'!O:O,H2):INDEX('Daily Returns'!O:O,I2),INDEX('Daily Returns'!C:C,H2):INDEX('Daily Returns'!C:C,I2))))))),"") -> 0.87059001
A3: ='Event Master List'!A3 -> NG-006 | B3: ='Event Master List'!C3 -> BMPS | C3: ='Event Master List'!D3 -> 42178 | D3: =IF(B3="UCG","E",IF(B3="BMPS","G",IF(B3="ISP","I",IF(B3="BPE","K",IF(B3="BAMI","M",IF(B3="BPSO","O","?")))))) -> G | E3: C | F3: =WORKDAY(C3,-130) -> 41996 | G3: =WORKDAY(C3,-11) -> 42163 | H3: =MATCH(F3,'Daily Returns'!A:A,1) -> 177 | I3: =MATCH(G3,'Daily Returns'!A:A,1) -> 344 | J3: =IFERROR(IF(B3="UCG",SLOPE(INDEX('Daily Returns'!E:E,H3):INDEX('Daily Returns'!E:E,I3),INDEX('Daily Returns'!C:C,H3):INDEX('Daily Returns'!C:C,I3)),IF(B3="BMPS",SLOPE(INDEX('Daily Returns'!G:G,H3):INDEX('Daily Returns'!G:G,I3),INDEX('Daily Returns'!C:C,H3):INDEX('Daily Returns'!C:C,I3)),IF(B3="ISP",SLOPE(INDEX('Daily Returns'!I:I,H3):INDEX('Daily Returns'!I:I,I3),INDEX('Daily Returns'!C:C,H3):INDEX('Daily Returns'!C:C,I3)),IF(B3="BPE",SLOPE(INDEX('Daily Returns'!K:K,H3):INDEX('Daily Returns'!K:K,I3),INDEX('Daily Returns'!C:C,H3):INDEX('Daily Returns'!C:C,I3)),IF(B3="BAMI",SLOPE(INDEX('Daily Returns'!M:M,H3):INDEX('Daily Returns'!M:M,I3),INDEX('Daily Returns'!C:C,H3):INDEX('Daily Returns'!C:C,I3)),SLOPE(INDEX('Daily Returns'!O:O,H3):INDEX('Daily Returns'!O:O,I3),INDEX('Daily Returns'!C:C,H3):INDEX('Daily Returns'!C:C,I3))))))),"") -> 1.0331623 | K3: =IFERROR(IF(B3="UCG",INTERCEPT(INDEX('Daily Returns'!E:E,H3):INDEX('Daily Returns'!E:E,I3),INDEX('Daily Returns'!C:C,H3):INDEX('Daily Returns'!C:C,I3)),IF(B3="BMPS",INTERCEPT(INDEX('Daily Returns'!G:G,H3):INDEX('Daily Returns'!G:G,I3),INDEX('Daily Returns'!C:C,H3):INDEX('Daily Returns'!C:C,I3)),IF(B3="ISP",INTERCEPT(INDEX('Daily Returns'!I:I,H3):INDEX('Daily Returns'!I:I,I3),INDEX('Daily Returns'!C:C,H3):INDEX('Daily Returns'!C:C,I3)),IF(B3="BPE",INTERCEPT(INDEX('Daily Returns'!K:K,H3):INDEX('Daily Returns'!K:K,I3),INDEX('Daily Returns'!C:C,H3):INDEX('Daily Returns'!C:C,I3)),IF(B3="BAMI",INTERCEPT(INDEX('Daily Returns'!M:M,H3):INDEX('Daily Returns'!M:M,I3),INDEX('Daily Returns'!C:C,H3):INDEX('Daily Returns'!C:C,I3)),INTERCEPT(INDEX('Daily Returns'!O:O,H3):INDEX('Daily Returns'!O:O,I3),INDEX('Daily Returns'!C:C,H3):INDEX('Daily Returns'!C:C,I3))))))),"") -> -0.0015581928 | L3: =IFERROR(IF(B3="UCG",RSQ(INDEX('Daily Returns'!E:E,H3):INDEX('Daily Returns'!E:E,I3),INDEX('Daily Returns'!C:C,H3):INDEX('Daily Returns'!C:C,I3)),IF(B3="BMPS",RSQ(INDEX('Daily Returns'!G:G,H3):INDEX('Daily Returns'!G:G,I3),INDEX('Daily Returns'!C:C,H3):INDEX('Daily Returns'!C:C,I3)),IF(B3="ISP",RSQ(INDEX('Daily Returns'!I:I,H3):INDEX('Daily Returns'!I:I,I3),INDEX('Daily Returns'!C:C,H3):INDEX('Daily Returns'!C:C,I3)),IF(B3="BPE",RSQ(INDEX('Daily Returns'!K:K,H3):INDEX('Daily Returns'!K:K,I3),INDEX('Daily Returns'!C:C,H3):INDEX('Daily Returns'!C:C,I3)),IF(B3="BAMI",RSQ(INDEX('Daily Returns'!M:M,H3):INDEX('Daily Returns'!M:M,I3),INDEX('Daily Returns'!C:C,H3):INDEX('Daily Returns'!C:C,I3)),RSQ(INDEX('Daily Returns'!O:O,H3):INDEX('Daily Returns'!O:O,I3),INDEX('Daily Returns'!C:C,H3):INDEX('Daily Returns'!C:C,I3))))))),"") -> 0.12843969
A4: ='Event Master List'!A4 -> NG-002 | B4: ='Event Master List'!C4 -> UCG | C4: ='Event Master List'!D4 -> 42185 | D4: =IF(B4="UCG","E",IF(B4="BMPS","G",IF(B4="ISP","I",IF(B4="BPE","K",IF(B4="BAMI","M",IF(B4="BPSO","O","?")))))) -> E | E4: C | F4: =WORKDAY(C4,-130) -> 42003 | G4: =WORKDAY(C4,-11) -> 42170 | H4: =MATCH(F4,'Daily Returns'!A:A,1) -> 184 | I4: =MATCH(G4,'Daily Returns'!A:A,1) -> 351 | J4: =IFERROR(IF(B4="UCG",SLOPE(INDEX('Daily Returns'!E:E,H4):INDEX('Daily Returns'!E:E,I4),INDEX('Daily Returns'!C:C,H4):INDEX('Daily Returns'!C:C,I4)),IF(B4="BMPS",SLOPE(INDEX('Daily Returns'!G:G,H4):INDEX('Daily Returns'!G:G,I4),INDEX('Daily Returns'!C:C,H4):INDEX('Daily Returns'!C:C,I4)),IF(B4="ISP",SLOPE(INDEX('Daily Returns'!I:I,H4):INDEX('Daily Returns'!I:I,I4),INDEX('Daily Returns'!C:C,H4):INDEX('Daily Returns'!C:C,I4)),IF(B4="BPE",SLOPE(INDEX('Daily Returns'!K:K,H4):INDEX('Daily Returns'!K:K,I4),INDEX('Daily Returns'!C:C,H4):INDEX('Daily Returns'!C:C,I4)),IF(B4="BAMI",SLOPE(INDEX('Daily Returns'!M:M,H4):INDEX('Daily Returns'!M:M,I4),INDEX('Daily Returns'!C:C,H4):INDEX('Daily Returns'!C:C,I4)),SLOPE(INDEX('Daily Returns'!O:O,H4):INDEX('Daily Returns'!O:O,I4),INDEX('Daily Returns'!C:C,H4):INDEX('Daily Returns'!C:C,I4))))))),"") -> 1.3234115 | K4: =IFERROR(IF(B4="UCG",INTERCEPT(INDEX('Daily Returns'!E:E,H4):INDEX('Daily Returns'!E:E,I4),INDEX('Daily Returns'!C:C,H4):INDEX('Daily Returns'!C:C,I4)),IF(B4="BMPS",INTERCEPT(INDEX('Daily Returns'!G:G,H4):INDEX('Daily Returns'!G:G,I4),INDEX('Daily Returns'!C:C,H4):INDEX('Daily Returns'!C:C,I4)),IF(B4="ISP",INTERCEPT(INDEX('Daily Returns'!I:I,H4):INDEX('Daily Returns'!I:I,I4),INDEX('Daily Returns'!C:C,H4):INDEX('Daily Returns'!C:C,I4)),IF(B4="BPE",INTERCEPT(INDEX('Daily Returns'!K:K,H4):INDEX('Daily Returns'!K:K,I4),INDEX('Daily Returns'!C:C,H4):INDEX('Daily Returns'!C:C,I4)),IF(B4="BAMI",INTERCEPT(INDEX('Daily Returns'!M:M,H4):INDEX('Daily Returns'!M:M,I4),INDEX('Daily Returns'!C:C,H4):INDEX('Daily Returns'!C:C,I4)),INTERCEPT(INDEX('Daily Returns'!O:O,H4):INDEX('Daily Returns'!O:O,I4),INDEX('Daily Returns'!C:C,H4):INDEX('Daily Returns'!C:C,I4))))))),"") -> -0.00063993117 | L4: =IFERROR(IF(B4="UCG",RSQ(INDEX('Daily Returns'!E:E,H4):INDEX('Daily Returns'!E:E,I4),INDEX('Daily Returns'!C:C,H4):INDEX('Daily Returns'!C:C,I4)),IF(B4="BMPS",RSQ(INDEX('Daily Returns'!G:G,H4):INDEX('Daily Returns'!G:G,I4),INDEX('Daily Returns'!C:C,H4):INDEX('Daily Returns'!C:C,I4)),IF(B4="ISP",RSQ(INDEX('Daily Returns'!I:I,H4):INDEX('Daily Returns'!I:I,I4),INDEX('Daily Returns'!C:C,H4):INDEX('Daily Returns'!C:C,I4)),IF(B4="BPE",RSQ(INDEX('Daily Returns'!K:K,H4):INDEX('Daily Returns'!K:K,I4),INDEX('Daily Returns'!C:C,H4):INDEX('Daily Returns'!C:C,I4)),IF(B4="BAMI",RSQ(INDEX('Daily Returns'!M:M,H4):INDEX('Daily Returns'!M:M,I4),INDEX('Daily Returns'!C:C,H4):INDEX('Daily Returns'!C:C,I4)),RSQ(INDEX('Daily Returns'!O:O,H4):INDEX('Daily Returns'!O:O,I4),INDEX('Daily Returns'!C:C,H4):INDEX('Daily Returns'!C:C,I4))))))),"") -> 0.76423548
A5: ='Event Master List'!A5 -> NG-003 | B5: ='Event Master List'!C5 -> UCG | C5: ='Event Master List'!D5 -> 42186 | D5: =IF(B5="UCG","E",IF(B5="BMPS","G",IF(B5="ISP","I",IF(B5="BPE","K",IF(B5="BAMI","M",IF(B5="BPSO","O","?")))))) -> E | E5: C | F5: =WORKDAY(C5,-130) -> 42004 | G5: =WORKDAY(C5,-11) -> 42171 | H5: =MATCH(F5,'Daily Returns'!A:A,1) -> 185 | I5: =MATCH(G5,'Daily Returns'!A:A,1) -> 352 | J5: =IFERROR(IF(B5="UCG",SLOPE(INDEX('Daily Returns'!E:E,H5):INDEX('Daily Returns'!E:E,I5),INDEX('Daily Returns'!C:C,H5):INDEX('Daily Returns'!C:C,I5)),IF(B5="BMPS",SLOPE(INDEX('Daily Returns'!G:G,H5):INDEX('Daily Returns'!G:G,I5),INDEX('Daily Returns'!C:C,H5):INDEX('Daily Returns'!C:C,I5)),IF(B5="ISP",SLOPE(INDEX('Daily Returns'!I:I,H5):INDEX('Daily Returns'!I:I,I5),INDEX('Daily Returns'!C:C,H5):INDEX('Daily Returns'!C:C,I5)),IF(B5="BPE",SLOPE(INDEX('Daily Returns'!K:K,H5):INDEX('Daily Returns'!K:K,I5),INDEX('Daily Returns'!C:C,H5):INDEX('Daily Returns'!C:C,I5)),IF(B5="BAMI",SLOPE(INDEX('Daily Returns'!M:M,H5):INDEX('Daily Returns'!M:M,I5),INDEX('Daily Returns'!C:C,H5):INDEX('Daily Returns'!C:C,I5)),SLOPE(INDEX('Daily Returns'!O:O,H5):INDEX('Daily Returns'!O:O,I5),INDEX('Daily Returns'!C:C,H5):INDEX('Daily Returns'!C:C,I5))))))),"") -> 1.32588 | K5: =IFERROR(IF(B5="UCG",INTERCEPT(INDEX('Daily Returns'!E:E,H5):INDEX('Daily Returns'!E:E,I5),INDEX('Daily Returns'!C:C,H5):INDEX('Daily Returns'!C:C,I5)),IF(B5="BMPS",INTERCEPT(INDEX('Daily Returns'!G:G,H5):INDEX('Daily Returns'!G:G,I5),INDEX('Daily Returns'!C:C,H5):INDEX('Daily Returns'!C:C,I5)),IF(B5="ISP",INTERCEPT(INDEX('Daily Returns'!I:I,H5):INDEX('Daily Returns'!I:I,I5),INDEX('Daily Returns'!C:C,H5):INDEX('Daily Returns'!C:C,I5)),IF(B5="BPE",INTERCEPT(INDEX('Daily Returns'!K:K,H5):INDEX('Daily Returns'!K:K,I5),INDEX('Daily Returns'!C:C,H5):INDEX('Daily Returns'!C:C,I5)),IF(B5="BAMI",INTERCEPT(INDEX('Daily Returns'!M:M,H5):INDEX('Daily Returns'!M:M,I5),INDEX('Daily Returns'!C:C,H5):INDEX('Daily Returns'!C:C,I5)),INTERCEPT(INDEX('Daily Returns'!O:O,H5):INDEX('Daily Returns'!O:O,I5),INDEX('Daily Returns'!C:C,H5):INDEX('Daily Returns'!C:C,I5))))))),"") -> -0.00065702139 | L5: =IFERROR(IF(B5="UCG",RSQ(INDEX('Daily Returns'!E:E,H5):INDEX('Daily Returns'!E:E,I5),INDEX('Daily Returns'!C:C,H5):INDEX('Daily Returns'!C:C,I5)),IF(B5="BMPS",RSQ(INDEX('Daily Returns'!G:G,H5):INDEX('Daily Returns'!G:G,I5),INDEX('Daily Returns'!C:C,H5):INDEX('Daily Returns'!C:C,I5)),IF(B5="ISP",RSQ(INDEX('Daily Returns'!I:I,H5):INDEX('Daily Returns'!I:I,I5),INDEX('Daily Returns'!C:C,H5):INDEX('Daily Returns'!C:C,I5)),IF(B5="BPE",RSQ(INDEX('Daily Returns'!K:K,H5):INDEX('Daily Returns'!K:K,I5),INDEX('Daily Returns'!C:C,H5):INDEX('Daily Returns'!C:C,I5)),IF(B5="BAMI",RSQ(INDEX('Daily Returns'!M:M,H5):INDEX('Daily Returns'!M:M,I5),INDEX('Daily Returns'!C:C,H5):INDEX('Daily Returns'!C:C,I5)),RSQ(INDEX('Daily Returns'!O:O,H5):INDEX('Daily Returns'!O:O,I5),INDEX('Daily Returns'!C:C,H5):INDEX('Daily Returns'!C:C,I5))))))),"") -> 0.7646816
A6: ='Event Master List'!A6 -> NG-004 | B6: ='Event Master List'!C6 -> UCG | C6: ='Event Master List'!D6 -> 42275 | D6: =IF(B6="UCG","E",IF(B6="BMPS","G",IF(B6="ISP","I",IF(B6="BPE","K",IF(B6="BAMI","M",IF(B6="BPSO","O","?")))))) -> E | E6: C | F6: =WORKDAY(C6,-130) -> 42093 | G6: =WORKDAY(C6,-11) -> 42258 | H6: =MATCH(F6,'Daily Returns'!A:A,1) -> 274 | I6: =MATCH(G6,'Daily Returns'!A:A,1) -> 439 | J6: =IFERROR(IF(B6="UCG",SLOPE(INDEX('Daily Returns'!E:E,H6):INDEX('Daily Returns'!E:E,I6),INDEX('Daily Returns'!C:C,H6):INDEX('Daily Returns'!C:C,I6)),IF(B6="BMPS",SLOPE(INDEX('Daily Returns'!G:G,H6):INDEX('Daily Returns'!G:G,I6),INDEX('Daily Returns'!C:C,H6):INDEX('Daily Returns'!C:C,I6)),IF(B6="ISP",SLOPE(INDEX('Daily Returns'!I:I,H6):INDEX('Daily Returns'!I:I,I6),INDEX('Daily Returns'!C:C,H6):INDEX('Daily Returns'!C:C,I6)),IF(B6="BPE",SLOPE(INDEX('Daily Returns'!K:K,H6):INDEX('Daily Returns'!K:K,I6),INDEX('Daily Returns'!C:C,H6):INDEX('Daily Returns'!C:C,I6)),IF(B6="BAMI",SLOPE(INDEX('Daily Returns'!M:M,H6):INDEX('Daily Returns'!M:M,I6),INDEX('Daily Returns'!C:C,H6):INDEX('Daily Returns'!C:C,I6)),SLOPE(INDEX('Daily Returns'!O:O,H6):INDEX('Daily Returns'!O:O,I6),INDEX('Daily Returns'!C:C,H6):INDEX('Daily Returns'!C:C,I6))))))),"") -> 1.2508924 | K6: =IFERROR(IF(B6="UCG",INTERCEPT(INDEX('Daily Returns'!E:E,H6):INDEX('Daily Returns'!E:E,I6),INDEX('Daily Returns'!C:C,H6):INDEX('Daily Returns'!C:C,I6)),IF(B6="BMPS",INTERCEPT(INDEX('Daily Returns'!G:G,H6):INDEX('Daily Returns'!G:G,I6),INDEX('Daily Returns'!C:C,H6):INDEX('Daily Returns'!C:C,I6)),IF(B6="ISP",INTERCEPT(INDEX('Daily Returns'!I:I,H6):INDEX('Daily Returns'!I:I,I6),INDEX('Daily Returns'!C:C,H6):INDEX('Daily Returns'!C:C,I6)),IF(B6="BPE",INTERCEPT(INDEX('Daily Returns'!K:K,H6):INDEX('Daily Returns'!K:K,I6),INDEX('Daily Returns'!C:C,H6):INDEX('Daily Returns'!C:C,I6)),IF(B6="BAMI",INTERCEPT(INDEX('Daily Returns'!M:M,H6):INDEX('Daily Returns'!M:M,I6),INDEX('Daily Returns'!C:C,H6):INDEX('Daily Returns'!C:C,I6)),INTERCEPT(INDEX('Daily Returns'!O:O,H6):INDEX('Daily Returns'!O:O,I6),INDEX('Daily Returns'!C:C,H6):INDEX('Daily Returns'!C:C,I6))))))),"") -> -8.9946085e-05 | L6: =IFERROR(IF(B6="UCG",RSQ(INDEX('Daily Returns'!E:E,H6):INDEX('Daily Returns'!E:E,I6),INDEX('Daily Returns'!C:C,H6):INDEX('Daily Returns'!C:C,I6)),IF(B6="BMPS",RSQ(INDEX('Daily Returns'!G:G,H6):INDEX('Daily Returns'!G:G,I6),INDEX('Daily Returns'!C:C,H6):INDEX('Daily Returns'!C:C,I6)),IF(B6="ISP",RSQ(INDEX('Daily Returns'!I:I,H6):INDEX('Daily Returns'!I:I,I6),INDEX('Daily Returns'!C:C,H6):INDEX('Daily Returns'!C:C,I6)),IF(B6="BPE",RSQ(INDEX('Daily Returns'!K:K,H6):INDEX('Daily Returns'!K:K,I6),INDEX('Daily Returns'!C:C,H6):INDEX('Daily Returns'!C:C,I6)),IF(B6="BAMI",RSQ(INDEX('Daily Returns'!M:M,H6):INDEX('Daily Returns'!M:M,I6),INDEX('Daily Returns'!C:C,H6):INDEX('Daily Returns'!C:C,I6)),RSQ(INDEX('Daily Returns'!O:O,H6):INDEX('Daily Returns'!O:O,I6),INDEX('Daily Returns'!C:C,H6):INDEX('Daily Returns'!C:C,I6))))))),"") -> 0.84421678
A7: ='Event Master List'!A7 -> NG-005 | B7: ='Event Master List'!C7 -> UCG | C7: ='Event Master List'!D7 -> 42355 | D7: =IF(B7="UCG","E",IF(B7="BMPS","G",IF(B7="ISP","I",IF(B7="BPE","K",IF(B7="BAMI","M",IF(B7="BPSO","O","?")))))) -> E | E7: C | F7: =WORKDAY(C7,-130) -> 42173 | G7: =WORKDAY(C7,-11) -> 42340 | H7: =MATCH(F7,'Daily Returns'!A:A,1) -> 354 | I7: =MATCH(G7,'Daily Returns'!A:A,1) -> 521 | J7: =IFERROR(IF(B7="UCG",SLOPE(INDEX('Daily Returns'!E:E,H7):INDEX('Daily Returns'!E:E,I7),INDEX('Daily Returns'!C:C,H7):INDEX('Daily Returns'!C:C,I7)),IF(B7="BMPS",SLOPE(INDEX('Daily Returns'!G:G,H7):INDEX('Daily Returns'!G:G,I7),INDEX('Daily Returns'!C:C,H7):INDEX('Daily Returns'!C:C,I7)),IF(B7="ISP",SLOPE(INDEX('Daily Returns'!I:I,H7):INDEX('Daily Returns'!I:I,I7),INDEX('Daily Returns'!C:C,H7):INDEX('Daily Returns'!C:C,I7)),IF(B7="BPE",SLOPE(INDEX('Daily Returns'!K:K,H7):INDEX('Daily Returns'!K:K,I7),INDEX('Daily Returns'!C:C,H7):INDEX('Daily Returns'!C:C,I7)),IF(B7="BAMI",SLOPE(INDEX('Daily Returns'!M:M,H7):INDEX('Daily Returns'!M:M,I7),INDEX('Daily Returns'!C:C,H7):INDEX('Daily Returns'!C:C,I7)),SLOPE(INDEX('Daily Returns'!O:O,H7):INDEX('Daily Returns'!O:O,I7),INDEX('Daily Returns'!C:C,H7):INDEX('Daily Returns'!C:C,I7))))))),"") -> 1.1795179 | K7: =IFERROR(IF(B7="UCG",INTERCEPT(INDEX('Daily Returns'!E:E,H7):INDEX('Daily Returns'!E:E,I7),INDEX('Daily Returns'!C:C,H7):INDEX('Daily Returns'!C:C,I7)),IF(B7="BMPS",INTERCEPT(INDEX('Daily Returns'!G:G,H7):INDEX('Daily Returns'!G:G,I7),INDEX('Daily Returns'!C:C,H7):INDEX('Daily Returns'!C:C,I7)),IF(B7="ISP",INTERCEPT(INDEX('Daily Returns'!I:I,H7):INDEX('Daily Returns'!I:I,I7),INDEX('Daily Returns'!C:C,H7):INDEX('Daily Returns'!C:C,I7)),IF(B7="BPE",INTERCEPT(INDEX('Daily Returns'!K:K,H7):INDEX('Daily Returns'!K:K,I7),INDEX('Daily Returns'!C:C,H7):INDEX('Daily Returns'!C:C,I7)),IF(B7="BAMI",INTERCEPT(INDEX('Daily Returns'!M:M,H7):INDEX('Daily Returns'!M:M,I7),INDEX('Daily Returns'!C:C,H7):INDEX('Daily Returns'!C:C,I7)),INTERCEPT(INDEX('Daily Returns'!O:O,H7):INDEX('Daily Returns'!O:O,I7),INDEX('Daily Returns'!C:C,H7):INDEX('Daily Returns'!C:C,I7))))))),"") -> -0.00079902232 | L7: =IFERROR(IF(B7="UCG",RSQ(INDEX('Daily Returns'!E:E,H7):INDEX('Daily Returns'!E:E,I7),INDEX('Daily Returns'!C:C,H7):INDEX('Daily Returns'!C:C,I7)),IF(B7="BMPS",RSQ(INDEX('Daily Returns'!G:G,H7):INDEX('Daily Returns'!G:G,I7),INDEX('Daily Returns'!C:C,H7):INDEX('Daily Returns'!C:C,I7)),IF(B7="ISP",RSQ(INDEX('Daily Returns'!I:I,H7):INDEX('Daily Returns'!I:I,I7),INDEX('Daily Returns'!C:C,H7):INDEX('Daily Returns'!C:C,I7)),IF(B7="BPE",RSQ(INDEX('Daily Returns'!K:K,H7):INDEX('Daily Returns'!K:K,I7),INDEX('Daily Returns'!C:C,H7):INDEX('Daily Returns'!C:C,I7)),IF(B7="BAMI",RSQ(INDEX('Daily Returns'!M:M,H7):INDEX('Daily Returns'!M:M,I7),INDEX('Daily Returns'!C:C,H7):INDEX('Daily Returns'!C:C,I7)),RSQ(INDEX('Daily Returns'!O:O,H7):INDEX('Daily Returns'!O:O,I7),INDEX('Daily Returns'!C:C,H7):INDEX('Daily Returns'!C:C,I7))))))),"") -> 0.8306923
A8: ='Event Master List'!A8 -> NG-008 | B8: ='Event Master List'!C8 -> UCG | C8: ='Event Master List'!D8 -> 42717 | D8: =IF(B8="UCG","E",IF(B8="BMPS","G",IF(B8="ISP","I",IF(B8="BPE","K",IF(B8="BAMI","M",IF(B8="BPSO","O","?")))))) -> E | E8: C | F8: =WORKDAY(C8,-130) -> 42535 | G8: =WORKDAY(C8,-11) -> 42702 | H8: =MATCH(F8,'Daily Returns'!A:A,1) -> 716 | I8: =MATCH(G8,'Daily Returns'!A:A,1) -> 883 | J8: =IFERROR(IF(B8="UCG",SLOPE(INDEX('Daily Returns'!E:E,H8):INDEX('Daily Returns'!E:E,I8),INDEX('Daily Returns'!C:C,H8):INDEX('Daily Returns'!C:C,I8)),IF(B8="BMPS",SLOPE(INDEX('Daily Returns'!G:G,H8):INDEX('Daily Returns'!G:G,I8),INDEX('Daily Returns'!C:C,H8):INDEX('Daily Returns'!C:C,I8)),IF(B8="ISP",SLOPE(INDEX('Daily Returns'!I:I,H8):INDEX('Daily Returns'!I:I,I8),INDEX('Daily Returns'!C:C,H8):INDEX('Daily Returns'!C:C,I8)),IF(B8="BPE",SLOPE(INDEX('Daily Returns'!K:K,H8):INDEX('Daily Returns'!K:K,I8),INDEX('Daily Returns'!C:C,H8):INDEX('Daily Returns'!C:C,I8)),IF(B8="BAMI",SLOPE(INDEX('Daily Returns'!M:M,H8):INDEX('Daily Returns'!M:M,I8),INDEX('Daily Returns'!C:C,H8):INDEX('Daily Returns'!C:C,I8)),SLOPE(INDEX('Daily Returns'!O:O,H8):INDEX('Daily Returns'!O:O,I8),INDEX('Daily Returns'!C:C,H8):INDEX('Daily Returns'!C:C,I8))))))),"") -> 1.9161166 | K8: =IFERROR(IF(B8="UCG",INTERCEPT(INDEX('Daily Returns'!E:E,H8):INDEX('Daily Returns'!E:E,I8),INDEX('Daily Returns'!C:C,H8):INDEX('Daily Returns'!C:C,I8)),IF(B8="BMPS",INTERCEPT(INDEX('Daily Returns'!G:G,H8):INDEX('Daily Returns'!G:G,I8),INDEX('Daily Returns'!C:C,H8):INDEX('Daily Returns'!C:C,I8)),IF(B8="ISP",INTERCEPT(INDEX('Daily Returns'!I:I,H8):INDEX('Daily Returns'!I:I,I8),INDEX('Daily Returns'!C:C,H8):INDEX('Daily Returns'!C:C,I8)),IF(B8="BPE",INTERCEPT(INDEX('Daily Returns'!K:K,H8):INDEX('Daily Returns'!K:K,I8),INDEX('Daily Returns'!C:C,H8):INDEX('Daily Returns'!C:C,I8)),IF(B8="BAMI",INTERCEPT(INDEX('Daily Returns'!M:M,H8):INDEX('Daily Returns'!M:M,I8),INDEX('Daily Returns'!C:C,H8):INDEX('Daily Returns'!C:C,I8)),INTERCEPT(INDEX('Daily Returns'!O:O,H8):INDEX('Daily Returns'!O:O,I8),INDEX('Daily Returns'!C:C,H8):INDEX('Daily Returns'!C:C,I8))))))),"") -> -0.00054395946 | L8: =IFERROR(IF(B8="UCG",RSQ(INDEX('Daily Returns'!E:E,H8):INDEX('Daily Returns'!E:E,I8),INDEX('Daily Returns'!C:C,H8):INDEX('Daily Returns'!C:C,I8)),IF(B8="BMPS",RSQ(INDEX('Daily Returns'!G:G,H8):INDEX('Daily Returns'!G:G,I8),INDEX('Daily Returns'!C:C,H8):INDEX('Daily Returns'!C:C,I8)),IF(B8="ISP",RSQ(INDEX('Daily Returns'!I:I,H8):INDEX('Daily Returns'!I:I,I8),INDEX('Daily Returns'!C:C,H8):INDEX('Daily Returns'!C:C,I8)),IF(B8="BPE",RSQ(INDEX('Daily Returns'!K:K,H8):INDEX('Daily Returns'!K:K,I8),INDEX('Daily Returns'!C:C,H8):INDEX('Daily Returns'!C:C,I8)),IF(B8="BAMI",RSQ(INDEX('Daily Returns'!M:M,H8):INDEX('Daily Returns'!M:M,I8),INDEX('Daily Returns'!C:C,H8):INDEX('Daily Returns'!C:C,I8)),RSQ(INDEX('Daily Returns'!O:O,H8):INDEX('Daily Returns'!O:O,I8),INDEX('Daily Returns'!C:C,H8):INDEX('Daily Returns'!C:C,I8))))))),"") -> 0.70019408
A9: ='Event Master List'!A9 -> NG-009 | B9: ='Event Master List'!C9 -> ISP | C9: ='Event Master List'!D9 -> 42859 | D9: =IF(B9="UCG","E",IF(B9="BMPS","G",IF(B9="ISP","I",IF(B9="BPE","K",IF(B9="BAMI","M",IF(B9="BPSO","O","?")))))) -> I | E9: C | F9: =WORKDAY(C9,-130) -> 42677 | G9: =WORKDAY(C9,-11) -> 42844 | H9: =MATCH(F9,'Daily Returns'!A:A,1) -> 858 | I9: =MATCH(G9,'Daily Returns'!A:A,1) -> 1025 | J9: =IFERROR(IF(B9="UCG",SLOPE(INDEX('Daily Returns'!E:E,H9):INDEX('Daily Returns'!E:E,I9),INDEX('Daily Returns'!C:C,H9):INDEX('Daily Returns'!C:C,I9)),IF(B9="BMPS",SLOPE(INDEX('Daily Returns'!G:G,H9):INDEX('Daily Returns'!G:G,I9),INDEX('Daily Returns'!C:C,H9):INDEX('Daily Returns'!C:C,I9)),IF(B9="ISP",SLOPE(INDEX('Daily Returns'!I:I,H9):INDEX('Daily Returns'!I:I,I9),INDEX('Daily Returns'!C:C,H9):INDEX('Daily Returns'!C:C,I9)),IF(B9="BPE",SLOPE(INDEX('Daily Returns'!K:K,H9):INDEX('Daily Returns'!K:K,I9),INDEX('Daily Returns'!C:C,H9):INDEX('Daily Returns'!C:C,I9)),IF(B9="BAMI",SLOPE(INDEX('Daily Returns'!M:M,H9):INDEX('Daily Returns'!M:M,I9),INDEX('Daily Returns'!C:C,H9):INDEX('Daily Returns'!C:C,I9)),SLOPE(INDEX('Daily Returns'!O:O,H9):INDEX('Daily Returns'!O:O,I9),INDEX('Daily Returns'!C:C,H9):INDEX('Daily Returns'!C:C,I9))))))),"") -> 1.4561863 | K9: =IFERROR(IF(B9="UCG",INTERCEPT(INDEX('Daily Returns'!E:E,H9):INDEX('Daily Returns'!E:E,I9),INDEX('Daily Returns'!C:C,H9):INDEX('Daily Returns'!C:C,I9)),IF(B9="BMPS",INTERCEPT(INDEX('Daily Returns'!G:G,H9):INDEX('Daily Returns'!G:G,I9),INDEX('Daily Returns'!C:C,H9):INDEX('Daily Returns'!C:C,I9)),IF(B9="ISP",INTERCEPT(INDEX('Daily Returns'!I:I,H9):INDEX('Daily Returns'!I:I,I9),INDEX('Daily Returns'!C:C,H9):INDEX('Daily Returns'!C:C,I9)),IF(B9="BPE",INTERCEPT(INDEX('Daily Returns'!K:K,H9):INDEX('Daily Returns'!K:K,I9),INDEX('Daily Returns'!C:C,H9):INDEX('Daily Returns'!C:C,I9)),IF(B9="BAMI",INTERCEPT(INDEX('Daily Returns'!M:M,H9):INDEX('Daily Returns'!M:M,I9),INDEX('Daily Returns'!C:C,H9):INDEX('Daily Returns'!C:C,I9)),INTERCEPT(INDEX('Daily Returns'!O:O,H9):INDEX('Daily Returns'!O:O,I9),INDEX('Daily Returns'!C:C,H9):INDEX('Daily Returns'!C:C,I9))))))),"") -> -0.00044061513 | L9: =IFERROR(IF(B9="UCG",RSQ(INDEX('Daily Returns'!E:E,H9):INDEX('Daily Returns'!E:E,I9),INDEX('Daily Returns'!C:C,H9):INDEX('Daily Returns'!C:C,I9)),IF(B9="BMPS",RSQ(INDEX('Daily Returns'!G:G,H9):INDEX('Daily Returns'!G:G,I9),INDEX('Daily Returns'!C:C,H9):INDEX('Daily Returns'!C:C,I9)),IF(B9="ISP",RSQ(INDEX('Daily Returns'!I:I,H9):INDEX('Daily Returns'!I:I,I9),INDEX('Daily Returns'!C:C,H9):INDEX('Daily Returns'!C:C,I9)),IF(B9="BPE",RSQ(INDEX('Daily Returns'!K:K,H9):INDEX('Daily Returns'!K:K,I9),INDEX('Daily Returns'!C:C,H9):INDEX('Daily Returns'!C:C,I9)),IF(B9="BAMI",RSQ(INDEX('Daily Returns'!M:M,H9):INDEX('Daily Returns'!M:M,I9),INDEX('Daily Returns'!C:C,H9):INDEX('Daily Returns'!C:C,I9)),RSQ(INDEX('Daily Returns'!O:O,H9):INDEX('Daily Returns'!O:O,I9),INDEX('Daily Returns'!C:C,H9):INDEX('Daily Returns'!C:C,I9))))))),"") -> 0.65473041
A10: ='Event Master List'!A10 -> NG-010 | B10: ='Event Master List'!C10 -> BAMI | C10: ='Event Master List'!D10 -> 42908 | D10: =IF(B10="UCG","E",IF(B10="BMPS","G",IF(B10="ISP","I",IF(B10="BPE","K",IF(B10="BAMI","M",IF(B10="BPSO","O","?")))))) -> M | E10: C | F10: =WORKDAY(C10,-130) -> 42726 | G10: =WORKDAY(C10,-11) -> 42893 | H10: =MATCH(F10,'Daily Returns'!A:A,1) -> 907 | I10: =MATCH(G10,'Daily Returns'!A:A,1) -> 1074 | J10: =IFERROR(IF(B10="UCG",SLOPE(INDEX('Daily Returns'!E:E,H10):INDEX('Daily Returns'!E:E,I10),INDEX('Daily Returns'!C:C,H10):INDEX('Daily Returns'!C:C,I10)),IF(B10="BMPS",SLOPE(INDEX('Daily Returns'!G:G,H10):INDEX('Daily Returns'!G:G,I10),INDEX('Daily Returns'!C:C,H10):INDEX('Daily Returns'!C:C,I10)),IF(B10="ISP",SLOPE(INDEX('Daily Returns'!I:I,H10):INDEX('Daily Returns'!I:I,I10),INDEX('Daily Returns'!C:C,H10):INDEX('Daily Returns'!C:C,I10)),IF(B10="BPE",SLOPE(INDEX('Daily Returns'!K:K,H10):INDEX('Daily Returns'!K:K,I10),INDEX('Daily Returns'!C:C,H10):INDEX('Daily Returns'!C:C,I10)),IF(B10="BAMI",SLOPE(INDEX('Daily Returns'!M:M,H10):INDEX('Daily Returns'!M:M,I10),INDEX('Daily Returns'!C:C,H10):INDEX('Daily Returns'!C:C,I10)),SLOPE(INDEX('Daily Returns'!O:O,H10):INDEX('Daily Returns'!O:O,I10),INDEX('Daily Returns'!C:C,H10):INDEX('Daily Returns'!C:C,I10))))))),"") -> 2.1757603 | K10: =IFERROR(IF(B10="UCG",INTERCEPT(INDEX('Daily Returns'!E:E,H10):INDEX('Daily Returns'!E:E,I10),INDEX('Daily Returns'!C:C,H10):INDEX('Daily Returns'!C:C,I10)),IF(B10="BMPS",INTERCEPT(INDEX('Daily Returns'!G:G,H10):INDEX('Daily Returns'!G:G,I10),INDEX('Daily Returns'!C:C,H10):INDEX('Daily Returns'!C:C,I10)),IF(B10="ISP",INTERCEPT(INDEX('Daily Returns'!I:I,H10):INDEX('Daily Returns'!I:I,I10),INDEX('Daily Returns'!C:C,H10):INDEX('Daily Returns'!C:C,I10)),IF(B10="BPE",INTERCEPT(INDEX('Daily Returns'!K:K,H10):INDEX('Daily Returns'!K:K,I10),INDEX('Daily Returns'!C:C,H10):INDEX('Daily Returns'!C:C,I10)),IF(B10="BAMI",INTERCEPT(INDEX('Daily Returns'!M:M,H10):INDEX('Daily Returns'!M:M,I10),INDEX('Daily Returns'!C:C,H10):INDEX('Daily Returns'!C:C,I10)),INTERCEPT(INDEX('Daily Returns'!O:O,H10):INDEX('Daily Returns'!O:O,I10),INDEX('Daily Returns'!C:C,H10):INDEX('Daily Returns'!C:C,I10))))))),"") -> -0.00012028305 | L10: =IFERROR(IF(B10="UCG",RSQ(INDEX('Daily Returns'!E:E,H10):INDEX('Daily Returns'!E:E,I10),INDEX('Daily Returns'!C:C,H10):INDEX('Daily Returns'!C:C,I10)),IF(B10="BMPS",RSQ(INDEX('Daily Returns'!G:G,H10):INDEX('Daily Returns'!G:G,I10),INDEX('Daily Returns'!C:C,H10):INDEX('Daily Returns'!C:C,I10)),IF(B10="ISP",RSQ(INDEX('Daily Returns'!I:I,H10):INDEX('Daily Returns'!I:I,I10),INDEX('Daily Returns'!C:C,H10):INDEX('Daily Returns'!C:C,I10)),IF(B10="BPE",RSQ(INDEX('Daily Returns'!K:K,H10):INDEX('Daily Returns'!K:K,I10),INDEX('Daily Returns'!C:C,H10):INDEX('Daily Returns'!C:C,I10)),IF(B10="BAMI",RSQ(INDEX('Daily Returns'!M:M,H10):INDEX('Daily Returns'!M:M,I10),INDEX('Daily Returns'!C:C,H10):INDEX('Daily Returns'!C:C,I10)),RSQ(INDEX('Daily Returns'!O:O,H10):INDEX('Daily Returns'!O:O,I10),INDEX('Daily Returns'!C:C,H10):INDEX('Daily Returns'!C:C,I10))))))),"") -> 0.46613197
A11: ='Event Master List'!A11 -> GACS-001 | B11: ='Event Master List'!C11 -> UCG | C11: ='Event Master List'!D11 -> 43081 | D11: =IF(B11="UCG","E",IF(B11="BMPS","G",IF(B11="ISP","I",IF(B11="BPE","K",IF(B11="BAMI","M",IF(B11="BPSO","O","?")))))) -> E | E11: C | F11: =WORKDAY(C11,-130) -> 42899 | G11: =WORKDAY(C11,-11) -> 43066 | H11: =MATCH(F11,'Daily Returns'!A:A,1) -> 1080 | I11: =MATCH(G11,'Daily Returns'!A:A,1) -> 1247 | J11: =IFERROR(IF(B11="UCG",SLOPE(INDEX('Daily Returns'!E:E,H11):INDEX('Daily Returns'!E:E,I11),INDEX('Daily Returns'!C:C,H11):INDEX('Daily Returns'!C:C,I11)),IF(B11="BMPS",SLOPE(INDEX('Daily Returns'!G:G,H11):INDEX('Daily Returns'!G:G,I11),INDEX('Daily Returns'!C:C,H11):INDEX('Daily Returns'!C:C,I11)),IF(B11="ISP",SLOPE(INDEX('Daily Returns'!I:I,H11):INDEX('Daily Returns'!I:I,I11),INDEX('Daily Returns'!C:C,H11):INDEX('Daily Returns'!C:C,I11)),IF(B11="BPE",SLOPE(INDEX('Daily Returns'!K:K,H11):INDEX('Daily Returns'!K:K,I11),INDEX('Daily Returns'!C:C,H11):INDEX('Daily Returns'!C:C,I11)),IF(B11="BAMI",SLOPE(INDEX('Daily Returns'!M:M,H11):INDEX('Daily Returns'!M:M,I11),INDEX('Daily Returns'!C:C,H11):INDEX('Daily Returns'!C:C,I11)),SLOPE(INDEX('Daily Returns'!O:O,H11):INDEX('Daily Returns'!O:O,I11),INDEX('Daily Returns'!C:C,H11):INDEX('Daily Returns'!C:C,I11))))))),"") -> 1.584 | K11: =IFERROR(IF(B11="UCG",INTERCEPT(INDEX('Daily Returns'!E:E,H11):INDEX('Daily Returns'!E:E,I11),INDEX('Daily Returns'!C:C,H11):INDEX('Daily Returns'!C:C,I11)),IF(B11="BMPS",INTERCEPT(INDEX('Daily Returns'!G:G,H11):INDEX('Daily Returns'!G:G,I11),INDEX('Daily Returns'!C:C,H11):INDEX('Daily Returns'!C:C,I11)),IF(B11="ISP",INTERCEPT(INDEX('Daily Returns'!I:I,H11):INDEX('Daily Returns'!I:I,I11),INDEX('Daily Returns'!C:C,H11):INDEX('Daily Returns'!C:C,I11)),IF(B11="BPE",INTERCEPT(INDEX('Daily Returns'!K:K,H11):INDEX('Daily Returns'!K:K,I11),INDEX('Daily Returns'!C:C,H11):INDEX('Daily Returns'!C:C,I11)),IF(B11="BAMI",INTERCEPT(INDEX('Daily Returns'!M:M,H11):INDEX('Daily Returns'!M:M,I11),INDEX('Daily Returns'!C:C,H11):INDEX('Daily Returns'!C:C,I11)),INTERCEPT(INDEX('Daily Returns'!O:O,H11):INDEX('Daily Returns'!O:O,I11),INDEX('Daily Returns'!C:C,H11):INDEX('Daily Returns'!C:C,I11))))))),"") -> -0.00020699381 | L11: =IFERROR(IF(B11="UCG",RSQ(INDEX('Daily Returns'!E:E,H11):INDEX('Daily Returns'!E:E,I11),INDEX('Daily Returns'!C:C,H11):INDEX('Daily Returns'!C:C,I11)),IF(B11="BMPS",RSQ(INDEX('Daily Returns'!G:G,H11):INDEX('Daily Returns'!G:G,I11),INDEX('Daily Returns'!C:C,H11):INDEX('Daily Returns'!C:C,I11)),IF(B11="ISP",RSQ(INDEX('Daily Returns'!I:I,H11):INDEX('Daily Returns'!I:I,I11),INDEX('Daily Returns'!C:C,H11):INDEX('Daily Returns'!C:C,I11)),IF(B11="BPE",RSQ(INDEX('Daily Returns'!K:K,H11):INDEX('Daily Returns'!K:K,I11),INDEX('Daily Returns'!C:C,H11):INDEX('Daily Returns'!C:C,I11)),IF(B11="BAMI",RSQ(INDEX('Daily Returns'!M:M,H11):INDEX('Daily Returns'!M:M,I11),INDEX('Daily Returns'!C:C,H11):INDEX('Daily Returns'!C:C,I11)),RSQ(INDEX('Daily Returns'!O:O,H11):INDEX('Daily Returns'!O:O,I11),INDEX('Daily Returns'!C:C,H11):INDEX('Daily Returns'!C:C,I11))))))),"") -> 0.47403689
A12: ='Event Master List'!A12 -> NG-011 | B12: ='Event Master List'!C12 -> ISP | C12: ='Event Master List'!D12 -> 43206 | D12: =IF(B12="UCG","E",IF(B12="BMPS","G",IF(B12="ISP","I",IF(B12="BPE","K",IF(B12="BAMI","M",IF(B12="BPSO","O","?")))))) -> I | E12: C | F12: =WORKDAY(C12,-130) -> 43024 | G12: =WORKDAY(C12,-11) -> 43189 | H12: =MATCH(F12,'Daily Returns'!A:A,1) -> 1205 | I12: =MATCH(G12,'Daily Returns'!A:A,1) -> 1370 | J12: =IFERROR(IF(B12="UCG",SLOPE(INDEX('Daily Returns'!E:E,H12):INDEX('Daily Returns'!E:E,I12),INDEX('Daily Returns'!C:C,H12):INDEX('Daily Returns'!C:C,I12)),IF(B12="BMPS",SLOPE(INDEX('Daily Returns'!G:G,H12):INDEX('Daily Returns'!G:G,I12),INDEX('Daily Returns'!C:C,H12):INDEX('Daily Returns'!C:C,I12)),IF(B12="ISP",SLOPE(INDEX('Daily Returns'!I:I,H12):INDEX('Daily Returns'!I:I,I12),INDEX('Daily Returns'!C:C,H12):INDEX('Daily Returns'!C:C,I12)),IF(B12="BPE",SLOPE(INDEX('Daily Returns'!K:K,H12):INDEX('Daily Returns'!K:K,I12),INDEX('Daily Returns'!C:C,H12):INDEX('Daily Returns'!C:C,I12)),IF(B12="BAMI",SLOPE(INDEX('Daily Returns'!M:M,H12):INDEX('Daily Returns'!M:M,I12),INDEX('Daily Returns'!C:C,H12):INDEX('Daily Returns'!C:C,I12)),SLOPE(INDEX('Daily Returns'!O:O,H12):INDEX('Daily Returns'!O:O,I12),INDEX('Daily Returns'!C:C,H12):INDEX('Daily Returns'!C:C,I12))))))),"") -> 0.905534 | K12: =IFERROR(IF(B12="UCG",INTERCEPT(INDEX('Daily Returns'!E:E,H12):INDEX('Daily Returns'!E:E,I12),INDEX('Daily Returns'!C:C,H12):INDEX('Daily Returns'!C:C,I12)),IF(B12="BMPS",INTERCEPT(INDEX('Daily Returns'!G:G,H12):INDEX('Daily Returns'!G:G,I12),INDEX('Daily Returns'!C:C,H12):INDEX('Daily Returns'!C:C,I12)),IF(B12="ISP",INTERCEPT(INDEX('Daily Returns'!I:I,H12):INDEX('Daily Returns'!I:I,I12),INDEX('Daily Returns'!C:C,H12):INDEX('Daily Returns'!C:C,I12)),IF(B12="BPE",INTERCEPT(INDEX('Daily Returns'!K:K,H12):INDEX('Daily Returns'!K:K,I12),INDEX('Daily Returns'!C:C,H12):INDEX('Daily Returns'!C:C,I12)),IF(B12="BAMI",INTERCEPT(INDEX('Daily Returns'!M:M,H12):INDEX('Daily Returns'!M:M,I12),INDEX('Daily Returns'!C:C,H12):INDEX('Daily Returns'!C:C,I12)),INTERCEPT(INDEX('Daily Returns'!O:O,H12):INDEX('Daily Returns'!O:O,I12),INDEX('Daily Returns'!C:C,H12):INDEX('Daily Returns'!C:C,I12))))))),"") -> 0.00029229059 | L12: =IFERROR(IF(B12="UCG",RSQ(INDEX('Daily Returns'!E:E,H12):INDEX('Daily Returns'!E:E,I12),INDEX('Daily Returns'!C:C,H12):INDEX('Daily Returns'!C:C,I12)),IF(B12="BMPS",RSQ(INDEX('Daily Returns'!G:G,H12):INDEX('Daily Returns'!G:G,I12),INDEX('Daily Returns'!C:C,H12):INDEX('Daily Returns'!C:C,I12)),IF(B12="ISP",RSQ(INDEX('Daily Returns'!I:I,H12):INDEX('Daily Returns'!I:I,I12),INDEX('Daily Returns'!C:C,H12):INDEX('Daily Returns'!C:C,I12)),IF(B12="BPE",RSQ(INDEX('Daily Returns'!K:K,H12):INDEX('Daily Returns'!K:K,I12),INDEX('Daily Returns'!C:C,H12):INDEX('Daily Returns'!C:C,I12)),IF(B12="BAMI",RSQ(INDEX('Daily Returns'!M:M,H12):INDEX('Daily Returns'!M:M,I12),INDEX('Daily Returns'!C:C,H12):INDEX('Daily Returns'!C:C,I12)),RSQ(INDEX('Daily Returns'!O:O,H12):INDEX('Daily Returns'!O:O,I12),INDEX('Daily Returns'!C:C,H12):INDEX('Daily Returns'!C:C,I12))))))),"") -> 0.55516618
A13: ='Event Master List'!A13 -> GACS-002 | B13: ='Event Master List'!C13 -> BMPS | C13: ='Event Master List'!D13 -> 43230 | D13: =IF(B13="UCG","E",IF(B13="BMPS","G",IF(B13="ISP","I",IF(B13="BPE","K",IF(B13="BAMI","M",IF(B13="BPSO","O","?")))))) -> G | E13: C | F13: =WORKDAY(C13,-130) -> 43048 | G13: =WORKDAY(C13,-11) -> 43215 | H13: =MATCH(F13,'Daily Returns'!A:A,1) -> 1229 | I13: =MATCH(G13,'Daily Returns'!A:A,1) -> 1396 | J13: =IFERROR(IF(B13="UCG",SLOPE(INDEX('Daily Returns'!E:E,H13):INDEX('Daily Returns'!E:E,I13),INDEX('Daily Returns'!C:C,H13):INDEX('Daily Returns'!C:C,I13)),IF(B13="BMPS",SLOPE(INDEX('Daily Returns'!G:G,H13):INDEX('Daily Returns'!G:G,I13),INDEX('Daily Returns'!C:C,H13):INDEX('Daily Returns'!C:C,I13)),IF(B13="ISP",SLOPE(INDEX('Daily Returns'!I:I,H13):INDEX('Daily Returns'!I:I,I13),INDEX('Daily Returns'!C:C,H13):INDEX('Daily Returns'!C:C,I13)),IF(B13="BPE",SLOPE(INDEX('Daily Returns'!K:K,H13):INDEX('Daily Returns'!K:K,I13),INDEX('Daily Returns'!C:C,H13):INDEX('Daily Returns'!C:C,I13)),IF(B13="BAMI",SLOPE(INDEX('Daily Returns'!M:M,H13):INDEX('Daily Returns'!M:M,I13),INDEX('Daily Returns'!C:C,H13):INDEX('Daily Returns'!C:C,I13)),SLOPE(INDEX('Daily Returns'!O:O,H13):INDEX('Daily Returns'!O:O,I13),INDEX('Daily Returns'!C:C,H13):INDEX('Daily Returns'!C:C,I13))))))),"") -> 0.8323228 | K13: =IFERROR(IF(B13="UCG",INTERCEPT(INDEX('Daily Returns'!E:E,H13):INDEX('Daily Returns'!E:E,I13),INDEX('Daily Returns'!C:C,H13):INDEX('Daily Returns'!C:C,I13)),IF(B13="BMPS",INTERCEPT(INDEX('Daily Returns'!G:G,H13):INDEX('Daily Returns'!G:G,I13),INDEX('Daily Returns'!C:C,H13):INDEX('Daily Returns'!C:C,I13)),IF(B13="ISP",INTERCEPT(INDEX('Daily Returns'!I:I,H13):INDEX('Daily Returns'!I:I,I13),INDEX('Daily Returns'!C:C,H13):INDEX('Daily Returns'!C:C,I13)),IF(B13="BPE",INTERCEPT(INDEX('Daily Returns'!K:K,H13):INDEX('Daily Returns'!K:K,I13),INDEX('Daily Returns'!C:C,H13):INDEX('Daily Returns'!C:C,I13)),IF(B13="BAMI",INTERCEPT(INDEX('Daily Returns'!M:M,H13):INDEX('Daily Returns'!M:M,I13),INDEX('Daily Returns'!C:C,H13):INDEX('Daily Returns'!C:C,I13)),INTERCEPT(INDEX('Daily Returns'!O:O,H13):INDEX('Daily Returns'!O:O,I13),INDEX('Daily Returns'!C:C,H13):INDEX('Daily Returns'!C:C,I13))))))),"") -> -0.0039737395 | L13: =IFERROR(IF(B13="UCG",RSQ(INDEX('Daily Returns'!E:E,H13):INDEX('Daily Returns'!E:E,I13),INDEX('Daily Returns'!C:C,H13):INDEX('Daily Returns'!C:C,I13)),IF(B13="BMPS",RSQ(INDEX('Daily Returns'!G:G,H13):INDEX('Daily Returns'!G:G,I13),INDEX('Daily Returns'!C:C,H13):INDEX('Daily Returns'!C:C,I13)),IF(B13="ISP",RSQ(INDEX('Daily Returns'!I:I,H13):INDEX('Daily Returns'!I:I,I13),INDEX('Daily Returns'!C:C,H13):INDEX('Daily Returns'!C:C,I13)),IF(B13="BPE",RSQ(INDEX('Daily Returns'!K:K,H13):INDEX('Daily Returns'!K:K,I13),INDEX('Daily Returns'!C:C,H13):INDEX('Daily Returns'!C:C,I13)),IF(B13="BAMI",RSQ(INDEX('Daily Returns'!M:M,H13):INDEX('Daily Returns'!M:M,I13),INDEX('Daily Returns'!C:C,H13):INDEX('Daily Returns'!C:C,I13)),RSQ(INDEX('Daily Returns'!O:O,H13):INDEX('Daily Returns'!O:O,I13),INDEX('Daily Returns'!C:C,H13):INDEX('Daily Returns'!C:C,I13))))))),"") -> 0.075476548
... A75: ='Event Master List'!A75 -> NG-068 | B75: ='Event Master List'!C75 -> BPE | C75: ='Event Master List'!D75 -> 44777 | D75: =IF(B75="UCG","E",IF(B75="BMPS","G",IF(B75="ISP","I",IF(B75="BPE","K",IF(B75="BAMI","M",IF(B75="BPSO","O","?")))))) -> K | E75: C | F75: =WORKDAY(C75,-130) -> 44595 | G75: =WORKDAY(C75,-11) -> 44762 | H75: =MATCH(F75,'Daily Returns'!A:A,1) -> 2776 | I75: =MATCH(G75,'Daily Returns'!A:A,1) -> 2943 | J75: =IFERROR(IF(B75="UCG",SLOPE(INDEX('Daily Returns'!E:E,H75):INDEX('Daily Returns'!E:E,I75),INDEX('Daily Returns'!C:C,H75):INDEX('Daily Returns'!C:C,I75)),IF(B75="BMPS",SLOPE(INDEX('Daily Returns'!G:G,H75):INDEX('Daily Returns'!G:G,I75),INDEX('Daily Returns'!C:C,H75):INDEX('Daily Returns'!C:C,I75)),IF(B75="ISP",SLOPE(INDEX('Daily Returns'!I:I,H75):INDEX('Daily Returns'!I:I,I75),INDEX('Daily Returns'!C:C,H75):INDEX('Daily Returns'!C:C,I75)),IF(B75="BPE",SLOPE(INDEX('Daily Returns'!K:K,H75):INDEX('Daily Returns'!K:K,I75),INDEX('Daily Returns'!C:C,H75):INDEX('Daily Returns'!C:C,I75)),IF(B75="BAMI",SLOPE(INDEX('Daily Returns'!M:M,H75):INDEX('Daily Returns'!M:M,I75),INDEX('Daily Returns'!C:C,H75):INDEX('Daily Returns'!C:C,I75)),SLOPE(INDEX('Daily Returns'!O:O,H75):INDEX('Daily Returns'!O:O,I75),INDEX('Daily Returns'!C:C,H75):INDEX('Daily Returns'!C:C,I75))))))),"") -> 1.5522794 | K75: =IFERROR(IF(B75="UCG",INTERCEPT(INDEX('Daily Returns'!E:E,H75):INDEX('Daily Returns'!E:E,I75),INDEX('Daily Returns'!C:C,H75):INDEX('Daily Returns'!C:C,I75)),IF(B75="BMPS",INTERCEPT(INDEX('Daily Returns'!G:G,H75):INDEX('Daily Returns'!G:G,I75),INDEX('Daily Returns'!C:C,H75):INDEX('Daily Returns'!C:C,I75)),IF(B75="ISP",INTERCEPT(INDEX('Daily Returns'!I:I,H75):INDEX('Daily Returns'!I:I,I75),INDEX('Daily Returns'!C:C,H75):INDEX('Daily Returns'!C:C,I75)),IF(B75="BPE",INTERCEPT(INDEX('Daily Returns'!K:K,H75):INDEX('Daily Returns'!K:K,I75),INDEX('Daily Returns'!C:C,H75):INDEX('Daily Returns'!C:C,I75)),IF(B75="BAMI",INTERCEPT(INDEX('Daily Returns'!M:M,H75):INDEX('Daily Returns'!M:M,I75),INDEX('Daily Returns'!C:C,H75):INDEX('Daily Returns'!C:C,I75)),INTERCEPT(INDEX('Daily Returns'!O:O,H75):INDEX('Daily Returns'!O:O,I75),INDEX('Daily Returns'!C:C,H75):INDEX('Daily Returns'!C:C,I75))))))),"") -> 0.00062718287 | L75: =IFERROR(IF(B75="UCG",RSQ(INDEX('Daily Returns'!E:E,H75):INDEX('Daily Returns'!E:E,I75),INDEX('Daily Returns'!C:C,H75):INDEX('Daily Returns'!C:C,I75)),IF(B75="BMPS",RSQ(INDEX('Daily Returns'!G:G,H75):INDEX('Daily Returns'!G:G,I75),INDEX('Daily Returns'!C:C,H75):INDEX('Daily Returns'!C:C,I75)),IF(B75="ISP",RSQ(INDEX('Daily Returns'!I:I,H75):INDEX('Daily Returns'!I:I,I75),INDEX('Daily Returns'!C:C,H75):INDEX('Daily Returns'!C:C,I75)),IF(B75="BPE",RSQ(INDEX('Daily Returns'!K:K,H75):INDEX('Daily Returns'!K:K,I75),INDEX('Daily Returns'!C:C,H75):INDEX('Daily Returns'!C:C,I75)),IF(B75="BAMI",RSQ(INDEX('Daily Returns'!M:M,H75):INDEX('Daily Returns'!M:M,I75),INDEX('Daily Returns'!C:C,H75):INDEX('Daily Returns'!C:C,I75)),RSQ(INDEX('Daily Returns'!O:O,H75):INDEX('Daily Returns'!O:O,I75),INDEX('Daily Returns'!C:C,H75):INDEX('Daily Returns'!C:C,I75))))))),"") -> 0.66411611

Sheet Abnormal Returns
A1: Event_ID | B1: Ticker | C1: Announcement_Date | D1: Alpha | E1: Beta | F1: R_actual_t0 | G1: R_market_t0 | H1: R_normal_t0 | I1: AR_t0 | J1: CAR[-1,+1] | K1: CAR[-1,+3] | L1: CAR[-5,+5] | M1: GACS | N1: Crisis_Period | O1: Notes | P1: Day-5_Date | Q1: Day-5_AR | R1: Day-4_Date | S1: Day-4_AR | T1: Day-3_Date | U1: Day-3_AR | V1: Day-2_Date | W1: Day-2_AR | X1: Day-1_Date | Y1: Day-1_AR | Z1: Day0_Date | AA1: Day0_AR | AB1: Day+1_Date | AC1: Day+1_AR | AD1: Day+2_Date | AE1: Day+2_AR | AF1: Day+3_Date | AG1: Day+3_AR | AH1: Day+4_Date | AI1: Day+4_AR | AJ1: Day+5_Date | AK1: Day+5_AR
A2: ='Event Master List'!A2 -> NG-001 | B2: ='Event Master List'!C2 -> UCG | C2: ='Event Master List'!D2 -> 42046 | D2: ='Estimation Parameters'!K2 -> -0.00070115916 | E2: ='Estimation Parameters'!J2 -> 1.3560016 | F2: =IFERROR(IF(B2="UCG",INDEX('Daily Returns'!E:E,MATCH(C2,'Daily Returns'!A:A,1)),IF(B2="BMPS",INDEX('Daily Returns'!G:G,MATCH(C2,'Daily Returns'!A:A,1)),IF(B2="ISP",INDEX('Daily Returns'!I:I,MATCH(C2,'Daily Returns'!A:A,1)),IF(B2="BPE",INDEX('Daily Returns'!K:K,MATCH(C2,'Daily Returns'!A:A,1)),IF(B2="BAMI",INDEX('Daily Returns'!M:M,MATCH(C2,'Daily Returns'!A:A,1)),INDEX('Daily Returns'!O:O,MATCH(C2,'Daily Returns'!A:A,1))))))),"") -> -0.034896401 | G2: =IFERROR(INDEX('Daily Returns'!C:C,MATCH(C2,'Daily Returns'!A:A,1)),"") -> -0.0077197723 | H2: =IFERROR(D2+E2*G2,"") -> -0.011169183 | I2: =IFERROR(F2-H2,"") -> -0.023727219 | J2: =IFERROR(Y2+AA2+AC2,"") -> -0.054260886 | K2: =IFERROR(Y2+AA2+AC2+AE2+AG2,"") -> -0.021968955 | L2: =IFERROR(Q2+S2+U2+W2+Y2+AA2+AC2+AE2+AG2+AI2+AK2,"") -> -0.0030616769 | M2: ='Event Master List'!F2 -> No | N2: =IF(YEAR(C2)<=2017,"Yes","No") -> Yes | O2: =IF(AND(B2="BMPS",C2>=DATE(2017,2,1),C2<=DATE(2017,10,31)),"BMPS delisted ~Feb-Oct 2017: returns may be unavailable","") | P2: =WORKDAY(C2,-5) -> 42039 | Q2: =IFERROR(IF(B2="UCG",INDEX('Daily Returns'!E:E,MATCH(P2,'Daily Returns'!A:A,1)),IF(B2="BMPS",INDEX('Daily Returns'!G:G,MATCH(P2,'Daily Returns'!A:A,1)),IF(B2="ISP",INDEX('Daily Returns'!I:I,MATCH(P2,'Daily Returns'!A:A,1)),IF(B2="BPE",INDEX('Daily Returns'!K:K,MATCH(P2,'Daily Returns'!A:A,1)),IF(B2="BAMI",INDEX('Daily Returns'!M:M,MATCH(P2,'Daily Returns'!A:A,1)),INDEX('Daily Returns'!O:O,MATCH(P2,'Daily Returns'!A:A,1)))))))-(D2+E2*INDEX('Daily Returns'!C:C,MATCH(P2,'Daily Returns'!A:A,1))),"") -> -0.0019421759 | R2: =WORKDAY(C2,-4) -> 42040 | S2: =IFERROR(IF(B2="UCG",INDEX('Daily Returns'!E:E,MATCH(R2,'Daily Returns'!A:A,1)),IF(B2="BMPS",INDEX('Daily Returns'!G:G,MATCH(R2,'Daily Returns'!A:A,1)),IF(B2="ISP",INDEX('Daily Returns'!I:I,MATCH(R2,'Daily Returns'!A:A,1)),IF(B2="BPE",INDEX('Daily Returns'!K:K,MATCH(R2,'Daily Returns'!A:A,1)),IF(B2="BAMI",INDEX('Daily Returns'!M:M,MATCH(R2,'Daily Returns'!A:A,1)),INDEX('Daily Returns'!O:O,MATCH(R2,'Daily Returns'!A:A,1)))))))-(D2+E2*INDEX('Daily Returns'!C:C,MATCH(R2,'Daily Returns'!A:A,1))),"") -> 0.0014530455 | T2: =WORKDAY(C2,-3) -> 42041 | U2: =IFERROR(IF(B2="UCG",INDEX('Daily Returns'!E:E,MATCH(T2,'Daily Returns'!A:A,1)),IF(B2="BMPS",INDEX('Daily Returns'!G:G,MATCH(T2,'Daily Returns'!A:A,1)),IF(B2="ISP",INDEX('Daily Returns'!I:I,MATCH(T2,'Daily Returns'!A:A,1)),IF(B2="BPE",INDEX('Daily Returns'!K:K,MATCH(T2,'Daily Returns'!A:A,1)),IF(B2="BAMI",INDEX('Daily Returns'!M:M,MATCH(T2,'Daily Returns'!A:A,1)),INDEX('Daily Returns'!O:O,MATCH(T2,'Daily Returns'!A:A,1)))))))-(D2+E2*INDEX('Daily Returns'!C:C,MATCH(T2,'Daily Returns'!A:A,1))),"") -> 0.0099274682 | V2: =WORKDAY(C2,-2) -> 42044 | W2: =IFERROR(IF(B2="UCG",INDEX('Daily Returns'!E:E,MATCH(V2,'Daily Returns'!A:A,1)),IF(B2="BMPS",INDEX('Daily Returns'!G:G,MATCH(V2,'Daily Returns'!A:A,1)),IF(B2="ISP",INDEX('Daily Returns'!I:I,MATCH(V2,'Daily Returns'!A:A,1)),IF(B2="BPE",INDEX('Daily Returns'!K:K,MATCH(V2,'Daily Returns'!A:A,1)),IF(B2="BAMI",INDEX('Daily Returns'!M:M,MATCH(V2,'Daily Returns'!A:A,1)),INDEX('Daily Returns'!O:O,MATCH(V2,'Daily Returns'!A:A,1)))))))-(D2+E2*INDEX('Daily Returns'!C:C,MATCH(V2,'Daily Returns'!A:A,1))),"") -> 0.0054814529 | X2: =WORKDAY(C2,-1) -> 42045 | Y2: =IFERROR(IF(B2="UCG",INDEX('Daily Returns'!E:E,MATCH(X2,'Daily Returns'!A:A,1)),IF(B2="BMPS",INDEX('Daily Returns'!G:G,MATCH(X2,'Daily Returns'!A:A,1)),IF(B2="ISP",INDEX('Daily Returns'!I:I,MATCH(X2,'Daily Returns'!A:A,1)),IF(B2="BPE",INDEX('Daily Returns'!K:K,MATCH(X2,'Daily Returns'!A:A,1)),IF(B2="BAMI",INDEX('Daily Returns'!M:M,MATCH(X2,'Daily Returns'!A:A,1)),INDEX('Daily Returns'!O:O,MATCH(X2,'Daily Returns'!A:A,1)))))))-(D2+E2*INDEX('Daily Returns'!C:C,MATCH(X2,'Daily Returns'!A:A,1))),"") -> -0.0080713233 | Z2: =C2 -> 42046 | AA2: =IFERROR(IF(B2="UCG",INDEX('Daily Returns'!E:E,MATCH(Z2,'Daily Returns'!A:A,1)),IF(B2="BMPS",INDEX('Daily Returns'!G:G,MATCH(Z2,'Daily Returns'!A:A,1)),IF(B2="ISP",INDEX('Daily Returns'!I:I,MATCH(Z2,'Daily Returns'!A:A,1)),IF(B2="BPE",INDEX('Daily Returns'!K:K,MATCH(Z2,'Daily Returns'!A:A,1)),IF(B2="BAMI",INDEX('Daily Returns'!M:M,MATCH(Z2,'Daily Returns'!A:A,1)),INDEX('Daily Returns'!O:O,MATCH(Z2,'Daily Returns'!A:A,1)))))))-(D2+E2*INDEX('Daily Returns'!C:C,MATCH(Z2,'Daily Returns'!A:A,1))),"") -> -0.023727219 | AB2: =WORKDAY(C2,1) -> 42047 | AC2: =IFERROR(IF(B2="UCG",INDEX('Daily Returns'!E:E,MATCH(AB2,'Daily Returns'!A:A,1)),IF(B2="BMPS",INDEX('Daily Returns'!G:G,MATCH(AB2,'Daily Returns'!A:A,1)),IF(B2="ISP",INDEX('Daily Returns'!I:I,MATCH(AB2,'Daily Returns'!A:A,1)),IF(B2="BPE",INDEX('Daily Returns'!K:K,MATCH(AB2,'Daily Returns'!A:A,1)),IF(B2="BAMI",INDEX('Daily Returns'!M:M,MATCH(AB2,'Daily Returns'!A:A,1)),INDEX('Daily Returns'!O:O,MATCH(AB2,'Daily Returns'!A:A,1)))))))-(D2+E2*INDEX('Daily Returns'!C:C,MATCH(AB2,'Daily Returns'!A:A,1))),"") -> -0.022462344 | AD2: =WORKDAY(C2,2) -> 42048 | AE2: =IFERROR(IF(B2="UCG",INDEX('Daily Returns'!E:E,MATCH(AD2,'Daily Returns'!A:A,1)),IF(B2="BMPS",INDEX('Daily Returns'!G:G,MATCH(AD2,'Daily Returns'!A:A,1)),IF(B2="ISP",INDEX('Daily Returns'!I:I,MATCH(AD2,'Daily Returns'!A:A,1)),IF(B2="BPE",INDEX('Daily Returns'!K:K,MATCH(AD2,'Daily Returns'!A:A,1)),IF(B2="BAMI",INDEX('Daily Returns'!M:M,MATCH(AD2,'Daily Returns'!A:A,1)),INDEX('Daily Returns'!O:O,MATCH(AD2,'Daily Returns'!A:A,1)))))))-(D2+E2*INDEX('Daily Returns'!C:C,MATCH(AD2,'Daily Returns'!A:A,1))),"") -> 0.025551856 | AF2: =WORKDAY(C2,3) -> 42051 | AG2: =IFERROR(IF(B2="UCG",INDEX('Daily Returns'!E:E,MATCH(AF2,'Daily Returns'!A:A,1)),IF(B2="BMPS",INDEX('Daily Returns'!G:G,MATCH(AF2,'Daily Returns'!A:A,1)),IF(B2="ISP",INDEX('Daily Returns'!I:I,MATCH(AF2,'Daily Returns'!A:A,1)),IF(B2="BPE",INDEX('Daily Returns'!K:K,MATCH(AF2,'Daily Returns'!A:A,1)),IF(B2="BAMI",INDEX('Daily Returns'!M:M,MATCH(AF2,'Daily Returns'!A:A,1)),INDEX('Daily Returns'!O:O,MATCH(AF2,'Daily Returns'!A:A,1)))))))-(D2+E2*INDEX('Daily Returns'!C:C,MATCH(AF2,'Daily Returns'!A:A,1))),"") -> 0.006740075 | AH2: =WORKDAY(C2,4) -> 42052 | AI2: =IFERROR(IF(B2="UCG",INDEX('Daily Returns'!E:E,MATCH(AH2,'Daily Returns'!A:A,1)),IF(B2="BMPS",INDEX('Daily Returns'!G:G,MATCH(AH2,'Daily Returns'!A:A,1)),IF(B2="ISP",INDEX('Daily Returns'!I:I,MATCH(AH2,'Daily Returns'!A:A,1)),IF(B2="BPE",INDEX('Daily Returns'!K:K,MATCH(AH2,'Daily Returns'!A:A,1)),IF(B2="BAMI",INDEX('Daily Returns'!M:M,MATCH(AH2,'Daily Returns'!A:A,1)),INDEX('Daily Returns'!O:O,MATCH(AH2,'Daily Returns'!A:A,1)))))))-(D2+E2*INDEX('Daily Returns'!C:C,MATCH(AH2,'Daily Returns'!A:A,1))),"") -> -0.0021095206 | AJ2: =WORKDAY(C2,5) -> 42053 | AK2: =IFERROR(IF(B2="UCG",INDEX('Daily Returns'!E:E,MATCH(AJ2,'Daily Returns'!A:A,1)),IF(B2="BMPS",INDEX('Daily Returns'!G:G,MATCH(AJ2,'Daily Returns'!A:A,1)),IF(B2="ISP",INDEX('Daily Returns'!I:I,MATCH(AJ2,'Daily Returns'!A:A,1)),IF(B2="BPE",INDEX('Daily Returns'!K:K,MATCH(AJ2,'Daily Returns'!A:A,1)),IF(B2="BAMI",INDEX('Daily Returns'!M:M,MATCH(AJ2,'Daily Returns'!A:A,1)),INDEX('Daily Returns'!O:O,MATCH(AJ2,'Daily Returns'!A:A,1)))))))-(D2+E2*INDEX('Daily Returns'!C:C,MATCH(AJ2,'Daily Returns'!A:A,1))),"") -> 0.0060970081
A3: ='Event Master List'!A3 -> NG-006 | B3: ='Event Master List'!C3 -> BMPS | C3: ='Event Master List'!D3 -> 42178 | D3: ='Estimation Parameters'!K3 -> -0.0015581928 | E3: ='Estimation Parameters'!J3 -> 1.0331623 | F3: =IFERROR(IF(B3="UCG",INDEX('Daily Returns'!E:E,MATCH(C3,'Daily Returns'!A:A,1)),IF(B3="BMPS",INDEX('Daily Returns'!G:G,MATCH(C3,'Daily Returns'!A:A,1)),IF(B3="ISP",INDEX('Daily Returns'!I:I,MATCH(C3,'Daily Returns'!A:A,1)),IF(B3="BPE",INDEX('Daily Returns'!K:K,MATCH(C3,'Daily Returns'!A:A,1)),IF(B3="BAMI",INDEX('Daily Returns'!M:M,MATCH(C3,'Daily Returns'!A:A,1)),INDEX('Daily Returns'!O:O,MATCH(C3,'Daily Returns'!A:A,1))))))),"") -> 0.0072090628 | G3: =IFERROR(INDEX('Daily Returns'!C:C,MATCH(C3,'Daily Returns'!A:A,1)),"") -> 0.0034488632 | H3: =IFERROR(D3+E3*G3,"") -> 0.0020050426 | I3: =IFERROR(F3-H3,"") -> 0.0052040203 | J3: =IFERROR(Y3+AA3+AC3,"") -> 0.0083514848 | K3: =IFERROR(Y3+AA3+AC3+AE3+AG3,"") -> 0.024813906 | L3: =IFERROR(Q3+S3+U3+W3+Y3+AA3+AC3+AE3+AG3+AI3+AK3,"") -> 0.033256269 | M3: ='Event Master List'!F3 -> No | N3: =IF(YEAR(C3)<=2017,"Yes","No") -> Yes | O3: =IF(AND(B3="BMPS",C3>=DATE(2017,2,1),C3<=DATE(2017,10,31)),"BMPS delisted ~Feb-Oct 2017: returns may be unavailable","") | P3: =WORKDAY(C3,-5) -> 42171 | Q3: =IFERROR(IF(B3="UCG",INDEX('Daily Returns'!E:E,MATCH(P3,'Daily Returns'!A:A,1)),IF(B3="BMPS",INDEX('Daily Returns'!G:G,MATCH(P3,'Daily Returns'!A:A,1)),IF(B3="ISP",INDEX('Daily Returns'!I:I,MATCH(P3,'Daily Returns'!A:A,1)),IF(B3="BPE",INDEX('Daily Returns'!K:K,MATCH(P3,'Daily Returns'!A:A,1)),IF(B3="BAMI",INDEX('Daily Returns'!M:M,MATCH(P3,'Daily Returns'!A:A,1)),INDEX('Daily Returns'!O:O,MATCH(P3,'Daily Returns'!A:A,1)))))))-(D3+E3*INDEX('Daily Returns'!C:C,MATCH(P3,'Daily Returns'!A:A,1))),"") -> 0.036803928 | R3: =WORKDAY(C3,-4) -> 42172 | S3: =IFERROR(IF(B3="UCG",INDEX('Daily Returns'!E:E,MATCH(R3,'Daily Returns'!A:A,1)),IF(B3="BMPS",INDEX('Daily Returns'!G:G,MATCH(R3,'Daily Returns'!A:A,1)),IF(B3="ISP",INDEX('Daily Returns'!I:I,MATCH(R3,'Daily Returns'!A:A,1)),IF(B3="BPE",INDEX('Daily Returns'!K:K,MATCH(R3,'Daily Returns'!A:A,1)),IF(B3="BAMI",INDEX('Daily Returns'!M:M,MATCH(R3,'Daily Returns'!A:A,1)),INDEX('Daily Returns'!O:O,MATCH(R3,'Daily Returns'!A:A,1)))))))-(D3+E3*INDEX('Daily Returns'!C:C,MATCH(R3,'Daily Returns'!A:A,1))),"") -> 0.056470259 | T3: =WORKDAY(C3,-3) -> 42173 | U3: =IFERROR(IF(B3="UCG",INDEX('Daily Returns'!E:E,MATCH(T3,'Daily Returns'!A:A,1)),IF(B3="BMPS",INDEX('Daily Returns'!G:G,MATCH(T3,'Daily Returns'!A:A,1)),IF(B3="ISP",INDEX('Daily Returns'!I:I,MATCH(T3,'Daily Returns'!A:A,1)),IF(B3="BPE",INDEX('Daily Returns'!K:K,MATCH(T3,'Daily Returns'!A:A,1)),IF(B3="BAMI",INDEX('Daily Returns'!M:M,MATCH(T3,'Daily Returns'!A:A,1)),INDEX('Daily Returns'!O:O,MATCH(T3,'Daily Returns'!A:A,1)))))))-(D3+E3*INDEX('Daily Returns'!C:C,MATCH(T3,'Daily Returns'!A:A,1))),"") -> -0.031291267 | V3: =WORKDAY(C3,-2) -> 42174 | W3: =IFERROR(IF(B3="UCG",INDEX('Daily Returns'!E:E,MATCH(V3,'Daily Returns'!A:A,1)),IF(B3="BMPS",INDEX('Daily Returns'!G:G,MATCH(V3,'Daily Returns'!A:A,1)),IF(B3="ISP",INDEX('Daily Returns'!I:I,MATCH(V3,'Daily Returns'!A:A,1)),IF(B3="BPE",INDEX('Daily Returns'!K:K,MATCH(V3,'Daily Returns'!A:A,1)),IF(B3="BAMI",INDEX('Daily Returns'!M:M,MATCH(V3,'Daily Returns'!A:A,1)),INDEX('Daily Returns'!O:O,MATCH(V3,'Daily Returns'!A:A,1)))))))-(D3+E3*INDEX('Daily Returns'!C:C,MATCH(V3,'Daily Returns'!A:A,1))),"") -> 0.00095235858 | X3: =WORKDAY(C3,-1) -> 42177 | Y3: =IFERROR(IF(B3="UCG",INDEX('Daily Returns'!E:E,MATCH(X3,'Daily Returns'!A:A,1)),IF(B3="BMPS",INDEX('Daily Returns'!G:G,MATCH(X3,'Daily Returns'!A:A,1)),IF(B3="ISP",INDEX('Daily Returns'!I:I,MATCH(X3,'Daily Returns'!A:A,1)),IF(B3="BPE",INDEX('Daily Returns'!K:K,MATCH(X3,'Daily Returns'!A:A,1)),IF(B3="BAMI",INDEX('Daily Returns'!M:M,MATCH(X3,'Daily Returns'!A:A,1)),INDEX('Daily Returns'!O:O,MATCH(X3,'Daily Returns'!A:A,1)))))))-(D3+E3*INDEX('Daily Returns'!C:C,MATCH(X3,'Daily Returns'!A:A,1))),"") -> 0.016603088 | Z3: =C3 -> 42178 | AA3: =IFERROR(IF(B3="UCG",INDEX('Daily Returns'!E:E,MATCH(Z3,'Daily Returns'!A:A,1)),IF(B3="BMPS",INDEX('Daily Returns'!G:G,MATCH(Z3,'Daily Returns'!A:A,1)),IF(B3="ISP",INDEX('Daily Returns'!I:I,MATCH(Z3,'Daily Returns'!A:A,1)),IF(B3="BPE",INDEX('Daily Returns'!K:K,MATCH(Z3,'Daily Returns'!A:A,1)),IF(B3="BAMI",INDEX('Daily Returns'!M:M,MATCH(Z3,'Daily Returns'!A:A,1)),INDEX('Daily Returns'!O:O,MATCH(Z3,'Daily Returns'!A:A,1)))))))-(D3+E3*INDEX('Daily Returns'!C:C,MATCH(Z3,'Daily Returns'!A:A,1))),"") -> 0.0052040203 | AB3: =WORKDAY(C3,1) -> 42179 | AC3: =IFERROR(IF(B3="UCG",INDEX('Daily Returns'!E:E,MATCH(AB3,'Daily Returns'!A:A,1)),IF(B3="BMPS",INDEX('Daily Returns'!G:G,MATCH(AB3,'Daily Returns'!A:A,1)),IF(B3="ISP",INDEX('Daily Returns'!I:I,MATCH(AB3,'Daily Returns'!A:A,1)),IF(B3="BPE",INDEX('Daily Returns'!K:K,MATCH(AB3,'Daily Returns'!A:A,1)),IF(B3="BAMI",INDEX('Daily Returns'!M:M,MATCH(AB3,'Daily Returns'!A:A,1)),INDEX('Daily Returns'!O:O,MATCH(AB3,'Daily Returns'!A:A,1)))))))-(D3+E3*INDEX('Daily Returns'!C:C,MATCH(AB3,'Daily Returns'!A:A,1))),"") -> -0.013455624 | AD3: =WORKDAY(C3,2) -> 42180 | AE3: =IFERROR(IF(B3="UCG",INDEX('Daily Returns'!E:E,MATCH(AD3,'Daily Returns'!A:A,1)),IF(B3="BMPS",INDEX('Daily Returns'!G:G,MATCH(AD3,'Daily Returns'!A:A,1)),IF(B3="ISP",INDEX('Daily Returns'!I:I,MATCH(AD3,'Daily Returns'!A:A,1)),IF(B3="BPE",INDEX('Daily Returns'!K:K,MATCH(AD3,'Daily Returns'!A:A,1)),IF(B3="BAMI",INDEX('Daily Returns'!M:M,MATCH(AD3,'Daily Returns'!A:A,1)),INDEX('Daily Returns'!O:O,MATCH(AD3,'Daily Returns'!A:A,1)))))))-(D3+E3*INDEX('Daily Returns'!C:C,MATCH(AD3,'Daily Returns'!A:A,1))),"") -> 0.005270039 | AF3: =WORKDAY(C3,3) -> 42181 | AG3: =IFERROR(IF(B3="UCG",INDEX('Daily Returns'!E:E,MATCH(AF3,'Daily Returns'!A:A,1)),IF(B3="BMPS",INDEX('Daily Returns'!G:G,MATCH(AF3,'Daily Returns'!A:A,1)),IF(B3="ISP",INDEX('Daily Returns'!I:I,MATCH(AF3,'Daily Returns'!A:A,1)),IF(B3="BPE",INDEX('Daily Returns'!K:K,MATCH(AF3,'Daily Returns'!A:A,1)),IF(B3="BAMI",INDEX('Daily Returns'!M:M,MATCH(AF3,'Daily Returns'!A:A,1)),INDEX('Daily Returns'!O:O,MATCH(AF3,'Daily Returns'!A:A,1)))))))-(D3+E3*INDEX('Daily Returns'!C:C,MATCH(AF3,'Daily Returns'!A:A,1))),"") -> 0.011192383 | AH3: =WORKDAY(C3,4) -> 42184 | AI3: =IFERROR(IF(B3="UCG",INDEX('Daily Returns'!E:E,MATCH(AH3,'Daily Returns'!A:A,1)),IF(B3="BMPS",INDEX('Daily Returns'!G:G,MATCH(AH3,'Daily Returns'!A:A,1)),IF(B3="ISP",INDEX('Daily Returns'!I:I,MATCH(AH3,'Daily Returns'!A:A,1)),IF(B3="BPE",INDEX('Daily Returns'!K:K,MATCH(AH3,'Daily Returns'!A:A,1)),IF(B3="BAMI",INDEX('Daily Returns'!M:M,MATCH(AH3,'Daily Returns'!A:A,1)),INDEX('Daily Returns'!O:O,MATCH(AH3,'Daily Returns'!A:A,1)))))))-(D3+E3*INDEX('Daily Returns'!C:C,MATCH(AH3,'Daily Returns'!A:A,1))),"") -> -0.047481362 | AJ3: =WORKDAY(C3,5) -> 42185 | AK3: =IFERROR(IF(B3="UCG",INDEX('Daily Returns'!E:E,MATCH(AJ3,'Daily Returns'!A:A,1)),IF(B3="BMPS",INDEX('Daily Returns'!G:G,MATCH(AJ3,'Daily Returns'!A:A,1)),IF(B3="ISP",INDEX('Daily Returns'!I:I,MATCH(AJ3,'Daily Returns'!A:A,1)),IF(B3="BPE",INDEX('Daily Returns'!K:K,MATCH(AJ3,'Daily Returns'!A:A,1)),IF(B3="BAMI",INDEX('Daily Returns'!M:M,MATCH(AJ3,'Daily Returns'!A:A,1)),INDEX('Daily Returns'!O:O,MATCH(AJ3,'Daily Returns'!A:A,1)))))))-(D3+E3*INDEX('Daily Returns'!C:C,MATCH(AJ3,'Daily Returns'!A:A,1))),"") -> -0.0070115549
