Workbook

Sheet Summary_Table
A1: Company name | B1: Ticker Symbol | C1: Yahoo Finance Format | D1: Beta (Last 5y, monthly) | E1: Sector | F1: Dimensions | G1: MKT CAP AVG 2015-2019 | H1: MKT CAP AVG 2019-2024 | I1: MKT CAP AVG 2015-2024 | J1: AVG PE 2015-2019 | K1: AVG PE 2020-2024 | L1: AVG PE 2015-2024 | M1: AVG Return 2015-2019 | N1: AVG Return 2020-2024 | O1: AVG Return 2015-2024 | P1: TA/MKTCAP 2015-2019 | Q1: TA/MKTCAP 2020-2024 | R1: TA/MKTCAP 2015-2024 | S1: TA/BE 2015 - 2019 | T1: TA/BE 2020 - 2024 | U1: TA/BE 2015-2024 | V1: BE/MKTCAP 2015 - 2019 | W1: BE/MKTCAP 2020-2024 | X1: BE/MKTCAP 2015-2024
A2: A2a | B2: A2A | C2: A2A.MI | D2: 0.943 | E2: =VLOOKUP(A2,Overview_Table!$A$1:$E$38,5) -> Energy & Utilities | F2: =VLOOKUP(A2,Overview_Table!A1:H38,4) -> Small | G2: 4.5224391e+09 | H2: 5.1466613e+09 | I2: 4.8345502e+09 | J2: 22.873289 | K2: 9.5626214 | L2: 16.217955 | M2: 0.13876656 | N2: 0.054452368 | O2: 0.10115832 | P2: 2.26369 | Q2: 3.508799 | R2: 2.9264356 | S2: 2.8276986 | T2: 3.8398044 | U2: 3.3995723 | V2: 0.80054147 | W2: 0.91379629 | X2: 0.80862131
A3: Amplifon | B3: AMP | C3: AMP.MI | D3: 0.842 | E3: =VLOOKUP(A3,Overview_Table!$A$1:$E$38,5) -> Health | F3: =VLOOKUP(A3,Overview_Table!A2:H39,4) -> Small | G3: 3.0608607e+09 | H3: 7.440943e+09 | I3: 5.2509018e+09 | J3: 35.874403 | K3: 52.427972 | L3: 44.151188 | M3: 0.23204398 | N3: -0.0069909464 | O3: 0.17666442 | P3: 0.60297675 | Q3: 0.48394955 | R3: 0.51864127 | S3: 2.8681753 | T3: 3.2888472 | U3: 3.1331325 | V3: 0.21023009 | W3: 0.14714869 | X3: 0.11681382
A4: Azimut | B4: AZM | C4: AZM.MI | D4: 1.058 | E4: =VLOOKUP(A4,Overview_Table!$A$1:$E$38,5) -> Banking & Financials | F4: =VLOOKUP(A4,Overview_Table!A3:H40,4) -> Small | G4: 2.2625578e+09 | H4: 3.0599763e+09 | I4: 2.6612671e+09 | J4: 10.381668 | K4: 6.4665529 | L4: 8.4241107 | M4: -0.11362536 | N4: 0.024963902 | O4: 0.036483083 | P4: 3.3696077 | Q4: 3.1434373 | R4: 3.2395802 | S4: 13.654279 | T4: 6.9041599 | U4: 8.8354253 | V4: 0.24678035 | W4: 0.45529614 | X4: 0.31888322
A5: Banca Mediolanum | B5: BMED | C5: BMED.MI | D5: 0.844 | E5: =VLOOKUP(A5,Overview_Table!$A$1:$E$38,5) -> Banking & Financials | F5: =VLOOKUP(A5,Overview_Table!A4:H41,4) -> Medium | G5: 5.1671227e+09 | H5: 6.433942e+09 | I5: 5.8005324e+09 | J5: 12.953422 | K5: 9.5185307 | L5: 11.235976 | M5: -0.011844442 | N5: 0.054722038 | O5: 0.078951648 | P5: 8.9318689 | Q5: 11.505712 | R5: 10.359321 | S5: 2.9067348 | T5: 24.426565 | U5: 6.3559179 | V5: 3.0728187 | W5: 0.47103275 | X5: 1.4694124
A6: Banca Monte Paschi Siena | B6: BMPS | C6: BMPS.MI | D6: 0.936 | E6: =VLOOKUP(A6,Overview_Table!$A$1:$E$38,5) -> Banking & Financials | F6: =VLOOKUP(A6,Overview_Table!A5:H42,4) -> Medium | G6: 7.373882e+09 | H6: 4.8090272e+09 | I6: 6.0914546e+09 | J6: 27.789554 | K6: 6.6356609 | L6: 15.097218 | M6: -0.6210918 | N6: -0.45627717 | O6: -0.54973301 | P6: 19.637462 | Q6: 27.186534 | R6: 22.617349 | S6: 17.209826 | T6: 18.368602 | U6: 17.740852 | V6: 1.1410611 | W6: 1.4800546 | X6: 1.6148456
A7: Banco Bpm | B7: BAMI | C7: BAMI.MI | D7: 0.618 | E7: =VLOOKUP(A7,Overview_Table!$A$1:$E$38,5) -> Banking & Financials | F7: =VLOOKUP(A7,Overview_Table!A6:H43,4) -> Medium | G7: 3.3161038e+09 | H7: 6.1413572e+09 | I7: 4.7287305e+09 | J7: 5.385909 | K7: 31.403341 | L7: 21.646804 | M7: -0.23589693 | N7: 0.30536941 | O7: 0.0016886803 | P7: 43.824344 | Q7: 31.72593 | R7: 35.968041 | S7: 13.854071 | T7: 14.376611 | U7: 14.148625 | V7: 3.1632827 | W7: 2.206774 | X7: 1.9574143
A8: Bca Pop Sondrio | B8: BPSO | C8: BPSO.MI | D8: 0.771 | E8: =VLOOKUP(A8,Overview_Table!$A$1:$E$38,5) -> Banking & Financials | F8: =VLOOKUP(A8,Overview_Table!A7:H44,4) -> Small | G8: 1.3590077e+09 | H8: 2.1342088e+09 | I8: 1.7466082e+09 | J8: 11.000139 | K8: 6.8737367 | L8: 8.9369378 | M8: -0.035066948 | N8: 0.30274782 | O8: 0.0991478 | P8: 28.937731 | Q8: 25.960764 | R8: 27.118929 | S8: 14.544075 | T8: 15.633884 | U8: 15.162238 | V8: 1.9896577 | W8: 1.6605448 | X8: 1.4637531
A9: Bper Banca | B9: BPE | C9: BPE.MI | D9: 0.74 | E9: =VLOOKUP(A9,Overview_Table!$A$1:$E$38,5) -> Banking & Financials | F9: =VLOOKUP(A9,Overview_Table!A8:H45,4) -> Medium | G9: 2.3261782e+09 | H9: 3.8504821e+09 | I9: 3.0883302e+09 | J9: 9.1238978 | K9: 4.0080392 | L9: 6.2817541 | M9: -0.10016556 | N9: 0.13893037 | O9: 0.046587265 | P9: 29.853717 | Q9: 34.51107 | R9: 32.757075 | S9: 13.913543 | T9: 15.913088 | U9: 15.165057 | V9: 2.1456588 | W9: 2.1687224 | X9: 1.7324858
A10: Brunello Cucinelli | B10: BC | C10: BC.MI | D10: 1.064 | E10: =VLOOKUP(A10,Overview_Table!$A$1:$E$38,5) -> Consumer & Luxury | F10: =VLOOKUP(A10,Overview_Table!A9:H46,4) -> Small | G10: 1708840000 | H10: 4.8889609e+09 | I10: 3.2989004e+09 | J10: 37.772313 | K10: 62.062349 | L10: 48.567885 | M10: 0.10915715 | N10: 0.2663031 | O10: 0.19287549 | P10: 0.32580031 | Q10: 0.27392291 | R10: 0.28735923 | S10: 2.2070758 | T10: 3.4604306 | U10: 2.9658525 | V10: 0.14761628 | W10: 0.079158621 | X10: 0.065377492
A11: Buzzi | B11: BZU | C11: BZU.MI | D11: 1.113 | E11: =VLOOKUP(A11,Overview_Table!$A$1:$E$38,5) -> Industrials | F11: =VLOOKUP(A11,Overview_Table!A10:H47,4) -> Small | G11: 4.0889395e+09 | H11: 4.5265314e+09 | I11: 4.3077355e+09 | J11: 18.19962 | K11: 6.6792562 | L11: 12.439438 | M11: 0.076577005 | N11: 0.097342624 | O11: 0.13100113 | P11: 1.4277349 | Q11: 1.6399077 | R11: 1.5392096 | S11: 1.7899934 | T11: 1.4415141 | U11: 1.5766403 | V11: 0.7976202 | W11: 1.1376287 | X11: 0.92907039
A12: Campari | B12: CPR | C12: CPR.MI | D12: 0.458 | E12: =VLOOKUP(A12,Overview_Table!$A$1:$E$38,5) -> Consumer & Luxury | F12: =VLOOKUP(A12,Overview_Table!A11:H48,4) -> Medium | G12: 7.0407889e+09 | H12: 1.092525e+10 | I12: 8.9830192e+09 | J12: 27.660733 | K12: 42.074388 | L12: 34.867561 | M12: 0.23940542 | N12: -0.055602647 | O12: 0.092428268 | P12: 0.64199056 | Q12: 0.56409879 | R12: 0.59462413 | S12: 1.9018951 | T12: 1.987872 | U12: 1.9505633 | V12: 0.33755308 | W12: 0.28377018 | X12: 0.25065331
A13: Diasorin | B13: DIA | C13: DIA.MI | D13: 0.573 | E13: =VLOOKUP(A13,Overview_Table!$A$1:$E$38,5) -> Health | F13: =VLOOKUP(A13,Overview_Table!A12:H49,4) -> Small | G13: 4.0216004e+09 | H13: 7.4338867e+09 | I13: 5.7277435e+09 | J13: 28.829762 | K13: 32.336115 | L13: 30.582939 | M13: 0.16268244 | N13: -0.029114473 | O13: 0.11608986 | P13: 0.22338067 | Q13: 0.38746996 | R13: 0.32986425 | S13: 1.261038 | T13: 1.7994777 | U13: 1.6336477 | V13: 0.17714032 | W13: 0.21532357 | X13: 0.15557667
... A18: Generali | B18: G | C18: G.MI | D18: 0.692 | E18: =VLOOKUP(A18,Overview_Table!$A$1:$E$38,5) -> Banking & Financials | F18: =VLOOKUP(A18,Overview_Table!A17:H54,4) -> Large | G18: 2.4664704e+10 | H18: 2.9838645e+10 | I18: 2.7251675e+10 | J18: 11.05797 | K18: 10.278929 | L18: 10.66845 | M18: -0.031633929 | N18: 0.083179751 | O18: 0.049406982 | P18: 20.995298 | Q18: 18.06958 | R18: 19.393571 | S18: 18.707518 | T18: 18.259184 | U18: 18.476111 | V18: 1.122292 | W18: 0.98961598 | X18: 0.95865277
A19: Hera | B19: HER | C19: HER.MI | D19: 0.847 | E19: =VLOOKUP(A19,Overview_Table!$A$1:$E$38,5) -> Energy & Utilities | F19: =VLOOKUP(A19,Overview_Table!A17:H55,4) -> Small | G19: 4.1788776e+09 | H19: 4.5258023e+09 | I19: 4.35234e+09 | J19: 16.372856 | K19: 12.916758 | L19: 14.644807 | M19: 0.069925245 | N19: -0.023657266 | O19: 0.059564592 | P19: 2.1442935 | Q19: 3.1961361 | R19: 2.6911753 | S19: 3.4608142 | T19: 4.153052 | U19: 3.8578802 | V19: 0.61959221 | W19: 0.7695873 | X19: 0.67084238
A20: Intesa Sanpaolo | B20: ISP | C20: ISP.MI | D20: 0.862 | E20: =VLOOKUP(A20,Overview_Table!$A$1:$E$38,5) -> Banking & Financials | F20: =VLOOKUP(A20,Overview_Table!A18:H56,4) -> Large | G20: 4.0813778e+10 | H20: 47409511688 | I20: 4.4111645e+10 | J20: 10.783476 | K20: 8.9242024 | L20: 9.8538391 | M20: -0.048577415 | N20: 0.10097322 | O20: 0.04623553 | P20: 18.632336 | Q20: 20.857228 | R20: 19.82795 | S20: 14.09766 | T20: 15.286064 | U20: 14.745689 | V20: 1.3216615 | W20: 1.3644604 | X20: 1.2511245
A21: Inwit | B21: INW | C21: INW.MI | D21: 0.653 | E21: =VLOOKUP(A21,Overview_Table!$A$1:$E$38,5) -> Industrials | F21: =VLOOKUP(A21,Overview_Table!A19:H57,4) -> Medium | G21: 3.5178289e+09 | H21: 9.6082887e+09 | I21: 6.5630588e+09 | J21: 31.451878 | K21: 39.54189 | L21: 35.496884 | M21: 0.053081636 | N21: 0.028860126 | O21: 0.081383945 | P21: 0.55918463 | Q21: 0.96879048 | R21: 0.85901519 | S21: 1.2645786 | T21: 2.0261307 | U21: 1.8334992 | V21: 0.44219048 | W21: 0.47814808 | X21: 0.3200224
A22: Italgas | B22: IG | C22: IG.MI | D22: 0.671 | E22: =VLOOKUP(A22,Overview_Table!$A$1:$E$38,5) -> Energy & Utilities | F22: =VLOOKUP(A22,Overview_Table!A20:H58,4) -> Small | G22: 3.7460638e+09 | H22: 4.3800519e+09 | I22: 4.0630579e+09 | J22: 11.697656 | K22: 10.697289 | L22: 11.141897 | M22: 0.099196104 | N22: -0.0039813063 | O22: 0.046004272 | P22: 1.7168116 | Q22: 2.4391711 | R22: 2.1061701 | S22: 4.2344058 | T22: 4.9604568 | U22: 4.660195 | V22: 0.40544333 | W22: 0.49172308 | X22: 0.41924037
A23: Leonardo | B23: LDO | C23: LDO.MI | D23: 0.481 | E23: =VLOOKUP(A23,Overview_Table!$A$1:$E$38,5) -> Industrials | F23: =VLOOKUP(A23,Overview_Table!A21:H59,4) -> Large | G23: 6257406004 | H23: 7034291190 | I23: 6645848597 | J23: 13.45736 | K23: 10.44743 | L23: 11.952395 | M23: -0.0012970212 | N23: 0.19983804 | O23: 0.12922242 | P23: 4.114932 | Q23: 4.2193306 | R23: 4.1701823 | S23: 5.5987823 | T23: 4.1478003 | U23: 4.7154986 | V23: 0.73496909 | W23: 1.0172453 | X23: 0.83552128
A24: Mediobanca | B24: MB | C24: MB.MI | D24: 0.644 | E24: =VLOOKUP(A24,Overview_Table!$A$1:$E$38,5) -> Banking & Financials | F24: =VLOOKUP(A24,Overview_Table!A22:H60,4) -> Medium | G24: 6.802855e+09 | H24: 8.356809e+09 | I24: 7.579832e+09 | J24: 9.4613728 | K24: 9.0876144 | L24: 9.2744936 | M24: 0.012216062 | N24: 0.071589458 | O24: 0.074777442 | P24: 10.62848 | Q24: 10.601704 | R24: 10.613719 | S24: 7.6032247 | T24: 7.9533248 | U24: 7.7920919 | V24: 1.3978911 | W24: 1.3329901 | X24: 1.2354712
A25: Moncler | B25: MONC | C25: MONC.MI | D25: 1.161 | E25: =VLOOKUP(A25,Overview_Table!$A$1:$E$38,5) -> Consumer & Luxury | F25: =VLOOKUP(A25,Overview_Table!A23:H61,4) -> Medium | G25: 6.2563027e+09 | H25: 1.4364271e+10 | I25: 1.0310287e+10 | J25: 23.303086 | K25: 30.695589 | L25: 26.999338 | M25: 0.21374647 | N25: 0.04655504 | O25: 0.1649524 | P25: 0.24726988 | Q25: 0.30855061 | R25: 0.28995797 | S25: 1.5800663 | T25: 1.5559278 | U25: 1.5621023 | V25: 0.15649335 | W25: 0.19830651 | X25: 0.13323329
A26: Nexi | B26: NEXI | C26: NEXI.MI | D26: 1.135 | E26: =VLOOKUP(A26,Overview_Table!$A$1:$E$38,5) -> Banking & Financials | F26: =VLOOKUP(A26,Overview_Table!A23:H62,4) -> Small | G26: 5.8212541e+09 | H26: 9.6348425e+09 | I26: 7.9399143e+09 | J26: 80.48468 | K26: 63.387967 | L26: 70.226652 | M26: / | N26: -0.15619199 | O26: -0.15619199 | P26: 0.96301475 | Q26: 2.2379687 | R26: 1.8225245 | S26: 4.009039 | T26: 2.0814321 | U26: 2.4614679 | V26: 0.24021087 | W26: 1.0752062 | X26: 0.61016934
A27: Poste Italiane | B27: PST | C27: PST.MI | D27: 0.749 | E27: =VLOOKUP(A27,Overview_Table!$A$1:$E$38,5) -> Banking & Financials | F27: =VLOOKUP(A27,Overview_Table!A24:H63,4) -> Large | G27: 9.5992069e+09 | H27: 1.3753236e+10 | I27: 1.1676222e+10 | J27: 11.656738 | K27: 8.3660706 | L27: 10.011404 | M27: 0 | N27: 0.061550124 | O27: 0.078414073 | P27: 21.227691 | Q27: 19.873664 | R27: 20.430248 | S27: 21.584785 | T27: 23.593605 | U27: 22.691637 | V27: 0.98345625 | W27: 0.84233265 | X27: 0.76437282
A28: Prysmian | B28: PRY | C28: PRY.MI | D28: 0.819 | E28: =VLOOKUP(A28,Overview_Table!$A$1:$E$38,5) -> Industrials | F28: =VLOOKUP(A28,Overview_Table!A24:H64,4) -> Large | G28: 5.0023686e+09 | H28: 1.0845975e+10 | I28: 7.9241718e+09 | J28: 23.614447 | K28: 26.947125 | L28: 25.280786 | M28: 0.034893405 | N28: 0.23782385 | O28: 0.15676107 | P28: 1.5911662 | Q28: 1.2212272 | R28: 1.3379947 | S28: 4.1395881 | T28: 3.4859985 | U28: 3.705613 | V28: 0.38437792 | W28: 0.35032351 | X28: 0.26380293
A29: Recordati Ord | B29: REC | C29: REC.MI | D29: 0.646 | E29: =VLOOKUP(A29,Overview_Table!$A$1:$E$38,5) -> Health | F29: =VLOOKUP(A29,Overview_Table!A25:H65,4) -> Medium | G29: 6.4103296e+09 | H29: 9.8897248e+09 | I29: 8.1500272e+09 | J29: 23.101787 | K29: 26.578003 | L29: 24.839895 | M29: 0.18111858 | N29: 0.063995313 | O29: 0.14761633 | P29: 0.31381844 | Q29: 0.38159327 | R29: 0.35493943 | S29: 2.1198456 | T29: 2.4069689 | U29: 2.2987099 | V29: 0.14803835 | W29: 0.15853685 | X29: 0.12724623
A30: Saipem | B30: SPM | C30: SPM.MI | D30: 1.678 | E30: =VLOOKUP(A30,Overview_Table!$A$1:$E$38,5) -> Energy & Utilities | F30: =VLOOKUP(A30,Overview_Table!A26:H66,4) -> Small | G30: 2.3343971e+09 | H30: 2.2000142e+09 | I30: 2.2672056e+09 | J30: 23.332866 | K30: 16.262173 | L30: 18.619071 | M30: -0.21574251 | N30: -0.24716849 | O30: -0.20899812 | P30: 5.8157199 | Q30: 5.6895089 | R30: 5.7544846 | S30: 3.289605 | T30: 6.2304629 | U30: 4.2524772 | V30: 1.7679083 | W30: 0.91317594 | X30: 1.3945365
A31: Snam | B31: SRG | C31: SRG.MI | D31: 0.709 | E31: =VLOOKUP(A31,Overview_Table!$A$1:$E$38,5) -> Energy & Utilities | F31: =VLOOKUP(A31,Overview_Table!A27:H67,4) -> Medium | G31: 1.4623004e+10 | H31: 1.5496382e+10 | I31: 1.5059693e+10 | J31: 14.577263 | K31: 14.590594 | L31: 14.583928 | M31: 0.028712515 | N31: -0.013673576 | O31: 0.024345149 | P31: 1.5685285 | Q31: 2.00501 | R31: 1.7930976 | S31: 3.466314 | T31: 4.0181052 | U31: 3.7636589 | V31: 0.45250619 | W31: 0.49899391 | X31: 0.46299841
A32: Stellantis | B32: STLAM | C32: STLAM.MI | D32: 1.151 | E32: =VLOOKUP(A32,Overview_Table!$A$1:$E$38,5) -> Industrials | F32: =VLOOKUP(A32,Overview_Table!A28:H68,4) -> Large | G32: 17888685282 | H32: 4.3659058e+10 | I32: 3.0773871e+10 | J32: 12.250312 | K32: 159.38477 | L32: 85.81754 | M32: 0.146337 | N32: -0.011331769 | O32: 0.071096408 | P32: 5.5968227 | Q32: 3.9734573 | R32: 4.4452841 | S32: 4.4449881 | T32: 2.5748419 | U32: 3.0434113 | V32: 1.2591311 | W32: 1.5431849 | X32: 1.0295481
A33: Stmicroelectronics | B33: STMMI | C33: STMMI.MI | D33: 1.292 | E33: =VLOOKUP(A33,Overview_Table!$A$1:$E$38,5) -> Industrials | F33: =VLOOKUP(A33,Overview_Table!A29:H69,4) -> Large | G33: 1.4495176e+10 | H33: 3.5431396e+10 | I33: 2.4963286e+10 | J33: 47.901453 | K33: 17.223115 | L33: 32.562284 | M33: 0.14273658 | N33: -0.0077942237 | O33: 0.14347621 | P33: 0.72793874 | Q33: 0.57520737 | R33: 0.61954985 | S33: 1.7311895 | T33: 1.5501704 | U33: 1.6075085 | V33: 0.42048473 | W33: 0.37106074 | X33: 0.27154166
A34: Telecom Italia | B34: TIT | C34: TIT.MI | D34: 0.705 | E34: =VLOOKUP(A34,Overview_Table!$A$1:$E$38,5) -> Industrials | F34: =VLOOKUP(A34,Overview_Table!A30:H70,4) -> Small | G34: 1.5905947e+10 | H34: 6.6494451e+09 | I34: 1.1277696e+10 | J34: 10.982715 | K34: 1.1012493 | L34: 8.5123489 | M34: -0.10984126 | N34: -0.1490115 | O34: -0.11795358 | P34: 4.3527995 | Q34: 9.151741 | R34: 5.767552 | S34: 3.6178816 | T34: 3.5778371 | U34: 3.5990383 | V34: 1.2031349 | W34: 2.5578976 | X34: 2.7179411
A35: Tenaris | B35: TEN | C35: TEN.MI | D35: 0.557 | E35: =VLOOKUP(A35,Overview_Table!$A$1:$E$38,5) -> Energy & Utilities | F35: =VLOOKUP(A35,Overview_Table!A31:H71,4) -> Large | G35: 1.6012805e+10 | H35: 1.6808379e+10 | I35: 1.6410592e+10 | J35: 22.365862 | K35: 8.7189603 | L35: 14.567633 | M35: -0.051945806 | N35: 0.12806727 | O35: 0.04028545 | P35: 0.90406092 | Q35: 1.0381476 | R35: 0.97272934 | S35: 1.1918828 | T35: 1.2225757 | U35: 1.2084647 | V35: 0.75851493 | W35: 0.84914787 | X35: 0.7858804
A36: Terna | B36: TRN | C36: TRN.MI | D36: 0.64 | E36: =VLOOKUP(A36,Overview_Table!$A$1:$E$38,5) -> Energy & Utilities | F36: =VLOOKUP(A36,Overview_Table!A32:H72,4) -> Large | G36: 1.0021795e+10 | H36: 1.4091361e+10 | I36: 1.2056578e+10 | J36: 14.822319 | K36: 16.188229 | L36: 15.505274 | M36: 0.062173197 | N36: 0.055076259 | O36: 0.075154729 | P36: 1.6757716 | Q36: 1.6542035 | R36: 1.6631676 | S36: 4.3268734 | T36: 4.1325649 | U36: 4.2117699 | V36: 0.38729389 | W36: 0.40028496 | X36: 0.33786445
A37: Unicredit | B37: UCG | C37: UCG.MI | D37: 1.084 | E37: =VLOOKUP(A37,Overview_Table!$A$1:$E$38,5) -> Banking & Financials | F37: =VLOOKUP(A37,Overview_Table!A33:H73,4) -> Large | G37: 2.9514634e+10 | H37: 3.6378293e+10 | I37: 3.2946463e+10 | J37: 11.251718 | K37: 7.435646 | L37: 9.3436821 | M37: -0.18535315 | N37: 0.2325899 | O37: 0.034917505 | P37: 28.757745 | Q37: 23.502357 | R37: 25.85634 | S37: 15.78955 | T37: 13.671035 | U37: 14.650287 | V37: 1.821315 | W37: 1.7191351 | X37: 1.5984072
A38: Unipol | B38: UNI | C38: UNI.MI | D38: 0.895 | E38: =VLOOKUP(A38,Overview_Table!$A$1:$E$38,5) -> Banking & Financials | F38: =VLOOKUP(A38,Overview_Table!A34:H74,4) -> Medium | G38: 2959033000 | H38: 4358114060 | I38: 3658573530 | J38: 4.2659532 | K38: 5.4010999 | L38: 4.8965902 | M38: -0.03691832 | N38: 0.1796021 | O38: 0.11030459 | P38: 28.747621 | Q38: 18.222901 | R38: 22.479067 | S38: 14.880741 | T38: 10.071433 | U38: 12.09264 | V38: 1.9318676 | W38: 1.8093652 | X38: 1.5605236
A39: Total Market | B39: FTSMIB | C39: FTSIMIB.MI | D39: 0.895 | F39: / | G39: =AVERAGE(J2:J38) -> 20.495407 | H39: =AVERAGE(K2:K38) -> 23.643448 | I39: =AVERAGE(L2:L38) -> 22.000249 | J39: -0.0084965322 | K39: 0.07597422 | L39: 0.060358626 | M39: 8.4277122 | N39: 8.1356907 | O39: 7.8943793 | P39: 7.2262442 | Q39: 7.4954329 | R39: 8.8225176 | S39: 1.0410527 | T39: 1.1786898 | U39: 0.76781086

Sheet Overview_Table
A1: Company | B1: Ticker Symbol | C1: Yahoo Finance Format | D1: Dimensions | E1: Sector | F1: Market Cap (2024) | G1: Book Equity (2024) | H1: Book-to-Market Equity (BE/ME) | I1: Beta (Last 5y, monthly)
A2: A2a | B2: A2A | C2: A2A.MI | D2: Small | E2: Energy & Utilities | F2: {=_xldudf_WISE(C2, "Market Cap", 2024)} -> 6.7353154e+09 | G2: {=_xldudf_WISE(C2, "Total Stockholders Equity", 2024) + _xldudf_WISE(C2, "Deferred Tax Liabilities Non Current", 2024) - _xldudf_WISE(C2, "Preferred Stock", 2024)} -> 5445000000 | H2: =G2/F2 -> 0.80842539 | I2: {=_xldudf_WISEPRICE(C2, "beta")} -> 0.943
A3: Amplifon | B3: AMP | C3: AMP.MI | D3: Small | E3: Health | F3: {=_xldudf_WISE(C3, "Market Cap", 2024)} -> 5610931200 | G3: {=_xldudf_WISE(C3, "Total Stockholders Equity", 2024) + _xldudf_WISE(C3, "Deferred Tax Liabilities Non Current", 2024) - _xldudf_WISE(C3, "Preferred Stock", 2024)} -> 1249495000 | H3: =G3/F3 -> 0.22268942 | I3: {=_xldudf_WISEPRICE(C3, "beta")} -> 0.842
A4: Azimut | B4: AZM | C4: AZM.MI | D4: Small | E4: Banking & Financials | F4: {=_xldudf_WISE(C4, "Market Cap", 2024)} -> 3.3712679e+09 | G4: {=_xldudf_WISE(C4, "Total Stockholders Equity", 2024) + _xldudf_WISE(C4, "Deferred Tax Liabilities Non Current", 2024) - _xldudf_WISE(C4, "Preferred Stock", 2024)} -> 1992495000 | H4: =G4/F4 -> 0.59102245 | I4: {=_xldudf_WISEPRICE(C4, "beta")} -> 1.058
A5: Banca Mediolanum | B5: BMED | C5: BMED.MI | D5: Medium | E5: Banking & Financials | F5: {=_xldudf_WISE(C5, "Market Cap", 2024)} -> 8471898720 | G5: {=_xldudf_WISE(C5, "Total Stockholders Equity", 2024) + _xldudf_WISE(C5, "Deferred Tax Liabilities Non Current", 2024) - _xldudf_WISE(C5, "Preferred Stock", 2024)} -> 4025720000 | H5: =G5/F5 -> 0.4751851 | I5: {=_xldudf_WISEPRICE(C5, "beta")} -> 0.844
A6: Banca Monte Paschi Siena | B6: BMPS | C6: BMPS.MI | D6: Medium | E6: Banking & Financials | F6: {=_xldudf_WISE(C6, "Market Cap", 2024)} -> 8.5764674e+09 | G6: {=_xldudf_WISE(C6, "Total Stockholders Equity", 2024) + _xldudf_WISE(C6, "Deferred Tax Liabilities Non Current", 2024) - _xldudf_WISE(C6, "Preferred Stock", 2024)} -> 11648948000 | H6: =G6/F6 -> 1.3582455 | I6: {=_xldudf_WISEPRICE(C6, "beta")} -> 0.936
A7: Banco Bpm | B7: BAMI | C7: BAMI.MI | D7: Medium | E7: Banking & Financials | F7: {=_xldudf_WISE(C7, "Market Cap", 2024)} -> 1.1754059e+10 | G7: {=_xldudf_WISE(C7, "Total Stockholders Equity", 2024) + _xldudf_WISE(C7, "Deferred Tax Liabilities Non Current", 2024) - _xldudf_WISE(C7, "Preferred Stock", 2024)} -> 14603943000 | H7: =G7/F7 -> 1.2424596 | I7: {=_xldudf_WISEPRICE(C7, "beta")} -> 0.618
A8: Bca Pop Sondrio | B8: BPSO | C8: BPSO.MI | D8: Small | E8: Banking & Financials | F8: {=_xldudf_WISE(C8, "Market Cap", 2024)} -> 3660864064 | G8: {=_xldudf_WISE(C8, "Total Stockholders Equity", 2024) + _xldudf_WISE(C8, "Deferred Tax Liabilities Non Current", 2024) - _xldudf_WISE(C8, "Preferred Stock", 2024)} -> 4156325000 | H8: =G8/F8 -> 1.1353399 | I8: {=_xldudf_WISEPRICE(C8, "beta")} -> 0.771
A9: Bper Banca | B9: BPE | C9: BPE.MI | D9: Medium | E9: Banking & Financials | F9: {=_xldudf_WISE(C9, "Market Cap", 2024)} -> 8671406050 | G9: {=_xldudf_WISE(C9, "Total Stockholders Equity", 2024) + _xldudf_WISE(C9, "Deferred Tax Liabilities Non Current", 2024) - _xldudf_WISE(C9, "Preferred Stock", 2024)} -> 11353867000 | H9: =G9/F9 -> 1.3093456 | I9: {=_xldudf_WISEPRICE(C9, "beta")} -> 0.74
A10: Brunello Cucinelli | B10: BC | C10: BC.MI | D10: Small | E10: Consumer & Luxury | F10: {=_xldudf_WISE(C10, "Market Cap", 2024)} -> 7.1667922e+09 | G10: {=_xldudf_WISE(C10, "Total Stockholders Equity", 2024) + _xldudf_WISE(C10, "Deferred Tax Liabilities Non Current", 2024) - _xldudf_WISE(C10, "Preferred Stock", 2024)} -> 497862000 | H10: =G10/F10 -> 0.069467899 | I10: {=_xldudf_WISEPRICE(C10, "beta")} -> 1.064
A11: Buzzi | B11: BZU | C11: BZU.MI | D11: Small | E11: Industrials | F11: {=_xldudf_WISE(C11, "Market Cap", 2024)} -> 6.522511e+09 | G11: {=_xldudf_WISE(C11, "Total Stockholders Equity", 2024) + _xldudf_WISE(C11, "Deferred Tax Liabilities Non Current", 2024) - _xldudf_WISE(C11, "Preferred Stock", 2024)} -> 7078379000 | H11: =G11/F11 -> 1.085223 | I11: {=_xldudf_WISEPRICE(C11, "beta")} -> 1.113
A12: Campari | B12: CPR | C12: CPR.MI | D12: Medium | E12: Consumer & Luxury | F12: {=_xldudf_WISE(C12, "Market Cap", 2024)} -> 7.2260886e+09 | G12: {=_xldudf_WISE(C12, "Total Stockholders Equity", 2024) + _xldudf_WISE(C12, "Deferred Tax Liabilities Non Current", 2024) - _xldudf_WISE(C12, "Preferred Stock", 2024)} -> 4352200000 | H12: =G12/F12 -> 0.60228987 | I12: {=_xldudf_WISEPRICE(C12, "beta")} -> 0.458
A13: Diasorin | B13: DIA | C13: DIA.MI | D13: Small | E13: Health | F13: {=_xldudf_WISE(C13, "Market Cap", 2024)} -> 5.5622887e+09 | G13: {=_xldudf_WISE(C13, "Total Stockholders Equity", 2024) + _xldudf_WISE(C13, "Deferred Tax Liabilities Non Current", 2024) - _xldudf_WISE(C13, "Preferred Stock", 2024)} -> 2000491000 | H13: =G13/F13 -> 0.3596525 | I13: {=_xldudf_WISEPRICE(C13, "beta")} -> 0.573
... A38: Unipol | B38: UNI | C38: UNI.MI | D38: Medium | E38: Banking & Financials | F38: {=_xldudf_WISE(C38, "Market Cap", 2024)} -> 8613480000 | G38: {=_xldudf_WISE(C38, "Total Stockholders Equity", 2024) + _xldudf_WISE(C38, "Deferred Tax Liabilities Non Current", 2024) - _xldudf_WISE(C38, "Preferred Stock", 2024)} -> 9383000000 | H38: =G38/F38 -> 1.089339 | I38: {=_xldudf_WISEPRICE(C38, "beta")} -> 0.895

Sheet MKTCAP_BE
A2: Company | B2: Yahoo Finance Format | C2: Market Cap | M2: Book to Equity | W2: Total Assets | AG2: Market CAP AVG | AJ2: Book To Equity AVG | AM2: Total Assets AVG | AP2: Market Leverage (TA/MKTCAP) | AS2: Book Leverage (TA/BE) | AV2: MKTCAP/BE AVG
C3: 2015 | D3: =C3+1 -> 2016 | E3: =D3+1 -> 2017 | F3: =E3+1 -> 2018 | G3: =F3+1 -> 2019 | H3: =G3+1 -> 2020 | I3: =H3+1 -> 2021 | J3: =I3+1 -> 2022 | K3: =J3+1 -> 2023 | L3: =K3+1 -> 2024 | M3: 2015 | N3: =M3+1 -> 2016 | O3: =N3+1 -> 2017 | P3: =O3+1 -> 2018 | Q3: =P3+1 -> 2019 | R3: =Q3+1 -> 2020 | S3: =R3+1 -> 2021 | T3: =S3+1 -> 2022 | U3: =T3+1 -> 2023 | V3: =U3+1 -> 2024 | W3: 2015 | X3: =W3+1 -> 2016 | Y3: =X3+1 -> 2017 | Z3: =Y3+1 -> 2018 | AA3: =Z3+1 -> 2019 | AB3: =AA3+1 -> 2020 | AC3: =AB3+1 -> 2021 | AD3: =AC3+1 -> 2022 | AE3: =AD3+1 -> 2023 | AF3: =AE3+1 -> 2024 | AG3: MKT CAP AVG 2015-2019 | AH3: MKT CAP AVG 2019-2024 | AI3: MKT CAP AVG 2015-2024 | AJ3: AVG 2015-2019 | AK3: AVG 2019-2024 | AL3: AVG 2015-2024 | AM3: TA 2015 - 2019 | AN3: TA 2020 - 2024 | AO3: AVG 2015-2024 | AP3: TA/MKTCAP 2015-2019 | AQ3: TA/MKTCAP 2020-2024 | AR3: TA/MKTCAP 2015-2024 | AS3: TA/BE 2015 - 2019 | AT3: TA/BE 2020 - 2024 | AU3: TA/BE 2015-2024 | AV3: BE/MKTCAP 2015 - 2019 | AW3: BE/MKTCAP 2020-2024 | AX3: BE/MKTCAP 2015-2024
A4: A2a | B4: A2A.MI | C4: 3.8949085e+09 | D4: 3.8242961e+09 | E4: 4.7259595e+09 | F4: 4.9746942e+09 | G4: 5.192337e+09 | H4: 4.041939e+09 | I4: 5.2867404e+09 | J4: 3.8421078e+09 | K4: 5.8272038e+09 | L4: 6.7353154e+09 | M4: 3432000000 | N4: 3429000000 | O4: 3543000000 | P4: 3805000000 | Q4: 3893000000 | R4: 4603000000 | S4: 4880000000 | T4: 4347000000 | U4: 4240000000 | V4: 5445000000 | W4: 9801000000 | X4: 10379000000 | Y4: 9949000000 | Z4: 10333000000 | AA4: 10725000000 | AB4: 12226000000 | AC4: 18008000000 | AD4: 21367000000 | AE4: 18798000000 | AF4: 19894000000 | AG4: =AVERAGE(C4:G4) -> 4.5224391e+09 | AH4: =AVERAGE(H4:L4) -> 5.1466613e+09 | AI4: =AVERAGE(C4:L4) -> 4.8345502e+09 | AJ4: =AVERAGE(M4:Q4) -> 3620400000 | AK4: =AVERAGE(R4:V4) -> 4703000000 | AL4: =AVERAGE(M4:V4) -> 4161700000 | AM4: =AVERAGE(W4:AA4) -> 10237400000 | AN4: =AVERAGE(AB4:AF4) -> 18058600000 | AO4: =AVERAGE(W4:AF4) -> 14148000000 | AP4: =AM4/AG4 -> 2.26369 | AQ4: =AN4/AH4 -> 3.508799 | AR4: =AO4/AI4 -> 2.9264356 | AS4: =AM4/AJ4 -> 2.8276986 | AT4: =AN4/AK4 -> 3.8398044 | AU4: =AO4/AL4 -> 3.3995723 | AV4: =AJ4/AG4 -> 0.80054147 | AW4: =AK4/AH4 -> 0.91379629 | AX4: =AL4/AH4 -> 0.80862131
A5: Amplifon | B5: AMP.MI | C5: 1.7432934e+09 | D5: 1.9848673e+09 | E5: 2.8307183e+09 | F5: 3.05684e+09 | G5: 5.6885843e+09 | H5: 7.6180727e+09 | I5: 1.0667895e+10 | J5: 6.2417875e+09 | K5: 7.0660282e+09 | L5: 5610931200 | M5: 555166000 | N5: 619776000 | O5: 634392001 | P5: 635618000 | Q5: 772473000 | R5: 855471000 | S5: 1025097000 | T5: 1145192000 | U5: 1199370000 | V5: 1249495000 | W5: 1286985000 | X5: 1405963000 | Y5: 1465419000 | Z5: 2218434000 | AA5: 2851338000 | AB5: 3228472000 | AC5: 3515291000 | AD5: 3575465000 | AE5: 3693215000 | AF5: 3992762000 | AG5: =AVERAGE(C5:G5) -> 3.0608607e+09 | AH5: =AVERAGE(H5:L5) -> 7.440943e+09 | AI5: =AVERAGE(C5:L5) -> 5.2509018e+09 | AJ5: =AVERAGE(M5:Q5) -> 6.43485e+08 | AK5: =AVERAGE(R5:V5) -> 1094925000 | AL5: =AVERAGE(M5:V5) -> 8.69205e+08 | AM5: =AVERAGE(W5:AA5) -> 1845627800 | AN5: =AVERAGE(AB5:AF5) -> 3601041000 | AO5: =AVERAGE(W5:AF5) -> 2723334400 | AP5: =AM5/AG5 -> 0.60297675 | AQ5: =AN5/AH5 -> 0.48394955 | AR5: =AO5/AI5 -> 0.51864127 | AS5: =AM5/AJ5 -> 2.8681753 | AT5: =AN5/AK5 -> 3.2888472 | AU5: =AO5/AL5 -> 3.1331325 | AV5: =AJ5/AG5 -> 0.21023009 | AW5: =AK5/AH5 -> 0.14714869 | AX5: =AL5/AH5 -> 0.11681382
A6: Azimut | B6: AZM.MI | C6: 3.0639467e+09 | D6: 2.0783863e+09 | E6: 1.9559503e+09 | F6: 1.2749798e+09 | G6: 2.9395259e+09 | H6: 2.4281042e+09 | I6: 3385628985 | J6: 2.8722356e+09 | K6: 3.2426448e+09 | L6: 3.3712679e+09 | M6: 775303000 | N6: 512365000 | O6: 654285000 | P6: 149696001 | Q6: 700125000 | R6: 802556000 | S6: 1152812000 | T6: 1390614000 | U6: 1627500000 | V6: 1992495000 | W6: 6946241000 | X6: 7727276000 | Y6: 8106607000 | Z6: 7085877000 | AA6: 8253660000 | AB6: 8473501000 | AC6: 9922499000 | AD6: 9506645000 | AE6: 9958322000 | AF6: 10233252000 | AG6: =AVERAGE(C6:G6) -> 2.2625578e+09 | AH6: =AVERAGE(H6:L6) -> 3.0599763e+09 | AI6: =AVERAGE(C6:L6) -> 2.6612671e+09 | AJ6: =AVERAGE(M6:Q6) -> 5.583548e+08 | AK6: =AVERAGE(R6:V6) -> 1393195400 | AL6: =AVERAGE(M6:V6) -> 9.757751e+08 | AM6: =AVERAGE(W6:AA6) -> 7623932200 | AN6: =AVERAGE(AB6:AF6) -> 9618843800 | AO6: =AVERAGE(W6:AF6) -> 8621388000 | AP6: =AM6/AG6 -> 3.3696077 | AQ6: =AN6/AH6 -> 3.1434373 | AR6: =AO6/AI6 -> 3.2395802 | AS6: =AM6/AJ6 -> 13.654279 | AT6: =AN6/AK6 -> 6.9041599 | AU6: =AO6/AL6 -> 8.8354253 | AV6: =AJ6/AG6 -> 0.24678035 | AW6: =AK6/AH6 -> 0.45529614 | AX6: =AL6/AH6 -> 0.31888322
A7: Banca Mediolanum | B7: BMED.MI | C7: 5.394191e+09 | D7: 5.0340304e+09 | E7: 5.2099309e+09 | F7: 3.7025383e+09 | G7: 6.4949231e+09 | H7: 5.2139732e+09 | I7: 6.3860132e+09 | J7: 5.7505673e+09 | K7: 6.3472577e+09 | L7: 8471898720 | M7: 2185139000 | N7: 22834146000 | O7: 23622355000 | P7: 28459627000 | Q7: 2286889000 | R7: 2772001000 | S7: 2369701000 | T7: 2629144000 | U7: 3356420999 | V7: 4025720000 | W7: 44710171000 | X7: 41971360000 | Y7: 43266786000 | Z7: 47374365000 | AA7: 53437634000 | AB7: 59029046000 | AC7: 73522370000 | AD7: 73598890000 | AE7: 77830851000 | AF7: 86154272000 | AG7: =AVERAGE(C7:G7) -> 5.1671227e+09 | AH7: =AVERAGE(H7:L7) -> 6.433942e+09 | AI7: =AVERAGE(C7:L7) -> 5.8005324e+09 | AJ7: =AVERAGE(M7:Q7) -> 15877631200 | AK7: =AVERAGE(R7:V7) -> 3.0305974e+09 | AL7: =AVERAGE(M7:V7) -> 9.4541143e+09 | AM7: =AVERAGE(W7:AA7) -> 46152063200 | AN7: =AVERAGE(AB7:AF7) -> 74027085800 | AO7: =AVERAGE(W7:AF7) -> 60089574500 | AP7: =AM7/AG7 -> 8.9318689 | AQ7: =AN7/AH7 -> 11.505712 | AR7: =AO7/AI7 -> 10.359321 | AS7: =AM7/AJ7 -> 2.9067348 | AT7: =AN7/AK7 -> 24.426565 | AU7: =AO7/AL7 -> 6.3559179 | AV7: =AJ7/AG7 -> 3.0728187 | AW7: =AK7/AH7 -> 0.47103275 | AX7: =AL7/AH7 -> 1.4694124
A8: Banca Monte Paschi Siena | B8: BMPS.MI | C8: 10276728000 | D8: 2121873624 | E8: 8957364905 | F8: 8106409863 | G8: 7.4070335e+09 | H8: 5.4675163e+09 | I8: 4.221127e+09 | J8: 1.9384106e+09 | K8: 3.8416145e+09 | L8: 8.5764674e+09 | M8: 9883963000 | N8: 6744401000 | O8: 10660938000 | P8: 8171404000 | Q8: 6609543000 | R8: 2758460000 | S8: 3294734001 | T8: 7907514000 | U8: 9978458000 | V8: 11648948000 | W8: 169011977000 | X8: 153178466000 | Y8: 139154192000 | Z8: 130481006000 | AA8: 132196007000 | AB8: 150356103000 | AC8: 137868562000 | AD8: 120172918000 | AE8: 122704556000 | AF8: 122601750000 | AG8: =AVERAGE(C8:G8) -> 7.373882e+09 | AH8: =AVERAGE(H8:L8) -> 4.8090272e+09 | AI8: =AVERAGE(C8:L8) -> 6.0914546e+09 | AJ8: =AVERAGE(M8:Q8) -> 8414049800 | AK8: =AVERAGE(R8:V8) -> 7.1176228e+09 | AL8: =AVERAGE(M8:V8) -> 7.7658363e+09 | AM8: =AVERAGE(W8:AA8) -> 144804329600 | AN8: =AVERAGE(AB8:AF8) -> 130740777800 | AO8: =AVERAGE(W8:AF8) -> 137772553700 | AP8: =AM8/AG8 -> 19.637462 | AQ8: =AN8/AH8 -> 27.186534 | AR8: =AO8/AI8 -> 22.617349 | AS8: =AM8/AJ8 -> 17.209826 | AT8: =AN8/AK8 -> 18.368602 | AU8: =AO8/AL8 -> 17.740852 | AV8: =AJ8/AG8 -> 1.1410611 | AW8: =AK8/AH8 -> 1.4800546 | AX8: =AL8/AH8 -> 1.6148456
A9: Banco Bpm | B9: BAMI.MI | C9: 4.6362092e+09 | D9: 1.8711103e+09 | E9: 3.9983805e+09 | F9: 3.0068001e+09 | G9: 3.0680186e+09 | H9: 2.7322036e+09 | I9: 3.9885735e+09 | J9: 5.0242714e+09 | K9: 7.2076787e+09 | L9: 1.1754059e+10 | M9: 8828029000 | N9: 7840871999 | O9: 12555231000 | P9: 10753696000 | Q9: 12471040000 | R9: 12684105000 | S9: 13388873000 | T9: 13047924000 | U9: 14038092000 | V9: 14603943000 | W9: 120509595000 | X9: 117411003000 | Y9: 161206765000 | Z9: 160464791000 | AA9: 167038201000 | AB9: 183685182000 | AC9: 200489216000 | AD9: 189685895000 | AE9: 202131973000 | AF9: 198209087000 | AG9: =AVERAGE(C9:G9) -> 3.3161038e+09 | AH9: =AVERAGE(H9:L9) -> 6.1413572e+09 | AI9: =AVERAGE(C9:L9) -> 4.7287305e+09 | AJ9: =AVERAGE(M9:Q9) -> 1.0489774e+10 | AK9: =AVERAGE(R9:V9) -> 13552587400 | AL9: =AVERAGE(M9:V9) -> 1.202118e+10 | AM9: =AVERAGE(W9:AA9) -> 145326071000 | AN9: =AVERAGE(AB9:AF9) -> 194840270600 | AO9: =AVERAGE(W9:AF9) -> 170083170800 | AP9: =AM9/AG9 -> 43.824344 | AQ9: =AN9/AH9 -> 31.72593 | AR9: =AO9/AI9 -> 35.968041 | AS9: =AM9/AJ9 -> 13.854071 | AT9: =AN9/AK9 -> 14.376611 | AU9: =AO9/AL9 -> 14.148625 | AV9: =AJ9/AG9 -> 3.1632827 | AW9: =AK9/AH9 -> 2.206774 | AX9: =AL9/AH9 -> 1.9574143
A10: Bca Pop Sondrio | B10: BPSO.MI | C10: 1.8673029e+09 | D10: 1.4076455e+09 | E10: 1.3896359e+09 | F10: 1.1738104e+09 | G10: 9.5664399e+08 | H10: 9.8941871e+08 | I10: 1.6638878e+09 | J10: 1.7000325e+09 | K10: 2.6568407e+09 | L10: 3660864064 | M10: 2626978000 | N10: 2630429000 | O10: 2715070000 | P10: 2676337000 | Q10: 2870987000 | R10: 3031404000 | S10: 3306108000 | T10: 3416635000 | U10: 3809274000 | V10: 4156325000 | W10: 35537648000 | X10: 37196325000 | Y10: 41624654000 | Z10: 41128185000 | AA10: 41146189000 | AB10: 49807597000 | AC10: 55016149000 | AD10: 57854361000 | AE10: 57721765000 | AF10: 56628582000 | AG10: =AVERAGE(C10:G10) -> 1.3590077e+09 | AH10: =AVERAGE(H10:L10) -> 2.1342088e+09 | AI10: =AVERAGE(C10:L10) -> 1.7466082e+09 | AJ10: =AVERAGE(M10:Q10) -> 2703960200 | AK10: =AVERAGE(R10:V10) -> 3543949200 | AL10: =AVERAGE(M10:V10) -> 3123954700 | AM10: =AVERAGE(W10:AA10) -> 39326600200 | AN10: =AVERAGE(AB10:AF10) -> 55405690800 | AO10: =AVERAGE(W10:AF10) -> 47366145500 | AP10: =AM10/AG10 -> 28.937731 | AQ10: =AN10/AH10 -> 25.960764 | AR10: =AO10/AI10 -> 27.118929 | AS10: =AM10/AJ10 -> 14.544075 | AT10: =AN10/AK10 -> 15.633884 | AU10: =AO10/AL10 -> 15.162238 | AV10: =AJ10/AG10 -> 1.9896577 | AW10: =AK10/AH10 -> 1.6605448 | AX10: =AL10/AH10 -> 1.4637531
A11: Bper Banca | B11: BPE.MI | C11: 3.3885773e+09 | D11: 2.4366495e+09 | E11: 2.0033095e+09 | F11: 1.5841777e+09 | G11: 2.2181771e+09 | H11: 1.0117325e+09 | I11: 2.5704289e+09 | J11: 2.7108715e+09 | K11: 4.2879715e+09 | L11: 8671406050 | M11: 5129613000 | N11: 4980624000 | O11: 5167681000 | P11: 4447789000 | Q11: 5230217000 | R11: 6274340000 | S11: 6755216000 | T11: 8003561000 | U11: 9366149000 | V11: 11353867000 | W11: 61261231000 | X11: 64957028000 | Y11: 71338807000 | Z11: 70634767000 | AA11: 79033498000 | AB11: 93050838000 | AC11: 136347873000 | AD11: 152302794000 | AE11: 142128359000 | AF11: 140591432000 | AG11: =AVERAGE(C11:G11) -> 2.3261782e+09 | AH11: =AVERAGE(H11:L11) -> 3.8504821e+09 | AI11: =AVERAGE(C11:L11) -> 3.0883302e+09 | AJ11: =AVERAGE(M11:Q11) -> 4991184800 | AK11: =AVERAGE(R11:V11) -> 8350626600 | AL11: =AVERAGE(M11:V11) -> 6670905700 | AM11: =AVERAGE(W11:AA11) -> 69445066200 | AN11: =AVERAGE(AB11:AF11) -> 132884259200 | AO11: =AVERAGE(W11:AF11) -> 101164662700 | AP11: =AM11/AG11 -> 29.853717 | AQ11: =AN11/AH11 -> 34.51107 | AR11: =AO11/AI11 -> 32.757075 | AS11: =AM11/AJ11 -> 13.913543 | AT11: =AN11/AK11 -> 15.913088 | AU11: =AO11/AL11 -> 15.165057 | AV11: =AJ11/AG11 -> 2.1456588 | AW11: =AK11/AH11 -> 2.1687224 | AX11: =AL11/AH11 -> 1.7324858
A12: Brunello Cucinelli | B12: BC.MI | C12: 1109760000 | D12: 1383120000 | E12: 1844840000 | F12: 2060400000 | G12: 2146080000 | H12: 2427600000 | I12: 4127600000 | J12: 4698800000 | K12: 6.0240123e+09 | L12: 7.1667922e+09 | M12: 192603000 | N12: 221462000 | O12: 261116000 | P12: 285929000 | Q12: 300153000 | R12: 265371000 | S12: 324716000 | T12: 395021000 | U12: 452047000 | V12: 497862000 | W12: 411103000 | X12: 429894000 | Y12: 450024000 | Z12: 495755000 | AA12: 996927000 | AB12: 1079730000 | AC12: 1168501000 | AD12: 1322988000 | AE12: 1379880000 | AF12: 1744893000 | AG12: =AVERAGE(C12:G12) -> 1708840000 | AH12: =AVERAGE(H12:L12) -> 4.8889609e+09 | AI12: =AVERAGE(C12:L12) -> 3.2989004e+09 | AJ12: =AVERAGE(M12:Q12) -> 252252600 | AK12: =AVERAGE(R12:V12) -> 387003400 | AL12: =AVERAGE(M12:V12) -> 319628000 | AM12: =AVERAGE(W12:AA12) -> 556740600 | AN12: =AVERAGE(AB12:AF12) -> 1339198400 | AO12: =AVERAGE(W12:AF12) -> 947969500 | AP12: =AM12/AG12 -> 0.32580031 | AQ12: =AN12/AH12 -> 0.27392291 | AR12: =AO12/AI12 -> 0.28735923 | AS12: =AM12/AJ12 -> 2.2070758 | AT12: =AN12/AK12 -> 3.4604306 | AU12: =AO12/AL12 -> 2.9658525 | AV12: =AJ12/AG12 -> 0.14761628 | AW12: =AK12/AH12 -> 0.079158621 | AX12: =AL12/AH12 -> 0.065377492
A13: Buzzi | B13: BZU.MI | C13: 3.411828e+09 | D13: 4.626521e+09 | E13: 4.6985694e+09 | F13: 3.10923e+09 | G13: 4.5985493e+09 | H13: 4.0111175e+09 | I13: 3.6457016e+09 | J13: 3354795054 | K13: 5.0985318e+09 | L13: 6.522511e+09 | M13: 3008233000 | N13: 3282139000 | O13: 2864761000 | P13: 3231143001 | Q13: 3920828000 | R13: 3369072000 | S13: 4432286001 | T13: 5241467001 | U13: 5626355000 | V13: 7078379000 | W13: 5520818000 | X13: 5808885000 | Y13: 5783194000 | Z13: 5674147000 | AA13: 6402564000 | AB13: 6386760000 | AC13: 6921783000 | AD13: 7503088000 | AE13: 7615403000 | AF13: 8688435000 | AG13: =AVERAGE(C13:G13) -> 4.0889395e+09 | AH13: =AVERAGE(H13:L13) -> 4.5265314e+09 | AI13: =AVERAGE(C13:L13) -> 4.3077355e+09 | AJ13: =AVERAGE(M13:Q13) -> 3.2614208e+09 | AK13: =AVERAGE(R13:V13) -> 5.1495118e+09 | AL13: =AVERAGE(M13:V13) -> 4.2054663e+09 | AM13: =AVERAGE(W13:AA13) -> 5837921600 | AN13: =AVERAGE(AB13:AF13) -> 7423093800 | AO13: =AVERAGE(W13:AF13) -> 6630507700 | AP13: =AM13/AG13 -> 1.4277349 | AQ13: =AN13/AH13 -> 1.6399077 | AR13: =AO13/AI13 -> 1.5392096 | AS13: =AM13/AJ13 -> 1.7899934 | AT13: =AN13/AK13 -> 1.4415141 | AU13: =AO13/AL13 -> 1.5766403 | AV13: =AJ13/AG13 -> 0.7976202 | AW13: =AK13/AH13 -> 1.1376287 | AX13: =AL13/AH13 -> 0.92907039
A14: Campari | B14: CPR.MI | C14: 4624137592 | D14: 5370839208 | E14: 7.3825948e+09 | F14: 8.5116414e+09 | G14: 9.3147316e+09 | H14: 1.0589847e+10 | I14: 1.4487932e+10 | J14: 1.0675064e+10 | K14: 1.1647316e+10 | L14: 7.2260886e+09 | M14: 2037000000 | N14: 2356600000 | O14: 2306600000 | P14: 2452600000 | Q14: 2730400000 | R14: 2101700000 | S14: 2644100000 | T14: 3074400000 | U14: 3328900000 | V14: 4352200000 | W14: 4224000000 | X14: 4534300000 | Y14: 4419100000 | Z14: 4582500000 | AA14: 4840700000 | AB14: 4555500000 | AC14: 5093100000 | AD14: 6007100000 | AE14: 6675600000 | AF14: 8483300000 | AG14: =AVERAGE(C14:G14) -> 7.0407889e+09 | AH14: =AVERAGE(H14:L14) -> 1.092525e+10 | AI14: =AVERAGE(C14:L14) -> 8.9830192e+09 | AJ14: =AVERAGE(M14:Q14) -> 2376640000 | AK14: =AVERAGE(R14:V14) -> 3100260000 | AL14: =AVERAGE(M14:V14) -> 2738450000 | AM14: =AVERAGE(W14:AA14) -> 4520120000 | AN14: =AVERAGE(AB14:AF14) -> 6162920000 | AO14: =AVERAGE(W14:AF14) -> 5341520000 | AP14: =AM14/AG14 -> 0.64199056 | AQ14: =AN14/AH14 -> 0.56409879 | AR14: =AO14/AI14 -> 0.59462413 | AS14: =AM14/AJ14 -> 1.9018951 | AT14: =AN14/AK14 -> 1.987872 | AU14: =AO14/AL14 -> 1.9505633 | AV14: =AJ14/AG14 -> 0.33755308 | AW14: =AK14/AH14 -> 0.28377018 | AX14: =AL14/AH14 -> 0.25065331
A15: Diasorin | B15: DIA.MI | C15: 2.659107e+09 | D15: 3.0853065e+09 | E15: 4.0973082e+09 | F15: 3.9525336e+09 | G15: 6.3137468e+09 | H15: 9.3142741e+09 | I15: 9.5644088e+09 | J15: 7530710840 | K15: 5.197751e+09 | L15: 5.5622887e+09 | M15: 588863000 | N15: 664218000 | O15: 743316000 | P15: 709783000 | Q15: 855758000 | R15: 964744000 | S15: 1551714000 | T15: 1748299000 | U15: 1738207000 | V15: 2000491000 | W15: 707906000 | X15: 868618000 | Y15: 945723000 | Z15: 905940000 | AA15: 1063552000 | AB15: 1246446000 | AC15: 3231152000 | AD15: 3408082000 | AE15: 3211439000 | AF15: 3304920000 | AG15: =AVERAGE(C15:G15) -> 4.0216004e+09 | AH15: =AVERAGE(H15:L15) -> 7.4338867e+09 | AI15: =AVERAGE(C15:L15) -> 5.7277435e+09 | AJ15: =AVERAGE(M15:Q15) -> 712387600 | AK15: =AVERAGE(R15:V15) -> 1600691000 | AL15: =AVERAGE(M15:V15) -> 1156539300 | AM15: =AVERAGE(W15:AA15) -> 898347800 | AN15: =AVERAGE(AB15:AF15) -> 2880407800 | AO15: =AVERAGE(W15:AF15) -> 1889377800 | AP15: =AM15/AG15 -> 0.22338067 | AQ15: =AN15/AH15 -> 0.38746996 | AR15: =AO15/AI15 -> 0.32986425 | AS15: =AM15/AJ15 -> 1.261038 | AT15: =AN15/AK15 -> 1.7994777 | AU15: =AO15/AL15 -> 1.6336477 | AV15: =AJ15/AG15 -> 0.17714032 | AW15: =AK15/AH15 -> 0.21532357 | AX15: =AL15/AH15 -> 0.15557667
... A27: Moncler | B27: MONC.MI | C27: 3.2311128e+09 | D27: 4.1204005e+09 | E27: 6.5031504e+09 | F27: 7.3402707e+09 | G27: 1.0086579e+10 | H27: 1.2669106e+10 | I27: 1.7001836e+10 | J27: 1.3314227e+10 | K27: 1.5044931e+10 | L27: 1.3791256e+10 | M27: 614911000 | N27: 774405000 | O27: 992122000 | P27: 1138913000 | Q27: 1374998000 | R27: 1633444000 | S27: 2724607000 | T27: 2917360000 | U27: 3277369000 | V27: 3689862000 | W27: 1012064000 | X27: 1151799000 | Y27: 1380047000 | Z27: 1625643000 | AA27: 2565423000 | AB27: 2756612000 | AC27: 4267988999 | AD27: 4639312000 | AE27: 4992020000 | AF27: 5504590000 | AG27: =AVERAGE(C27:G27) -> 6.2563027e+09 | AH27: =AVERAGE(H27:L27) -> 1.4364271e+10 | AI27: =AVERAGE(C27:L27) -> 1.0310287e+10 | AJ27: =AVERAGE(M27:Q27) -> 979069800 | AK27: =AVERAGE(R27:V27) -> 2848528400 | AL27: =AVERAGE(M27:V27) -> 1913799100 | AM27: =AVERAGE(W27:AA27) -> 1546995200 | AN27: =AVERAGE(AB27:AF27) -> 4.4321046e+09 | AO27: =AVERAGE(W27:AF27) -> 2.9895499e+09 | AP27: =AM27/AG27 -> 0.24726988 | AQ27: =AN27/AH27 -> 0.30855061 | AR27: =AO27/AI27 -> 0.28995797 | AS27: =AM27/AJ27 -> 1.5800663 | AT27: =AN27/AK27 -> 1.5559278 | AU27: =AO27/AL27 -> 1.5621023 | AV27: =AJ27/AG27 -> 0.15649335 | AW27: =AK27/AH27 -> 0.19830651 | AX27: =AL27/AH27 -> 0.13323329
A28: Nexi | B28: NEXI.MI | C28: Unavailable | D28: 5.2485294e+09 | E28: 5.2485294e+09 | F28: 5.2105555e+09 | G28: 7577401840 | H28: 10257892520 | I28: 11678208460 | J28: 9655013964 | K28: 9717162780 | L28: 6865934880 | M28: =AVERAGE(N28:Q28) -> 1398328500 | N28: 1997832000 | O28: 1990789000 | P28: 157139000 | Q28: 1447554000 | R28: 1772214000 | S28: 13549696000 | T28: 13345047000 | U28: 11274415000 | V28: 11855841000 | W28: Unavailable | X28: 5319990000 | Y28: 6560842000 | Z28: 5254689000 | AA28: 5288293000 | AB28: 6286101000 | AC28: 25205713000 | AD28: 25475461000 | AE28: 26349788000 | AF28: 24495318000 | AG28: =AVERAGE(C28:G28) -> 5.8212541e+09 | AH28: =AVERAGE(H28:L28) -> 9.6348425e+09 | AI28: =AVERAGE(C28:L28) -> 7.9399143e+09 | AJ28: =AVERAGE(M28:Q28) -> 1398328500 | AK28: =AVERAGE(R28:V28) -> 10359442600 | AL28: =AVERAGE(M28:V28) -> 5878885550 | AM28: =AVERAGE(W28:AA28) -> 5605953500 | AN28: =AVERAGE(AB28:AF28) -> 21562476200 | AO28: =AVERAGE(W28:AF28) -> 1.4470688e+10 | AP28: =AM28/AG28 -> 0.96301475 | AQ28: =AN28/AH28 -> 2.2379687 | AR28: =AO28/AI28 -> 1.8225245 | AS28: =AM28/AJ28 -> 4.009039 | AT28: =AN28/AK28 -> 2.0814321 | AU28: =AO28/AL28 -> 2.4614679 | AV28: =AJ28/AG28 -> 0.24021087 | AW28: =AK28/AH28 -> 1.0752062 | AX28: =AL28/AH28 -> 0.61016934
A29: Poste Italiane | B29: PST.MI | C29: 9.2652482e+09 | D29: 8241554100 | E29: 8.2210227e+09 | F29: 9103586700 | G29: 1.3164623e+10 | H29: 1.0823089e+10 | I29: 1.5012121e+10 | J29: 1.1855981e+10 | K29: 1.3439744e+10 | L29: 1.7635247e+10 | M29: 10835000000 | N29: 8880000000 | O29: 8096000000 | P29: 8806000000 | Q29: 10585000000 | R29: 12731000000 | S29: 13055000000 | T29: 8436000000 | U29: 11222000000 | V29: 12480000000 | W29: 175836000000 | X29: 193205000000 | Y29: 202670000000 | Z29: 208883000000 | AA29: 238251000000 | AB29: 272357000000 | AC29: 284728000000 | AD29: 261626000000 | AE29: 270827000000 | AF29: 277098000000 | AG29: =AVERAGE(C29:G29) -> 9.5992069e+09 | AH29: =AVERAGE(H29:L29) -> 1.3753236e+10 | AI29: =AVERAGE(C29:L29) -> 1.1676222e+10 | AJ29: =AVERAGE(M29:Q29) -> 9440400000 | AK29: =AVERAGE(R29:V29) -> 11584800000 | AL29: =AVERAGE(M29:V29) -> 10512600000 | AM29: =AVERAGE(W29:AA29) -> 203769000000 | AN29: =AVERAGE(AB29:AF29) -> 273327200000 | AO29: =AVERAGE(W29:AF29) -> 238548100000 | AP29: =AM29/AG29 -> 21.227691 | AQ29: =AN29/AH29 -> 19.873664 | AR29: =AO29/AI29 -> 20.430248 | AS29: =AM29/AJ29 -> 21.584785 | AT29: =AN29/AK29 -> 23.593605 | AU29: =AO29/AL29 -> 22.691637 | AV29: =AJ29/AG29 -> 0.98345625 | AW29: =AK29/AH29 -> 0.84233265 | AX29: =AL29/AH29 -> 0.76437282
A30: Prysmian | B30: PRY.MI | C30: 4.3345054e+09 | D30: 5.2230282e+09 | E30: 5524952400 | F30: 4274499650 | G30: 5654857110 | H30: 7656007920 | I30: 8721438880 | J30: 9132806020 | K30: 1.1359866e+10 | L30: 17359756400 | M30: 1341000000 | N30: 1559000000 | O30: 1590000000 | P30: 2496000000 | Q30: 2628000000 | R30: 2454000000 | S30: 3103000000 | T30: 3772000000 | U30: 4003000000 | V30: 5666000000 | W30: 6115000000 | X30: 6311000000 | Y30: 6743000000 | Z30: 10143000000 | AA30: 10486000000 | AB30: 9930000000 | AC30: 12016000000 | AD30: 12756000000 | AE30: 13323000000 | AF30: 18202000000 | AG30: =AVERAGE(C30:G30) -> 5.0023686e+09 | AH30: =AVERAGE(H30:L30) -> 1.0845975e+10 | AI30: =AVERAGE(C30:L30) -> 7.9241718e+09 | AJ30: =AVERAGE(M30:Q30) -> 1922800000 | AK30: =AVERAGE(R30:V30) -> 3799600000 | AL30: =AVERAGE(M30:V30) -> 2861200000 | AM30: =AVERAGE(W30:AA30) -> 7959600000 | AN30: =AVERAGE(AB30:AF30) -> 13245400000 | AO30: =AVERAGE(W30:AF30) -> 10602500000 | AP30: =AM30/AG30 -> 1.5911662 | AQ30: =AN30/AH30 -> 1.2212272 | AR30: =AO30/AI30 -> 1.3379947 | AS30: =AM30/AJ30 -> 4.1395881 | AT30: =AN30/AK30 -> 3.4859985 | AU30: =AO30/AL30 -> 3.705613 | AV30: =AJ30/AG30 -> 0.38437792 | AW30: =AK30/AH30 -> 0.35032351 | AX30: =AL30/AH30 -> 0.26380293
A31: Recordati Ord | B31: REC.MI | C31: 4.9449566e+09 | D31: 5.5486809e+09 | E31: 7.7222309e+09 | F31: 6.1354625e+09 | G31: 7.7003169e+09 | H31: 9.3270158e+09 | I31: 1.1639627e+10 | J31: 7.9663074e+09 | K31: 10076072664 | L31: 1.0439602e+10 | M31: 864602000 | N31: 881055000 | O31: 955457000 | P31: 889582001 | Q31: 1154177000 | R31: 1167947000 | S31: 1254047000 | T31: 1576604000 | U31: 1830600000 | V31: 2010231000 | W31: 1468886000 | X31: 1560743000 | Y31: 2056407000 | Z31: 2163432000 | AA31: 2808930000 | AB31: 2711654000 | AC31: 2816199000 | AD31: 3998823000 | AE31: 4208131000 | AF31: 5134455000 | AG31: =AVERAGE(C31:G31) -> 6.4103296e+09 | AH31: =AVERAGE(H31:L31) -> 9.8897248e+09 | AI31: =AVERAGE(C31:L31) -> 8.1500272e+09 | AJ31: =AVERAGE(M31:Q31) -> 9.489746e+08 | AK31: =AVERAGE(R31:V31) -> 1567885800 | AL31: =AVERAGE(M31:V31) -> 1.2584302e+09 | AM31: =AVERAGE(W31:AA31) -> 2011679600 | AN31: =AVERAGE(AB31:AF31) -> 3773852400 | AO31: =AVERAGE(W31:AF31) -> 2892766000 | AP31: =AM31/AG31 -> 0.31381844 | AQ31: =AN31/AH31 -> 0.38159327 | AR31: =AO31/AI31 -> 0.35493943 | AS31: =AM31/AJ31 -> 2.1198456 | AT31: =AN31/AK31 -> 2.4069689 | AU31: =AO31/AL31 -> 2.2987099 | AV31: =AJ31/AG31 -> 0.14803835 | AW31: =AK31/AH31 -> 0.15853685 | AX31: =AL31/AH31 -> 0.12724623
A32: Saipem | B32: SPM.MI | C32: 3.2911696e+09 | D32: 2.3546078e+09 | E32: 2.0179544e+09 | F32: 1.721633e+09 | G32: 2.2866209e+09 | H32: 1.151601e+09 | I32: 9.1429469e+08 | J32: 1.0625864e+09 | K32: 2.9328674e+09 | L32: 4938721180 | M32: 3369000000 | N32: 4845000000 | O32: 4549000000 | P32: 3858000000 | Q32: 4014000000 | R32: 2929000000 | S32: 234000000 | T32: 1955000000 | U32: 2394000000 | V32: 2533000000 | W32: 16319000000 | X32: 14286000000 | Y32: 12590000000 | Z32: 11677000000 | AA32: 13009000000 | AB32: 11262000000 | AC32: 11542000000 | AD32: 12397000000 | AE32: 12865000000 | AF32: 14519000000 | AG32: =AVERAGE(C32:G32) -> 2.3343971e+09 | AH32: =AVERAGE(H32:L32) -> 2.2000142e+09 | AI32: =AVERAGE(C32:L32) -> 2.2672056e+09 | AJ32: =AVERAGE(M32:Q32) -> 4127000000 | AK32: =AVERAGE(R32:V32) -> 2009000000 | AL32: =AVERAGE(M32:V32) -> 3068000000 | AM32: =AVERAGE(W32:AA32) -> 13576200000 | AN32: =AVERAGE(AB32:AF32) -> 12517000000 | AO32: =AVERAGE(W32:AF32) -> 13046600000 | AP32: =AM32/AG32 -> 5.8157199 | AQ32: =AN32/AH32 -> 5.6895089 | AR32: =AO32/AI32 -> 5.7544846 | AS32: =AM32/AJ32 -> 3.289605 | AT32: =AN32/AK32 -> 6.2304629 | AU32: =AO32/AL32 -> 4.2524772 | AV32: =AJ32/AG32 -> 1.7679083 | AW32: =AK32/AH32 -> 0.91317594 | AX32: =AL32/AH32 -> 1.3945365
A33: Snam | B33: SRG.MI | C33: 1.7042619e+10 | D33: 1.3570566e+10 | E33: 1.3792299e+10 | F33: 1.3229756e+10 | G33: 1.5479782e+10 | H33: 15051296094 | I33: 1.7335418e+10 | J33: 1.5114783e+10 | K33: 1.5625537e+10 | L33: 1.4354874e+10 | M33: 7038000000 | N33: 6583000000 | O33: 6358000000 | P33: 6431000000 | Q33: 6675000000 | R33: 6921000000 | S33: 7373000000 | T33: 7596000000 | U33: 7776000000 | V33: 8997000000 | W33: 24880000000 | X33: 20129000000 | Y33: 22200000000 | Z33: 22989000000 | AA33: 24485000000 | AB33: 26130000000 | AC33: 27356000000 | AD33: 32470000000 | AE33: 33607000000 | AF33: 35789000000 | AG33: =AVERAGE(C33:G33) -> 1.4623004e+10 | AH33: =AVERAGE(H33:L33) -> 1.5496382e+10 | AI33: =AVERAGE(C33:L33) -> 1.5059693e+10 | AJ33: =AVERAGE(M33:Q33) -> 6617000000 | AK33: =AVERAGE(R33:V33) -> 7732600000 | AL33: =AVERAGE(M33:V33) -> 7174800000 | AM33: =AVERAGE(W33:AA33) -> 22936600000 | AN33: =AVERAGE(AB33:AF33) -> 31070400000 | AO33: =AVERAGE(W33:AF33) -> 27003500000 | AP33: =AM33/AG33 -> 1.5685285 | AQ33: =AN33/AH33 -> 2.00501 | AR33: =AO33/AI33 -> 1.7930976 | AS33: =AM33/AJ33 -> 3.466314 | AT33: =AN33/AK33 -> 4.0181052 | AU33: =AO33/AL33 -> 3.7636589 | AV33: =AJ33/AG33 -> 0.45250619 | AW33: =AK33/AH33 -> 0.49899391 | AX33: =AL33/AH33 -> 0.46299841
A34: Stellantis | B34: STLAM.MI | C34: 12960561900 | D34: 13102744540 | E34: 23285578080 | F34: 19463878230 | G34: 20630663660 | H34: 22635069320 | I34: 51059449960 | J34: 41637580140 | K34: 65790538250 | L34: 3.717265e+10 | M34: 16248000000 | N34: 19362000000 | O34: 21207000000 | P34: 25639000000 | Q34: 30165000000 | R34: 27582000000 | S34: 60281000000 | T34: 76331000000 | U34: 86477000000 | V34: 86199000000 | W34: 105040000000 | X34: 104343000000 | Y34: 96299000000 | Z34: 96873000000 | AA34: 98044000000 | AB34: 99730000000 | AC34: 171766000000 | AD34: 186156000000 | AE34: 202128000000 | AF34: 207607000000 | AG34: =AVERAGE(C34:G34) -> 17888685282 | AH34: =AVERAGE(H34:L34) -> 4.3659058e+10 | AI34: =AVERAGE(C34:L34) -> 3.0773871e+10 | AJ34: =AVERAGE(M34:Q34) -> 22524200000 | AK34: =AVERAGE(R34:V34) -> 67374000000 | AL34: =AVERAGE(M34:V34) -> 44949100000 | AM34: =AVERAGE(W34:AA34) -> 100119800000 | AN34: =AVERAGE(AB34:AF34) -> 173477400000 | AO34: =AVERAGE(W34:AF34) -> 136798600000 | AP34: =AM34/AG34 -> 5.5968227 | AQ34: =AN34/AH34 -> 3.9734573 | AR34: =AO34/AI34 -> 4.4452841 | AS34: =AM34/AJ34 -> 4.4449881 | AT34: =AN34/AK34 -> 2.5748419 | AU34: =AO34/AL34 -> 3.0434113 | AV34: =AJ34/AG34 -> 1.2591311 | AW34: =AK34/AH34 -> 1.5431849 | AX34: =AL34/AH34 -> 1.0295481
A35: Stmicroelectronics | B35: STMMI.MI | C35: 5.8844192e+09 | D35: 9.991363e+09 | E35: 1.9604406e+10 | F35: 1.2855996e+10 | G35: 2.4139694e+10 | H35: 3.3089688e+10 | I35: 4.467895e+10 | J35: 3.1965497e+10 | K35: 4.4764893e+10 | L35: 2.2657951e+10 | M35: 5350000000 | N35: 5215000000 | O35: 5771000000 | P35: 7077000000 | Q35: 7062000000 | R35: 8313000000 | S35: 9565000000 | T35: 13579000000 | U35: 16783000000 | V35: 17496000000 | W35: 9159000000 | X35: 9069000000 | Y35: 10872000000 | Z35: 11790000000 | AA35: 11868000000 | AB35: 15306000000 | AC35: 16413000000 | AD35: 20987000000 | AE35: 24453000000 | AF35: 24743000000 | AG35: =AVERAGE(C35:G35) -> 1.4495176e+10 | AH35: =AVERAGE(H35:L35) -> 3.5431396e+10 | AI35: =AVERAGE(C35:L35) -> 2.4963286e+10 | AJ35: =AVERAGE(M35:Q35) -> 6095000000 | AK35: =AVERAGE(R35:V35) -> 13147200000 | AL35: =AVERAGE(M35:V35) -> 9621100000 | AM35: =AVERAGE(W35:AA35) -> 10551600000 | AN35: =AVERAGE(AB35:AF35) -> 20380400000 | AO35: =AVERAGE(W35:AF35) -> 15466000000 | AP35: =AM35/AG35 -> 0.72793874 | AQ35: =AN35/AH35 -> 0.57520737 | AR35: =AO35/AI35 -> 0.61954985 | AS35: =AM35/AJ35 -> 1.7311895 | AT35: =AN35/AK35 -> 1.5501704 | AU35: =AO35/AL35 -> 1.6075085 | AV35: =AJ35/AG35 -> 0.42048473 | AW35: =AK35/AH35 -> 0.37106074 | AX35: =AL35/AH35 -> 0.27154166
A36: Telecom Italia | B36: TIT.MI | C36: 24576300000 | D36: 17633079000 | E36: 15284108500 | F36: 1.0314481e+10 | G36: 1.1721768e+10 | H36: 7.9554251e+09 | I36: 9.2073319e+09 | J36: 4.5944967e+09 | K36: 6.2518625e+09 | L36: 5.2381095e+09 | M36: 16336000000 | N36: 20675000000 | O36: 20389000000 | P36: 17757000000 | Q36: 20528000000 | R36: 26492000000 | S36: 17659000000 | T36: 15145000000 | U36: 13729000000 | V36: 12018000000 | W36: 71232000000 | X36: 70446000000 | Y36: 68776000000 | Z36: 65619000000 | AA36: 70104000000 | AB36: 73234000000 | AC36: 69187000000 | AD36: 62027000000 | AE36: 62159000000 | AF36: 37663000000 | AG36: =AVERAGE(C36:G36) -> 1.5905947e+10 | AH36: =AVERAGE(H36:L36) -> 6.6494451e+09 | AI36: =AVERAGE(C36:L36) -> 1.1277696e+10 | AJ36: =AVERAGE(M36:Q36) -> 19137000000 | AK36: =AVERAGE(R36:V36) -> 17008600000 | AL36: =AVERAGE(M36:V36) -> 18072800000 | AM36: =AVERAGE(W36:AA36) -> 69235400000 | AN36: =AVERAGE(AB36:AF36) -> 60854000000 | AO36: =AVERAGE(W36:AF36) -> 65044700000 | AP36: =AM36/AG36 -> 4.3527995 | AQ36: =AN36/AH36 -> 9.151741 | AR36: =AO36/AI36 -> 5.767552 | AS36: =AM36/AJ36 -> 3.6178816 | AT36: =AN36/AK36 -> 3.5778371 | AU36: =AO36/AL36 -> 3.5990383 | AV36: =AJ36/AG36 -> 1.2031349 | AW36: =AK36/AH36 -> 2.5578976 | AX36: =AL36/AH36 -> 2.7179411
A37: Tenaris | B37: TEN.MI | C37: 1.4029904e+10 | D37: 2.1070257e+10 | E37: 1.8786803e+10 | F37: 1.2862481e+10 | G37: 1.331458e+10 | H37: 9.5467588e+09 | I37: 1.237699e+10 | J37: 2.057596e+10 | K37: 2.0489951e+10 | L37: 2.1052233e+10 | M37: 12463669000 | N37: 11838074000 | O37: 11940155000 | P37: 12161921000 | Q37: 12325940000 | R37: 11517689000 | S37: 12235299000 | T37: 14174778000 | U37: 16842972000 | V37: 16593257000 | W37: 14886974000 | X37: 14003275000 | Y37: 14398218000 | Z37: 14251299000 | AA37: 14842991000 | AB37: 13716189000 | AC37: 14449431000 | AD37: 17550246000 | AE37: 21081895000 | AF37: 20450125000 | AG37: =AVERAGE(C37:G37) -> 1.6012805e+10 | AH37: =AVERAGE(H37:L37) -> 1.6808379e+10 | AI37: =AVERAGE(C37:L37) -> 1.6410592e+10 | AJ37: =AVERAGE(M37:Q37) -> 12145951800 | AK37: =AVERAGE(R37:V37) -> 14272799000 | AL37: =AVERAGE(M37:V37) -> 13209375400 | AM37: =AVERAGE(W37:AA37) -> 14476551400 | AN37: =AVERAGE(AB37:AF37) -> 17449577200 | AO37: =AVERAGE(W37:AF37) -> 15963064300 | AP37: =AM37/AG37 -> 0.90406092 | AQ37: =AN37/AH37 -> 1.0381476 | AR37: =AO37/AI37 -> 0.97272934 | AS37: =AM37/AJ37 -> 1.1918828 | AT37: =AN37/AK37 -> 1.2225757 | AU37: =AO37/AL37 -> 1.2084647 | AV37: =AJ37/AG37 -> 0.75851493 | AW37: =AK37/AH37 -> 0.84914787 | AX37: =AL37/AH37 -> 0.7858804
A38: Terna | B38: TRN.MI | C38: 9.5762838e+09 | D38: 8.7428095e+09 | E38: 9.6603509e+09 | F38: 1.0177449e+10 | G38: 1.1952082e+10 | H38: 1.2555946e+10 | I38: 1.4053649e+10 | J38: 13528049886 | K38: 1.5002716e+10 | L38: 1.5316445e+10 | M38: 3394600000 | N38: 3688400000 | O38: 3922600000 | P38: 4129000000 | Q38: 4272300000 | R38: 4436000000 | S38: 4713100000 | T38: 5180600000 | U38: 6324400000 | V38: 7548700000 | W38: 15457100000 | X38: 16135100000 | Y38: 17027500000 | Z38: 17265800000 | AA38: 18085700000 | AB38: 20696500000 | AC38: 22390400000 | AD38: 22830500000 | AE38: 23445900000 | AF38: 27186600000 | AG38: =AVERAGE(C38:G38) -> 1.0021795e+10 | AH38: =AVERAGE(H38:L38) -> 1.4091361e+10 | AI38: =AVERAGE(C38:L38) -> 1.2056578e+10 | AJ38: =AVERAGE(M38:Q38) -> 3881380000 | AK38: =AVERAGE(R38:V38) -> 5640560000 | AL38: =AVERAGE(M38:V38) -> 4760970000 | AM38: =AVERAGE(W38:AA38) -> 16794240000 | AN38: =AVERAGE(AB38:AF38) -> 23309980000 | AO38: =AVERAGE(W38:AF38) -> 20052110000 | AP38: =AM38/AG38 -> 1.6757716 | AQ38: =AN38/AH38 -> 1.6542035 | AR38: =AO38/AI38 -> 1.6631676 | AS38: =AM38/AJ38 -> 4.3268734 | AT38: =AN38/AK38 -> 4.1325649 | AU38: =AO38/AL38 -> 4.2117699 | AV38: =AJ38/AG38 -> 0.38729389 | AW38: =AK38/AH38 -> 0.40028496 | AX38: =AL38/AH38 -> 0.33786445
A39: Unicredit | B39: UCG.MI | C39: 4.3297578e+10 | D39: 2.3055658e+10 | E39: 3.0594427e+10 | F39: 2.1683595e+10 | G39: 28941910620 | H39: 1.7034014e+10 | I39: 30081804460 | J39: 27462158840 | K39: 42074257680 | L39: 65239227180 | M39: 50674196999 | N39: 39837174000 | O39: 59772259000 | P39: 56384599000 | Q39: 62109000000 | R39: 60073000000 | S39: 62224000000 | T39: 63879000000 | U39: 64079000000 | V39: 62441000000 | W39: 860433375000 | X39: 859532774000 | Y39: 836789724000 | Z39: 831468724000 | AA39: 855647000000 | AB39: 931456000000 | AC39: 916671000000 | AD39: 857773000000 | AE39: 784974000000 | AF39: 784004000000 | AG39: =AVERAGE(C39:G39) -> 2.9514634e+10 | AH39: =AVERAGE(H39:L39) -> 3.6378293e+10 | AI39: =AVERAGE(C39:L39) -> 3.2946463e+10 | AJ39: =AVERAGE(M39:Q39) -> 5.3755446e+10 | AK39: =AVERAGE(R39:V39) -> 62539200000 | AL39: =AVERAGE(M39:V39) -> 5.8147323e+10 | AM39: =AVERAGE(W39:AA39) -> 848774319400 | AN39: =AVERAGE(AB39:AF39) -> 854975600000 | AO39: =AVERAGE(W39:AF39) -> 851874959700 | AP39: =AM39/AG39 -> 28.757745 | AQ39: =AN39/AH39 -> 23.502357 | AR39: =AO39/AI39 -> 25.85634 | AS39: =AM39/AJ39 -> 15.78955 | AT39: =AN39/AK39 -> 13.671035 | AU39: =AO39/AL39 -> 14.650287 | AV39: =AJ39/AG39 -> 1.821315 | AW39: =AK39/AH39 -> 1.7191351 | AX39: =AL39/AH39 -> 1.5984072
A40: Unipol | B40: UNI.MI | C40: 3371482800 | D40: 2426588800 | E40: 2868191400 | F40: 2468710000 | G40: 3660192000 | H40: 2799951000 | I40: 3422241900 | J40: 3260337400 | K40: 3694560000 | L40: 8613480000 | M40: 5573000000 | N40: 5682000000 | O40: 5515500000 | P40: 5041300000 | Q40: 6770500000 | R40: 7731600000 | S40: 7895300000 | T40: 6131200000 | U40: 8286000000 | V40: 9383000000 | W40: 89773300000 | X40: 91896900000 | Y40: 89972900000 | Z40: 77580800000 | AA40: 76101900000 | AB40: 79406500000 | AC40: 80258500000 | AD40: 74539400000 | AE40: 79458000000 | AF40: 83425000000 | AG40: =AVERAGE(C40:G40) -> 2959033000 | AH40: =AVERAGE(H40:L40) -> 4358114060 | AI40: =AVERAGE(C40:L40) -> 3658573530 | AJ40: =AVERAGE(M40:Q40) -> 5716460000 | AK40: =AVERAGE(R40:V40) -> 7885420000 | AL40: =AVERAGE(M40:V40) -> 6800940000 | AM40: =AVERAGE(W40:AA40) -> 85065160000 | AN40: =AVERAGE(AB40:AF40) -> 79417480000 | AO40: =AVERAGE(W40:AF40) -> 82241320000 | AP40: =AM40/AG40 -> 28.747621 | AQ40: =AN40/AH40 -> 18.222901 | AR40: =AO40/AI40 -> 22.479067 | AS40: =AM40/AJ40 -> 14.880741 | AT40: =AN40/AK40 -> 10.071433 | AU40: =AO40/AL40 -> 12.09264 | AV40: =AJ40/AG40 -> 1.9318676 | AW40: =AK40/AH40 -> 1.8093652 | AX40: =AL40/AH40 -> 1.5605236
A41: FTSEMIB | B41: FTSEMIB.MI | AG41: =SUM(AG4:AG40) -> 4.1550274e+11 | AH41: =SUM(AH4:AH40) -> 5.8076985e+11 | AI41: =SUM(AI4:AI40) -> 4.9834816e+11 | AJ41: =SUM(AJ4:AJ40) -> 3.9911787e+11 | AK41: =SUM(AK4:AK40) -> 4.9272494e+11 | AL41: =SUM(AL4:AL40) -> 4.459214e+11 | AM41: =SUM(AM4:AM40) -> 3.5850446e+12 | AN41: =SUM(AN4:AN40) -> 4.2814814e+12 | AO41: =SUM(AO4:AO40) -> 3.9341494e+12 | AP41: =AVERAGE(AP4:AP40) -> 8.4277122 | AQ41: =AVERAGE(AQ4:AQ40) -> 8.1356907 | AR41: =AO41/AI41 -> 7.8943793 | AS41: =AVERAGE(AS4:AS40) -> 7.2262442 | AT41: =AVERAGE(AT4:AT40) -> 7.4954329 | AU41: =AO41/AL41 -> 8.8225176 | AV41: =AG41/AJ41 -> 1.0410527 | AW41: =AH41/AK41 -> 1.1786898 | AX41: =AL41/AH41 -> 0.76781086
AN52: Company | AO52: Ticker Symbol | AP52: Yahoo Finance Format | AQ52: Sector | AR52: Market Cap (2024) | AS52: Size Group
AN53: A2a | AO53: A2A | AP53: A2A.MI | AQ53: Energy & Utilities | AR53: 6.7353154e+09
AN54: Amplifon | AO54: AMP | AP54: AMP.MI | AQ54: Health | AR54: 5610931200
AN55: Azimut | AO55: AZM | AP55: AZM.MI | AQ55: Banking & Financials | AR55: 3.3712679e+09
AN56: Banca Mediolanum | AO56: BMED | AP56: BMED.MI | AQ56: Banking & Financials | AR56: 8471898720
AN57: Banca Monte Paschi Siena | AO57: BMPS | AP57: BMPS.MI | AQ57: Banking & Financials | AR57: 8.5764674e+09
AN58: Banco Bpm | AO58: BAMI | AP58: BAMI.MI | AQ58: Banking & Financials | AR58: 1.1754059e+10
AN59: Bca Pop Sondrio | AO59: BPSO | AP59: BPSO.MI | AQ59: Banking & Financials | AR59: 3660864064
AN60: Bper Banca | AO60: BPE | AP60: BPE.MI | AQ60: Banking & Financials | AR60: 8671406050
AN61: Brunello Cucinelli | AO61: BC | AP61: BC.MI | AQ61: Consumer & Luxury | AR61: 7.1667922e+09
AN62: Buzzi | AO62: BZU | AP62: BZU.MI | AQ62: Industrials | AR62: 6.522511e+09
AN63: Campari | AO63: CPR | AP63: CPR.MI | AQ63: Consumer & Luxury | AR63: 7.2260886e+09
AN64: Diasorin | AO64: DIA | AP64: DIA.MI | AQ64: Health | AR64: 5.5622887e+09
... AN89: Unipol | AO89: UNI | AP89: UNI.MI | AQ89: Banking & Financials | AR89: 8613480000
AN92: Distribution: Small: 12 | Medium: 12 | Large: 13

Sheet Returns
A2: Company | B2: Yahoo Finance Format | C2: 42006 | D2: 42373 | E2: 42737 | F2: 43102 | G2: 43467 | H2: 43832 | I2: 44200 | J2: 44565 | K2: 44928 | L2: 45293 | M2: 45659 | N2: AVG 2015-2019 | O2: AVG 2020-2024 | P2: AVG 2015-2024
A3: A2a | B3: A2A.MI | C3: =SUM(_xldudf_WISEPRICE($B$3, "close", , C2, C2)) -> 0.8355 | D3: =SUM(_xldudf_WISEPRICE($B$3, "close", , D2, D2)) -> 1.22 | E3: =SUM(_xldudf_WISEPRICE($B$3, "close", , E2, E2)) -> 1.26 | F3: =SUM(_xldudf_WISEPRICE($B$3, "close", , F2, F2)) -> 1.52 | G3: =SUM(_xldudf_WISEPRICE($B$3, "close", , G2, G2)) -> 1.6 | H3: =SUM(_xldudf_WISEPRICE($B$3, "close", , H2, H2)) -> 1.68 | I3: =SUM(_xldudf_WISEPRICE($B$3, "close", , I2, I2)) -> 1.33 | J3: =SUM(_xldudf_WISEPRICE($B$3, "close", , J2, J2)) -> 1.72 | ... M3: =SUM(_xldudf_WISEPRICE($B$3, "close", , M2, M2)) -> 2.19 | N3: =(G3 /C3)^(1/5) - 1 -> 0.13876656 | O3: =(M3 /H3)^(1/5) - 1 -> 0.054452368 | P3: =(M3 /C3)^(1/10) - 1 -> 0.10115832
A4: Amplifon | B4: AMP.MI | C4: =SUM(_xldudf_WISEPRICE($B4, "close", , C$2, C$2)) -> 4.9 | D4: =SUM(_xldudf_WISEPRICE($B4, "close", , D$2, D$2)) -> 7.88 | E4: =SUM(_xldudf_WISEPRICE($B4, "close", , E$2, E$2)) -> 9.2 | F4: =SUM(_xldudf_WISEPRICE($B4, "close", , F$2, F$2)) -> 12.92 | G4: =SUM(_xldudf_WISEPRICE($B4, "close", , G$2, G$2)) -> 13.91 | H4: =SUM(_xldudf_WISEPRICE($B4, "close", , H$2, H$2)) -> 25.82 | I4: =SUM(_xldudf_WISEPRICE($B4, "close", , I$2, I$2)) -> 33.94 | J4: =SUM(_xldudf_WISEPRICE($B4, "close", , J$2, J$2)) -> 45.68 | ... M4: =SUM(_xldudf_WISEPRICE($B4, "close", , M$2, M$2)) -> 24.93 | N4: =(G4 /C4)^(1/5) - 1 -> 0.23204398 | O4: =(M4 /H4)^(1/5) - 1 -> -0.0069909464 | P4: =(M4 /C4)^(1/10) - 1 -> 0.17666442
A5: Azimut | B5: AZM.MI | C5: =SUM(_xldudf_WISEPRICE($B5, "close", , C$2, C$2)) -> 16.87 | D5: =SUM(_xldudf_WISEPRICE($B5, "close", , D$2, D$2)) -> 20.26 | E5: =SUM(_xldudf_WISEPRICE($B5, "close", , E$2, E$2)) -> 14.82 | F5: =SUM(_xldudf_WISEPRICE($B5, "close", , F$2, F$2)) -> 14.66 | G5: =SUM(_xldudf_WISEPRICE($B5, "close", , G$2, G$2)) -> 9.23 | H5: =SUM(_xldudf_WISEPRICE($B5, "close", , H$2, H$2)) -> 21.34 | I5: =SUM(_xldudf_WISEPRICE($B5, "close", , I$2, I$2)) -> 17.5 | J5: =SUM(_xldudf_WISEPRICE($B5, "close", , J$2, J$2)) -> 24.86 | ... M5: =SUM(_xldudf_WISEPRICE($B5, "close", , M$2, M$2)) -> 24.14 | N5: =(G5 /C5)^(1/5) - 1 -> -0.11362536 | O5: =(M5 /H5)^(1/5) - 1 -> 0.024963902 | P5: =(M5 /C5)^(1/10) - 1 -> 0.036483083
A6: Banca Mediolanum | B6: BMED.MI | C6: =SUM(_xldudf_WISEPRICE($B6, "close", , C$2, C$2)) -> 5.36 | D6: =SUM(_xldudf_WISEPRICE($B6, "close", , D$2, D$2)) -> 6.96 | E6: =SUM(_xldudf_WISEPRICE($B6, "close", , E$2, E$2)) -> 6.92 | F6: =SUM(_xldudf_WISEPRICE($B6, "close", , F$2, F$2)) -> 7.09 | G6: =SUM(_xldudf_WISEPRICE($B6, "close", , G$2, G$2)) -> 5.05 | H6: 8.78 | I6: =SUM(_xldudf_WISEPRICE($B6, "close", , I$2, I$2)) -> 7.1 | J6: =SUM(_xldudf_WISEPRICE($B6, "close", , J$2, J$2)) -> 8.85 | K6: =SUM(_xldudf_WISEPRICE($B6, "close", , K$2, K$2)) -> 7.9 | L6: =SUM(_xldudf_WISEPRICE($B6, "close", , L$2, L$2)) -> 8.58 | M6: =SUM(_xldudf_WISEPRICE($B6, "close", , M$2, M$2)) -> 11.46 | N6: =(G6 /C6)^(1/5) - 1 -> -0.011844442 | O6: =(M6 /H6)^(1/5) - 1 -> 0.054722038 | P6: =(M6 /C6)^(1/10) - 1 -> 0.078951648
A7: Banca Monte Paschi Siena | B7: BMPS.MI | C7: =SUM(_xldudf_WISEPRICE($B7, "close", , C$2, C$2)) -> 19589.412 | D7: =SUM(_xldudf_WISEPRICE($B7, "close", , D$2, D$2)) -> 11690 | E7: =SUM(_xldudf_WISEPRICE($B7, "close", , E$2, E$2)) -> 1508 | F7: =SUM(_xldudf_WISEPRICE($B7, "close", , F$2, F$2)) -> 389 | G7: =SUM(_xldudf_WISEPRICE($B7, "close", , G$2, G$2)) -> 153 | H7: =SUM(_xldudf_WISEPRICE($B7, "close", , H$2, H$2)) -> 141.2 | I7: =SUM(_xldudf_WISEPRICE($B7, "close", , I$2, I$2)) -> 103.4 | J7: =SUM(_xldudf_WISEPRICE($B7, "close", , J$2, J$2)) -> 93.080002 | ... M7: =SUM(_xldudf_WISEPRICE($B7, "close", , M$2, M$2)) -> 6.71 | N7: =(G7 /C7)^(1/5) - 1 -> -0.6210918 | O7: =(M7 /H7)^(1/5) - 1 -> -0.45627717 | P7: =(M7 /C7)^(1/10) - 1 -> -0.54973301
A8: Banco Bpm | B8: BAMI.MI | C8: =SUM(_xldudf_WISEPRICE($B8, "close", , C$2, C$2)) -> 7.64 | D8: =SUM(_xldudf_WISEPRICE($B8, "close", , D$2, D$2)) -> 9.08 | E8: =SUM(_xldudf_WISEPRICE($B8, "close", , E$2, E$2)) -> 2.5 | F8: =SUM(_xldudf_WISEPRICE($B8, "close", , F$2, F$2)) -> 2.64 | G8: =SUM(_xldudf_WISEPRICE($B8, "close", , G$2, G$2)) -> 1.99 | H8: =SUM(_xldudf_WISEPRICE($B8, "close", , H$2, H$2)) -> 2.05 | I8: =SUM(_xldudf_WISEPRICE($B8, "close", , I$2, I$2)) -> 1.8 | J8: =SUM(_xldudf_WISEPRICE($B8, "close", , J$2, J$2)) -> 2.75 | ... M8: =SUM(_xldudf_WISEPRICE($B8, "close", , M$2, M$2)) -> 7.77 | N8: =(G8 /C8)^(1/5) - 1 -> -0.23589693 | O8: =(M8 /H8)^(1/5) - 1 -> 0.30536941 | P8: =(M8 /C8)^(1/10) - 1 -> 0.0016886803
A9: Bca Pop Sondrio | B9: BPSO.MI | C9: =SUM(_xldudf_WISEPRICE($B9, "close", , C$2, C$2)) -> 3.12 | D9: =SUM(_xldudf_WISEPRICE($B9, "close", , D$2, D$2)) -> 4.08 | E9: =SUM(_xldudf_WISEPRICE($B9, "close", , E$2, E$2)) -> 3.19 | F9: =SUM(_xldudf_WISEPRICE($B9, "close", , F$2, F$2)) -> 3.09 | G9: =SUM(_xldudf_WISEPRICE($B9, "close", , G$2, G$2)) -> 2.61 | H9: =SUM(_xldudf_WISEPRICE($B9, "close", , H$2, H$2)) -> 2.14 | I9: =SUM(_xldudf_WISEPRICE($B9, "close", , I$2, I$2)) -> 2.21 | J9: =SUM(_xldudf_WISEPRICE($B9, "close", , J$2, J$2)) -> 3.85 | ... M9: =SUM(_xldudf_WISEPRICE($B9, "close", , M$2, M$2)) -> 8.03 | N9: =(G9 /C9)^(1/5) - 1 -> -0.035066948 | O9: =(M9 /H9)^(1/5) - 1 -> 0.30274782 | P9: =(M9 /C9)^(1/10) - 1 -> 0.0991478
A10: Bper Banca | B10: BPE.MI | C10: =SUM(_xldudf_WISEPRICE($B10, "close", , C$2, C$2)) -> 3.78 | D10: =SUM(_xldudf_WISEPRICE($B10, "close", , D$2, D$2)) -> 4.59 | E10: =SUM(_xldudf_WISEPRICE($B10, "close", , E$2, E$2)) -> 3.57 | F10: =SUM(_xldudf_WISEPRICE($B10, "close", , F$2, F$2)) -> 2.82 | G10: =SUM(_xldudf_WISEPRICE($B10, "close", , G$2, G$2)) -> 2.23 | H10: 3.11 | I10: =SUM(_xldudf_WISEPRICE($B10, "close", , I$2, I$2)) -> 1.46 | J10: =SUM(_xldudf_WISEPRICE($B10, "close", , J$2, J$2)) -> 1.91 | K10: =SUM(_xldudf_WISEPRICE($B10, "close", , K$2, K$2)) -> 1.96 | L10: =SUM(_xldudf_WISEPRICE($B10, "close", , L$2, L$2)) -> 3.14 | M10: =SUM(_xldudf_WISEPRICE($B10, "close", , M$2, M$2)) -> 5.96 | N10: =(G10 /C10)^(1/5) - 1 -> -0.10016556 | O10: =(M10 /H10)^(1/5) - 1 -> 0.13893037 | P10: =(M10 /C10)^(1/10) - 1 -> 0.046587265
A11: Brunello Cucinelli | B11: BC.MI | C11: =SUM(_xldudf_WISEPRICE($B11, "close", , C$2, C$2)) -> 18.05 | D11: =SUM(_xldudf_WISEPRICE($B11, "close", , D$2, D$2)) -> 16.25 | E11: =SUM(_xldudf_WISEPRICE($B11, "close", , E$2, E$2)) -> 20.55 | F11: =SUM(_xldudf_WISEPRICE($B11, "close", , F$2, F$2)) -> 27.13 | G11: =SUM(_xldudf_WISEPRICE($B11, "close", , G$2, G$2)) -> 30.3 | H11: =SUM(_xldudf_WISEPRICE($B11, "close", , H$2, H$2)) -> 32.34 | I11: =SUM(_xldudf_WISEPRICE($B11, "close", , I$2, I$2)) -> 35.84 | J11: =SUM(_xldudf_WISEPRICE($B11, "close", , J$2, J$2)) -> 63.2 | ... M11: =SUM(_xldudf_WISEPRICE($B11, "close", , M$2, M$2)) -> 105.3 | N11: =(G11 /C11)^(1/5) - 1 -> 0.10915715 | O11: =(M11 /H11)^(1/5) - 1 -> 0.2663031 | P11: =(M11 /C11)^(1/10) - 1 -> 0.19287549
A12: Buzzi | B12: BZU.MI | C12: =SUM(_xldudf_WISEPRICE($B12, "close", , C$2, C$2)) -> 10.5 | D12: =SUM(_xldudf_WISEPRICE($B12, "close", , D$2, D$2)) -> 16.299999 | E12: =SUM(_xldudf_WISEPRICE($B12, "close", , E$2, E$2)) -> 23.52 | F12: =SUM(_xldudf_WISEPRICE($B12, "close", , F$2, F$2)) -> 22.83 | G12: =SUM(_xldudf_WISEPRICE($B12, "close", , G$2, G$2)) -> 15.185 | H12: =SUM(_xldudf_WISEPRICE($B12, "close", , H$2, H$2)) -> 22.6 | I12: =SUM(_xldudf_WISEPRICE($B12, "close", , I$2, I$2)) -> 20.209999 | J12: =SUM(_xldudf_WISEPRICE($B12, "close", , J$2, J$2)) -> 19.540001 | ... M12: =SUM(_xldudf_WISEPRICE($B12, "close", , M$2, M$2)) -> 35.96 | N12: =(G12 /C12)^(1/5) - 1 -> 0.076577005 | O12: =(M12 /H12)^(1/5) - 1 -> 0.097342624 | P12: =(M12 /C12)^(1/10) - 1 -> 0.13100113
A13: Campari | B13: CPR.MI | C13: =SUM(_xldudf_WISEPRICE($B13, "close", , C$2, C$2)) -> 2.52 | D13: =SUM(_xldudf_WISEPRICE($B13, "close", , D$2, D$2)) -> 3.88 | E13: =SUM(_xldudf_WISEPRICE($B13, "close", , E$2, E$2)) -> 4.68 | F13: =SUM(_xldudf_WISEPRICE($B13, "close", , F$2, F$2)) -> 6.36 | G13: =SUM(_xldudf_WISEPRICE($B13, "close", , G$2, G$2)) -> 7.37 | H13: =SUM(_xldudf_WISEPRICE($B13, "close", , H$2, H$2)) -> 8.12 | I13: =SUM(_xldudf_WISEPRICE($B13, "close", , I$2, I$2)) -> 9.22 | J13: =SUM(_xldudf_WISEPRICE($B13, "close", , J$2, J$2)) -> 12.87 | ... M13: =SUM(_xldudf_WISEPRICE($B13, "close", , M$2, M$2)) -> 6.1 | N13: =(G13 /C13)^(1/5) - 1 -> 0.23940542 | O13: =(M13 /H13)^(1/5) - 1 -> -0.055602647 | P13: =(M13 /C13)^(1/10) - 1 -> 0.092428268
A14: Diasorin | B14: DIA.MI | C14: =SUM(_xldudf_WISEPRICE($B14, "close", , C$2, C$2)) -> 33.51 | D14: =SUM(_xldudf_WISEPRICE($B14, "close", , D$2, D$2)) -> 48.18 | E14: =SUM(_xldudf_WISEPRICE($B14, "close", , E$2, E$2)) -> 57.75 | F14: =SUM(_xldudf_WISEPRICE($B14, "close", , F$2, F$2)) -> 74.5 | G14: =SUM(_xldudf_WISEPRICE($B14, "close", , G$2, G$2)) -> 71.2 | H14: =SUM(_xldudf_WISEPRICE($B14, "close", , H$2, H$2)) -> 116.5 | I14: =SUM(_xldudf_WISEPRICE($B14, "close", , I$2, I$2)) -> 169.6 | J14: =SUM(_xldudf_WISEPRICE($B14, "close", , J$2, J$2)) -> 158.95 | ... M14: =SUM(_xldudf_WISEPRICE($B14, "close", , M$2, M$2)) -> 100.5 | N14: =(G14 /C14)^(1/5) - 1 -> 0.16268244 | O14: =(M14 /H14)^(1/5) - 1 -> -0.029114473 | P14: =(M14 /C14)^(1/10) - 1 -> 0.11608986
A15: Enel | B15: ENEL.MI | C15: =SUM(_xldudf_WISEPRICE($B15, "close", , C$2, C$2)) -> 3.68 | D15: =SUM(_xldudf_WISEPRICE($B15, "close", , D$2, D$2)) -> 3.78 | E15: =SUM(_xldudf_WISEPRICE($B15, "close", , E$2, E$2)) -> 4.22 | F15: =SUM(_xldudf_WISEPRICE($B15, "close", , F$2, F$2)) -> 5.11 | G15: =SUM(_xldudf_WISEPRICE($B15, "close", , G$2, G$2)) -> 5.08 | H15: =SUM(_xldudf_WISEPRICE($B15, "close", , H$2, H$2)) -> 7.21 | I15: =SUM(_xldudf_WISEPRICE($B15, "close", , I$2, I$2)) -> 8.46 | J15: =SUM(_xldudf_WISEPRICE($B15, "close", , J$2, J$2)) -> 7.17 | ... M15: =SUM(_xldudf_WISEPRICE($B15, "close", , M$2, M$2)) -> 7.03 | N15: =(G15 /C15)^(1/5) - 1 -> 0.066603928 | O15: =(M15 /H15)^(1/5) - 1 -> -0.0050436868 | P15: =(M15 /C15)^(1/10) - 1 -> 0.066868152
A16: Eni | B16: ENI.MI | C16: =SUM(_xldudf_WISEPRICE($B16, "close", , C$2, C$2)) -> 14.59 | D16: =SUM(_xldudf_WISEPRICE($B16, "close", , D$2, D$2)) -> 13.43 | E16: =SUM(_xldudf_WISEPRICE($B16, "close", , E$2, E$2)) -> 15.64 | F16: =SUM(_xldudf_WISEPRICE($B16, "close", , F$2, F$2)) -> 13.83 | G16: =SUM(_xldudf_WISEPRICE($B16, "close", , G$2, G$2)) -> 13.78 | H16: =SUM(_xldudf_WISEPRICE($B16, "close", , H$2, H$2)) -> 14.01 | I16: =SUM(_xldudf_WISEPRICE($B16, "close", , I$2, I$2)) -> 8.45 | J16: =SUM(_xldudf_WISEPRICE($B16, "close", , J$2, J$2)) -> 12.61 | ... M16: =SUM(_xldudf_WISEPRICE($B16, "close", , M$2, M$2)) -> 13.46 | N16: =(G16 /C16)^(1/5) - 1 -> -0.011358618 | O16: =(M16 /H16)^(1/5) - 1 -> -0.0079778142 | P16: =(M16 /C16)^(1/10) - 1 -> -0.0080289979
A17: Ferrari | B17: RACE.MI | C17: =SUM(_xldudf_WISEPRICE($B17, "close", , C$2, C$2)) -> 0 | D17: =SUM(_xldudf_WISEPRICE($B17, "close", , D$2, D$2)) -> 43.67 | E17: =SUM(_xldudf_WISEPRICE($B17, "close", , E$2, E$2)) -> 56.2 | F17: =SUM(_xldudf_WISEPRICE($B17, "close", , F$2, F$2)) -> 87.3 | G17: =SUM(_xldudf_WISEPRICE($B17, "close", , G$2, G$2)) -> 86.52 | H17: =SUM(_xldudf_WISEPRICE($B17, "close", , H$2, H$2)) -> 149.55 | I17: =SUM(_xldudf_WISEPRICE($B17, "close", , I$2, I$2)) -> 187.6 | J17: =SUM(_xldudf_WISEPRICE($B17, "close", , J$2, J$2)) -> 235.1 | ... M17: =SUM(_xldudf_WISEPRICE($B17, "close", , M$2, M$2)) -> 409.2 | N17: =(G17 /D17)^(1/4) - 1 -> 0.18640599 | O17: =(M17 /H17)^(1/5) - 1 -> 0.22300953 | P17: =(M17 /D17)^(1/19) - 1 -> 0.12498016
A18: Finecobank | B18: FBK.MI | C18: =SUM(_xldudf_WISEPRICE($B18, "close", , C$2, C$2)) -> 4.74 | D18: =SUM(_xldudf_WISEPRICE($B18, "close", , D$2, D$2)) -> 7.4 | E18: =SUM(_xldudf_WISEPRICE($B18, "close", , E$2, E$2)) -> 5.49 | F18: =SUM(_xldudf_WISEPRICE($B18, "close", , F$2, F$2)) -> 8.45 | G18: =SUM(_xldudf_WISEPRICE($B18, "close", , G$2, G$2)) -> 8.75 | H18: =SUM(_xldudf_WISEPRICE($B18, "close", , H$2, H$2)) -> 11.01 | I18: =SUM(_xldudf_WISEPRICE($B18, "close", , I$2, I$2)) -> 13.69 | J18: =SUM(_xldudf_WISEPRICE($B18, "close", , J$2, J$2)) -> 15.76 | ... M18: =SUM(_xldudf_WISEPRICE($B18, "close", , M$2, M$2)) -> 16.9 | N18: =(G18 /C18)^(1/5) - 1 -> 0.1304359 | O18: =(M18 /H18)^(1/5) - 1 -> 0.089481543 | P18: =(M18 /C18)^(1/10) - 1 -> 0.13556196
A19: Generali | B19: G.MI | C19: =SUM(_xldudf_WISEPRICE($B19, "close", , C$2, C$2)) -> 17.04 | D19: =SUM(_xldudf_WISEPRICE($B19, "close", , D$2, D$2)) -> 16.2 | E19: =SUM(_xldudf_WISEPRICE($B19, "close", , E$2, E$2)) -> 14.35 | F19: =SUM(_xldudf_WISEPRICE($B19, "close", , F$2, F$2)) -> 15.02 | G19: =SUM(_xldudf_WISEPRICE($B19, "close", , G$2, G$2)) -> 14.51 | H19: =SUM(_xldudf_WISEPRICE($B19, "close", , H$2, H$2)) -> 18.51 | I19: =SUM(_xldudf_WISEPRICE($B19, "close", , I$2, I$2)) -> 14.07 | J19: =SUM(_xldudf_WISEPRICE($B19, "close", , J$2, J$2)) -> 19 | ... M19: =SUM(_xldudf_WISEPRICE($B19, "close", , M$2, M$2)) -> 27.6 | N19: =(G19 /C19)^(1/5) - 1 -> -0.031633929 | O19: =(M19 /H19)^(1/5) - 1 -> 0.083179751 | P19: =(M19 /C19)^(1/10) - 1 -> 0.049406982
A20: Hera | B20: HER.MI | C20: =SUM(_xldudf_WISEPRICE($B20, "close", , C$2, C$2)) -> 1.94 | D20: =SUM(_xldudf_WISEPRICE($B20, "close", , D$2, D$2)) -> 2.44 | E20: =SUM(_xldudf_WISEPRICE($B20, "close", , E$2, E$2)) -> 2.22 | F20: =SUM(_xldudf_WISEPRICE($B20, "close", , F$2, F$2)) -> 2.94 | G20: =SUM(_xldudf_WISEPRICE($B20, "close", , G$2, G$2)) -> 2.72 | H20: =SUM(_xldudf_WISEPRICE($B20, "close", , H$2, H$2)) -> 3.9 | I20: =SUM(_xldudf_WISEPRICE($B20, "close", , I$2, I$2)) -> 3.05 | J20: =SUM(_xldudf_WISEPRICE($B20, "close", , J$2, J$2)) -> 3.67 | ... M20: =SUM(_xldudf_WISEPRICE($B20, "close", , M$2, M$2)) -> 3.46 | N20: =(G20 /C20)^(1/5) - 1 -> 0.069925245 | O20: =(M20 /H20)^(1/5) - 1 -> -0.023657266 | P20: =(M20 /C20)^(1/10) - 1 -> 0.059564592
A21: Intesa Sanpaolo | B21: ISP.MI | C21: =SUM(_xldudf_WISEPRICE($B21, "close", , C$2, C$2)) -> 2.45 | D21: =SUM(_xldudf_WISEPRICE($B21, "close", , D$2, D$2)) -> 2.98 | E21: =SUM(_xldudf_WISEPRICE($B21, "close", , E$2, E$2)) -> 2.45 | F21: =SUM(_xldudf_WISEPRICE($B21, "close", , F$2, F$2)) -> 2.75 | G21: =SUM(_xldudf_WISEPRICE($B21, "close", , G$2, G$2)) -> 1.91 | H21: =SUM(_xldudf_WISEPRICE($B21, "close", , H$2, H$2)) -> 2.38 | I21: =SUM(_xldudf_WISEPRICE($B21, "close", , I$2, I$2)) -> 1.91 | J21: =SUM(_xldudf_WISEPRICE($B21, "close", , J$2, J$2)) -> 2.39 | ... M21: =SUM(_xldudf_WISEPRICE($B21, "close", , M$2, M$2)) -> 3.85 | N21: =(G21 /C21)^(1/5) - 1 -> -0.048577415 | O21: =(M21 /H21)^(1/5) - 1 -> 0.10097322 | P21: =(M21 /C21)^(1/10) - 1 -> 0.04623553
A22: Inwit | B22: INW.MI | C22: =SUM(_xldudf_WISEPRICE($B22, "close", , C$2, C$2)) -> 0 | D22: =SUM(_xldudf_WISEPRICE($B22, "close", , D$2, D$2)) -> 4.96 | E22: =SUM(_xldudf_WISEPRICE($B22, "close", , E$2, E$2)) -> 4.37 | F22: =SUM(_xldudf_WISEPRICE($B22, "close", , F$2, F$2)) -> 6.14 | G22: =SUM(_xldudf_WISEPRICE($B22, "close", , G$2, G$2)) -> 6.1 | H22: =SUM(_xldudf_WISEPRICE($B22, "close", , H$2, H$2)) -> 8.7 | I22: =SUM(_xldudf_WISEPRICE($B22, "close", , I$2, I$2)) -> 10.04 | J22: =SUM(_xldudf_WISEPRICE($B22, "close", , J$2, J$2)) -> 10.57 | ... M22: =SUM(_xldudf_WISEPRICE($B22, "close", , M$2, M$2)) -> 10.03 | N22: =(G22 /D22)^(1/4) - 1 -> 0.053081636 | O22: =(M22 /H22)^(1/5) - 1 -> 0.028860126 | P22: =(M22 /D22)^(1/9) - 1 -> 0.081383945
A23: Italgas | B23: IG.MI | C23: =SUM(_xldudf_WISEPRICE($B23, "close", , C$2, C$2)) -> 0 | D23: =SUM(_xldudf_WISEPRICE($B23, "close", , D$2, D$2)) -> 0 | E23: =SUM(_xldudf_WISEPRICE($B23, "close", , E$2, E$2)) -> 3.81 | F23: =SUM(_xldudf_WISEPRICE($B23, "close", , F$2, F$2)) -> 5 | G23: =SUM(_xldudf_WISEPRICE($B23, "close", , G$2, G$2)) -> 5.06 | H23: =SUM(_xldudf_WISEPRICE($B23, "close", , H$2, H$2)) -> 5.57 | I23: =SUM(_xldudf_WISEPRICE($B23, "close", , I$2, I$2)) -> 5.18 | J23: =SUM(_xldudf_WISEPRICE($B23, "close", , J$2, J$2)) -> 6.01 | ... M23: =SUM(_xldudf_WISEPRICE($B23, "close", , M$2, M$2)) -> 5.46 | N23: =(G23 /E23)^(1/3) - 1 -> 0.099196104 | O23: =(M23 /H23)^(1/5) - 1 -> -0.0039813063 | P23: =(M23 /E23)^(1/8) - 1 -> 0.046004272
A24: Leonardo | B24: LDO.MI | C24: =SUM(_xldudf_WISEPRICE($B24, "close", , C$2, C$2)) -> 7.73 | D24: =SUM(_xldudf_WISEPRICE($B24, "close", , D$2, D$2)) -> 12.37 | E24: =SUM(_xldudf_WISEPRICE($B24, "close", , E$2, E$2)) -> 13.41 | F24: =SUM(_xldudf_WISEPRICE($B24, "close", , F$2, F$2)) -> 10.08 | G24: =SUM(_xldudf_WISEPRICE($B24, "close", , G$2, G$2)) -> 7.68 | H24: =SUM(_xldudf_WISEPRICE($B24, "close", , H$2, H$2)) -> 10.48 | I24: =SUM(_xldudf_WISEPRICE($B24, "close", , I$2, I$2)) -> 5.83 | J24: =SUM(_xldudf_WISEPRICE($B24, "close", , J$2, J$2)) -> 6.43 | ... M24: =SUM(_xldudf_WISEPRICE($B24, "close", , M$2, M$2)) -> 26.06 | N24: =(G24 /C24)^(1/5) - 1 -> -0.0012970212 | O24: =(M24 /H24)^(1/5) - 1 -> 0.19983804 | P24: =(M24 /C24)^(1/10) - 1 -> 0.12922242
A25: Mediobanca | B25: MB.MI | C25: =SUM(_xldudf_WISEPRICE($B25, "close", , C$2, C$2)) -> 6.87 | D25: =SUM(_xldudf_WISEPRICE($B25, "close", , D$2, D$2)) -> 8.59 | E25: =SUM(_xldudf_WISEPRICE($B25, "close", , E$2, E$2)) -> 7.92 | F25: =SUM(_xldudf_WISEPRICE($B25, "close", , F$2, F$2)) -> 9.42 | G25: =SUM(_xldudf_WISEPRICE($B25, "close", , G$2, G$2)) -> 7.3 | H25: =SUM(_xldudf_WISEPRICE($B25, "close", , H$2, H$2)) -> 10 | I25: =SUM(_xldudf_WISEPRICE($B25, "close", , I$2, I$2)) -> 7.41 | J25: =SUM(_xldudf_WISEPRICE($B25, "close", , J$2, J$2)) -> 10.4 | ... M25: =SUM(_xldudf_WISEPRICE($B25, "close", , M$2, M$2)) -> 14.13 | N25: =(G25 /C25)^(1/5) - 1 -> 0.012216062 | O25: =(M25 /H25)^(1/5) - 1 -> 0.071589458 | P25: =(M25 /C25)^(1/10) - 1 -> 0.074777442
A26: Moncler | B26: MONC.MI | C26: =SUM(_xldudf_WISEPRICE($B26, "close", , C$2, C$2)) -> 11.07 | D26: =SUM(_xldudf_WISEPRICE($B26, "close", , D$2, D$2)) -> 12.45 | E26: =SUM(_xldudf_WISEPRICE($B26, "close", , E$2, E$2)) -> 16.8 | F26: =SUM(_xldudf_WISEPRICE($B26, "close", , F$2, F$2)) -> 25.8 | G26: =SUM(_xldudf_WISEPRICE($B26, "close", , G$2, G$2)) -> 29.16 | H26: =SUM(_xldudf_WISEPRICE($B26, "close", , H$2, H$2)) -> 40.59 | I26: =SUM(_xldudf_WISEPRICE($B26, "close", , I$2, I$2)) -> 50 | J26: =SUM(_xldudf_WISEPRICE($B26, "close", , J$2, J$2)) -> 65 | ... M26: =SUM(_xldudf_WISEPRICE($B26, "close", , M$2, M$2)) -> 50.96 | N26: =(G26 /C26)^(1/5) - 1 -> 0.21374647 | O26: =(M26 /H26)^(1/5) - 1 -> 0.04655504 | P26: =(M26 /C26)^(1/10) - 1 -> 0.1649524
A27: Nexi | B27: NEXI.MI | C27: =SUM(_xldudf_WISEPRICE($B27, "close", , C$2, C$2)) -> 0 | D27: =SUM(_xldudf_WISEPRICE($B27, "close", , D$2, D$2)) -> 0 | E27: =SUM(_xldudf_WISEPRICE($B27, "close", , E$2, E$2)) -> 0 | F27: =SUM(_xldudf_WISEPRICE($B27, "close", , F$2, F$2)) -> 0 | G27: =SUM(_xldudf_WISEPRICE($B27, "close", , G$2, G$2)) -> 0 | H27: =SUM(_xldudf_WISEPRICE($B27, "close", , H$2, H$2)) -> 12.6 | I27: =SUM(_xldudf_WISEPRICE($B27, "close", , I$2, I$2)) -> 16.555 | J27: =SUM(_xldudf_WISEPRICE($B27, "close", , J$2, J$2)) -> 14.32 | ... M27: =SUM(_xldudf_WISEPRICE($B27, "close", , M$2, M$2)) -> 5.39 | N27: / | O27: =(M27 /H27)^(1/5) - 1 -> -0.15619199 | P27: -0.15619199
A28: Poste Italiane | B28: PST.MI | C28: =SUM(_xldudf_WISEPRICE($B28, "close", , C$2, C$2)) -> 0 | D28: =SUM(_xldudf_WISEPRICE($B28, "close", , D$2, D$2)) -> 6.97 | E28: =SUM(_xldudf_WISEPRICE($B28, "close", , E$2, E$2)) -> 6.4 | F28: =SUM(_xldudf_WISEPRICE($B28, "close", , F$2, F$2)) -> 6.3 | G28: =SUM(_xldudf_WISEPRICE($B28, "close", , G$2, G$2)) -> 6.97 | H28: =SUM(_xldudf_WISEPRICE($B28, "close", , H$2, H$2)) -> 10.2 | I28: =SUM(_xldudf_WISEPRICE($B28, "close", , I$2, I$2)) -> 8.34 | J28: =SUM(_xldudf_WISEPRICE($B28, "close", , J$2, J$2)) -> 11.72 | ... M28: =SUM(_xldudf_WISEPRICE($B28, "close", , M$2, M$2)) -> 13.75 | N28: =(G28 /D28)^(1/4) - 1 -> 0 | O28: =(M28 /H28)^(1/5) - 1 -> 0.061550124 | P28: =(M28 /D28)^(1/9) - 1 -> 0.078414073
A29: Prysmian | B29: PRY.MI | C29: =SUM(_xldudf_WISEPRICE($B29, "close", , C$2, C$2)) -> 14.7 | D29: =SUM(_xldudf_WISEPRICE($B29, "close", , D$2, D$2)) -> 18.73 | E29: =SUM(_xldudf_WISEPRICE($B29, "close", , E$2, E$2)) -> 24.13 | F29: =SUM(_xldudf_WISEPRICE($B29, "close", , F$2, F$2)) -> 26.1 | G29: =SUM(_xldudf_WISEPRICE($B29, "close", , G$2, G$2)) -> 17.45 | H29: =SUM(_xldudf_WISEPRICE($B29, "close", , H$2, H$2)) -> 21.7 | I29: =SUM(_xldudf_WISEPRICE($B29, "close", , I$2, I$2)) -> 29.22 | J29: =SUM(_xldudf_WISEPRICE($B29, "close", , J$2, J$2)) -> 33.08 | ... M29: =SUM(_xldudf_WISEPRICE($B29, "close", , M$2, M$2)) -> 63.06 | N29: =(G29 /C29)^(1/5) - 1 -> 0.034893405 | O29: =(M29 /H29)^(1/5) - 1 -> 0.23782385 | P29: =(M29 /C29)^(1/10) - 1 -> 0.15676107
A30: Recordati Ord | B30: REC.MI | C30: =SUM(_xldudf_WISEPRICE($B30, "close", , C$2, C$2)) -> 13.06 | D30: =SUM(_xldudf_WISEPRICE($B30, "close", , D$2, D$2)) -> 23.64 | E30: =SUM(_xldudf_WISEPRICE($B30, "close", , E$2, E$2)) -> 27.31 | F30: =SUM(_xldudf_WISEPRICE($B30, "close", , F$2, F$2)) -> 37.3 | G30: =SUM(_xldudf_WISEPRICE($B30, "close", , G$2, G$2)) -> 30.02 | H30: =SUM(_xldudf_WISEPRICE($B30, "close", , H$2, H$2)) -> 37.95 | I30: =SUM(_xldudf_WISEPRICE($B30, "close", , I$2, I$2)) -> 44.86 | J30: =SUM(_xldudf_WISEPRICE($B30, "close", , J$2, J$2)) -> 54.62 | ... M30: =SUM(_xldudf_WISEPRICE($B30, "close", , M$2, M$2)) -> 51.75 | N30: =(G30 /C30)^(1/5) - 1 -> 0.18111858 | O30: =(M30 /H30)^(1/5) - 1 -> 0.063995313 | P30: =(M30 /C30)^(1/10) - 1 -> 0.14761633
A31: Saipem | B31: SPM.MI | C31: =SUM(_xldudf_WISEPRICE($B31, "close", , C$2, C$2)) -> 27.74 | D31: =SUM(_xldudf_WISEPRICE($B31, "close", , D$2, D$2)) -> 22.88 | E31: =SUM(_xldudf_WISEPRICE($B31, "close", , E$2, E$2)) -> 14.03 | F31: =SUM(_xldudf_WISEPRICE($B31, "close", , F$2, F$2)) -> 9.59 | G31: =SUM(_xldudf_WISEPRICE($B31, "close", , G$2, G$2)) -> 8.23 | H31: =SUM(_xldudf_WISEPRICE($B31, "close", , H$2, H$2)) -> 11 | I31: =SUM(_xldudf_WISEPRICE($B31, "close", , I$2, I$2)) -> 5.59 | J31: =SUM(_xldudf_WISEPRICE($B31, "close", , J$2, J$2)) -> 4.83 | ... M31: =SUM(_xldudf_WISEPRICE($B31, "close", , M$2, M$2)) -> 2.66 | N31: =(G31 /C31)^(1/5) - 1 -> -0.21574251 | O31: =(M31 /H31)^(1/5) - 1 -> -0.24716849 | P31: =(M31 /C31)^(1/10) - 1 -> -0.20899812
A32: Snam | B32: SRG.MI | C32: =SUM(_xldudf_WISEPRICE($B32, "close", , C$2, C$2)) -> 3.42 | D32: =SUM(_xldudf_WISEPRICE($B32, "close", , D$2, D$2)) -> 4.05 | E32: =SUM(_xldudf_WISEPRICE($B32, "close", , E$2, E$2)) -> 3.97 | F32: =SUM(_xldudf_WISEPRICE($B32, "close", , F$2, F$2)) -> 4.03 | G32: =SUM(_xldudf_WISEPRICE($B32, "close", , G$2, G$2)) -> 3.94 | H32: =SUM(_xldudf_WISEPRICE($B32, "close", , H$2, H$2)) -> 4.66 | I32: =SUM(_xldudf_WISEPRICE($B32, "close", , I$2, I$2)) -> 4.62 | J32: =SUM(_xldudf_WISEPRICE($B32, "close", , J$2, J$2)) -> 5.27 | ... M32: =SUM(_xldudf_WISEPRICE($B32, "close", , M$2, M$2)) -> 4.35 | N32: =(G32 /C32)^(1/5) - 1 -> 0.028712515 | O32: =(M32 /H32)^(1/5) - 1 -> -0.013673576 | P32: =(M32 /C32)^(1/10) - 1 -> 0.024345149
A33: Stellantis | B33: STLAM.MI | C33: =SUM(_xldudf_WISEPRICE($B33, "close", , C$2, C$2)) -> 6.35 | D33: =SUM(_xldudf_WISEPRICE($B33, "close", , D$2, D$2)) -> 8.15 | E33: =SUM(_xldudf_WISEPRICE($B33, "close", , E$2, E$2)) -> 8.96 | F33: =SUM(_xldudf_WISEPRICE($B33, "close", , F$2, F$2)) -> 15.16 | G33: =SUM(_xldudf_WISEPRICE($B33, "close", , G$2, G$2)) -> 12.57 | H33: =SUM(_xldudf_WISEPRICE($B33, "close", , H$2, H$2)) -> 13.36 | I33: =SUM(_xldudf_WISEPRICE($B33, "close", , I$2, I$2)) -> 14.88 | J33: =SUM(_xldudf_WISEPRICE($B33, "close", , J$2, J$2)) -> 17.71 | ... M33: =SUM(_xldudf_WISEPRICE($B33, "close", , M$2, M$2)) -> 12.62 | N33: =(G33 /C33)^(1/5) - 1 -> 0.146337 | O33: =(M33 /H33)^(1/5) - 1 -> -0.011331769 | P33: =(M33 /C33)^(1/10) - 1 -> 0.071096408
A34: Stmicroelectronics | B34: STMMI.MI | C34: =SUM(_xldudf_WISEPRICE($B34, "close", , C$2, C$2)) -> 6.23 | D34: =SUM(_xldudf_WISEPRICE($B34, "close", , D$2, D$2)) -> 6.04 | E34: =SUM(_xldudf_WISEPRICE($B34, "close", , E$2, E$2)) -> 10.81 | F34: =SUM(_xldudf_WISEPRICE($B34, "close", , F$2, F$2)) -> 18.43 | G34: =SUM(_xldudf_WISEPRICE($B34, "close", , G$2, G$2)) -> 12.14 | H34: =SUM(_xldudf_WISEPRICE($B34, "close", , H$2, H$2)) -> 24.76 | I34: =SUM(_xldudf_WISEPRICE($B34, "close", , I$2, I$2)) -> 31.72 | J34: =SUM(_xldudf_WISEPRICE($B34, "close", , J$2, J$2)) -> 43.23 | ... M34: =SUM(_xldudf_WISEPRICE($B34, "close", , M$2, M$2)) -> 23.81 | N34: =(G34 /C34)^(1/5) - 1 -> 0.14273658 | O34: =(M34 /H34)^(1/5) - 1 -> -0.0077942237 | P34: =(M34 /C34)^(1/10) - 1 -> 0.14347621
A35: Telecom Italia | B35: TIT.MI | C35: =SUM(_xldudf_WISEPRICE($B35, "close", , C$2, C$2)) -> 0.876 | D35: =SUM(_xldudf_WISEPRICE($B35, "close", , D$2, D$2)) -> 1.127 | E35: =SUM(_xldudf_WISEPRICE($B35, "close", , E$2, E$2)) -> 0.858 | F35: =SUM(_xldudf_WISEPRICE($B35, "close", , F$2, F$2)) -> 0.7255 | G35: =SUM(_xldudf_WISEPRICE($B35, "close", , G$2, G$2)) -> 0.4896 | H35: =SUM(_xldudf_WISEPRICE($B35, "close", , H$2, H$2)) -> 0.5595 | I35: =SUM(_xldudf_WISEPRICE($B35, "close", , I$2, I$2)) -> 0.3811 | J35: =SUM(_xldudf_WISEPRICE($B35, "close", , J$2, J$2)) -> 0.4449 | ... M35: =SUM(_xldudf_WISEPRICE($B35, "close", , M$2, M$2)) -> 0.2497 | N35: =(G35 /C35)^(1/5) - 1 -> -0.10984126 | O35: =(M35 /H35)^(1/5) - 1 -> -0.1490115 | P35: =(M35 /C35)^(1/10) - 1 -> -0.11795358
A36: Tenaris | B36: TEN.MI | C36: =SUM(_xldudf_WISEPRICE($B36, "close", , C$2, C$2)) -> 12.43 | D36: =SUM(_xldudf_WISEPRICE($B36, "close", , D$2, D$2)) -> 10.8 | E36: =SUM(_xldudf_WISEPRICE($B36, "close", , E$2, E$2)) -> 17.25 | F36: =SUM(_xldudf_WISEPRICE($B36, "close", , F$2, F$2)) -> 13.25 | G36: =SUM(_xldudf_WISEPRICE($B36, "close", , G$2, G$2)) -> 9.52 | H36: =SUM(_xldudf_WISEPRICE($B36, "close", , H$2, H$2)) -> 10.1 | I36: =SUM(_xldudf_WISEPRICE($B36, "close", , I$2, I$2)) -> 6.54 | J36: =SUM(_xldudf_WISEPRICE($B36, "close", , J$2, J$2)) -> 9.71 | ... M36: =SUM(_xldudf_WISEPRICE($B36, "close", , M$2, M$2)) -> 18.45 | N36: =(G36 /C36)^(1/5) - 1 -> -0.051945806 | O36: =(M36 /H36)^(1/5) - 1 -> 0.12806727 | P36: =(M36 /C36)^(1/10) - 1 -> 0.04028545
A37: Terna | B37: TRN.MI | C37: =SUM(_xldudf_WISEPRICE($B37, "close", , C$2, C$2)) -> 3.75 | D37: =SUM(_xldudf_WISEPRICE($B37, "close", , D$2, D$2)) -> 4.72 | E37: =SUM(_xldudf_WISEPRICE($B37, "close", , E$2, E$2)) -> 4.43 | F37: =SUM(_xldudf_WISEPRICE($B37, "close", , F$2, F$2)) -> 4.8 | G37: =SUM(_xldudf_WISEPRICE($B37, "close", , G$2, G$2)) -> 5.07 | H37: =SUM(_xldudf_WISEPRICE($B37, "close", , H$2, H$2)) -> 5.92 | I37: =SUM(_xldudf_WISEPRICE($B37, "close", , I$2, I$2)) -> 6.23 | J37: =SUM(_xldudf_WISEPRICE($B37, "close", , J$2, J$2)) -> 7.16 | ... M37: =SUM(_xldudf_WISEPRICE($B37, "close", , M$2, M$2)) -> 7.74 | N37: =(G37 /C37)^(1/5) - 1 -> 0.062173197 | O37: =(M37 /H37)^(1/5) - 1 -> 0.055076259 | P37: =(M37 /C37)^(1/10) - 1 -> 0.075154729
A38: Unicredit | B38: UCG.MI | C38: =SUM(_xldudf_WISEPRICE($B38, "close", , C$2, C$2)) -> 27.23 | D38: =SUM(_xldudf_WISEPRICE($B38, "close", , D$2, D$2)) -> 24.97 | E38: =SUM(_xldudf_WISEPRICE($B38, "close", , E$2, E$2)) -> 14.05 | F38: =SUM(_xldudf_WISEPRICE($B38, "close", , F$2, F$2)) -> 15.71 | G38: =SUM(_xldudf_WISEPRICE($B38, "close", , G$2, G$2)) -> 9.77 | H38: =SUM(_xldudf_WISEPRICE($B38, "close", , H$2, H$2)) -> 13.49 | I38: =SUM(_xldudf_WISEPRICE($B38, "close", , I$2, I$2)) -> 7.58 | J38: =SUM(_xldudf_WISEPRICE($B38, "close", , J$2, J$2)) -> 14.28 | ... M38: =SUM(_xldudf_WISEPRICE($B38, "close", , M$2, M$2)) -> 38.38 | N38: =(G38 /C38)^(1/5) - 1 -> -0.18535315 | O38: =(M38 /H38)^(1/5) - 1 -> 0.2325899 | P38: =(M38 /C38)^(1/10) - 1 -> 0.034917505
A39: Unipol | B39: UNI.MI | C39: =SUM(_xldudf_WISEPRICE($B39, "close", , C$2, C$2)) -> 4.176 | D39: =SUM(_xldudf_WISEPRICE($B39, "close", , D$2, D$2)) -> 4.576 | E39: =SUM(_xldudf_WISEPRICE($B39, "close", , E$2, E$2)) -> 3.502 | F39: =SUM(_xldudf_WISEPRICE($B39, "close", , F$2, F$2)) -> 4.038 | G39: =SUM(_xldudf_WISEPRICE($B39, "close", , G$2, G$2)) -> 3.46 | H39: =SUM(_xldudf_WISEPRICE($B39, "close", , H$2, H$2)) -> 5.206 | I39: =SUM(_xldudf_WISEPRICE($B39, "close", , I$2, I$2)) -> 3.89 | J39: =SUM(_xldudf_WISEPRICE($B39, "close", , J$2, J$2)) -> 4.85 | ... M39: =SUM(_xldudf_WISEPRICE($B39, "close", , M$2, M$2)) -> 11.89 | N39: =(G39 /C39)^(1/5) - 1 -> -0.03691832 | O39: =(M39 /H39)^(1/5) - 1 -> 0.1796021 | P39: =(M39 /C39)^(1/10) - 1 -> 0.11030459
A40: FTSEMIB | B40: FTSEMIB.MI | C40: =SUM(_xldudf_WISEPRICE($B40, "close", , C$2, C$2)) -> 19130 | D40: =SUM(_xldudf_WISEPRICE($B40, "close", , D$2, D$2)) -> 20734 | E40: =SUM(_xldudf_WISEPRICE($B40, "close", , E$2, E$2)) -> 19567 | F40: =SUM(_xldudf_WISEPRICE($B40, "close", , F$2, F$2)) -> 21845 | G40: =SUM(_xldudf_WISEPRICE($B40, "close", , G$2, G$2)) -> 18331 | H40: =SUM(_xldudf_WISEPRICE($B40, "close", , H$2, H$2)) -> 23836 | I40: =SUM(_xldudf_WISEPRICE($B40, "close", , I$2, I$2)) -> 22316 | J40: =SUM(_xldudf_WISEPRICE($B40, "close", , J$2, J$2)) -> 27955 | ... M40: =SUM(_xldudf_WISEPRICE($B40, "close", , M$2, M$2)) -> 34375 | N40: =(G40 /C40)^(1/5) - 1 -> -0.0084965322 | O40: =(M40 /H40)^(1/5) - 1 -> 0.07597422 | P40: =(M40 /C40)^(1/10) - 1 -> 0.060358626

Sheet PE_Ratio
A2: Company | B2: Yahoo Finance Format | C2: 2015 | D2: =C2+1 -> 2016 | E2: =D2+1 -> 2017 | F2: =E2+1 -> 2018 | G2: =F2+1 -> 2019 | H2: =G2+1 -> 2020 | I2: =H2+1 -> 2021 | J2: =I2+1 -> 2022 | K2: =J2+1 -> 2023 | L2: =K2+1 -> 2024 | M2: AVG 2015-2019 | N2: AVG 2020-2024 | O2: AVG 2015-2024
A3: A2a | B3: A2A.MI | C3: 53.354911 | D3: 17.072751 | E3: 16.129554 | F3: 14.46132 | G3: 13.34791 | H3: 11.104228 | I3: 10.489564 | J3: 9.5813163 | K3: 8.8424944 | L3: 7.795504 | M3: =AVERAGE(C3:G3) -> 22.873289 | N3: =AVERAGE(H3:L3) -> 9.5626214 | O3: =AVERAGE(C3:L3) -> 16.217955
A4: Amplifon | B4: AMP.MI | C4: 37.245879 | D4: 31.198795 | E4: 28.144508 | F4: 30.433579 | G4: 52.349257 | H4: 75.423476 | I4: 67.610326 | J4: 34.9631 | K4: 45.546434 | L4: 38.596525 | M4: =AVERAGE(C4:G4) -> 35.874403 | N4: =AVERAGE(H4:L4) -> 52.427972 | O4: =AVERAGE(C4:L4) -> 44.151188
A5: Azimut | B5: AZM.MI | C5: 12.383535 | D5: 12.035708 | E5: 9.1065074 | F5: 10.438163 | G5: 7.9444284 | H5: 6.3614562 | I5: 5.591857 | J5: 7.0664483 | K5: 7.4617835 | L5: 5.8512195 | M5: =AVERAGE(C5:G5) -> 10.381668 | N5: =AVERAGE(H5:L5) -> 6.4665529 | O5: =AVERAGE(C5:L5) -> 8.4241107
A6: Banca Mediolanum | B6: BMED.MI | C6: 12.298293 | D6: 12.792084 | E6: 13.710633 | F6: 14.479443 | G6: 11.486656 | H6: 12.000988 | I6: 8.9558494 | J6: 11.346169 | K6: 7.7229461 | L6: 7.5667018 | M6: =AVERAGE(C6:G6) -> 12.953422 | N6: =AVERAGE(H6:L6) -> 9.5185307 | O6: =AVERAGE(C6:L6) -> 11.235976
A7: Banca Monte Paschi Siena | B7: BMPS.MI | C7: 26.479861 | D7: Negative | E7: Negative | F7: 29.099246 | G7: Negative | H7: Negative | I7: 13.638228 | J7: Negative | K7: 1.8723316 | L7: 4.3964231 | M7: =AVERAGE(C7:G7) -> 27.789554 | N7: =AVERAGE(H7:L7) -> 6.6356609 | O7: =AVERAGE(C7:L7) -> 15.097218
A8: Banco Bpm | B8: BAMI.MI | C8: 10.780052 | D8: Negative | E8: 1.5282214 | F8: Negative | G8: 3.8494539 | H8: 130.85266 | I8: 7.0089576 | J8: 7.3341996 | K8: 5.7002346 | L8: 6.1206528 | M8: =AVERAGE(C8:G8) -> 5.385909 | N8: =AVERAGE(H8:L8) -> 31.403341 | O8: =AVERAGE(C8:L8) -> 21.646804
A9: Bca Pop Sondrio | B9: BPSO.MI | C9: 14.441631 | D9: 14.276468 | E9: 8.7283203 | F9: 10.593574 | G9: 6.9607013 | H9: 9.2818626 | I9: 6.1938839 | J9: 6.7643872 | K9: 5.7611873 | L9: 6.3673624 | M9: =AVERAGE(C9:G9) -> 11.000139 | N9: =AVERAGE(H9:L9) -> 6.8737367 | O9: =AVERAGE(C9:L9) -> 8.9369378
A10: Bper Banca | B10: BPE.MI | C10: 15.356485 | D10: negative | E10: 11.354184 | F10: 3.9412013 | G10: 5.843721 | H10: 4.2702649 | I10: 4.8949083 | J10: 1.8708891 | K10: 2.8219696 | L10: 6.1821639 | M10: =AVERAGE(C10:G10) -> 9.1238978 | N10: =AVERAGE(H10:L10) -> 4.0080392 | O10: =AVERAGE(C10:L10) -> 6.2817541
A11: Brunello Cucinelli | B11: BC.MI | C11: 33.28814 | D11: 38.000934 | E11: 36.090537 | F11: 40.645467 | G11: 40.836489 | H11: Negative | I11: 77.408949 | J11: 58.29849 | K11: 52.557755 | L11: 59.9842 | M11: =AVERAGE(C11:G11) -> 37.772313 | N11: =AVERAGE(H11:L11) -> 62.062349 | O11: =AVERAGE(C11:L11) -> 48.567885
A12: Buzzi | B12: BZU.MI | C12: 27.222756 | D12: 31.717611 | E12: 11.997716 | F12: 8.1365126 | G12: 11.923503 | H12: 7.1595648 | I12: 6.7275908 | J12: 7.3123309 | K12: 5.2750071 | L12: 6.9217874 | M12: =AVERAGE(C12:G12) -> 18.19962 | N12: =AVERAGE(H12:L12) -> 6.6792562 | O12: =AVERAGE(C12:L12) -> 12.439438
A13: Campari | B13: CPR.MI | C13: 26.363384 | D13: 32.296087 | E13: 20.714351 | F13: 28.726431 | G13: 30.20341 | H13: 56.35895 | I13: 50.870549 | J13: 32.057249 | K13: 35.241501 | L13: 35.843694 | M13: =AVERAGE(C13:G13) -> 27.660733 | N13: =AVERAGE(H13:L13) -> 42.074388 | O13: =AVERAGE(C13:L13) -> 34.867561
A14: Diasorin | B14: DIA.MI | C14: 26.479855 | D14: 27.453498 | E14: 29.292013 | F14: 24.995786 | G14: 35.927657 | H14: 37.577103 | I14: 30.756891 | J14: 31.259826 | K14: 32.516631 | L14: 29.570127 | M14: =AVERAGE(C14:G14) -> 28.829762 | N14: =AVERAGE(H14:L14) -> 32.336115 | O14: =AVERAGE(C14:L14) -> 30.582939
A15: Enel | B15: ENEL.MI | C15: 16.657132 | D15: 16.264128 | E15: 13.747482 | F15: 10.781207 | G15: 33.047771 | H15: 32.246356 | I15: 22.466638 | J15: 30.384962 | K15: 19.887378 | L15: 9.9737572 | M15: =AVERAGE(C15:G15) -> 18.099544 | N15: =AVERAGE(H15:L15) -> 22.991818 | O15: =AVERAGE(C15:L15) -> 20.545681
A16: Eni | B16: ENI.MI | C16: Negative | D16: Negative | E16: 14.729026 | F16: 12.027075 | G16: Negative | H16: Negative | I16: 7.4860337 | J16: 3.3338731 | K16: 10.629497 | L16: 15.798822 | M16: =AVERAGE(C16:G16) -> 13.37805 | N16: =AVERAGE(H16:L16) -> 9.3120564 | O16: =AVERAGE(C16:L16) -> 10.667388
A17: Ferrari | B17: RACE.MI | C17: 28.665076 | D17: 26.199693 | E17: 30.753678 | F17: 20.796035 | G17: 39.698368 | H17: 57.358797 | I17: 50.509306 | J17: 39.248571 | K17: 44.1743 | L17: 48.706967 | M17: =AVERAGE(C17:G17) -> 29.22257 | N17: =AVERAGE(H17:L17) -> 47.999588 | O17: =AVERAGE(C17:L17) -> 38.611079
A18: Finecobank | B18: FBK.MI | C18: 24.18977 | D18: 15.238419 | E18: 23.96077 | F18: 22.039233 | G18: 22.528845 | H18: 25.219028 | I18: 24.72651 | J18: 22.091102 | K18: 13.644592 | L18: 15.722929 | M18: =AVERAGE(C18:G18) -> 21.591407 | N18: =AVERAGE(H18:L18) -> 20.280832 | O18: =AVERAGE(C18:L18) -> 20.93612
A19: Generali | B19: G.MI | C19: 12.972795 | D19: 10.574815 | E19: 11.110326 | F19: 9.8267256 | G19: 10.805191 | H19: 12.83276 | I19: 10.294423 | J19: 8.9565274 | K19: 8.0434506 | L19: 11.267482 | M19: =AVERAGE(C19:G19) -> 11.05797 | N19: =AVERAGE(H19:L19) -> 10.278929 | O19: =AVERAGE(C19:L19) -> 10.66845
A20: Hera | B20: HER.MI | C20: 20.05921 | D20: 15.548925 | E20: 17.202675 | F20: 14.164134 | G20: 14.889334 | H20: 14.451806 | I20: 16.03638 | J20: 14.363961 | K20: 9.7300116 | L20: 10.001632 | M20: =AVERAGE(C20:G20) -> 16.372856 | N20: =AVERAGE(H20:L20) -> 12.916758 | O20: =AVERAGE(C20:L20) -> 14.644807
A21: Intesa Sanpaolo | B21: ISP.MI | C21: 17.861401 | D21: 12.373769 | E21: 5.9530407 | F21: 7.9099354 | G21: 9.8192328 | H21: 10.631473 | I21: 10.510642 | J21: 9.1747722 | K21: 6.2788613 | L21: 8.0252634 | M21: =AVERAGE(C21:G21) -> 10.783476 | N21: =AVERAGE(H21:L21) -> 8.9242024 | O21: =AVERAGE(C21:L21) -> 9.8538391
A22: Inwit | B22: INW.MI | C22: 37.647966 | D22: 26.959454 | E22: 29.067205 | F22: 26.000105 | G22: 37.584662 | H22: 55.226487 | I22: 53.575055 | J22: 30.79303 | K22: 32.243058 | L22: 25.871818 | M22: =AVERAGE(C22:G22) -> 31.451878 | N22: =AVERAGE(H22:L22) -> 39.54189 | O22: =AVERAGE(C22:L22) -> 35.496884
A23: Italgas | B23: IG.MI | C23: 9.4478469 | D23: Negative | E23: 13.818809 | F23: 12.974359 | G23: 10.549607 | H23: 10.93921 | I23: 13.503095 | J23: 10.32482 | K23: 9.5540627 | L23: 9.1652589 | M23: =AVERAGE(C23:G23) -> 11.697656 | N23: =AVERAGE(H23:L23) -> 10.697289 | O23: =AVERAGE(C23:L23) -> 11.141897
A24: Leonardo | B24: LDO.MI | C24: 15.218901 | D24: 15.177037 | E24: 20.903264 | F24: 8.669875 | G24: 7.3177239 | H24: 14.098513 | I24: 6.1842026 | J24: 5.0021299 | K24: 13.062442 | L24: 13.889861 | M24: =AVERAGE(C24:G24) -> 13.45736 | N24: =AVERAGE(H24:L24) -> 10.44743 | O24: =AVERAGE(C24:L24) -> 11.952395
A25: Mediobanca | B25: MB.MI | C25: 12.644741 | D25: 7.254088 | E25: 9.8405929 | F25: 8.0868286 | G25: 9.4806134 | H25: 9.1596769 | I25: 10.518187 | J25: 7.6395035 | K25: 8.9742687 | L25: 9.1464365 | M25: =AVERAGE(C25:G25) -> 9.4613728 | N25: =AVERAGE(H25:L25) -> 9.0876144 | O25: =AVERAGE(C25:L25) -> 9.2744936
A26: Moncler | B26: MONC.MI | C26: 19.248511 | D26: 21.017841 | E26: 26.045106 | F26: 22.082976 | G26: 28.120995 | H26: 42.181001 | I26: 43.203075 | J26: 21.945431 | K26: 24.585992 | L26: 21.562449 | M26: =AVERAGE(C26:G26) -> 23.303086 | N26: =AVERAGE(H26:L26) -> 30.695589 | O26: =AVERAGE(C26:L26) -> 26.999338
A27: Nexi | B27: NEXI.MI | C27: Unavailable | D27: 89.181836 | E27: 71.787523 | F27: Negative | G27: Negative | H27: 80.186143 | I27: Negative | J27: 68.953057 | K27: Negative | L27: 41.0247 | M27: =AVERAGE(C27:G27) -> 80.48468 | N27: =AVERAGE(H27:L27) -> 63.387967 | O27: =AVERAGE(C27:L27) -> 70.226652
A28: Poste Italiane | B28: PST.MI | C28: 16.78487 | D28: 13.250087 | E28: 11.931818 | F28: 6.5072099 | G28: 9.8097039 | H28: 8.9669337 | I28: 9.513385 | J28: 7.5132958 | K28: 6.9925826 | L28: 8.8441558 | M28: =AVERAGE(C28:G28) -> 11.656738 | N28: =AVERAGE(H28:L28) -> 8.3660706 | O28: =AVERAGE(C28:L28) -> 10.011404
A29: Prysmian | B29: PRY.MI | C29: 20.254698 | D29: 21.231822 | E29: 24.338997 | F29: 32.880767 | G29: 19.365949 | H29: 43.01128 | I29: 28.31636 | J29: 18.120647 | K29: 21.474227 | L29: 23.813109 | M29: =AVERAGE(C29:G29) -> 23.614447 | N29: =AVERAGE(H29:L29) -> 26.947125 | O29: =AVERAGE(C29:L29) -> 25.280786
A30: Recordati Ord | B30: REC.MI | C30: 24.875028 | D30: 23.372117 | E30: 26.742545 | F30: 19.641274 | G30: 20.877969 | H30: 26.274468 | I30: 30.157129 | J30: 25.505569 | K30: 25.888259 | L30: 25.064589 | M30: =AVERAGE(C30:G30) -> 23.101787 | N30: =AVERAGE(H30:L30) -> 26.578003 | O30: =AVERAGE(C30:L30) -> 24.839895
A31: Saipem | B31: SPM.MI | C31: Negative | D31: Negative | E31: Negative | F31: Negative | G31: 23.332866 | H31: Negative | I31: Negative | J31: Negative | K31: 16.384734 | L31: 16.139612 | M31: =AVERAGE(C31:G31) -> 23.332866 | N31: =AVERAGE(H31:L31) -> 16.262173 | O31: =AVERAGE(C31:L31) -> 18.619071
A32: Snam | B32: SRG.MI | C32: 13.766251 | D32: 15.761401 | E32: 15.37603 | F32: 13.780996 | G32: 14.201635 | H32: 13.670569 | I32: 11.587846 | J32: 22.525757 | K32: 13.766993 | L32: 11.401806 | M32: =AVERAGE(C32:G32) -> 14.577263 | N32: =AVERAGE(H32:L32) -> 14.590594 | O32: =AVERAGE(C32:L32) -> 14.583928
A33: Stellantis | B33: STLAM.MI | C33: 38.804078 | D33: 7.2671905 | E33: 6.6701742 | F33: 5.3946447 | G33: 3.1154732 | H33: 780.51963 | I33: 3.5957359 | J33: 2.4785749 | K33: 3.5378865 | L33: 6.7920062 | M33: =AVERAGE(C33:G33) -> 12.250312 | N33: =AVERAGE(H33:L33) -> 159.38477 | O33: =AVERAGE(C33:L33) -> 85.81754
A34: Stmicroelectronics | B34: STMMI.MI | C34: 33.625252 | D34: 82.573248 | E34: 89.928466 | F34: 9.9891193 | G34: 23.391177 | H34: 29.918344 | I34: 22.339475 | J34: 8.0720951 | K34: 11.233348 | L34: 14.552313 | M34: =AVERAGE(C34:G34) -> 47.901453 | N34: =AVERAGE(H34:L34) -> 17.223115 | O34: =AVERAGE(C34:L34) -> 32.562284
A35: Telecom Italia | B35: TIT.MI | C35: Negative | D35: 9.7528092 | E35: 13.634352 | F35: Negative | G35: 9.5609851 | H35: 1.1012493 | I35: Negative | J35: Negative | K35: Negative | L35: Negative | M35: =AVERAGE(C35:G35) -> 10.982715 | N35: =AVERAGE(H35:L35) -> 1.1012493 | O35: =AVERAGE(C35:L35) -> 8.5123489
A36: Tenaris | B36: TEN.MI | C36: Negative | D36: negative | E36: 34.487842 | F36: 14.682142 | G36: 17.927604 | H36: Negative | I36: 11.249856 | J36: 8.0586384 | K36: 5.2296098 | L36: 10.337737 | M36: =AVERAGE(C36:G36) -> 22.365862 | N36: =AVERAGE(H36:L36) -> 8.7189603 | O36: =AVERAGE(C36:L36) -> 14.567633
A37: Terna | B37: TRN.MI | C37: 16.081081 | D37: 13.809524 | E37: 14.035088 | F37: 14.403409 | G37: 15.782493 | H37: 15.984655 | I37: 17.802951 | J37: 15.785356 | K37: 16.944563 | L37: 14.423623 | M37: =AVERAGE(C37:G37) -> 14.822319 | N37: =AVERAGE(H37:L37) -> 16.188229 | O37: =AVERAGE(C37:L37) -> 15.505274
A38: Unicredit | B38: UCG.MI | C38: 25.555752 | D38: Negative | E38: 5.5899886 | F38: 5.5706962 | G38: 8.2904356 | H38: Negative | I38: 14.352006 | J38: 4.2524247 | K38: 4.4256083 | L38: 6.7125452 | M38: =AVERAGE(C38:G38) -> 11.251718 | N38: =AVERAGE(H38:L38) -> 7.435646 | O38: =AVERAGE(C38:L38) -> 9.3436821
A39: Unipol | B39: UNI.MI | C39: 5.8259596 | D39: 4.53568 | E39: Negative | F39: 2.6465587 | G39: 4.0556144 | H39: 3.9580874 | I39: 5.4616053 | J39: 6.2101665 | K39: 3.3556403 | L39: 8.02 | M39: =AVERAGE(C39:G39) -> 4.2659532 | N39: =AVERAGE(H39:L39) -> 5.4010999 | O39: =AVERAGE(C39:L39) -> 4.8965902
A40: FTSEMIB | B40: FTSEMIB.MI | C40: {=_xldudf_WISE(B40, "PE Ratio", 2023)} -> Unavailable | D40: {=_xldudf_WISE(C40,"PE ratio",D2)} -> Unavailable | E40: {=_xldudf_WISE(D40,"PE ratio",E2)} -> Unavailable | F40: {=_xldudf_WISE(E40,"PE ratio",F2)} -> Unavailable | G40: {=_xldudf_WISE(F40,"PE ratio",G2)} -> Unavailable | H40: {=_xldudf_WISE(G40,"PE ratio",H2)} -> Unavailable | I40: {=_xldudf_WISE(H40,"PE ratio",I2)} -> Unavailable | J40: {=_xldudf_WISE(I40,"PE ratio",J2)} -> Unavailable | K40: {=_xldudf_WISE(J40,"PE ratio",K2)} -> Unavailable | L40: {=_xldudf_WISE(K40,"PE ratio",L2)} -> Unavailable | M40: =AVERAGE(M3:M39) -> 20.495407 | N40: =AVERAGE(N3:N39) -> 23.643448 | O40: =AVERAGE(C40:L40) -> #DIV/0!

Sheet Free Risk Return
A1: Risk Free Rate: average yield of the 10-Year Italian Bond over that same 5-year period (2020–2024).
A3: Year | B3: Yield | C3: Notes
A4: 2020 | B4: 0.0054 | C4: Historic lows due to pandemic stimulus.
A5: 2021 | B5: 0.0102 | C5: Rates began to rise slightly as inflation concerns started.
A6: 2022 | B6: 0.0413 | C6: Sharp increase due to aggressive ECB rate hikes.
A7: 2023 | B7: 0.0382 | C7: Rates stabilized but remained high.
A8: 2024 | B8: 0.0336 | C8: The most recent "Snapshot" value for your study.
A9: Average | B9: =AVERAGE(B4:B8) -> 0.02574

Sheet Notes
A1: Notes
A3: French and Fama Used BE = {Stockholders' Equity} + {Deferred Taxes} - {Preferred Stock}
